Workbook

Sheet Resumen
B2: DEVON ENERGY (DVN) — RESUMEN EJECUTIVO DE VALORACION
B3: Modelo valoración integral · Fecha valoración: 19-may-2026 · Pro-forma Devon+Coterra (cierre 7-may-2026)
B5: 1. COMPANY SNAPSHOT / MARKET DATA (15-may-2026)
B6: CEO | C6: Clay Gaspar | E6: Spot ($) | F6: =Hipotesis!$C$6 -> 49.49
B7: CFO | C7: Shannon Young III | E7: Market Cap ($B) | F7: =Hipotesis!$C$21/1000 -> 57.06197
B8: Headquarters | C8: Oklahoma City, OK (HQ) + Houston (oficinas operativas, post-merger) | E8: Enterprise Value ($B) | F8: =(Hipotesis!$C$21+Hipotesis!$C$14-Hipotesis!$C$15)/1000 -> 67.33197
B9: Fundada | C9: 1971 (Devon Energy); 1989 IPO | E9: Shares Outstanding (M) | F9: =Hipotesis!$C$8 -> 1153
B10: Empleados (FY25) | C10: ~3,400 (DVN pre-merger) + ~1,400 (CTRA) ≈ ~4,800 post-merger (est.) | E10: 52-week range | F10: $30.24 – $52.71 (52-week, May-2026)
B11: Año fiscal | C11: Año calendario, cierre 31-dic | E11: All-time high (close) | F11: $78.65 (Mar-2014 close adjustado)
B12: Sector | C12: Exploración & Producción (E&P) — Petróleo, Gas natural, NGLs | E12: P/E TTM | F12: ~13.8× (post Q1 2026 EPS)
B13: Segmentos reportados | C13: 4 commodity lines: Oil, Gas, NGL, Marketing & Midstream (M&M pass-through) | E13: EPS TTM | F13: $2.16 (FY25 adj diluted) · $0.19 (Q1 26)
B14: Ticker / Exchange | C14: DVN / NYSE | E14: Beta (5Y) | F14: =Hipotesis!$C$11 -> 1.2
B15: Index | C15: S&P 500, S&P 500 Energy | E15: Dividend Yield | F15: ~1.85% ($0.92/sh annualized: $0.24 fixed quarterly)
B17: 2. Q1 2026 EARNINGS HIGHLIGHTS (trimestre cerrado 31-mar-2026, reportado 5-may-2026)
B18: Revenue Q1 (DVN standalone) | C18: $3,807M | E18: vs $4,455M Q1 25 (−14.5% YoY, oil price weak)
B19: Operating Income Q1 | C19: $275M | E19: Margin 7.2% (cyclical low)
B20: Net Income Q1 | C20: $120M | E20: Diluted EPS $0.19
B21: Oil production Q1 (MBbls/d) | C21: 389 MBbls/d | E21: Realized $69.66/Bbl
B22: Gas production Q1 (MMcf/d) | C22: 1,420 MMcf/d | E22: Realized $1.66/Mcf
B23: NGL production Q1 (MBbls/d) | C23: 225 MBbls/d | E23: Realized $17.80/Bbl
B24: Total production Q1 (MBoe/d) | C24: 851 MBoe/d | E24: Field-level cash margin $27.78/Boe
B25: Coterra merger close | C25: 7-may-2026 | E25: All-stock: 0.70 DVN per CTRA share
B26: Proved reserves (DVN, YE25) | C26: 2,428 MMBoe | E26: Pro-forma combined: ~3,650 MMBoe (est.)
B27: Synergies anunciadas (target) | C27: $1,000M anuales pre-tax | E27: YE 2027 run-rate (G&A 50%, capex/ops 50%)
B28: Capex Q1 | C28: $848M | E28: 22.3% Capex/Revenue (Q1 estacional alto)
B29: FCF Q1 | C29: $807M | E29: OCF $1,655M − Capex $848M
... B31: Dividends Q1 | C31: $152M | E31: $0.24/sh fixed quarterly + variable potentialmente
B33: 3. 5-YEAR HISTORICAL FINANCIALS — DVN STANDALONE (FY21-FY25, $mm except per-share / ratios)
B34: Metric | C34: FY21 | D34: FY22 | E34: FY23 | F34: FY24 | G34: FY25
B35: Revenue ($mm) | C35: 12206 | D35: 19169 | E35: 15258 | F35: 15938 | G35: 17188
B36: YoY growth | C36: n/a | D36: +57.0% | E36: −20.4% | F36: +4.5% | G36: +7.8%
B37: Operating Income | C37: 6628 | D37: 11555 | E37: 5896 | F37: 5309 | G37: 3834
B38: Operating margin | C38: 54.3% | D38: 60.3% | E38: 38.6% | F38: 33.3% | G38: 22.3%
B39: Net Income | C39: 2813 | D39: 6015 | E39: 3747 | F39: 2891 | G39: 2642
B40: Diluted EPS | C40: 4.18 | D40: 9.23 | E40: 5.81 | F40: 4.55 | G40: 4.19
B41: OCF | C41: 4899 | D41: 8538 | E41: 6498 | F41: 6906 | G41: 6711
B42: Capex | C42: -1971 | D42: -2517 | E42: -3766 | F42: -3713 | G42: -3713
B43: Free Cash Flow | C43: 2928 | D43: 6021 | E43: 2732 | F43: 3193 | G43: 2998
B44: Buybacks | C44: -591 | D44: -2399 | E44: -1456 | F44: -737 | G44: -750
B45: Dividends | C45: -689 | D45: -1685 | E45: -1248 | F45: -558 | G45: -619
B47: 4. VALUATION RESULTS — 8 metodologías (live link to Modelo, post-merger pro-forma)
B48: Method | C48: Implied Price | D48: Upside vs spot $49.49
B49: 1. DCF Gordon Growth | C49: =Modelo!J55 -> 56.614972 | D49: =Modelo!J55/Hipotesis!$C$6-1 -> 0.14396791
B50: 2. DCF H-Model (fade) | C50: =Modelo!J56 -> 41.431648 | D50: =Modelo!J56/Hipotesis!$C$6-1 -> -0.16282788
B51: 3. DCF Exit EV/EBITDA | C51: =Modelo!J57 -> 47.97336 | D51: =Modelo!J57/Hipotesis!$C$6-1 -> -0.030645377
B52: 4. DCF Exit EV/EBIT | C52: =Modelo!J58 -> 55.043776 | D52: =Modelo!J58/Hipotesis!$C$6-1 -> 0.11222017
B53: 5. DCF Exit EV/Revenue | C53: =Modelo!J59 -> 28.016701 | D53: =Modelo!J59/Hipotesis!$C$6-1 -> -0.43389167
B54: 6. NTM P/E × FY27E EPS | C54: =Modelo!J60 -> 63.097471 | D54: =Modelo!J60/Hipotesis!$C$6-1 -> 0.27495395
B55: 7. NTM EV/EBITDA × FY27E EBITDA | C55: =Modelo!J61 -> 43.996962 | D55: =Modelo!J61/Hipotesis!$C$6-1 -> -0.11099288
B56: 8. NTM EV/Revenue × FY27E Revenue | C56: =Modelo!J62 -> 17.634856 | D56: =Modelo!J62/Hipotesis!$C$6-1 -> -0.6436683
B57: MEDIANA (target price central) | C57: =MEDIAN(C49:C56) -> 45.985161 | D57: =C57/Hipotesis!$C$6-1 -> -0.070819129
B58: Promedio (8 métodos) | C58: =AVERAGE(C49:C56) -> 44.226218 | D58: =C58/Hipotesis!$C$6-1 -> -0.10636051
B59: Rango Min – Max | C59: =TEXT(MIN(C49:C56),"$#,##0")&" – "&TEXT(MAX(C49:C56),"$#,##0") -> $18 – $63
B61: 5. INVESTMENT THESIS (resumen ejecutivo)
B62: Target price (mediana, sin descuento) | C62: =C57 -> 45.985161 | D62: vs spot $49.49: | E62: =C57/Hipotesis!$C$6-1 -> -0.070819129
B64: ▸ Devon (post-Coterra) cotiza a ~13.8× P/E TTM y ~5.0× EV/EBITDA pro-forma — consistente con el peer group E&P de gran capitalización (EOG ~10×, FANG ~5×, COP ~10×) en un punto bajo del ciclo del petróleo (WTI ~$60-65).
B65: ▸ La fusión con Coterra (cerrada 7-mayo-2026) añade ~767M shares, $7.7B revenue Marcellus-pesado, y diversifica la mezcla hacia gas natural. Pro-forma la producción es ~1,587 MBoe/d (Oil 33%, Gas 50%, NGL 17%), reduciendo la sensibilidad puntual al WTI vs DVN standalone.
B66: ▸ $1,000M de sinergias anuales pre-tax target (YE 2027 run-rate; 50% G&A, 50% capex/ops eficiencia). En la valoración asumimos ramp 40% año 1 y 100% año 2+, descontando crédito creciente del management.
B67: ▸ La tesis NO es de "compounder" — es de FCF mid-cycle. La operating margin colapsa en cíclos bajos (FY25: 22% vs FY22: 60%) por el apalancamiento operativo a precios de commodities. La pregunta clave es si el FCF normalizado a través del ciclo es atractivo.
B68: ▸ Capex split (clave para distinguir valor): asumimos ~85% maintenance / 15% growth en FY26E, transicionando a ~95/5% en terminal. El maintenance capex per Boe (~$10/Boe = F&D cost) es la métrica más relevante; debajo del histórico DVN ~$11-12/Boe sería bullish.
B69: ▸ Sensibilidades clave: cada +$5/Bbl en precio realizado del crudo ≈ ±$8 en precio objetivo. Cada +100bp WACC ≈ −$6 precio. Beta sectorial E&P 1.20 (Damodaran), no la 0.43 de Google que sub-estima riesgo cíclico.
B70: ▸ Tesis base: mediana 8 métodos = $45.99, ligero downside −7% vs spot $49.49. Rango amplio $17.63–$63.10 refleja la incertidumbre cíclica genuina. NO es "obvious buy": valor depende crucialmente del deck de precios y la ejecución del integration.
B72: Detalle metodológico en hojas Hipotesis, Historico, Modelo, DuPont_WC, Conclusiones. Fuentes en hoja Fuentes.

Sheet Hipotesis
B1: DVN — HIPOTESIS Y SUPUESTOS DE VALORACION (Pro-forma post-merger Devon+Coterra)
B2: LEYENDA: | C2: Input (hardcoded) | D2: Driver clave | E2: Formula | F2: Link a otra hoja | G2: Resultado/output
B4: 1. MERCADO Y COSTE DE CAPITAL
B5: Concepto | C5: Valor | D5: Fuente / Nota
B6: Spot price DVN ($) | C6: 49.49 | D6: Source: Devon IR investor relations page, 15-may-2026 EOD
B7: Diluted shares outstanding post-merger (M) | C7: 1153 | D7: Source: Merger close 5/7/2026 — 616M DVN + 0.70x × 767M CTRA = 1,153M combined
B8: Shares outstanding actual (M) | C8: 1153 | D8: Source: Post-merger; Google Finance/Robinhood show ~1.15B
B9: Risk-free rate (10Y UST, %) | C9: 0.045 | D9: Source: FRED DGS10, May-2026; ~4.5% mid-range
B10: Equity Risk Premium implícita (%) | C10: 0.045 | D10: Source: Damodaran ERP 2026 Edition, ene-2026, implied ERP S&P500
B11: Beta (5Y E&P sector) | C11: 1.2 | D11: Source: Damodaran sector betas E&P ~1.10-1.25; Google Finance DVN beta 0.43 (post-Coterra spike). Use sectorial 1.20
B12: Pre-tax cost of debt (%) | C12: 0.055 | D12: Source: DVN investment-grade BBB+; ~100bp spread over 10Y UST
B13: Effective tax rate (%) | C13: 0.22 | D13: Source: DVN 10-K FY24 21%, FY25 23% (state taxes + OBBB minimum); use 22% normalized
B14: Total Debt PRO-FORMA ($mm) | C14: 12200 | D14: Source: DVN Q1 2026 8-K $8,386M + Coterra FY25 ~$3,800M (post Tranche B paydown Feb-26)
B15: Cash + ST investments PRO-FORMA ($mm) | C15: 1930 | D15: Source: DVN Q1 2026 $1,815M cash + Coterra YE25 $114M = ~$1,930M
B16: Equity investments (Matterhorn, Catalyst, etc., $mm) | C16: 715 | D16: Source: DVN Q1 2026 8-K — Investments $715M (Matterhorn, Catalyst, Cotton Draw)
B18: WACC computado
B19: Cost of equity Ke = Rf + Beta × ERP | C19: =Hipotesis!$C$9 + Hipotesis!$C$11*Hipotesis!$C$10 -> 0.099
B20: After-tax cost of debt Kd = Kd*(1-T) | C20: =Hipotesis!$C$12 * (1 - Hipotesis!$C$13) -> 0.0429
B21: Market cap = Spot × Shares ($mm) | C21: =Hipotesis!$C$6 * Hipotesis!$C$8 -> 57061.97
B22: Total enterprise capital = MC + Debt | C22: =Hipotesis!$C$21 + Hipotesis!$C$14 -> 69261.97
B23: Weight equity E/V | C23: =Hipotesis!$C$21 / Hipotesis!$C$22 -> 0.82385716
B24: Weight debt D/V | C24: =Hipotesis!$C$14 / Hipotesis!$C$22 -> 0.17614284
B25: WACC = E/V × Ke + D/V × Kd*(1-T) | C25: =Hipotesis!$C$23*Hipotesis!$C$19 + Hipotesis!$C$24*Hipotesis!$C$20 -> 0.089118387
B28: 2. PROYECCION DE REVENUE — DESCOMPOSICION P × Q (Pro-forma Devon+Coterra)
B29: Segmento / Driver | C29: FY2026E | D29: FY2027E | E29: FY2028E | F29: FY2029E | G29: FY2030E | H29: Terminal
B30: S1 Oil production growth % | C30: 0.45 | D30: 0.03 | E30: 0.025 | F30: 0.02 | G30: 0.015 | H30: 0 | J30: Pro-forma jump FY26E reflects 11mo Coterra; then modest organic growth. Note: includes synergy production optimization
B31: S2 NGL production growth % | C31: 0.45 | D31: 0.04 | E31: 0.03 | F31: 0.025 | G31: 0.02 | H31: 0 | J31: NGL grows w/ Marcellus (Coterra) + Permian liquids-rich gas
B32: S3 Gas production growth % | C32: 2.15 | D32: 0.04 | E32: 0.03 | F32: 0.025 | G32: 0.02 | H32: 0 | J32: Gas dominated by Coterra Marcellus (~1,090 Bcf/yr). +215% reflects merger
B33: S1 Oil contribution margin % | C33: 0.4 | D33: 0.42 | E33: 0.43 | F33: 0.43 | G33: 0.43 | H33: 0.42 | J33: Oil delivers most of operating income. Margin sensitive to WTI; 40-43% normalized at $65 WTI base case
B34: S2 NGL contribution margin % | C34: 0.18 | D34: 0.2 | E34: 0.22 | F34: 0.22 | G34: 0.22 | H34: 0.2 | J34: NGL margin compressed by GP&T costs; Mont Belvieu pricing volatile
B35: S3 Gas contribution margin % | C35: 0.1 | D35: 0.15 | E35: 0.18 | F35: 0.2 | G35: 0.22 | H35: 0.2 | J35: Gas margin improves: Coterra Marcellus higher quality (premium netbacks); Permian basis improves w/ Matterhorn
B37: 3. CAPEX, D&A Y CAPITAL ALLOCATION
B38: Driver | C38: FY1E | D38: FY2E | E38: FY3E | F38: FY4E | G38: FY5E | H38: Terminal
B39: TOTAL Capex / Revenue % | C39: 0.225 | D39: 0.22 | E39: 0.215 | F39: 0.215 | G39: 0.215 | H39: 0.22 | J39: Total capex (maintenance + growth). DVN 22-24% of revenue historical 2023-2025. CTRA ~28% — combined ~22-23%
B40: D&A / Revenue % | C40: 0.155 | D40: 0.16 | E40: 0.16 | F40: 0.155 | G40: 0.155 | H40: 0.15 | J40: DD&A reflects depletion of oil & gas property; DVN FY25 ~21% rev. Combined includes Marcellus (lower DD&A intensity)
B41: SBC / Revenue % | C41: 0.005 | D41: 0.005 | E41: 0.005 | F41: 0.005 | G41: 0.005 | H41: 0.005 | J41: E&P SBC very small (~$100M/yr DVN, $30M CTRA)
B42: ΔWC / Revenue % | C42: 0.005 | D42: 0.003 | E42: 0 | F42: 0 | G42: 0 | H42: 0 | J42: E&P WC small; cyclical with price moves. Conservative ~0%
B43: Buybacks + Dividends / FCF % | C43: 0.65 | D43: 0.7 | E43: 0.7 | F43: 0.7 | G43: 0.7 | H43: 0.7 | J43: DVN announced $8B buyback + 30% div increase post-merger. Combined returns target 70%+ of FCF
B45: 4. VALORES TERMINALES (TV) Y CROSS-CHECKS
B46: Concepto | C46: Valor | D46: Justificación
B47: Terminal growth rate g (perpetuidad, %) | C47: 0.02 | D47: E&P is cyclical w/ depletable inventory. Conservative g (PIB nominal -1%). 2% reflects inflation pass-through
B48: H-Model: años fase alta (n) | C48: 5 | D48: Periodo de crecimiento explícito antes de fade lineal
B49: H-Model: g inicial (%) | C49: 0.05 | D49: Combined entity growth ~5% blended (production + price recovery); fade to 2%
B50: Exit EV/EBITDA múltiple (x) | C50: 5.5 | D50: E&P peers EOG/FANG/PR 5-7x; DVN historical 4-6x; CTRA ~5x. Conservative mid-cycle
B51: Exit EV/EBIT múltiple (x) | C51: 9 | D51: Implied at ~3x EV/EBITDA-to-EV/EBIT ratio for E&P (DD&A heavy)
B52: Exit EV/Revenue múltiple (x) | C52: 1.5 | D52: E&P low multiple: high capex intensity. Peers 1.2-1.8x
B53: Exit P/E (x) | C53: 12 | D53: E&P P/E typically 10-15x mid-cycle. DVN TTM ~13.8x
B54: FCF conversion normalizada | C54: 0.8 | D54: FCF/NI = 80% post-merger steady-state (Δ inventory neutral, low taxes deferred)
B56: 5. INVERSIONES ESTRATEGICAS (opcional — no afectan EV directamente)
B57: Sinergias anuales pre-tax target ($mm) | C57: 1000 | D57: Source: Devon/Coterra merger announcement 2/2/2026 — $1B pre-tax synergies annual by YE2027
B58: Sinergias ramp factor año 1 (%) | C58: 0.4 | D58: FY26E captures ~40% of target ($400M); full run-rate by FY27
B59: $8B authorized buyback (post-merger announcement) | C59: 8000 | D59: Source: DVN press release 5/7/2026; $8B Board authorization, ~14% of market cap
B62: 2B. REALIZED PRICES ($/unit) — Pro-forma combined entity
B63: Driver | C63: FY2026E | D63: FY2027E | E63: FY2028E | F63: FY2029E | G63: FY2030E | H63: Terminal
B64: Oil realized price ($/Bbl) | C64: 67 | D64: 64 | E64: 63 | F64: 62 | G64: 62 | H64: 62 | J64: Base case: WTI mean-revert to $65 mid-cycle; DVN basis differential ~-$2.50; Coterra Permian similar; conservative vs Q1 26 spot
B65: Gas realized price ($/Mcf) | C65: 2.2 | D65: 2.4 | E65: 2.6 | F65: 2.7 | G65: 2.8 | H65: 2.8 | J65: Combined entity benefits from Marcellus (basis ~$0.30 below NYMEX) mix; Permian basis improves with Matterhorn capacity
B66: NGL realized price ($/Bbl) | C66: 19 | D66: 19.5 | E66: 20 | F66: 20 | G66: 20.5 | H66: 20.5 | J66: Mont Belvieu blended ~$24-25; DVN realization 70-75% of benchmark
B68: Memo: WTI benchmark ($/Bbl) | C68: 69.5 | D68: 66.5 | E68: 65 | F68: 64.5 | G68: 64.5 | H68: 64.5 | J68: EIA STEO forecast May-2026; long-run mid-cycle $60-70
B69: Memo: Henry Hub ($/MMBtu) | C69: 4.2 | D69: 4.3 | E69: 4.4 | F69: 4.3 | G69: 4.3 | H69: 4.3 | J69: EIA STEO; LNG export growth keeps HH structurally higher than 2020-24
B71: 2C. CAPEX SPLIT — Maintenance vs Growth
B72: Driver | C72: FY2026E | D72: FY2027E | E72: FY2028E | F72: FY2029E | G72: FY2030E | H72: Terminal
B73: Maintenance capex / Total capex % | C73: 0.85 | D73: 0.82 | E73: 0.85 | F73: 0.88 | G73: 0.9 | H73: 0.95 | J73: E&P maintenance capex (= keep production flat). Higher % as inventory matures
B74: Growth capex / Total capex % | C74: =1-C73 -> 0.15 | D74: =1-D73 -> 0.18 | E74: =1-E73 -> 0.15 | F74: =1-F73 -> 0.12 | G74: =1-G73 -> 0.1 | H74: =1-H73 -> 0.05 | J74: Growth capex enables production increases (drilling new wells in undeveloped acreage)
B75: Maintenance capex $/Boe (~F&D cost) | C75: 10 | D75: 10.2 | E75: 10.4 | F75: 10.6 | G75: 10.8 | H75: 11 | J75: DVN F&D cost FY25 ~$8.5/Boe per 10-K. Combined slightly higher due to mix. Conservative ramp

Sheet Historico
B1: DVN — HISTORICO FINANCIERO (FY2021 a FY2025 + Q1 2026)
B2: LEYENDA: | C2: Input (hardcoded) | D2: Cálculo (margen/growth) | E2: Inline ratio
B4: $ millions | C4: FY2021 | D4: FY2022 | E4: FY2023 | F4: FY2024 | G4: FY2025 | H4: Q1 2026
B5: A. CUENTA DE RESULTADOS ($mm except per-share)
B6: Total Revenue | C6: 12206 | D6: 19169 | E6: 15258 | F6: 15938 | G6: 17188 | H6: 3807 | I6: Source: DVN 10-K FY21-FY25 Consolidated Statements of Operations; DVN 8-K Q1 2026 (5/5/2026)
B7: Revenue YoY % | C7: n/a | D7: =D6/C6-1 -> 0.57045715 | E7: =E6/D6-1 -> -0.20402734 | F7: =F6/E6-1 -> 0.044566785 | G7: =G6/F6-1 -> 0.078428912 | H7: ytd | I7: CAGR FY21-FY25 ≈ 13.8%
B8: Production expenses | C8: 1473 | D8: 2098 | E8: 2476 | F8: 2891 | G8: 3567 | H8: 894 | I8: Source: DVN 10-K — LOE + G,P&T + Production taxes + Property taxes
B9: Production expense / Revenue % | C9: =C8/C6 -> 0.12067835 | D9: =D8/D6 -> 0.10944755 | E9: =E8/E6 -> 0.16227553 | F9: =F8/F6 -> 0.18139039 | G9: =G8/G6 -> 0.20752851 | H9: =H8/H6 -> 0.23483058 | I9: Sube con declive de precios realizados y mix; FY25 20.8% por oil price weak
B10: Marketing & midstream expenses | C10: 2032 | D10: 2856 | E10: 3855 | F10: 4377 | G10: 5635 | H10: 1547 | I10: Source: DVN 10-K — third-party gas/NGL marketing (effectively pass-through)
B11: M&M expenses / Revenue % | C11: =C10/C6 -> 0.1664755 | D11: =D10/D6 -> 0.14899056 | E11: =E10/E6 -> 0.25265435 | F11: =F10/F6 -> 0.27462668 | G11: =G10/G6 -> 0.32784501 | H11: =H10/H6 -> 0.40635671 | I11: 69-70% [Plataforma cloud] GM en Último trimestre
B12: Depreciation, depletion & amortization (DD&A) | C12: 1763 | D12: 2230 | E12: 2585 | F12: 2810 | G12: 3595 | H12: 904 | I12: Source: DVN 10-K Cash Flow Statement DD&A line
B13: DD&A / Revenue % | C13: =C12/C6 -> 0.14443716 | D13: =D12/D6 -> 0.11633366 | E13: =E12/E6 -> 0.16941932 | F13: =F12/F6 -> 0.17630819 | G13: =G12/G6 -> 0.20915755 | H13: =H12/H6 -> 0.23745732 | I13: Estable ~12% — leverage del modelo
B14: General & administrative (G&A) | C14: 285 | D14: 366 | E14: 397 | F14: 484 | G14: 492 | H14: 125 | I14: Source: DVN 10-K — G&A line
B15: G&A / Revenue % | C15: =C14/C6 -> 0.023349173 | D15: =D14/D6 -> 0.019093328 | E15: =E14/E6 -> 0.026019138 | F15: =F14/F6 -> 0.030367675 | G15: =G14/G6 -> 0.028624622 | H15: =H14/H6 -> 0.032834253 | I15: Bajando con scale (de 12% → 9%)
B16: Exploration, impairments, restructuring & other | C16: 25 | D16: 64 | E16: 49 | F16: 67 | G16: 65 | H16: 62 | I16: Source: DVN 10-K — Exploration + Impairments + Restructuring + Other
B17: Exploration & other / Revenue % | C17: =C16/C6 -> 0.002048173 | D17: =D16/D6 -> 0.003338724 | E17: =E16/E6 -> 0.0032114301 | F17: =F16/F6 -> 0.0042037897 | G17: =G16/G6 -> 0.0037817082 | H17: =H16/H6 -> 0.016285789 | I17: ~3% estable
B18: Operating income | C18: =C6-C8-C10-C12-C14-C16 -> 6628 | D18: =D6-D8-D10-D12-D14-D16 -> 11555 | E18: =E6-E8-E10-E12-E14-E16 -> 5896 | F18: =F6-F8-F10-F12-F14-F16 -> 5309 | G18: =G6-G8-G10-G12-G14-G16 -> 3834 | H18: =H6-H8-H10-H12-H14-H16 -> 275 | I18: Operating income (calculated bottoms-up)
B19: Operating margin % | C19: =C18/C6 -> 0.54301163 | D19: =D18/D6 -> 0.60279618 | E19: =E18/E6 -> 0.38642024 | F19: =F18/F6 -> 0.33310328 | G19: =G18/G6 -> 0.2230626 | H19: =H18/H6 -> 0.072235356 | I19: 📉 60% (FY22 cíclo alto) → 22% (FY25 cíclo bajo) — apalancamiento operativo a commodities
B20: Op income YoY % | C20: n/a | D20: =D18/C18-1 -> 0.7433615 | E20: =E18/D18-1 -> -0.4897447 | F20: =F18/E18-1 -> -0.099559023 | G20: =G18/F18-1 -> -0.2778301 | H20: ytd
B21: Financing costs, net (interest) | C21: 247 | D21: 220 | E21: 295 | F21: 369 | G21: 475 | H21: 109 | I21: Source: DVN 10-K — Financing costs, net (interest expense less interest income)
B22: Earnings before income taxes | C22: =C18-C21 -> 6381 | D22: =D18-D21 -> 11335 | E22: =E18-E21 -> 5601 | F22: =F18-F21 -> 4940 | G22: =G18-G21 -> 3359 | H22: =H18-H21 -> 166
B23: Income tax expense | C23: 588 | D23: 1364 | E23: 858 | F23: 619 | G23: 785 | H23: 46 | I23: Source: DVN 10-K — Income tax expense (Note: includes deferred)
B24: Effective tax rate | C24: =C23/C22 -> 0.092148566 | D24: =D23/D22 -> 0.12033524 | E24: =E23/E22 -> 0.15318693 | F24: =F23/F22 -> 0.12530364 | G24: =G23/G22 -> 0.23370051 | H24: =H23/H22 -> 0.27710843 | I24: 18% FY24-FY25, ligero uptick Último trimestre
B25: Net earnings attributable to Devon | C25: 2813 | D25: 6015 | E25: 3747 | F25: 2891 | G25: 2642 | H25: 120 | I25: Source: DVN 10-K — Net earnings attributable to Devon; FY25=$2,681M per 10-K (small diff from sum due to NCI)
B26: Net margin % | C26: =C25/C6 -> 0.23046043 | D26: =D25/D6 -> 0.31378789 | E26: =E25/E6 -> 0.24557609 | F26: =F25/F6 -> 0.18139039 | G26: =G25/G6 -> 0.15371189 | H26: =H25/H6 -> 0.031520883 | I26: ~36% — quality of earnings alto
B27: Net income YoY % | C27: n/a | D27: =D25/C25-1 -> 1.1382865 | E27: =E25/D25-1 -> -0.37705736 | F27: =F25/E25-1 -> -0.22844943 | G27: =G25/F25-1 -> -0.086129367 | H27: ytd
B28: Diluted EPS ($) | C28: 4.18 | D28: 9.23 | E28: 5.81 | F28: 4.55 | G28: 4.19 | H28: 0.19 | I28: Source: DVN 10-K — Diluted EPS attributable to Devon
B29: Diluted EPS YoY % | C29: n/a | D29: =D28/C28-1 -> 1.208134 | E29: =E28/D28-1 -> -0.37053088 | F29: =F28/E28-1 -> -0.21686747 | G29: =G28/F28-1 -> -0.079120879 | H29: ytd | I29: Buybacks ayudan ~50bp/año al EPS growth
B30: Diluted shares outstanding (M) | C30: 675 | D30: 652 | E30: 645 | F30: 636 | G30: 631 | H30: 618 | I30: Source: DVN 10-K cover and 10-Q diluted weighted-avg shares
B32: B. CASH FLOW ($mm)
B33: Net cash from operations (OCF) | C33: 4899 | D33: 8538 | E33: 6498 | F33: 6906 | G33: 6711 | H33: 1655 | I33: Source: DVN 10-K Cash Flow Statement; Q1 26 from 8-K supplemental table
B34: OCF / Revenue % | C34: =C33/C6 -> 0.40135999 | D34: =D33/D6 -> 0.44540665 | E34: =E33/E6 -> 0.42587495 | F34: =F33/F6 -> 0.43330405 | G34: =G33/G6 -> 0.39044682 | H34: =H33/H6 -> 0.43472551 | I34: ~48% — cash conversion alta
B35: OCF YoY % | C35: n/a | D35: =D33/C33-1 -> 0.74280465 | E35: =E33/D33-1 -> -0.23893183 | F35: =F33/E33-1 -> 0.06278855 | G35: =G33/F33-1 -> -0.028236316 | H35: ytd
B36: Capex (excl. acquisitions) | C36: 1971 | D36: 2517 | E36: 3766 | F36: 3713 | G36: 3713 | H36: 848 | I36: Source: DVN 10-K CF Statement — Capital expenditures (excl. acquisitions)
B37: Capex / Revenue % | C37: =C36/C6 -> 0.16147796 | D37: =D36/D6 -> 0.13130575 | E37: =E36/E6 -> 0.24682134 | F37: =F36/F6 -> 0.23296524 | G37: =G36/G6 -> 0.21602281 | H37: =H36/H6 -> 0.22274757 | I37: ~13-25% Capex/Rev — cíclico, sube cuando revenue cae por precios bajos
B38: Capex YoY % | C38: n/a | D38: =D36/C36-1 -> 0.27701674 | E38: =E36/D36-1 -> 0.49622567 | F38: =F36/E36-1 -> -0.014073287 | G38: =G36/F36-1 -> 0 | H38: ytd | I38: +213% acumulado FY21-FY25
B39: FCF simple = OCF − Capex | C39: =C33-C36 -> 2928 | D39: =D33-D36 -> 6021 | E39: =E33-E36 -> 2732 | F39: =F33-F36 -> 3193 | G39: =G33-G36 -> 2998 | H39: =H33-H36 -> 807
B40: FCF / Revenue % | C40: =C39/C6 -> 0.23988203 | D40: =D39/D6 -> 0.31410089 | E40: =E39/E6 -> 0.17905361 | F40: =F39/F6 -> 0.20033881 | G40: =G39/G6 -> 0.17442402 | H40: =H39/H6 -> 0.21197794 | I40: Bajando 33% → 25% por capex inversión
B41: FCF / Net Income % | C41: =C39/C25 -> 1.0408816 | D41: =D39/D25 -> 1.0009975 | E41: =E39/E25 -> 0.72911663 | F41: =F39/F25 -> 1.1044621 | G41: =G39/G25 -> 1.1347464 | H41: =H39/H25 -> 6.725 | I41: <70% confirma que la depreciación NO captura todo el outflow
B42: FCF YoY % | C42: n/a | D42: =D39/C39-1 -> 1.0563525 | E42: =E39/D39-1 -> -0.54625477 | F42: =F39/E39-1 -> 0.16874085 | G42: =G39/F39-1 -> -0.061071093 | H42: ytd
B43: D&A (CF statement, =IS DD&A) | C43: =C12 -> 1763 | D43: =D12 -> 2230 | E43: =E12 -> 2585 | F43: =F12 -> 2810 | G43: =G12 -> 3595 | H43: =H12 -> 904
B44: D&A / Revenue % | C44: =C43/C6 -> 0.14443716 | D44: =D43/D6 -> 0.11633366 | E44: =E43/E6 -> 0.16941932 | F44: =F43/F6 -> 0.17630819 | G44: =G43/G6 -> 0.20915755 | H44: =H43/H6 -> 0.23745732 | I44: Subiendo con el capex (lag de 2-3 años)
B45: Stock-based compensation (SBC) | C45: 70 | D45: 78 | E45: 85 | F45: 105 | G45: 99 | H45: 22 | I45: Source: DVN 10-K CF Statement — Share-based compensation
B46: SBC / Revenue % | C46: =C45/C6 -> 0.0057348845 | D46: =D45/D6 -> 0.0040690699 | E46: =E45/E6 -> 0.0055708481 | F46: =F45/F6 -> 0.0065880286 | G46: =G45/G6 -> 0.0057598324 | H46: =H45/H6 -> 0.0057788285 | I46: Estable ~4%
B47: Dividends paid | C47: 691 | D47: 2868 | E47: 2017 | F47: 596 | G47: 619 | H47: 155 | I47: Source: DVN 10-K — Dividends paid (fixed-plus-variable until 2024, then fixed-only)
B48: Common stock repurchased | C48: 590 | D48: 1216 | E48: 691 | F48: 715 | G48: 1050 | H48: 69 | I48: Source: DVN 10-K — Repurchases of common stock
B49: Capital returns total ($mm) | C49: =C47+C48 -> 1281 | D49: =D47+D48 -> 4084 | E49: =E47+E48 -> 2708 | F49: =F47+F48 -> 1311 | G49: =G47+G48 -> 1669 | H49: =H47+H48 -> 224
B50: Capital returns / FCF % | C50: =C49/C39 -> 0.4375 | D50: =D49/D39 -> 0.67829264 | E50: =E49/E39 -> 0.99121523 | F50: =F49/F39 -> 0.41058566 | G50: =G49/G39 -> 0.55670447 | H50: =H49/H39 -> 0.27757125 | I50: ~70-80%, sostenible
B52: C. BALANCE SHEET (fin de periodo)
B53: Cash, equivalents & restricted cash | C53: 2268 | D53: 1454 | E53: 875 | F53: 846 | G53: 1434 | H53: 1815 | I53: Source: DVN 10-K Balance Sheet — Cash + ST investments + restricted cash
B54: Investments (Matterhorn, Catalyst, etc.) | C54: 200 | D54: 280 | E54: 510 | F54: 712 | G54: 727 | H54: 715 | I54: Source: DVN 10-K Balance Sheet — Investments (Matterhorn, Catalyst, Cotton Draw)
B55: Accounts receivable, net | C55: 1565 | D55: 2102 | E55: 1740 | F55: 2225 | G55: 1792 | H55: 2250
B56: Total property and equipment, net | C56: 15263 | D56: 14914 | E56: 16906 | F56: 25025 | G56: 25419 | H56: 25598 | I56: Source: DVN 10-K — Oil & gas property + Other PP&E, net (successful efforts accounting)
B57: Goodwill + intangibles + ROU | C57: 800 | D57: 800 | E57: 800 | F57: 1015 | G57: 1052 | H57: 1065
B58: Total assets | C58: 21025 | D58: 23721 | E58: 23943 | F58: 30904 | G58: 31599 | H58: 32543 | I58: Source: DVN 10-K Balance Sheet — Total assets
B59: Total debt (short-term + long-term) | C59: 6531 | D59: 6452 | E59: 6149 | F59: 8880 | G59: 8389 | H59: 8386 | I59: Source: DVN 10-K BS — Short-term + Long-term debt
B60: Stockholders' equity (attributable to DVN) | C60: 7188 | D60: 8662 | E60: 9214 | F60: 13988 | G60: 15528 | H60: 15428 | I60: Source: DVN 10-K BS — Total stockholders equity attributable to Devon
B61: Common stock + Additional paid-in capital | C61: 4150 | D61: 3990 | E61: 3540 | F61: 6438 | G61: 5450 | H61: 5378
B62: Retained earnings | C62: 3145 | D62: 4790 | E62: 5790 | F62: 7674 | G62: 10200 | H62: 10171
B63: Asset retirement obligations + Other LT liab. | C63: 1500 | D63: 1600 | E63: 1700 | F63: 1850 | G63: 1770 | H63: 1926
B64: Proved reserves (MMBoe) | C64: 1597 | D64: 1839 | E64: 1825 | F64: 2210 | G64: 2428 | H64: n/d | I64: Source: DVN 10-K Item 1 Proved Reserves disclosure
B66: Capital structure / leverage
B67: Net cash position ($mm) | C67: =C53-C59 -> -4263 | D67: =D53-D59 -> -4998 | E67: =E53-E59 -> -5274 | F67: =F53-F59 -> -8034 | G67: =G53-G59 -> -6955 | H67: =H53-H59 -> -6571
B68: Debt / Equity (x) | C68: =C59/C60 -> 0.90859766 | D68: =D59/D60 -> 0.74486262 | E68: =E59/E60 -> 0.66735403 | F68: =F59/F60 -> 0.63482985 | G68: =G59/G60 -> 0.54024987 | H68: =H59/H60 -> 0.54355717 | I68: Desapalancando: 0.55 → 0.10
B69: PP&E / Revenue % | C69: =C56/C6 -> 1.2504506 | D69: =D56/D6 -> 0.77802702 | E69: =E56/E6 -> 1.1080089 | F69: =F56/F6 -> 1.5701468 | G69: =G56/G6 -> 1.4788806 | H69: =H56/H6 -> 6.7239296 | I69: PP&E pesado: E&P es capital-intensive estructuralmente (full-cost / successful-efforts)
B70: Asset turnover (Rev / Avg Assets, proxy con end-of-period) | C70: =C6/C58 -> 0.58054697 | D70: =D6/D58 -> 0.80810253 | E70: =E6/E58 -> 0.6372635 | F70: =F6/F58 -> 0.51572612 | G70: =G6/G58 -> 0.54394126 | H70: =H6/H58 -> 0.11698368 | I70: Asset turnover ~0.5-0.7× — típico E&P; baja en cíclos de precios bajos
B72: D. REVENUE BY COMMODITY (P × Q decomposition)
B73: (Oil + Gas + NGL = Upstream revenue. Marketing & midstream is largely pass-through.)
B74: Oil sales revenue ($mm) | C74: 6112 | D74: 10103 | E74: 8870 | F74: 9347 | G74: 8906 | H74: 2461 | I74: Source: DVN 10-K Note Revenue Recognition — Oil sales (= Oil production × Oil realized price)
B75: Natural gas sales revenue ($mm) | C75: 1138 | D75: 1840 | E75: 695 | F75: 397 | G75: 842 | H75: 205 | I75: Source: DVN 10-K — Gas sales (= Gas production × Gas realized price)
B76: NGL sales revenue ($mm) | C76: 1496 | D76: 1853 | E76: 1212 | F76: 1407 | G76: 1475 | H76: 349 | I76: Source: DVN 10-K — NGL sales (= NGL production × NGL realized price)
B77: Memo: Marketing & midstream revenue | C77: 2017 | D77: 2914 | E77: 4072 | F77: 4413 | G77: 5563 | H77: 1531 | I77: Pass-through: revenues ≈ expenses. Small margin contribution. Excluded from P×Q.
B78: Memo: Oil, gas, NGL derivative gain/(loss) | C78: -2700 | D78: -2030 | E78: 305 | F78: 365 | G78: 161 | H78: -701 | I78: Excluded from operating performance — MTM volatility
B79: Field-level cash margin ($mm = production × per-Boe margin) | C79: =C74+C75+C76-C8 -> 7273 | D79: =D74+D75+D76-D8 -> 11698 | E79: =E74+E75+E76-E8 -> 8301 | F79: =F74+F75+F76-F8 -> 8260 | G79: =G74+G75+G76-G8 -> 7656 | H79: =H74+H75+H76-H8 -> 2121 | I79: Upstream cash margin = O/G/NGL revenue − Production expenses
B81: Margen operativo por segmento
B82: E. KPIs — PRODUCTION VOLUMES & REALIZED PRICES (10-K Item 1/Item 7) | C82: n/d | D82: n/d | E82: n/d | F82: =IFERROR(F77/F74,"n/d") -> 0.4721301 | G82: =IFERROR(G77/G74,"n/d") -> 0.62463508 | H82: n/d
B83: Oil production (MMBbls) | C83: 106 | D83: 109 | E83: 117 | F83: 127 | G83: 142 | H83: 35 | I83: Source: DVN 10-K — Oil production volumes; 2021/22 derived from MBbls/d × 365
B84: Gas production (Bcf) | C84: 325 | D84: 356 | E84: 385 | F84: 438 | G84: 505 | H84: 125 | I84: Source: DVN 10-K — Gas production volumes
B85: NGL production (MMBbls) | C85: 49 | D85: 54 | E85: 59 | F85: 70 | G85: 81 | H85: 20 | I85: Source: DVN 10-K — NGL production volumes
B86: Total production (MMBoe) = Oil + NGL + Gas/6 | C86: =C83+C85+C84/6 -> 209.16667 | D86: =D83+D85+D84/6 -> 222.33333 | E86: =E83+E85+E84/6 -> 240.16667 | F86: =F83+F85+F84/6 -> 270 | G86: =G83+G85+G84/6 -> 307.16667 | H86: =H83+H85+H84/6 -> 75.833333 | I86: BoE conversion: 6 Mcf gas per Bbl oil; NGL 1:1 with oil
B87: S1 revenue YoY % | C87: n/d | D87: n/d | E87: n/d | F87: n/a | G87: =IFERROR(G74/F74-1,"n/d") -> -0.047180914 | H87: ytd
B88: Oil realized price ($/Bbl) | C88: 57.59 | D88: 92.85 | E88: 75.98 | F88: 73.78 | G88: 62.77 | H88: 69.66 | I88: Source: DVN 10-K — Oil average sales price (excl. hedges)
B89: Gas realized price ($/Mcf) | C89: 3.5 | D89: 5.17 | E89: 1.83 | F89: 0.91 | G89: 1.67 | H89: 1.66 | I89: Source: DVN 10-K — Gas average sales price (excl. hedges); large Permian basis differential vs Henry Hub
B90: NGL realized price ($/Bbl) | C90: 30.8 | D90: 34.05 | E90: 20.48 | F90: 20.2 | G90: 18.28 | H90: 17.8 | I90: Source: DVN 10-K — NGL average sales price (excl. hedges)
B92: Memo: WTI benchmark ($/Bbl, average) | C92: 67.91 | D92: 94.33 | E92: 77.62 | F92: 75.79 | G92: 64.87 | H92: 72.1 | I92: Source: EIA STEO; DVN 10-K benchmark prices
B93: Memo: Henry Hub benchmark ($/MMBtu, average) | C93: 3.89 | D93: 6.45 | E93: 2.54 | F93: 2.2 | G93: 3.43 | H93: 5.05 | I93: Source: EIA Henry Hub spot annual average
B94: Memo: Total production growth YoY (Boe)
B95: Production cost per Boe ($/Boe) | C95: =C8/C86 -> 7.0422311 | D95: =D8/D86 -> 9.4362819 | E95: =E8/E86 -> 10.309507 | F95: =F8/F86 -> 10.707407 | G95: =G8/G86 -> 11.612588 | H95: =H8/H86 -> 11.789011 | I95: Production expenses / total MMBoe production
B96: Capex per Boe of production ($/Boe) | C96: =C36/C86 -> 9.4231076 | D96: =D36/D86 -> 11.32084 | E96: =E36/E86 -> 15.680777 | F96: =F36/F86 -> 13.751852 | G96: =G36/G86 -> 12.0879 | H96: =H36/H86 -> 11.182418 | I96: Capital intensity — total capex / total annual production
B97: Memo: Mont Belvieu NGL benchmark ($/Bbl)
B98: Memo: pro-forma combined production (post-merger) | C98: ~1,587 MBoe/d (Oil 530, Gas 4,400 MMcf/d, NGL 315) — FY26E run-rate
B99: Memo: Devon/Coterra merger close | C99: 7-may-2026 (0.70 DVN per CTRA share)
B100: Memo: $8B buyback authorization (post-merger) | C100: $8,000M autorizado
B101: Guía capex FY2026 (combined, post-merger) | C101: ~$4.0-4.4Bn pro-forma (mantenimiento-pesado, disciplina de capital)
B102: Guía producción FY2026 (combined) | C102: ~1,580-1,600 MBoe/d run-rate combinado
B103: Sinergias target run-rate (YE2027) | C103: $1,000M anuales pre-tax (50% G&A, 50% capex/ops)
B104: Capital returns framework | C104: Dividendo fijo $0.24/sh trim. + $8Bn buyback autorizado
B105: Net Debt / EBITDA target (combined) | C105: ~1.4× post-merger, target <1.0× through-cycle

Sheet Modelo
B1: DVN — MODELO OPERATIVO + FCFF + VALORACION (Pro-forma post-merger, FY26-FY30 + Terminal)
B2: LEYENDA: | C2: Input (azul) | D2: Cálculo (negro) | E2: Inline ratio | F2: Total (negrita) | G2: Terminal
B4: $ millions | C4: FY2026E | D4: FY2027E | E4: FY2028E | F4: FY2029E | G4: FY2030E | H4: Terminal
L5: Tabla A — Precio (Gordon DCF) vs WACC × g_terminal
B6: A. PROYECCION DE INGRESOS POR SEGMENTO
B7: S1 Oil revenue ($mm) | C7: =(Historico!G83*(1+Hipotesis!C30))*Hipotesis!C64 -> 13795.3 | D7: =(Historico!G83*(1+Hipotesis!C30)*(1+Hipotesis!D30))*Hipotesis!D64 -> 13572.928 | E7: =(Historico!G83*(1+Hipotesis!C30)*(1+Hipotesis!D30)*(1+Hipotesis!E30))*Hipotesis!E64 -> 13694.872 | F7: =(Historico!G83*(1+Hipotesis!C30)*(1+Hipotesis!D30)*(1+Hipotesis!E30)*(1+Hipotesis!F30))*Hipotesis!F64 -> 13747.043 | G7: =(Historico!G83*(1+Hipotesis!C30)*(1+Hipotesis!D30)*(1+Hipotesis!E30)*(1+Hipotesis!F30)*(1+Hipotesis!G30))*Hipotesis!G64 -> 13953.249 | H7: =(Historico!G83*(1+Hipotesis!C30)*(1+Hipotesis!D30)*(1+Hipotesis!E30)*(1+Hipotesis!F30)*(1+Hipotesis!G30)*(1+Hipotesis!H30))*Hipotesis!H64 -> 13953.249 | L7: WACC ↓ \ g → | M7: 0.02 | N7: 0.025 | O7: 0.03 | P7: 0.035 | Q7: 0.04
B8: Oil production (MMBbls) | C8: =Historico!G83*(1+Hipotesis!C30) -> 205.9 | D8: =C8*(1+Hipotesis!D30) -> 212.077 | E8: =D8*(1+Hipotesis!E30) -> 217.37893 | F8: =E8*(1+Hipotesis!F30) -> 221.7265 | G8: =F8*(1+Hipotesis!G30) -> 225.0524 | H8: =G8*(1+Hipotesis!H30) -> 225.0524 | L8: 0.075 | M8: =((C36/(1+$L$8)^0.5 + D36/(1+$L$8)^1.5 + E36/(1+$L$8)^2.5 + F36/(1+$L$8)^3.5 + G36/(1+$L$8)^4.5)+(G36*(1+M$7)/($L$8-M$7))/(1+$L$8)^5+Hipotesis!$C$15+Hipotesis!$C$16-Hipotesis!$C$14)/Hipotesis!$C$8 -> 70.817653 | N8: =((C36/(1+$L$8)^0.5 + D36/(1+$L$8)^1.5 + E36/(1+$L$8)^2.5 + F36/(1+$L$8)^3.5 + G36/(1+$L$8)^4.5)+(G36*(1+N$7)/($L$8-N$7))/(1+$L$8)^5+Hipotesis!$C$15+Hipotesis!$C$16-Hipotesis!$C$14)/Hipotesis!$C$8 -> 77.288819 | O8: =((C36/(1+$L$8)^0.5 + D36/(1+$L$8)^1.5 + E36/(1+$L$8)^2.5 + F36/(1+$L$8)^3.5 + G36/(1+$L$8)^4.5)+(G36*(1+O$7)/($L$8-O$7))/(1+$L$8)^5+Hipotesis!$C$15+Hipotesis!$C$16-Hipotesis!$C$14)/Hipotesis!$C$8 -> 85.198023 | P8: =((C36/(1+$L$8)^0.5 + D36/(1+$L$8)^1.5 + E36/(1+$L$8)^2.5 + F36/(1+$L$8)^3.5 + G36/(1+$L$8)^4.5)+(G36*(1+P$7)/($L$8-P$7))/(1+$L$8)^5+Hipotesis!$C$15+Hipotesis!$C$16-Hipotesis!$C$14)/Hipotesis!$C$8 -> 95.084527 | Q8: =((C36/(1+$L$8)^0.5 + D36/(1+$L$8)^1.5 + E36/(1+$L$8)^2.5 + F36/(1+$L$8)^3.5 + G36/(1+$L$8)^4.5)+(G36*(1+Q$7)/($L$8-Q$7))/(1+$L$8)^5+Hipotesis!$C$15+Hipotesis!$C$16-Hipotesis!$C$14)/Hipotesis!$C$8 -> 107.79575
B9: Oil realized price ($/Bbl) | C9: =Hipotesis!C64 -> 67 | D9: =Hipotesis!D64 -> 64 | E9: =Hipotesis!E64 -> 63 | F9: =Hipotesis!F64 -> 62 | G9: =Hipotesis!G64 -> 62 | H9: =Hipotesis!H64 -> 62 | L9: 0.085 | M9: =((C36/(1+$L$9)^0.5 + D36/(1+$L$9)^1.5 + E36/(1+$L$9)^2.5 + F36/(1+$L$9)^3.5 + G36/(1+$L$9)^4.5)+(G36*(1+M$7)/($L$9-M$7))/(1+$L$9)^5+Hipotesis!$C$15+Hipotesis!$C$16-Hipotesis!$C$14)/Hipotesis!$C$8 -> 58.613157 | N9: =((C36/(1+$L$9)^0.5 + D36/(1+$L$9)^1.5 + E36/(1+$L$9)^2.5 + F36/(1+$L$9)^3.5 + G36/(1+$L$9)^4.5)+(G36*(1+N$7)/($L$9-N$7))/(1+$L$9)^5+Hipotesis!$C$15+Hipotesis!$C$16-Hipotesis!$C$14)/Hipotesis!$C$8 -> 63.010249 | O9: =((C36/(1+$L$9)^0.5 + D36/(1+$L$9)^1.5 + E36/(1+$L$9)^2.5 + F36/(1+$L$9)^3.5 + G36/(1+$L$9)^4.5)+(G36*(1+O$7)/($L$9-O$7))/(1+$L$9)^5+Hipotesis!$C$15+Hipotesis!$C$16-Hipotesis!$C$14)/Hipotesis!$C$8 -> 68.206812 | P9: =((C36/(1+$L$9)^0.5 + D36/(1+$L$9)^1.5 + E36/(1+$L$9)^2.5 + F36/(1+$L$9)^3.5 + G36/(1+$L$9)^4.5)+(G36*(1+P$7)/($L$9-P$7))/(1+$L$9)^5+Hipotesis!$C$15+Hipotesis!$C$16-Hipotesis!$C$14)/Hipotesis!$C$8 -> 74.442688 | Q9: =((C36/(1+$L$9)^0.5 + D36/(1+$L$9)^1.5 + E36/(1+$L$9)^2.5 + F36/(1+$L$9)^3.5 + G36/(1+$L$9)^4.5)+(G36*(1+Q$7)/($L$9-Q$7))/(1+$L$9)^5+Hipotesis!$C$15+Hipotesis!$C$16-Hipotesis!$C$14)/Hipotesis!$C$8 -> 82.064315
B10: S2 NGL revenue ($mm) | C10: =(Historico!G85*(1+Hipotesis!C31))*Hipotesis!C66 -> 2231.55 | D10: =(Historico!G85*(1+Hipotesis!C31)*(1+Hipotesis!D31))*Hipotesis!D66 -> 2381.886 | E10: =(Historico!G85*(1+Hipotesis!C31)*(1+Hipotesis!D31)*(1+Hipotesis!E31))*Hipotesis!E66 -> 2516.2488 | F10: =(Historico!G85*(1+Hipotesis!C31)*(1+Hipotesis!D31)*(1+Hipotesis!E31)*(1+Hipotesis!F31))*Hipotesis!F66 -> 2579.155 | G10: =(Historico!G85*(1+Hipotesis!C31)*(1+Hipotesis!D31)*(1+Hipotesis!E31)*(1+Hipotesis!F31)*(1+Hipotesis!G31))*Hipotesis!G66 -> 2696.5066 | H10: =(Historico!G85*(1+Hipotesis!C31)*(1+Hipotesis!D31)*(1+Hipotesis!E31)*(1+Hipotesis!F31)*(1+Hipotesis!G31)*(1+Hipotesis!H31))*Hipotesis!H66 -> 2696.5066 | L10: 0.089 | M10: =((C36/(1+$L$10)^0.5 + D36/(1+$L$10)^1.5 + E36/(1+$L$10)^2.5 + F36/(1+$L$10)^3.5 + G36/(1+$L$10)^4.5)+(G36*(1+M$7)/($L$10-M$7))/(1+$L$10)^5+Hipotesis!$C$15+Hipotesis!$C$16-Hipotesis!$C$14)/Hipotesis!$C$8 -> 54.727004 | N10: =((C36/(1+$L$10)^0.5 + D36/(1+$L$10)^1.5 + E36/(1+$L$10)^2.5 + F36/(1+$L$10)^3.5 + G36/(1+$L$10)^4.5)+(G36*(1+N$7)/($L$10-N$7))/(1+$L$10)^5+Hipotesis!$C$15+Hipotesis!$C$16-Hipotesis!$C$14)/Hipotesis!$C$8 -> 58.553564 | O10: =((C36/(1+$L$10)^0.5 + D36/(1+$L$10)^1.5 + E36/(1+$L$10)^2.5 + F36/(1+$L$10)^3.5 + G36/(1+$L$10)^4.5)+(G36*(1+O$7)/($L$10-O$7))/(1+$L$10)^5+Hipotesis!$C$15+Hipotesis!$C$16-Hipotesis!$C$14)/Hipotesis!$C$8 -> 63.028694 | P10: =((C36/(1+$L$10)^0.5 + D36/(1+$L$10)^1.5 + E36/(1+$L$10)^2.5 + F36/(1+$L$10)^3.5 + G36/(1+$L$10)^4.5)+(G36*(1+P$7)/($L$10-P$7))/(1+$L$10)^5+Hipotesis!$C$15+Hipotesis!$C$16-Hipotesis!$C$14)/Hipotesis!$C$8 -> 68.332552 | Q10: =((C36/(1+$L$10)^0.5 + D36/(1+$L$10)^1.5 + E36/(1+$L$10)^2.5 + F36/(1+$L$10)^3.5 + G36/(1+$L$10)^4.5)+(G36*(1+Q$7)/($L$10-Q$7))/(1+$L$10)^5+Hipotesis!$C$15+Hipotesis!$C$16-Hipotesis!$C$14)/Hipotesis!$C$8 -> 74.718829
B11: NGL production (MMBbls) | C11: =Historico!G85*(1+Hipotesis!C31) -> 117.45 | D11: =C11*(1+Hipotesis!D31) -> 122.148 | E11: =D11*(1+Hipotesis!E31) -> 125.81244 | F11: =E11*(1+Hipotesis!F31) -> 128.95775 | G11: =F11*(1+Hipotesis!G31) -> 131.53691 | H11: =G11*(1+Hipotesis!H31) -> 131.53691 | L11: 0.1 | M11: =((C36/(1+$L$11)^0.5 + D36/(1+$L$11)^1.5 + E36/(1+$L$11)^2.5 + F36/(1+$L$11)^3.5 + G36/(1+$L$11)^4.5)+(G36*(1+M$7)/($L$11-M$7))/(1+$L$11)^5+Hipotesis!$C$15+Hipotesis!$C$16-Hipotesis!$C$14)/Hipotesis!$C$8 -> 46.055997 | N11: =((C36/(1+$L$11)^0.5 + D36/(1+$L$11)^1.5 + E36/(1+$L$11)^2.5 + F36/(1+$L$11)^3.5 + G36/(1+$L$11)^4.5)+(G36*(1+N$7)/($L$11-N$7))/(1+$L$11)^5+Hipotesis!$C$15+Hipotesis!$C$16-Hipotesis!$C$14)/Hipotesis!$C$8 -> 48.76137 | O11: =((C36/(1+$L$11)^0.5 + D36/(1+$L$11)^1.5 + E36/(1+$L$11)^2.5 + F36/(1+$L$11)^3.5 + G36/(1+$L$11)^4.5)+(G36*(1+O$7)/($L$11-O$7))/(1+$L$11)^5+Hipotesis!$C$15+Hipotesis!$C$16-Hipotesis!$C$14)/Hipotesis!$C$8 -> 51.853225 | P11: =((C36/(1+$L$11)^0.5 + D36/(1+$L$11)^1.5 + E36/(1+$L$11)^2.5 + F36/(1+$L$11)^3.5 + G36/(1+$L$11)^4.5)+(G36*(1+P$7)/($L$11-P$7))/(1+$L$11)^5+Hipotesis!$C$15+Hipotesis!$C$16-Hipotesis!$C$14)/Hipotesis!$C$8 -> 55.42075 | Q11: =((C36/(1+$L$11)^0.5 + D36/(1+$L$11)^1.5 + E36/(1+$L$11)^2.5 + F36/(1+$L$11)^3.5 + G36/(1+$L$11)^4.5)+(G36*(1+Q$7)/($L$11-Q$7))/(1+$L$11)^5+Hipotesis!$C$15+Hipotesis!$C$16-Hipotesis!$C$14)/Hipotesis!$C$8 -> 59.582862
B12: NGL realized price ($/Bbl) | C12: =Hipotesis!C66 -> 19 | D12: =Hipotesis!D66 -> 19.5 | E12: =Hipotesis!E66 -> 20 | F12: =Hipotesis!F66 -> 20 | G12: =Hipotesis!G66 -> 20.5 | H12: =Hipotesis!H66 -> 20.5 | L12: 0.11 | M12: =((C36/(1+$L$12)^0.5 + D36/(1+$L$12)^1.5 + E36/(1+$L$12)^2.5 + F36/(1+$L$12)^3.5 + G36/(1+$L$12)^4.5)+(G36*(1+M$7)/($L$12-M$7))/(1+$L$12)^5+Hipotesis!$C$15+Hipotesis!$C$16-Hipotesis!$C$14)/Hipotesis!$C$8 -> 40.025292 | N12: =((C36/(1+$L$12)^0.5 + D36/(1+$L$12)^1.5 + E36/(1+$L$12)^2.5 + F36/(1+$L$12)^3.5 + G36/(1+$L$12)^4.5)+(G36*(1+N$7)/($L$12-N$7))/(1+$L$12)^5+Hipotesis!$C$15+Hipotesis!$C$16-Hipotesis!$C$14)/Hipotesis!$C$8 -> 42.071716 | O12: =((C36/(1+$L$12)^0.5 + D36/(1+$L$12)^1.5 + E36/(1+$L$12)^2.5 + F36/(1+$L$12)^3.5 + G36/(1+$L$12)^4.5)+(G36*(1+O$7)/($L$12-O$7))/(1+$L$12)^5+Hipotesis!$C$15+Hipotesis!$C$16-Hipotesis!$C$14)/Hipotesis!$C$8 -> 44.373944 | P12: =((C36/(1+$L$12)^0.5 + D36/(1+$L$12)^1.5 + E36/(1+$L$12)^2.5 + F36/(1+$L$12)^3.5 + G36/(1+$L$12)^4.5)+(G36*(1+P$7)/($L$12-P$7))/(1+$L$12)^5+Hipotesis!$C$15+Hipotesis!$C$16-Hipotesis!$C$14)/Hipotesis!$C$8 -> 46.983136 | Q12: =((C36/(1+$L$12)^0.5 + D36/(1+$L$12)^1.5 + E36/(1+$L$12)^2.5 + F36/(1+$L$12)^3.5 + G36/(1+$L$12)^4.5)+(G36*(1+Q$7)/($L$12-Q$7))/(1+$L$12)^5+Hipotesis!$C$15+Hipotesis!$C$16-Hipotesis!$C$14)/Hipotesis!$C$8 -> 49.965069
B13: S3 Gas revenue ($mm) | C13: =(Historico!G84*(1+Hipotesis!C32))*Hipotesis!C65 -> 3499.65 | D13: =(Historico!G84*(1+Hipotesis!C32)*(1+Hipotesis!D32))*Hipotesis!D65 -> 3970.512 | E13: =(Historico!G84*(1+Hipotesis!C32)*(1+Hipotesis!D32)*(1+Hipotesis!E32))*Hipotesis!E65 -> 4430.4296 | F13: =(Historico!G84*(1+Hipotesis!C32)*(1+Hipotesis!D32)*(1+Hipotesis!E32)*(1+Hipotesis!F32))*Hipotesis!F65 -> 4715.8515 | G13: =(Historico!G84*(1+Hipotesis!C32)*(1+Hipotesis!D32)*(1+Hipotesis!E32)*(1+Hipotesis!F32)*(1+Hipotesis!G32))*Hipotesis!G65 -> 4988.323 | H13: =(Historico!G84*(1+Hipotesis!C32)*(1+Hipotesis!D32)*(1+Hipotesis!E32)*(1+Hipotesis!F32)*(1+Hipotesis!G32)*(1+Hipotesis!H32))*Hipotesis!H65 -> 4988.323
B14: Gas production (Bcf) | C14: =Historico!G84*(1+Hipotesis!C32) -> 1590.75 | D14: =C14*(1+Hipotesis!D32) -> 1654.38 | E14: =D14*(1+Hipotesis!E32) -> 1704.0114 | F14: =E14*(1+Hipotesis!F32) -> 1746.6117 | G14: =F14*(1+Hipotesis!G32) -> 1781.5439 | H14: =G14*(1+Hipotesis!H32) -> 1781.5439
B15: Gas realized price ($/Mcf) | C15: =Hipotesis!C65 -> 2.2 | D15: =Hipotesis!D65 -> 2.4 | E15: =Hipotesis!E65 -> 2.6 | F15: =Hipotesis!F65 -> 2.7 | G15: =Hipotesis!G65 -> 2.8 | H15: =Hipotesis!H65 -> 2.8 | L15: Tabla B — Precio (Gordon DCF) vs WACC × Op margin terminal
B16: Total Upstream Revenue ($mm) | C16: =C7+C10+C13 -> 19526.5 | D16: =D7+D10+D13 -> 19925.326 | E16: =E7+E10+E13 -> 20641.551 | F16: =F7+F10+F13 -> 21042.05 | G16: =G7+G10+G13 -> 21638.078 | H16: =H7+H10+H13 -> 21638.078
B17: Revenue growth YoY % | C17: =C16/Historico!G6-1 -> 0.13605422 | D17: =D16/C16-1 -> 0.020424859 | E17: =E16/D16-1 -> 0.035945445 | F17: =F16/E16-1 -> 0.019402567 | G17: =G16/F16-1 -> 0.028325597 | H17: =H16/G16-1 -> 0 | L17: WACC ↓ \ margin → | M17: 0.2 | N17: 0.25 | O17: 0.3 | P17: 0.35 | Q17: 0.4
B18: Total production (MMBoe) = Oil + NGL + Gas/6 | C18: =C8+C11+C14/6 -> 588.475 | D18: =D8+D11+D14/6 -> 609.955 | E18: =E8+E11+E14/6 -> 627.19326 | F18: =F8+F11+F14/6 -> 641.7862 | G18: =G8+G11+G14/6 -> 653.51329 | H18: =H8+H11+H14/6 -> 653.51329 | L18: 0.075 | M18: =(C44+((G16*M$17*(1-Hipotesis!$C$13)+G31+G33+G35)*(1+Hipotesis!$C$47)/($L$18-Hipotesis!$C$47))/(1+$L$18)^5+Hipotesis!$C$15+Hipotesis!$C$16-Hipotesis!$C$14)/Hipotesis!$C$8 -> 32.118973 | N18: =(C44+((G16*N$17*(1-Hipotesis!$C$13)+G31+G33+G35)*(1+Hipotesis!$C$47)/($L$18-Hipotesis!$C$47))/(1+$L$18)^5+Hipotesis!$C$15+Hipotesis!$C$16-Hipotesis!$C$14)/Hipotesis!$C$8 -> 41.573704 | O18: =(C44+((G16*O$17*(1-Hipotesis!$C$13)+G31+G33+G35)*(1+Hipotesis!$C$47)/($L$18-Hipotesis!$C$47))/(1+$L$18)^5+Hipotesis!$C$15+Hipotesis!$C$16-Hipotesis!$C$14)/Hipotesis!$C$8 -> 51.028434 | P18: =(C44+((G16*P$17*(1-Hipotesis!$C$13)+G31+G33+G35)*(1+Hipotesis!$C$47)/($L$18-Hipotesis!$C$47))/(1+$L$18)^5+Hipotesis!$C$15+Hipotesis!$C$16-Hipotesis!$C$14)/Hipotesis!$C$8 -> 60.483165 | Q18: =(C44+((G16*Q$17*(1-Hipotesis!$C$13)+G31+G33+G35)*(1+Hipotesis!$C$47)/($L$18-Hipotesis!$C$47))/(1+$L$18)^5+Hipotesis!$C$15+Hipotesis!$C$16-Hipotesis!$C$14)/Hipotesis!$C$8 -> 69.937895
B19: B. OPERATING INCOME POR SEGMENTO | L19: 0.085 | M19: =(C44+((G16*M$17*(1-Hipotesis!$C$13)+G31+G33+G35)*(1+Hipotesis!$C$47)/($L$19-Hipotesis!$C$47))/(1+$L$19)^5+Hipotesis!$C$15+Hipotesis!$C$16-Hipotesis!$C$14)/Hipotesis!$C$8 -> 27.647561 | N19: =(C44+((G16*N$17*(1-Hipotesis!$C$13)+G31+G33+G35)*(1+Hipotesis!$C$47)/($L$19-Hipotesis!$C$47))/(1+$L$19)^5+Hipotesis!$C$15+Hipotesis!$C$16-Hipotesis!$C$14)/Hipotesis!$C$8 -> 35.28578 | O19: =(C44+((G16*O$17*(1-Hipotesis!$C$13)+G31+G33+G35)*(1+Hipotesis!$C$47)/($L$19-Hipotesis!$C$47))/(1+$L$19)^5+Hipotesis!$C$15+Hipotesis!$C$16-Hipotesis!$C$14)/Hipotesis!$C$8 -> 42.923999 | P19: =(C44+((G16*P$17*(1-Hipotesis!$C$13)+G31+G33+G35)*(1+Hipotesis!$C$47)/($L$19-Hipotesis!$C$47))/(1+$L$19)^5+Hipotesis!$C$15+Hipotesis!$C$16-Hipotesis!$C$14)/Hipotesis!$C$8 -> 50.562218 | Q19: =(C44+((G16*Q$17*(1-Hipotesis!$C$13)+G31+G33+G35)*(1+Hipotesis!$C$47)/($L$19-Hipotesis!$C$47))/(1+$L$19)^5+Hipotesis!$C$15+Hipotesis!$C$16-Hipotesis!$C$14)/Hipotesis!$C$8 -> 58.200438
B20: S1 Oil operating income | C20: =C7*Hipotesis!C33 -> 5518.12 | D20: =D7*Hipotesis!D33 -> 5700.6298 | E20: =E7*Hipotesis!E33 -> 5888.7951 | F20: =F7*Hipotesis!F33 -> 5911.2286 | G20: =G7*Hipotesis!G33 -> 5999.897 | H20: =H7*Hipotesis!H33 -> 5860.3645 | L20: 0.089 | M20: =(C44+((G16*M$17*(1-Hipotesis!$C$13)+G31+G33+G35)*(1+Hipotesis!$C$47)/($L$20-Hipotesis!$C$47))/(1+$L$20)^5+Hipotesis!$C$15+Hipotesis!$C$16-Hipotesis!$C$14)/Hipotesis!$C$8 -> 26.234698 | N20: =(C44+((G16*N$17*(1-Hipotesis!$C$13)+G31+G33+G35)*(1+Hipotesis!$C$47)/($L$20-Hipotesis!$C$47))/(1+$L$20)^5+Hipotesis!$C$15+Hipotesis!$C$16-Hipotesis!$C$14)/Hipotesis!$C$8 -> 33.298942 | O20: =(C44+((G16*O$17*(1-Hipotesis!$C$13)+G31+G33+G35)*(1+Hipotesis!$C$47)/($L$20-Hipotesis!$C$47))/(1+$L$20)^5+Hipotesis!$C$15+Hipotesis!$C$16-Hipotesis!$C$14)/Hipotesis!$C$8 -> 40.363186 | P20: =(C44+((G16*P$17*(1-Hipotesis!$C$13)+G31+G33+G35)*(1+Hipotesis!$C$47)/($L$20-Hipotesis!$C$47))/(1+$L$20)^5+Hipotesis!$C$15+Hipotesis!$C$16-Hipotesis!$C$14)/Hipotesis!$C$8 -> 47.427429 | Q20: =(C44+((G16*Q$17*(1-Hipotesis!$C$13)+G31+G33+G35)*(1+Hipotesis!$C$47)/($L$20-Hipotesis!$C$47))/(1+$L$20)^5+Hipotesis!$C$15+Hipotesis!$C$16-Hipotesis!$C$14)/Hipotesis!$C$8 -> 54.491673
B21: S1 Oil contribution margin % | C21: =C20/C7 -> 0.4 | D21: =D20/D7 -> 0.42 | E21: =E20/E7 -> 0.43 | F21: =F20/F7 -> 0.43 | G21: =G20/G7 -> 0.43 | H21: =H20/H7 -> 0.42 | L21: 0.1 | M21: =(C44+((G16*M$17*(1-Hipotesis!$C$13)+G31+G33+G35)*(1+Hipotesis!$C$47)/($L$21-Hipotesis!$C$47))/(1+$L$21)^5+Hipotesis!$C$15+Hipotesis!$C$16-Hipotesis!$C$14)/Hipotesis!$C$8 -> 23.108676 | N21: =(C44+((G16*N$17*(1-Hipotesis!$C$13)+G31+G33+G35)*(1+Hipotesis!$C$47)/($L$21-Hipotesis!$C$47))/(1+$L$21)^5+Hipotesis!$C$15+Hipotesis!$C$16-Hipotesis!$C$14)/Hipotesis!$C$8 -> 28.902973 | O21: =(C44+((G16*O$17*(1-Hipotesis!$C$13)+G31+G33+G35)*(1+Hipotesis!$C$47)/($L$21-Hipotesis!$C$47))/(1+$L$21)^5+Hipotesis!$C$15+Hipotesis!$C$16-Hipotesis!$C$14)/Hipotesis!$C$8 -> 34.69727 | P21: =(C44+((G16*P$17*(1-Hipotesis!$C$13)+G31+G33+G35)*(1+Hipotesis!$C$47)/($L$21-Hipotesis!$C$47))/(1+$L$21)^5+Hipotesis!$C$15+Hipotesis!$C$16-Hipotesis!$C$14)/Hipotesis!$C$8 -> 40.491567 | Q21: =(C44+((G16*Q$17*(1-Hipotesis!$C$13)+G31+G33+G35)*(1+Hipotesis!$C$47)/($L$21-Hipotesis!$C$47))/(1+$L$21)^5+Hipotesis!$C$15+Hipotesis!$C$16-Hipotesis!$C$14)/Hipotesis!$C$8 -> 46.285863
B22: S2 NGL operating income | C22: =C10*Hipotesis!C34 -> 401.679 | D22: =D10*Hipotesis!D34 -> 476.3772 | E22: =E10*Hipotesis!E34 -> 553.57474 | F22: =F10*Hipotesis!F34 -> 567.4141 | G22: =G10*Hipotesis!G34 -> 593.23145 | H22: =H10*Hipotesis!H34 -> 539.30131 | L22: 0.11 | M22: =(C44+((G16*M$17*(1-Hipotesis!$C$13)+G31+G33+G35)*(1+Hipotesis!$C$47)/($L$22-Hipotesis!$C$47))/(1+$L$22)^5+Hipotesis!$C$15+Hipotesis!$C$16-Hipotesis!$C$14)/Hipotesis!$C$8 -> 20.963022 | N22: =(C44+((G16*N$17*(1-Hipotesis!$C$13)+G31+G33+G35)*(1+Hipotesis!$C$47)/($L$22-Hipotesis!$C$47))/(1+$L$22)^5+Hipotesis!$C$15+Hipotesis!$C$16-Hipotesis!$C$14)/Hipotesis!$C$8 -> 25.885647 | O22: =(C44+((G16*O$17*(1-Hipotesis!$C$13)+G31+G33+G35)*(1+Hipotesis!$C$47)/($L$22-Hipotesis!$C$47))/(1+$L$22)^5+Hipotesis!$C$15+Hipotesis!$C$16-Hipotesis!$C$14)/Hipotesis!$C$8 -> 30.808272 | P22: =(C44+((G16*P$17*(1-Hipotesis!$C$13)+G31+G33+G35)*(1+Hipotesis!$C$47)/($L$22-Hipotesis!$C$47))/(1+$L$22)^5+Hipotesis!$C$15+Hipotesis!$C$16-Hipotesis!$C$14)/Hipotesis!$C$8 -> 35.730897 | Q22: =(C44+((G16*Q$17*(1-Hipotesis!$C$13)+G31+G33+G35)*(1+Hipotesis!$C$47)/($L$22-Hipotesis!$C$47))/(1+$L$22)^5+Hipotesis!$C$15+Hipotesis!$C$16-Hipotesis!$C$14)/Hipotesis!$C$8 -> 40.653522
B23: S2 NGL contribution margin % | C23: =C22/C10 -> 0.18 | D23: =D22/D10 -> 0.2 | E23: =E22/E10 -> 0.22 | F23: =F22/F10 -> 0.22 | G23: =G22/G10 -> 0.22 | H23: =H22/H10 -> 0.2
B24: S3 Gas operating income | C24: =C13*Hipotesis!C35 -> 349.965 | D24: =D13*Hipotesis!D35 -> 595.5768 | E24: =E13*Hipotesis!E35 -> 797.47734 | F24: =F13*Hipotesis!F35 -> 943.17031 | G24: =G13*Hipotesis!G35 -> 1097.4311 | H24: =H13*Hipotesis!H35 -> 997.66459 | L24: Tabla C — Precio (Gordon DCF) vs Capex/Rev terminal × g_terminal
B25: S3 Gas contribution margin % | C25: =C24/C13 -> 0.1 | D25: =D24/D13 -> 0.15 | E25: =E24/E13 -> 0.18 | F25: =F24/F13 -> 0.2 | G25: =G24/G13 -> 0.22 | H25: =H24/H13 -> 0.2
B26: Total Operating Income (EBIT incl. synergies) | C26: =C20+C22+C24+C28 -> 6669.764 | D26: =D20+D22+D24+D28 -> 7772.5838 | E26: =E20+E22+E24+E28 -> 8239.8471 | F26: =F20+F22+F24+F28 -> 8421.813 | G26: =G20+G22+G24+G28 -> 8690.5595 | H26: =H20+H22+H24+H28 -> 8397.3304 | L26: Capex/Rev ↓ \ g → | M26: 0.02 | N26: 0.025 | O26: 0.03 | P26: 0.035 | Q26: 0.04
B27: Operating margin % | C27: =C26/C16 -> 0.34157499 | D27: =D26/D16 -> 0.39008565 | E27: =E26/E16 -> 0.39918741 | F27: =F26/F16 -> 0.40023729 | G27: =G26/G16 -> 0.40163268 | H27: =H26/H16 -> 0.38808115 | L27: 0.17 | M27: =(C44+((G30+G31+(-G16*$L$27)+G35)*(1+M$26)/(Hipotesis!$C$25-M$26))/(1+Hipotesis!$C$25)^5+Hipotesis!$C$15+Hipotesis!$C$16-Hipotesis!$C$14)/Hipotesis!$C$8 -> 62.751551 | N27: =(C44+((G30+G31+(-G16*$L$27)+G35)*(1+N$26)/(Hipotesis!$C$25-N$26))/(1+Hipotesis!$C$25)^5+Hipotesis!$C$15+Hipotesis!$C$16-Hipotesis!$C$14)/Hipotesis!$C$8 -> 67.240012 | O27: =(C44+((G30+G31+(-G16*$L$27)+G35)*(1+O$26)/(Hipotesis!$C$25-O$26))/(1+Hipotesis!$C$25)^5+Hipotesis!$C$15+Hipotesis!$C$16-Hipotesis!$C$14)/Hipotesis!$C$8 -> 72.487707 | P27: =(C44+((G30+G31+(-G16*$L$27)+G35)*(1+P$26)/(Hipotesis!$C$25-P$26))/(1+Hipotesis!$C$25)^5+Hipotesis!$C$15+Hipotesis!$C$16-Hipotesis!$C$14)/Hipotesis!$C$8 -> 78.70507 | Q27: =(C44+((G30+G31+(-G16*$L$27)+G35)*(1+Q$26)/(Hipotesis!$C$25-Q$26))/(1+Hipotesis!$C$25)^5+Hipotesis!$C$15+Hipotesis!$C$16-Hipotesis!$C$14)/Hipotesis!$C$8 -> 86.188225
B28: (+) Merger synergies (pre-tax, ramped) ($mm) | C28: =Hipotesis!$C$57*Hipotesis!$C$58 -> 400 | D28: =Hipotesis!$C$57 -> 1000 | E28: =Hipotesis!$C$57 -> 1000 | F28: =Hipotesis!$C$57 -> 1000 | G28: =Hipotesis!$C$57 -> 1000 | H28: =Hipotesis!$C$57 -> 1000 | L28: 0.2 | M28: =(C44+((G30+G31+(-G16*$L$28)+G35)*(1+M$26)/(Hipotesis!$C$25-M$26))/(1+Hipotesis!$C$25)^5+Hipotesis!$C$15+Hipotesis!$C$16-Hipotesis!$C$14)/Hipotesis!$C$8 -> 57.329772 | N28: =(C44+((G30+G31+(-G16*$L$28)+G35)*(1+N$26)/(Hipotesis!$C$25-N$26))/(1+Hipotesis!$C$25)^5+Hipotesis!$C$15+Hipotesis!$C$16-Hipotesis!$C$14)/Hipotesis!$C$8 -> 61.36679 | O28: =(C44+((G30+G31+(-G16*$L$28)+G35)*(1+O$26)/(Hipotesis!$C$25-O$26))/(1+Hipotesis!$C$25)^5+Hipotesis!$C$15+Hipotesis!$C$16-Hipotesis!$C$14)/Hipotesis!$C$8 -> 66.086677 | P28: =(C44+((G30+G31+(-G16*$L$28)+G35)*(1+P$26)/(Hipotesis!$C$25-P$26))/(1+Hipotesis!$C$25)^5+Hipotesis!$C$15+Hipotesis!$C$16-Hipotesis!$C$14)/Hipotesis!$C$8 -> 71.678705 | Q28: =(C44+((G30+G31+(-G16*$L$28)+G35)*(1+Q$26)/(Hipotesis!$C$25-Q$26))/(1+Hipotesis!$C$25)^5+Hipotesis!$C$15+Hipotesis!$C$16-Hipotesis!$C$14)/Hipotesis!$C$8 -> 78.409214
B29: C. PUENTE DE EBIT A FREE CASH FLOW (FCFF) | L29: 0.225 | M29: =(C44+((G30+G31+(-G16*$L$29)+G35)*(1+M$26)/(Hipotesis!$C$25-M$26))/(1+Hipotesis!$C$25)^5+Hipotesis!$C$15+Hipotesis!$C$16-Hipotesis!$C$14)/Hipotesis!$C$8 -> 52.811624 | N29: =(C44+((G30+G31+(-G16*$L$29)+G35)*(1+N$26)/(Hipotesis!$C$25-N$26))/(1+Hipotesis!$C$25)^5+Hipotesis!$C$15+Hipotesis!$C$16-Hipotesis!$C$14)/Hipotesis!$C$8 -> 56.472437 | O29: =(C44+((G30+G31+(-G16*$L$29)+G35)*(1+O$26)/(Hipotesis!$C$25-O$26))/(1+Hipotesis!$C$25)^5+Hipotesis!$C$15+Hipotesis!$C$16-Hipotesis!$C$14)/Hipotesis!$C$8 -> 60.752486 | P29: =(C44+((G30+G31+(-G16*$L$29)+G35)*(1+P$26)/(Hipotesis!$C$25-P$26))/(1+Hipotesis!$C$25)^5+Hipotesis!$C$15+Hipotesis!$C$16-Hipotesis!$C$14)/Hipotesis!$C$8 -> 65.823401 | Q29: =(C44+((G30+G31+(-G16*$L$29)+G35)*(1+Q$26)/(Hipotesis!$C$25-Q$26))/(1+Hipotesis!$C$25)^5+Hipotesis!$C$15+Hipotesis!$C$16-Hipotesis!$C$14)/Hipotesis!$C$8 -> 71.926704
B30: NOPAT = EBIT × (1 − tax rate) | C30: =C26*(1-Hipotesis!$C$13) -> 5202.4159 | D30: =D26*(1-Hipotesis!$C$13) -> 6062.6153 | E30: =E26*(1-Hipotesis!$C$13) -> 6427.0808 | F30: =F26*(1-Hipotesis!$C$13) -> 6569.0141 | G30: =G26*(1-Hipotesis!$C$13) -> 6778.6364 | H30: =H26*(1-Hipotesis!$C$13) -> 6549.9177 | L30: 0.25 | M30: =(C44+((G30+G31+(-G16*$L$30)+G35)*(1+M$26)/(Hipotesis!$C$25-M$26))/(1+Hipotesis!$C$25)^5+Hipotesis!$C$15+Hipotesis!$C$16-Hipotesis!$C$14)/Hipotesis!$C$8 -> 48.293475 | N30: =(C44+((G30+G31+(-G16*$L$30)+G35)*(1+N$26)/(Hipotesis!$C$25-N$26))/(1+Hipotesis!$C$25)^5+Hipotesis!$C$15+Hipotesis!$C$16-Hipotesis!$C$14)/Hipotesis!$C$8 -> 51.578085 | O30: =(C44+((G30+G31+(-G16*$L$30)+G35)*(1+O$26)/(Hipotesis!$C$25-O$26))/(1+Hipotesis!$C$25)^5+Hipotesis!$C$15+Hipotesis!$C$16-Hipotesis!$C$14)/Hipotesis!$C$8 -> 55.418294 | P30: =(C44+((G30+G31+(-G16*$L$30)+G35)*(1+P$26)/(Hipotesis!$C$25-P$26))/(1+Hipotesis!$C$25)^5+Hipotesis!$C$15+Hipotesis!$C$16-Hipotesis!$C$14)/Hipotesis!$C$8 -> 59.968097 | Q30: =(C44+((G30+G31+(-G16*$L$30)+G35)*(1+Q$26)/(Hipotesis!$C$25-Q$26))/(1+Hipotesis!$C$25)^5+Hipotesis!$C$15+Hipotesis!$C$16-Hipotesis!$C$14)/Hipotesis!$C$8 -> 65.444194
B31: (+) D&A | C31: =C16*Hipotesis!C40 -> 3026.6075 | D31: =D16*Hipotesis!D40 -> 3188.0522 | E31: =E16*Hipotesis!E40 -> 3302.6481 | F31: =F16*Hipotesis!F40 -> 3261.5177 | G31: =G16*Hipotesis!G40 -> 3353.9022 | H31: =H16*Hipotesis!H40 -> 3245.7118 | L31: 0.3 | M31: =(C44+((G30+G31+(-G16*$L$31)+G35)*(1+M$26)/(Hipotesis!$C$25-M$26))/(1+Hipotesis!$C$25)^5+Hipotesis!$C$15+Hipotesis!$C$16-Hipotesis!$C$14)/Hipotesis!$C$8 -> 39.257178 | N31: =(C44+((G30+G31+(-G16*$L$31)+G35)*(1+N$26)/(Hipotesis!$C$25-N$26))/(1+Hipotesis!$C$25)^5+Hipotesis!$C$15+Hipotesis!$C$16-Hipotesis!$C$14)/Hipotesis!$C$8 -> 41.789381 | O31: =(C44+((G30+G31+(-G16*$L$31)+G35)*(1+O$26)/(Hipotesis!$C$25-O$26))/(1+Hipotesis!$C$25)^5+Hipotesis!$C$15+Hipotesis!$C$16-Hipotesis!$C$14)/Hipotesis!$C$8 -> 44.749912 | P31: =(C44+((G30+G31+(-G16*$L$31)+G35)*(1+P$26)/(Hipotesis!$C$25-P$26))/(1+Hipotesis!$C$25)^5+Hipotesis!$C$15+Hipotesis!$C$16-Hipotesis!$C$14)/Hipotesis!$C$8 -> 48.257489 | Q31: =(C44+((G30+G31+(-G16*$L$31)+G35)*(1+Q$26)/(Hipotesis!$C$25-Q$26))/(1+Hipotesis!$C$25)^5+Hipotesis!$C$15+Hipotesis!$C$16-Hipotesis!$C$14)/Hipotesis!$C$8 -> 52.479174
B32: D&A / Revenue % | C32: =C31/C16 -> 0.155 | D32: =D31/D16 -> 0.16 | E32: =E31/E16 -> 0.16 | F32: =F31/F16 -> 0.155 | G32: =G31/G16 -> 0.155 | H32: =H31/H16 -> 0.15
B33: (−) Capex | C33: =-C16*Hipotesis!C39 -> -4393.4625 | D33: =-D16*Hipotesis!D39 -> -4383.5717 | E33: =-E16*Hipotesis!E39 -> -4437.9334 | F33: =-F16*Hipotesis!F39 -> -4524.0407 | G33: =-G16*Hipotesis!G39 -> -4652.1869 | H33: =-H16*Hipotesis!H39 -> -4760.3773 | L33: Tabla D — Precio (Exit EV/EBITDA) vs WACC × Exit EV/EBITDA
B34: Capex / Revenue % | C34: =-C33/C16 -> 0.225 | D34: =-D33/D16 -> 0.22 | E34: =-E33/E16 -> 0.215 | F34: =-F33/F16 -> 0.215 | G34: =-G33/G16 -> 0.215 | H34: =-H33/H16 -> 0.22
B35: (−) ΔWorking Capital | C35: =-C16*Hipotesis!C42 -> -97.6325 | D35: =-D16*Hipotesis!D42 -> -59.775978 | E35: =-E16*Hipotesis!E42 -> 0 | F35: =-F16*Hipotesis!F42 -> 0 | G35: =-G16*Hipotesis!G42 -> 0 | H35: =-H16*Hipotesis!H42 -> 0 | L35: WACC ↓ \ EV/EBITDA → | M35: 4 | N35: 5 | O35: 5.5 | P35: 6.5 | Q35: 8
B36: Free Cash Flow to Firm (FCFF) | C36: =C30+C31+C33+C35 -> 3737.9284 | D36: =D30+D31+D33+D35 -> 4807.3198 | E36: =E30+E31+E33+E35 -> 5291.7955 | F36: =F30+F31+F33+F35 -> 5306.4912 | G36: =G30+G31+G33+G35 -> 5480.3517 | H36: =H30+H31+H33+H35 -> 5035.2522 | L36: 0.075 | M36: =((C36/(1+$L$36)^0.5 + D36/(1+$L$36)^1.5 + E36/(1+$L$36)^2.5 + F36/(1+$L$36)^3.5 + G36/(1+$L$36)^4.5)+(M$35*(G26+G31))/(1+$L$36)^5+Hipotesis!$C$15+Hipotesis!$C$16-Hipotesis!$C$14)/Hipotesis!$C$8 -> 38.522363 | N36: =((C36/(1+$L$36)^0.5 + D36/(1+$L$36)^1.5 + E36/(1+$L$36)^2.5 + F36/(1+$L$36)^3.5 + G36/(1+$L$36)^4.5)+(N$35*(G26+G31))/(1+$L$36)^5+Hipotesis!$C$15+Hipotesis!$C$16-Hipotesis!$C$14)/Hipotesis!$C$8 -> 45.79875 | O36: =((C36/(1+$L$36)^0.5 + D36/(1+$L$36)^1.5 + E36/(1+$L$36)^2.5 + F36/(1+$L$36)^3.5 + G36/(1+$L$36)^4.5)+(O$35*(G26+G31))/(1+$L$36)^5+Hipotesis!$C$15+Hipotesis!$C$16-Hipotesis!$C$14)/Hipotesis!$C$8 -> 49.436943 | P36: =((C36/(1+$L$36)^0.5 + D36/(1+$L$36)^1.5 + E36/(1+$L$36)^2.5 + F36/(1+$L$36)^3.5 + G36/(1+$L$36)^4.5)+(P$35*(G26+G31))/(1+$L$36)^5+Hipotesis!$C$15+Hipotesis!$C$16-Hipotesis!$C$14)/Hipotesis!$C$8 -> 56.71333 | Q36: =((C36/(1+$L$36)^0.5 + D36/(1+$L$36)^1.5 + E36/(1+$L$36)^2.5 + F36/(1+$L$36)^3.5 + G36/(1+$L$36)^4.5)+(Q$35*(G26+G31))/(1+$L$36)^5+Hipotesis!$C$15+Hipotesis!$C$16-Hipotesis!$C$14)/Hipotesis!$C$8 -> 67.627909
B37: FCFF / Revenue % | C37: =C36/C16 -> 0.19142849 | D37: =D36/D16 -> 0.24126681 | E37: =E36/E16 -> 0.25636618 | F37: =F36/F16 -> 0.25218509 | G37: =G36/G16 -> 0.25327349 | H37: =H36/H16 -> 0.2327033 | L37: 0.085 | M37: =((C36/(1+$L$37)^0.5 + D36/(1+$L$37)^1.5 + E36/(1+$L$37)^2.5 + F36/(1+$L$37)^3.5 + G36/(1+$L$37)^4.5)+(M$35*(G26+G31))/(1+$L$37)^5+Hipotesis!$C$15+Hipotesis!$C$16-Hipotesis!$C$14)/Hipotesis!$C$8 -> 36.797868 | N37: =((C36/(1+$L$37)^0.5 + D36/(1+$L$37)^1.5 + E36/(1+$L$37)^2.5 + F36/(1+$L$37)^3.5 + G36/(1+$L$37)^4.5)+(N$35*(G26+G31))/(1+$L$37)^5+Hipotesis!$C$15+Hipotesis!$C$16-Hipotesis!$C$14)/Hipotesis!$C$8 -> 43.745061 | O37: =((C36/(1+$L$37)^0.5 + D36/(1+$L$37)^1.5 + E36/(1+$L$37)^2.5 + F36/(1+$L$37)^3.5 + G36/(1+$L$37)^4.5)+(O$35*(G26+G31))/(1+$L$37)^5+Hipotesis!$C$15+Hipotesis!$C$16-Hipotesis!$C$14)/Hipotesis!$C$8 -> 47.218658 | P37: =((C36/(1+$L$37)^0.5 + D36/(1+$L$37)^1.5 + E36/(1+$L$37)^2.5 + F36/(1+$L$37)^3.5 + G36/(1+$L$37)^4.5)+(P$35*(G26+G31))/(1+$L$37)^5+Hipotesis!$C$15+Hipotesis!$C$16-Hipotesis!$C$14)/Hipotesis!$C$8 -> 54.165852 | Q37: =((C36/(1+$L$37)^0.5 + D36/(1+$L$37)^1.5 + E36/(1+$L$37)^2.5 + F36/(1+$L$37)^3.5 + G36/(1+$L$37)^4.5)+(Q$35*(G26+G31))/(1+$L$37)^5+Hipotesis!$C$15+Hipotesis!$C$16-Hipotesis!$C$14)/Hipotesis!$C$8 -> 64.586642
B38: FCFF / NOPAT % (conversion) | C38: =C36/C30 -> 0.71849857 | D38: =D36/D30 -> 0.79294488 | E38: =E36/E30 -> 0.82335911 | F38: =F36/F30 -> 0.80780632 | G38: =G36/G30 -> 0.80847406 | H38: =H36/H30 -> 0.76875046 | L38: 0.089 | M38: =((C36/(1+$L$38)^0.5 + D36/(1+$L$38)^1.5 + E36/(1+$L$38)^2.5 + F36/(1+$L$38)^3.5 + G36/(1+$L$38)^4.5)+(M$35*(G26+G31))/(1+$L$38)^5+Hipotesis!$C$15+Hipotesis!$C$16-Hipotesis!$C$14)/Hipotesis!$C$8 -> 36.132604 | N38: =((C36/(1+$L$38)^0.5 + D36/(1+$L$38)^1.5 + E36/(1+$L$38)^2.5 + F36/(1+$L$38)^3.5 + G36/(1+$L$38)^4.5)+(N$35*(G26+G31))/(1+$L$38)^5+Hipotesis!$C$15+Hipotesis!$C$16-Hipotesis!$C$14)/Hipotesis!$C$8 -> 42.953143 | O38: =((C36/(1+$L$38)^0.5 + D36/(1+$L$38)^1.5 + E36/(1+$L$38)^2.5 + F36/(1+$L$38)^3.5 + G36/(1+$L$38)^4.5)+(O$35*(G26+G31))/(1+$L$38)^5+Hipotesis!$C$15+Hipotesis!$C$16-Hipotesis!$C$14)/Hipotesis!$C$8 -> 46.363412 | P38: =((C36/(1+$L$38)^0.5 + D36/(1+$L$38)^1.5 + E36/(1+$L$38)^2.5 + F36/(1+$L$38)^3.5 + G36/(1+$L$38)^4.5)+(P$35*(G26+G31))/(1+$L$38)^5+Hipotesis!$C$15+Hipotesis!$C$16-Hipotesis!$C$14)/Hipotesis!$C$8 -> 53.183951 | Q38: =((C36/(1+$L$38)^0.5 + D36/(1+$L$38)^1.5 + E36/(1+$L$38)^2.5 + F36/(1+$L$38)^3.5 + G36/(1+$L$38)^4.5)+(Q$35*(G26+G31))/(1+$L$38)^5+Hipotesis!$C$15+Hipotesis!$C$16-Hipotesis!$C$14)/Hipotesis!$C$8 -> 63.414759
L39: 0.1 | M39: =((C36/(1+$L$39)^0.5 + D36/(1+$L$39)^1.5 + E36/(1+$L$39)^2.5 + F36/(1+$L$39)^3.5 + G36/(1+$L$39)^4.5)+(M$35*(G26+G31))/(1+$L$39)^5+Hipotesis!$C$15+Hipotesis!$C$16-Hipotesis!$C$14)/Hipotesis!$C$8 -> 34.371778 | N39: =((C36/(1+$L$39)^0.5 + D36/(1+$L$39)^1.5 + E36/(1+$L$39)^2.5 + F36/(1+$L$39)^3.5 + G36/(1+$L$39)^4.5)+(N$35*(G26+G31))/(1+$L$39)^5+Hipotesis!$C$15+Hipotesis!$C$16-Hipotesis!$C$14)/Hipotesis!$C$8 -> 40.858042 | O39: =((C36/(1+$L$39)^0.5 + D36/(1+$L$39)^1.5 + E36/(1+$L$39)^2.5 + F36/(1+$L$39)^3.5 + G36/(1+$L$39)^4.5)+(O$35*(G26+G31))/(1+$L$39)^5+Hipotesis!$C$15+Hipotesis!$C$16-Hipotesis!$C$14)/Hipotesis!$C$8 -> 44.101175 | P39: =((C36/(1+$L$39)^0.5 + D36/(1+$L$39)^1.5 + E36/(1+$L$39)^2.5 + F36/(1+$L$39)^3.5 + G36/(1+$L$39)^4.5)+(P$35*(G26+G31))/(1+$L$39)^5+Hipotesis!$C$15+Hipotesis!$C$16-Hipotesis!$C$14)/Hipotesis!$C$8 -> 50.587439 | Q39: =((C36/(1+$L$39)^0.5 + D36/(1+$L$39)^1.5 + E36/(1+$L$39)^2.5 + F36/(1+$L$39)^3.5 + G36/(1+$L$39)^4.5)+(Q$35*(G26+G31))/(1+$L$39)^5+Hipotesis!$C$15+Hipotesis!$C$16-Hipotesis!$C$14)/Hipotesis!$C$8 -> 60.316836
B40: D. DCF DISCOUNTING & VALUE BRIDGE | L40: 0.11 | M40: =((C36/(1+$L$40)^0.5 + D36/(1+$L$40)^1.5 + E36/(1+$L$40)^2.5 + F36/(1+$L$40)^3.5 + G36/(1+$L$40)^4.5)+(M$35*(G26+G31))/(1+$L$40)^5+Hipotesis!$C$15+Hipotesis!$C$16-Hipotesis!$C$14)/Hipotesis!$C$8 -> 32.854049 | N40: =((C36/(1+$L$40)^0.5 + D36/(1+$L$40)^1.5 + E36/(1+$L$40)^2.5 + F36/(1+$L$40)^3.5 + G36/(1+$L$40)^4.5)+(N$35*(G26+G31))/(1+$L$40)^5+Hipotesis!$C$15+Hipotesis!$C$16-Hipotesis!$C$14)/Hipotesis!$C$8 -> 39.053357 | O40: =((C36/(1+$L$40)^0.5 + D36/(1+$L$40)^1.5 + E36/(1+$L$40)^2.5 + F36/(1+$L$40)^3.5 + G36/(1+$L$40)^4.5)+(O$35*(G26+G31))/(1+$L$40)^5+Hipotesis!$C$15+Hipotesis!$C$16-Hipotesis!$C$14)/Hipotesis!$C$8 -> 42.153011 | P40: =((C36/(1+$L$40)^0.5 + D36/(1+$L$40)^1.5 + E36/(1+$L$40)^2.5 + F36/(1+$L$40)^3.5 + G36/(1+$L$40)^4.5)+(P$35*(G26+G31))/(1+$L$40)^5+Hipotesis!$C$15+Hipotesis!$C$16-Hipotesis!$C$14)/Hipotesis!$C$8 -> 48.352319 | Q40: =((C36/(1+$L$40)^0.5 + D36/(1+$L$40)^1.5 + E36/(1+$L$40)^2.5 + F36/(1+$L$40)^3.5 + G36/(1+$L$40)^4.5)+(Q$35*(G26+G31))/(1+$L$40)^5+Hipotesis!$C$15+Hipotesis!$C$16-Hipotesis!$C$14)/Hipotesis!$C$8 -> 57.65128
B41: Período (años desde valoración) | C41: 0.5 | D41: 1.5 | E41: 2.5 | F41: 3.5 | G41: 4.5 | H41: TV at end FY30
B42: Discount factor (mid-year) | C42: =1/(1+Hipotesis!$C$25)^C41 -> 0.95821387 | D42: =1/(1+Hipotesis!$C$25)^D41 -> 0.8798069 | E42: =1/(1+Hipotesis!$C$25)^E41 -> 0.80781567 | F42: =1/(1+Hipotesis!$C$25)^F41 -> 0.74171521 | G42: =1/(1+Hipotesis!$C$25)^G41 -> 0.6810235 | H42: —
B43: PV of FCFF (explicit period) | C43: =C36*C42 -> 3581.7349 | D43: =D36*D42 -> 4229.5131 | E43: =E36*E42 -> 4274.7953 | F43: =F36*F42 -> 3935.9052 | G43: =G36*G42 -> 3732.2483 | H43: (see TV below)
B44: Σ PV of explicit FCFF | C44: =SUM(C43:G43) -> 19754.197
B46: Cálculos de Valor Terminal (4 métodos)
B47: Method 1: Gordon Growth perpetuity | C47: =G36*(1+Hipotesis!$C$47)/(Hipotesis!$C$25-Hipotesis!$C$47) -> 80875.133 | D47: TV nominal | G47: =C47*G42 -> 55077.866 | H47: (PV)
B48: Method 2: Exit EV/EBITDA × FY30 EBITDA | C48: =Hipotesis!$C$50*(G26+G31) -> 66244.539 | D48: EV exit | G48: =C48*G42 -> 45114.088
B49: Method 3: Exit EV/EBIT × FY30 EBIT | C49: =Hipotesis!$C$51*G26 -> 78215.036 | D49: EV exit | G49: =C49*G42 -> 53266.277
B50: Method 4: H-Model (fade gST → gLT) | C50: =(G36*(1+Hipotesis!$C$47)+G36*Hipotesis!$C$48*(G17-Hipotesis!$C$47))/(Hipotesis!$C$25-Hipotesis!$C$47) -> 84175.789 | D50: EV total | G50: =C50*G42 -> 57325.69
B51: Method 5: Exit EV/Revenue × FY30 Revenue | C51: =Hipotesis!$C$52*G16 -> 32457.118 | D51: Cross-check | G51: =C51*G42 -> 22104.06
B53: F. PUENTE EV → EQUITY → PRICE TARGET (8 metodologías)
B54: Método | C54: EV ($mm) | D54: (+) Cash | E54: (−) Debt | F54: (+) Eq.inv | G54: Equity ($mm) | H54: Shares (M) | I54: Price ($)
B55: 1. DCF Gordon Growth | C55: =C44+G47 -> 74832.063 | D55: =Hipotesis!$C$15 -> 1930 | E55: =-Hipotesis!$C$14 -> -12200 | F55: =Hipotesis!$C$16 -> 715 | G55: =C55+D55+E55+F55 -> 65277.063 | H55: =Hipotesis!$C$8 -> 1153 | I55: =G55/H55 -> 56.614972 | J55: =I55 -> 56.614972
B56: 2. DCF H-Model (fade) | C56: =G50 -> 57325.69 | D56: =Hipotesis!$C$15 -> 1930 | E56: =-Hipotesis!$C$14 -> -12200 | F56: =Hipotesis!$C$16 -> 715 | G56: =C56+D56+E56+F56 -> 47770.69 | H56: =Hipotesis!$C$8 -> 1153 | I56: =G56/H56 -> 41.431648 | J56: =I56 -> 41.431648
B57: 3. DCF Exit EV/EBITDA | C57: =C44+G48 -> 64868.284 | D57: =Hipotesis!$C$15 -> 1930 | E57: =-Hipotesis!$C$14 -> -12200 | F57: =Hipotesis!$C$16 -> 715 | G57: =C57+D57+E57+F57 -> 55313.284 | H57: =Hipotesis!$C$8 -> 1153 | I57: =G57/H57 -> 47.97336 | J57: =I57 -> 47.97336
B58: 4. DCF Exit EV/EBIT | C58: =C44+G49 -> 73020.474 | D58: =Hipotesis!$C$15 -> 1930 | E58: =-Hipotesis!$C$14 -> -12200 | F58: =Hipotesis!$C$16 -> 715 | G58: =C58+D58+E58+F58 -> 63465.474 | H58: =Hipotesis!$C$8 -> 1153 | I58: =G58/H58 -> 55.043776 | J58: =I58 -> 55.043776
B59: 5. DCF Exit EV/Revenue | C59: =C44+G51 -> 41858.257 | D59: =Hipotesis!$C$15 -> 1930 | E59: =-Hipotesis!$C$14 -> -12200 | F59: =Hipotesis!$C$16 -> 715 | G59: =C59+D59+E59+F59 -> 32303.257 | H59: =Hipotesis!$C$8 -> 1153 | I59: =G59/H59 -> 28.016701 | J59: =I59 -> 28.016701
B60: 6. NTM P/E × FY27E EPS | C60: — | D60: — | E60: — | F60: — | G60: =Hipotesis!$C$53*D30 -> 72751.384 | H60: =Hipotesis!$C$8 -> 1153 | I60: =G60/H60 -> 63.097471 | J60: =I60 -> 63.097471
B61: 7. NTM EV/EBITDA × FY27E EBITDA | C61: =Hipotesis!$C$50*(D26+D31) -> 60283.498 | D61: =Hipotesis!$C$15 -> 1930 | E61: =-Hipotesis!$C$14 -> -12200 | F61: =Hipotesis!$C$16 -> 715 | G61: =C61+D61+E61+F61 -> 50728.498 | H61: =Hipotesis!$C$8 -> 1153 | I61: =G61/H61 -> 43.996962 | J61: =I61 -> 43.996962
B62: 8. NTM EV/Revenue × FY27E Revenue | C62: =Hipotesis!$C$52*D16 -> 29887.989 | D62: =Hipotesis!$C$15 -> 1930 | E62: =-Hipotesis!$C$14 -> -12200 | F62: =Hipotesis!$C$16 -> 715 | G62: =C62+D62+E62+F62 -> 20332.989 | H62: =Hipotesis!$C$8 -> 1153 | I62: =G62/H62 -> 17.634856 | J62: =I62 -> 17.634856
B64: G. ESTADISTICAS DE LAS 8 VALORACIONES
B65: Promedio | J65: =AVERAGE(J55:J62) -> 44.226218
B66: Mediana | J66: =MEDIAN(J55:J62) -> 45.985161
B67: Mínimo | J67: =MIN(J55:J62) -> 17.634856
B68: Máximo | J68: =MAX(J55:J62) -> 63.097471
B69: Spot price | J69: =Hipotesis!$C$6 -> 49.49
B70: Upside (Mediana vs Spot) | J70: =J66/J69-1 -> -0.070819129
B73: H. CAPEX SPLIT MEMO — Maintenance vs Growth
B74: Driver | C74: FY2026E | D74: FY2027E | E74: FY2028E | F74: FY2029E | G74: FY2030E | H74: Terminal
B75: Total capex ($mm) | C75: =-C33 -> 4393.4625 | D75: =-D33 -> 4383.5717 | E75: =-E33 -> 4437.9334 | F75: =-F33 -> 4524.0407 | G75: =-G33 -> 4652.1869 | H75: =-H33 -> 4760.3773
B76: Maintenance capex ($mm) | C76: =C75*Hipotesis!C73 -> 3734.4431 | D76: =D75*Hipotesis!D73 -> 3594.5288 | E76: =E75*Hipotesis!E73 -> 3772.2434 | F76: =F75*Hipotesis!F73 -> 3981.1558 | G76: =G75*Hipotesis!G73 -> 4186.9682 | H76: =H75*Hipotesis!H73 -> 4522.3584
B77: Growth capex ($mm) | C77: =C75*Hipotesis!C74 -> 659.01937 | D77: =D75*Hipotesis!D74 -> 789.04291 | E77: =E75*Hipotesis!E74 -> 665.69001 | F77: =F75*Hipotesis!F74 -> 542.88488 | G77: =G75*Hipotesis!G74 -> 465.21869 | H77: =H75*Hipotesis!H74 -> 238.01886
B78: Implied maintenance capex / Boe ($/Boe) | C78: =C76/C18 -> 6.3459673 | D78: =D76/D18 -> 5.8931049 | E78: =E76/E18 -> 6.0144833 | F78: =F76/F18 -> 6.2032431 | G78: =G76/G18 -> 6.40686 | H78: =H76/H18 -> 6.920071 | I78: Sense check vs Hipotesis F&D assumption ($10/Boe). >$15 = expensive; <$8 = optimistic
B79: Implied YoY production growth from growth capex | C79: =C18/Historico!G86-1 -> 0.9158166 | D79: =D18/C18-1 -> 0.036501126 | E79: =E18/D18-1 -> 0.028261536 | F79: =F18/E18-1 -> 0.02326705 | G79: =G18/F18-1 -> 0.018272583 | H79: =H18/G18-1 -> 0 | I79: Match this vs growth capex / total capex — high growth capex should imply high prod growth

Sheet DuPont_WC
B2: DEVON ENERGY — DuPont Decomposition + Análisis E&P (F&D, Recycle, RRR)
B3: Periodo FY21-FY25 anual + Q1 2026 (annualized donde aplique). Datos en $mm except ratios y operacionales.
B5: 1. INPUTS HISTORICOS (Source: DVN 10-K FY21-FY25 + Q1 2026 8-K)
C6: FY2021 | D6: FY2022 | E6: FY2023 | F6: FY2024 | G6: FY2025 | H6: Q1 2026
B7: Revenue ($mm) | C7: 12206 | D7: 19169 | E7: 15258 | F7: 15938 | G7: 17188 | H7: 3807 | I7: Income Statement (10-K + 8-K)
B8: Operating Income ($mm) | C8: 6628 | D8: 11555 | E8: 5896 | F8: 5309 | G8: 3834 | H8: 275
B9: Net Income ($mm) | C9: 2813 | D9: 6015 | E9: 3747 | F9: 2891 | G9: 2642 | H9: 120
B10: Total Assets ($mm) | C10: 21025 | D10: 23721 | E10: 23943 | F10: 30904 | G10: 31599 | H10: 32543 | I10: Balance Sheet (10-K)
B11: Stockholders' Equity ($mm) | C11: 7188 | D11: 8662 | E11: 9214 | F11: 13988 | G11: 15528 | H11: 15428
B12: Total Debt (incl. current portion) ($mm) | C12: 6531 | D12: 6452 | E12: 6149 | F12: 8880 | G12: 8389 | H12: 8386
B13: Cash + STI ($mm) | C13: 2268 | D13: 1454 | E13: 875 | F13: 846 | G13: 1434 | H13: 1815
B14: Operating Cash Flow ($mm) | C14: 4899 | D14: 8538 | E14: 6498 | F14: 6906 | G14: 6711 | H14: 1655 | I14: Cash Flow Statement
B15: Capex ($mm) | C15: 1971 | D15: 2517 | E15: 3766 | F15: 3713 | G15: 3713 | H15: 848
B16: Free Cash Flow ($mm) | C16: 2928 | D16: 6021 | E16: 2732 | F16: 3193 | G16: 2998 | H16: 807
B17: D&A ($mm) | C17: 1763 | D17: 2230 | E17: 2585 | F17: 2810 | G17: 3595 | H17: 904
B18: Effective Tax Rate | C18: 0.0921 | D18: 0.1203 | E18: 0.1532 | F18: 0.1253 | G18: 0.2337 | H18: 0.2771 | I18: 10-K Nota Income Taxes
B20: 2. DUPONT DECOMPOSITION (ROE = Tax Burden × Interest Burden × OpMargin × Asset Turnover × Equity Multiplier)
C21: FY2021 | D21: FY2022 | E21: FY2023 | F21: FY2024 | G21: FY2025 | H21: Q1 2026
B22: Tax Burden = 1 − effective tax rate | C22: =1-C18 -> 0.9079 | D22: =1-D18 -> 0.8797 | E22: =1-E18 -> 0.8468 | F22: =1-F18 -> 0.8747 | G22: =1-G18 -> 0.7663 | H22: =1-H18 -> 0.7229 | I22: Retención post-tax — E&P tax rate variable con depletion/IDC
B23: Interest Burden = EBT / EBIT (proxy: (NI/(1-T)) / OI) | C23: =(C9/(1-C18))/C8 -> 0.46746513 | D23: =(D9/(1-D18))/D8 -> 0.59174022 | E23: =(E9/(1-E18))/E8 -> 0.75049079 | F23: =(F9/(1-F18))/F8 -> 0.62255287 | G23: =(G9/(1-G18))/G8 -> 0.89925297 | H23: =(H9/(1-H18))/H8 -> 0.60362932 | I23: ~1.0 — DVN poco non-op income; interest expense ~$300-500M
B24: Operating Margin = EBIT / Revenue | C24: =C8/C7 -> 0.54301163 | D24: =D8/D7 -> 0.60279618 | E24: =E8/E7 -> 0.38642024 | F24: =F8/F7 -> 0.33310328 | G24: =G8/G7 -> 0.2230626 | H24: =H8/H7 -> 0.072235356 | I24: Operating margin colapsa en cíclos bajos (FY25: 22%; FY22: 60%)
B25: Asset Turnover = Revenue / Total Assets | C25: =C7/C10 -> 0.58054697 | D25: =D7/D10 -> 0.80810253 | E25: =E7/E10 -> 0.6372635 | F25: =F7/F10 -> 0.51572612 | G25: =G7/G10 -> 0.54394126 | H25: =H7/H10 -> 0.11698368 | I25: Asset turnover ~0.5-0.8× — E&P es capital-intensive
B26: Equity Multiplier = Total Assets / Equity | C26: =C10/C11 -> 2.9250139 | D26: =D10/D11 -> 2.738513 | E26: =E10/E11 -> 2.5985457 | F26: =F10/F11 -> 2.2093223 | G26: =G10/G11 -> 2.0349691 | H26: =H10/H11 -> 2.1093466 | I26: Equity multiplier ~2.0-3.0× — debt/equity moderate
B28: ROE (DuPont) = product of 5 factors | C28: =C22*C23*C24*C25*C26 -> 0.39134669 | D28: =D22*D23*D24*D25*D26 -> 0.69441238 | E28: =E22*E23*E24*E25*E26 -> 0.40666377 | F28: =F22*F23*F24*F25*F26 -> 0.20667715 | G28: =G22*G23*G24*G25*G26 -> 0.17014426 | H28: =H22*H23*H24*H25*H26 -> 0.0077780659 | I28: ROE GAAP — ver cross-check abajo
B29: ROE cross-check = NI / period-end Equity | C29: =C9/C11 -> 0.39134669 | D29: =D9/D11 -> 0.69441238 | E29: =E9/E11 -> 0.40666377 | F29: =F9/F11 -> 0.20667715 | G29: =G9/G11 -> 0.17014426 | H29: =H9/H11*4 -> 0.031112263 | I29: Q1 26 anualizado: NI×4/Equity period-end
B31: 3. ROS2 OPERATIVO (NOPAT / Invested Capital) — métrica relevante para valoración DCF
C32: FY2021 | D32: FY2022 | E32: FY2023 | F32: FY2024 | G32: FY2025 | H32: Q1 2026
B33: NOPAT = EBIT × (1 − effective tax rate) | C33: =C8*(1-C18) -> 6017.5612 | D33: =D8*(1-D18) -> 10164.933 | E33: =E8*(1-E18) -> 4992.7328 | F33: =F8*(1-F18) -> 4643.7823 | G33: =G8*(1-G18) -> 2937.9942 | H33: =H8*(1-H18) -> 198.7975 | I33: Excluye non-op income (más conservador que NI)
B34: Invested Capital = Equity + Debt − Excess Cash/STI | C34: =C11+C12-C13 -> 11451 | D34: =D11+D12-D13 -> 13660 | E34: =E11+E12-E13 -> 14488 | F34: =F11+F12-F13 -> 22022 | G34: =G11+G12-G13 -> 22483 | H34: =H11+H12-H13 -> 21999 | I34: Capital efectivamente desplegado en operaciones
B35: ROS2 operativo = NOPAT / S2 | C35: =C33/C34 -> 0.5255053 | D35: =D33/D34 -> 0.74413862 | E35: =E33/E34 -> 0.3446116 | F35: =F33/F34 -> 0.21087014 | G35: =G33/G34 -> 0.13067625 | H35: =H33/H34 -> 0.0090366608 | I35: NOPAT/IC: lectura clave de creación de valor en E&P. Mid-cycle target >12%
B37: ROS2 − WACC spread (WACC=9.12% from Hipotesis!$C$25) | C37: =C35-Hipotesis!$C$25 -> 0.43638691 | D37: =D35-Hipotesis!$C$25 -> 0.65502023 | E37: =E35-Hipotesis!$C$25 -> 0.25549321 | F37: =F35-Hipotesis!$C$25 -> 0.12175176 | G37: =G35-Hipotesis!$C$25 -> 0.041557866 | H37: =H35-Hipotesis!$C$25 -> -0.080081726 | I37: Spread ROS2−WACC: E&P depende del ciclo, spread negativo en cíclos bajos es normal
B39: 4. MÉTRICAS E&P ESPECÍFICAS — F&D Cost, Recycle Ratio, Reserve Replacement, ROCE
C40: FY2021 | D40: FY2022 | E40: FY2023 | F40: FY2024 | G40: FY2025 | H40: Q1 2026
B41: Total production (MMBoe annual) | C41: 220 | D41: 232 | E41: 245 | F41: 269 | G41: 307 | H41: 76.6 | I41: 10-K segment data; Q1 = 851 MBoe/d × 90 days
B42: Proved reserves YE (MMBoe) | C42: 1604 | D42: 1844 | E42: 1814 | F42: 1953 | G42: 2428 | H42: — | I42: 10-K reserves disclosures; YE25 2,428 MMBoe
B43: Capex per Boe ($/Boe) | C43: =C15/C41 -> 8.9590909 | D43: =D15/D41 -> 10.849138 | E43: =E15/E41 -> 15.371429 | F43: =F15/F41 -> 13.802974 | G43: =G15/G41 -> 12.094463 | H43: =H15/H41 -> 11.070496 | I43: Proxy F&D cost: DVN histórico ~$9-15/Boe. Mid-cycle target <$12/Boe
B44: Production cost per Boe ($/Boe, from 10-K) | C44: 6.69 | D44: 9.04 | E44: 10.11 | F44: 10.75 | G44: 11.62 | H44: — | I44: 10-K production cost disclosure; FY25 $11.62/Boe is industry-leading
B45: Field-level cash margin ($/Boe) | C45: =(C7-C44*C41)/C41 -> 48.791818 | D45: =(D7-D44*D41)/D41 -> 73.585 | E45: =(E7-E44*E41)/E41 -> 52.167551 | F45: =(F7-F44*F41)/F41 -> 48.499071 | G45: =(G7-G44*G41)/G41 -> 44.366971 | H45: 27.78 | I45: Q1 2026: $27.78/Boe reported. Métrica clave de unit economics
B46: Recycle ratio (cash margin / Capex per Boe) | C46: =C45/C43 -> 5.446068 | D46: =D45/D43 -> 6.7825665 | E46: =E45/E43 -> 3.3937998 | F46: =F45/F43 -> 3.5136682 | G46: =G45/G43 -> 3.6683706 | H46: =H45/H43 -> 2.5093726 | I46: Recycle >2× excelente, >1.5× bueno, <1× destruyendo valor
B47: Reserves growth YoY % | C47: n/a | D47: =D42/C42-1 -> 0.14962594 | E47: =E42/D42-1 -> -0.01626898 | F47: =F42/E42-1 -> 0.07662624 | G47: =G42/F42-1 -> 0.24321557 | H47: — | I47: YE25 +24% YoY refleja Permian additions principalmente
B48: Reserve life (R/P, años) | C48: =C42/C41 -> 7.2909091 | D48: =D42/D41 -> 7.9482759 | E48: =E42/E41 -> 7.4040816 | F48: =F42/F41 -> 7.260223 | G48: =G42/G41 -> 7.9087948 | H48: — | I48: ~7-8 años típico Permian shale (high decline); >10 años indica más diversificación
B49: ROCE = NOPAT / Capital Employed | C49: =C8*(1-C18)/(C11+C12-C13) -> 0.5255053 | D49: =D8*(1-D18)/(D11+D12-D13) -> 0.74413862 | E49: =E8*(1-E18)/(E11+E12-E13) -> 0.3446116 | F49: =F8*(1-F18)/(F11+F12-F13) -> 0.21087014 | G49: =G8*(1-G18)/(G11+G12-G13) -> 0.13067625 | H49: =H8*(1-H18)/(H11+H12-H13)*4 -> 0.036146643 | I49: ROCE mid-cycle target >12%; Q1 26 anualizado refleja bottom-of-cycle
B50: OCF / Revenue % | C50: =C14/C7 -> 0.40135999 | D50: =D14/D7 -> 0.44540665 | E50: =E14/E7 -> 0.42587495 | F50: =F14/F7 -> 0.43330405 | G50: =G14/G7 -> 0.39044682 | H50: =H14/H7 -> 0.43472551 | I50: OCF/Rev ~40-45% en DVN — alta calidad de earnings (high cash conversion)
B51: FCF / Revenue % | C51: =C16/C7 -> 0.23988203 | D51: =D16/D7 -> 0.31410089 | E51: =E16/E7 -> 0.17905361 | F51: =F16/F7 -> 0.20033881 | G51: =G16/G7 -> 0.17442402 | H51: =H16/H7 -> 0.21197794 | I51: FCF/Rev: 18-31% cíclico — máximo FY22 cíclo alto, mínimo FY23-25 reinversión + ciclo bajo
B52: Net Debt / EBITDA (leverage, leve proxy: EBIT+DA) | C52: =(C12-C13)/(C8+C17) -> 0.50804433 | D52: =(D12-D13)/(D8+D17) -> 0.36256801 | E52: =(E12-E13)/(E8+E17) -> 0.62186063 | F52: =(F12-F13)/(F8+F17) -> 0.98953073 | G52: =(G12-G13)/(G8+G17) -> 0.93619599 | H52: — | I52: Target <1.0× through-cycle; FY25 ~1.0× sano; pro-forma combined ~1.4× post-merger
B55: 5. SÍNTESIS — Lectura E&P de DuPont + métricas operativas
B56: ▸ ROE GAAP DVN ciclico: peak ~70% FY22 (cíclo oil $96/Bbl), bottom ~17% FY25 (cíclo $66/Bbl). Q1 26 anualizado ~3% es bottom-of-cycle señal.
B57: ▸ Operating margin: 60% FY22 → 22% FY25 = swing de 38pp por commodity prices. Esta es la realidad fundamental del E&P. Mid-cycle target ~35-40%.
B58: ▸ Asset turnover ~0.5-0.7×: E&P es capital-intensive estructuralmente. La fusión con Coterra eleva total assets a ~$65B pro-forma, requiere producción combinada para mantener turnover.
B59: ▸ Equity multiplier ~2.0-2.5×: moderate leverage. Pro-forma post-merger ~2.2× con debt $12.2B, equity $30B+ combined. Sustainable through-cycle.
B60: ▸ ROCE peak ~50%+ FY22 vs trough ~10% FY25: la métrica de creación de valor más relevante. Mid-cycle target 15-20%. Q1 26 anualizado refleja bottom; debe normalizar con sinergias + ciclo.
B61: ▸ Capex per Boe (proxy F&D cost): $9-15/Boe range. FY25 $12.1/Boe ($3,713M / 307 MMBoe). Excellent for Permian unconventional. Target terminal $10-11/Boe asume eficiencia operativa post-merger.
B62: ▸ Production cost $11.62/Boe FY25 industry-leading: refleja DVN focus en tier-1 inventory + scale operacional. Coterra adds Marcellus low-cost gas. Pro-forma combined producción cost <$11/Boe probable.
B63: ▸ Recycle ratio: ~3-5× en cíclos altos (excelente), ~1.5-2× en cíclos bajos. Es el "north star" del E&P investing — capacidad de regenerar valor por barril producido.
B64: ▸ Reserve life (R/P): ~7-8 años Permian-heavy. Coterra Marcellus aporta gas de longer-life. Pro-forma R/P puede subir a ~9 años, lo cual reduce el riesgo de inventory depletion.
B65: ▸ Conclusión: DVN tiene una franquicia E&P de tier-1 (margin, cost, recycle) pero está atrapado por la realidad cíclica del E&P. El valor "compounder-style" no existe; el valor está en disciplina de capital + retornos de FCF normalizado. La fusión Coterra mejora el mix (diversifica gas) y unit economics si las sinergias se realizan.

Sheet Reverse_DCF
B2: DEVON ENERGY — REVERSE DCF: ¿Qué pricea el mercado a $49.49?
B3: Dado spot $49.49 vs mediana modelo $45.99, ¿qué assumptions se requieren? Closed-form solutions.
B5: INPUTS COMUNES (link a Modelo/Hipotesis)
B6: Spot price ($) | C6: =Hipotesis!$C$6 -> 49.49
B7: Shares diluidas (M) | C7: =Hipotesis!$C$8 -> 1153
B8: Cash + STI ($mm) | C8: =Hipotesis!$C$15 -> 1930
B9: Equity & other investments ($mm) | C9: =Hipotesis!$C$16 -> 715
B10: Total Debt ($mm) | C10: =Hipotesis!$C$14 -> 12200
B11: WACC (caso base) | C11: =Hipotesis!$C$25 -> 0.089118387
B12: Terminal g (caso base) | C12: =Hipotesis!$C$47 -> 0.02
B13: Σ PV explicit FCFF FY26-FY30 (Modelo) | C13: =Modelo!$C$44 -> 19754.197
B14: FY30E FCFF (Modelo) | C14: =Modelo!$G$36 -> 5480.3517
B15: FY30E EBIT (Modelo) | C15: =Modelo!$G$26 -> 8690.5595
B16: FY30E D&A (Modelo) | C16: =Modelo!$G$31 -> 3353.9022
B17: FY30E Revenue (Modelo) | C17: =Modelo!$G$16 -> 21638.078
B18: FY30E NOPAT (Modelo) | C18: =Modelo!$G$30 -> 6778.6364
B19: Effective tax rate | C19: =Hipotesis!$C$13 -> 0.22
B21: CÁLCULOS INTERMEDIOS (Δ implícita vs caso base)
B22: Equity target = Spot × Shares ($mm) | C22: =C6*C7 -> 57061.97
B23: (+) Debt | C23: =C10 -> 12200
B24: (−) Cash + STI | C24: =-C8 -> -1930
B25: (−) Equity & other investments | C25: =-C9 -> -715
B26: Enterprise Value target ($mm) | C26: =C22+C10-C8-C9 -> 66616.97
B27: (−) Σ PV explicit FCFF | C27: =-C13 -> -19754.197
B28: PV(TV) implícito ($mm) | C28: =C26-C13 -> 46862.773
B29: TV nominal implícito (×(1+WACC)^5) | C29: =C28*(1+C11)^5 -> 71813.06
B31: A. ¿Qué g_terminal implica el spot? (manteniendo WACC, FCFF base, bridge)
B32: Fórmula: g = (TV·WACC − FCFF_30) / (TV + FCFF_30)
B33: g_terminal implícito (Gordon) | C33: =(C29*C11-C14)/(C29+C14) -> 0.011896387 | D33: vs base 2.0%: | E33: =C33-C12 -> -0.0081036126 | G33: Si >0 ↑ → mercado más optimista que base 2.0%. Si <0 → más pesimista.
B35: B. ¿Qué WACC implica el spot? (manteniendo g_terminal=3%, FCFF base, bridge)
B36: Aproximación: como WACC afecta TV y descuento, no hay fórmula cerrada. Tabla de precios implícitos:
B37: WACC → | C37: 0.075 | D37: 0.085 | E37: 0.0912 | F37: 0.095 | G37: 0.105 | H37: 0.115
B38: Precio implícito ($) | C38: =((Modelo!C36/(1+C$37)^0.5 + Modelo!D36/(1+C$37)^1.5 + Modelo!E36/(1+C$37)^2.5 + Modelo!F36/(1+C$37)^3.5 + Modelo!G36/(1+C$37)^4.5)+(Modelo!G36*(1+C12)/(C$37-C12))/(1+C$37)^5+C8+C9-C10)/C7 -> 70.817653 | D38: =((Modelo!C36/(1+D$37)^0.5 + Modelo!D36/(1+D$37)^1.5 + Modelo!E36/(1+D$37)^2.5 + Modelo!F36/(1+D$37)^3.5 + Modelo!G36/(1+D$37)^4.5)+(Modelo!G36*(1+C12)/(D$37-C12))/(1+D$37)^5+C8+C9-C10)/C7 -> 58.613157 | E38: =((Modelo!C36/(1+E$37)^0.5 + Modelo!D36/(1+E$37)^1.5 + Modelo!E36/(1+E$37)^2.5 + Modelo!F36/(1+E$37)^3.5 + Modelo!G36/(1+E$37)^4.5)+(Modelo!G36*(1+C12)/(E$37-C12))/(1+E$37)^5+C8+C9-C10)/C7 -> 52.776896 | F38: =((Modelo!C36/(1+F$37)^0.5 + Modelo!D36/(1+F$37)^1.5 + Modelo!E36/(1+F$37)^2.5 + Modelo!F36/(1+F$37)^3.5 + Modelo!G36/(1+F$37)^4.5)+(Modelo!G36*(1+C12)/(F$37-C12))/(1+F$37)^5+C8+C9-C10)/C7 -> 49.679775 | G38: =((Modelo!C36/(1+G$37)^0.5 + Modelo!D36/(1+G$37)^1.5 + Modelo!E36/(1+G$37)^2.5 + Modelo!F36/(1+G$37)^3.5 + Modelo!G36/(1+G$37)^4.5)+(Modelo!G36*(1+C12)/(G$37-C12))/(1+G$37)^5+C8+C9-C10)/C7 -> 42.861743 | H38: =((Modelo!C36/(1+H$37)^0.5 + Modelo!D36/(1+H$37)^1.5 + Modelo!E36/(1+H$37)^2.5 + Modelo!F36/(1+H$37)^3.5 + Modelo!G36/(1+H$37)^4.5)+(Modelo!G36*(1+C12)/(H$37-C12))/(1+H$37)^5+C8+C9-C10)/C7 -> 37.490029
B39: WACC implícito (interpolado vs spot) | C39: =SLOPE(C37:H37,C38:H38)*C6+INTERCEPT(C37:H37,C38:H38) -> 0.097387905 | D39: vs base 8.9%: | E39: =C39-C11 -> 0.0082695181 | G39: (FORECAST.LINEAR sobre la tabla — válida en el entorno del spot $49.49)
B41: C. ¿Qué margen EBIT FY30E implica el spot? (manteniendo Rev FY30E, Capex/Rev, g, WACC)
B42: Aprox: terminal margin solo afecta TV (PV explícito a caso base).
B43: FCFF terminal implícito ($mm) | C43: =C29*(C11-C12)/(1+C12) -> 4866.2773 | D43: vs base: | E43: =C43/C14-1 -> -0.11205018
B44: NOPAT terminal implícito = FCFF − D&A − Capex_signed − ΔWC_signed | C44: =C43-C16-Modelo!G33-Modelo!G35 -> 6164.562
B45: EBIT terminal implícito = NOPAT / (1−T) | C45: =C44/(1-C19) -> 7903.2847
B46: EBIT margin FY30E implícito | C46: =C45/C17 -> 0.36524892 | D46: vs base: | E46: =C46-C15/C17 -> -0.036383769 | G46: Si <base, mercado descuenta margen operativo presionado (oil prices bajos persistentes).
B48: D. ¿Qué Capex/Rev terminal implica el spot? (manteniendo EBIT margin base, g, WACC)
B49: Capex terminal implícito ($mm) | C49: =C18+C16-C43-Modelo!G35 -> 5266.2612
B50: Capex/Rev terminal implícito | C50: =C49/C17 -> 0.24337934 | D50: vs base 22.5%: | E50: =C50-Hipotesis!$H$39 -> 0.02337934 | G50: Si >base 22.5%, mercado descuenta capex inflation y growth capex sostenido.
B52: E. ¿Qué Revenue CAGR FY25→FY30 implica el spot? (escala uniforme, margenes y Capex/Rev fijos)
B53: Base EV = PV_explicit + PV(TV_base) (from Modelo) | C53: =C13 + C14*(1+C12)/(C11-C12)/(1+C11)^5 -> 72530.572
B54: Scaling factor k = Target EV / Base EV | C54: =C26/C53 -> 0.91846745
B55: Implied FY30E Revenue = Base × k | C55: =C17*C54 -> 19873.871
B56: Revenue CAGR FY25→FY30 implícito | C56: =(C55/Historico!G6)^(1/5)-1 -> 0.029464615 | D56: vs base: | E56: =C56-((C17/Historico!G6)^(1/5)-1) -> -0.017660724 | G56: Tasa de crecimiento que necesita DVN para que $49.49 sea justo, manteniendo ratios.
B58: F. SÍNTESIS — qué pricea el mercado vs caso base
B59: Variable | C59: Base case | D59: Implícito (ceteris paribus) | E59: Δ | F59: Lectura
B60: Terminal g (perpetuidad) | C60: =C12 -> 0.02 | D60: =C33 -> 0.011896387 | E60: =D60-C60 -> -0.0081036126 | F60: Implícito 1.2% < base 2.0% → mercado algo más conservador en terminal growth
B61: WACC | C61: =C11 -> 0.089118387 | D61: =C39 -> 0.097387905 | E61: =D61-C61 -> 0.0082695181 | F61: Implícito 9.7% > base 8.9% → mercado exige ~80bp más retorno (riesgo cíclico)
B62: EBIT margin FY30E | C62: =C15/C17 -> 0.40163268 | D62: =C45/C17 -> 0.36524892 | E62: =D62-C62 -> -0.036383769 | F62: Si implícito margen > base, mercado pricea upside cíclico (oil higher mid-cycle)
B63: Capex/Rev terminal | C63: =Hipotesis!$H$39 -> 0.22 | D63: =C49/C17 -> 0.24337934 | E63: =D63-C63 -> 0.02337934 | F63: Si implícito Capex/Rev < base 22.5%, mercado expects normalización a lower capex intensity
B64: Revenue CAGR FY25→FY30 | C64: =(C17/Historico!G6)^(1/5)-1 -> 0.047125339 | D64: =(C55/Historico!G6)^(1/5)-1 -> 0.029464615 | E64: =D64-C64 -> -0.017660724 | F64: Es la combinación implícita de growth de volumen × precio realizado FY25→FY30
B66: G. LECTURA INTEGRAL
B67: ▸ El reverse-DCF se ancla en el método DCF Gordon, cuyo valor base es $56.61 (WACC 8.9%, g 2.0%). El spot $49.49 está POR DEBAJO de ese ancla DCF, de modo que el mercado descuenta un escenario marginalmente MÁS CONSERVADOR que mi caso DCF base: WACC implícito ~9.7% (vs 8.9%), g implícito ~1.2% (vs 2.0%) y Revenue CAGR FY25-FY30 implícito ~3% (vs ~5% base).
B68: ▸ Importante: el spot $49.49 está POR ENCIMA de la mediana de los 8 métodos ($45.99) porque los múltiplos de revenue (EV/Revenue $17-28) arrastran la mediana hacia abajo. Frente al DCF está barato; frente a la mediana global está caro. Esta divergencia es la señal central: la valoración depende críticamente de qué metodología se priorice.
B69: ▸ Si crees que DVN ejecuta sinergias 100% y oil mid-cycle se mantiene en $70-75/Bbl, el DCF Gordon $56.61 es defendible y hay upside ~14% vs spot. Si crees que el ciclo queda en $55-65/Bbl y las sinergias se realizan parcialmente, el spot ya descuenta razonablemente y los múltiplos de revenue avisan de downside.
B70: ▸ Las 8 metodologías rinden $17.63-$63.10. El spot $49.49 cae entre el DCF Exit EV/EBITDA ($47.97) y el DCF Exit EV/EBIT ($55.04) — coherente con un nombre fairly-to-slightly-fully valued en este punto del ciclo.
B71: ▸ El reverse-DCF en E&P es especialmente revelador: hace explícito el deck de precios del crudo que el mercado descuenta. La apuesta no es sobre "el spot vs mi target" sino sobre "mi deck de oil/gas mid-cycle vs el deck implícito del mercado". Ahí está la verdadera decisión de inversión.

Sheet Conclusiones
B2: DEVON ENERGY — CONCLUSIONES Y SÍNTESIS DE LA VALORACIÓN
B3: Síntesis cualitativa. Compañera de Modelo (números) y DuPont_WC (returns).
B5: 1. TESIS CENTRAL
B6: Tesis | C6: DVN (post-Coterra) es una tesis E&P cíclica. El valor depende del FCF mid-cycle through-the-cycle, la disciplina de capital, y la credibilidad de los $1B en sinergias. NO es un compounder; sí puede ser un retorno-de-capital story atractivo si el ciclo acompaña y el balance se mantiene.
B8: 2. EL DEBATE CENTRAL — ¿Cuánto del FCF FY22 ($6B) es repetible mid-cycle?
B9: Bear case | C9: BEAR: Oil $50-55/Bbl, gas $1.50/Mcf, capex inflation aprieta margenes, sinergias se realizan solo 50% del target, el equity ratio buyback se ralentiza. Precio implícito: $25-35.
B11: Bull case | C11: BULL: Oil $75-85/Bbl sostenido, gas $3-4/Mcf con demanda LNG/AI, sinergias se realizan 100%+ con upside operacional, productividad de inventario Permian+Marcellus excede expectativas. Precio implícito: $70-85.
B13: Mi lectura | C13: BASE (lectura del modelo): asumiendo Oil $62-67/Bbl, gas $2-2.80/Mcf normalized, sinergias 100% ejecutadas, maintenance capex disciplinado, el FCFF FY26-FY30 es $3.7-5.5B/año. La mediana 8 metodologías = $45.99, casi en línea con spot. Margen de seguridad limitado.
B15: 3. ESCENARIOS DE VALORACIÓN
B16: Escenario | C16: Drivers clave | D16: Precio implícito
B17: Bear (30%) | C17: ~$30 | D17: 30%
B18: Base (45%) | C18: ~$46 | D18: 45%
B19: Bull (25%) | C19: ~$70 | D19: 25%
B20: Probabilistic mean | C20: =0.3*30+0.45*46+0.25*70 -> 47.2 | D20: 100%
B22: 4. DRIVERS CLAVE — RANKED BY SENSITIVITY
B23: #1 — Precio realizado del crudo ($/Bbl) | C23: Cada +$5/Bbl en oil realized ≈ +$8-10 precio (mayor sensibilidad del modelo). Oil = 66% del revenue upstream. WTI ~$72/Bbl Q1 26, $69/Bbl spot pet-25. Riesgo: deck OPEC+, demanda china, electrificación EV.
B24: #2 — Volumen de producción combinado (MBoe/d) | C24: Pro-forma combined 1,587 MBoe/d FY26E. Cada +5% volumen ≈ +$3-4 precio. Depende de decline rates (Permian 30%+ year-1), drilling efficiency, y capex allocation entre cuencas. La integration post-merger es clave.
B25: #3 — Sinergias realizadas vs prometidas | C25: $1,000M target = ~$11/share NPV simple. Asumimos 40% Y1, 100% Y2+. Si se realizan solo 50%, precio cae ~$5-6. Si se exceden $1.2B con upside operacional, +$3-4.
B26: #4 — Capex de mantenimiento ($/Boe) | C26: Asumimos $10/Boe terminal (F&D cost). DVN histórico $11-13/Boe. Cada +$1/Boe ≈ −$4-5 precio terminal. Inflación de servicios (rigs, frac crews, sand, steel) es el riesgo principal.
B27: #5 — WACC (8.9% computed) | C27: Cada +100bp WACC ≈ −$6-8 precio. Sensible al beta sectorial (usamos 1.20 Damodaran E&P, no 0.43 Google). Risk de re-rating si crédito spreads se amplían en downcycle.
B28: #6 — Capital allocation (buyback vs deuda) | C28: $8B authorized post-merger. Si se ejecuta dilutivamente arriba de $55 ya no es accretive. Riesgo de prociclicidad: comprar más cuando el ciclo está alto y reducir cuando está bajo.
B30: 5. RIESGOS PRINCIPALES
B31: Riesgo | C31: Magnitud / Impacto
B32: Commodity price downside | C32: Oil < $50/Bbl + gas < $1.50/Mcf simultáneo es el escenario que rompe la tesis. FCF caería de $5B a <$2B, capital returns deben ajustarse. La beta 1.20 ya incorpora algo, pero −20% en oil = −$20 precio approximate.
B33: Integración Coterra | C33: Riesgo operativo: cultura DVN (Permian/oil-focus) vs CTRA (Marcellus/gas-focus). Cumberbatch (CFO CTRA) ya fuera; Gaspar (DVN) CEO retained. Si las sinergias se retrasan 12-18 meses, valoración cae $5-8.
B34: Cost inflation servicios | C34: Rig rates, frac crews, sand, steel — cíclico con el precio del petróleo. En cíclo alto los costes suben más rápido que precios realizados (margin squeeze). Riesgo de capex inflation +10-15% en escenario alto.
B35: Reservas / decline rates | C35: Proved reserves 2,428 MMBoe DVN + ~1,200 MMBoe CTRA. Permian decline 30%+ year-1 requires continuous drilling. Si productividad por pozo cae (high-grading exhaustion), maintenance capex sube y FCF cae.
B36: Competencia / consolidación | C36: Permian: COP, FANG, OXY, EOG son rivales por tier-1 inventory. CTRA Marcellus: EQT, AR, RRC. Riesgo de re-rating relativo si DVN under-performs operationally vs peers (production growth, well productivity).
B37: Regulación / ESG / transición energética | C37: Federal lands moratoria (poco impacto, DVN ~95% state/private). Methane rules EPA — costes incrementales $50-100M/año. Carbon tax: hipotético pero existencial. Equity-friendly regulación post-2026 elections es factor binario.
B38: Macro / recesión | C38: Demanda de petróleo es pro-cíclica. Recesión EE.UU. 2026-27 = WTI puede caer a $40s temporalmente. DVN aguanta por balance (Debt/EBITDA ~1.5×) pero capital returns se ajustarían rápidamente.
B39: Tail risk geopolítico (asimétrico al alza) | C39: Oriente Medio (Irán/Israel/Hormuz), Rusia/Ucrania resolución, sanciones Venezuela. Eventos +20-30% WTI temporales benefician a DVN desproporcionadamente. Difícil de modelar; opcionalidad gratis.
B41: 6. CONCLUSIÓN — DECISIÓN DE INVERSIÓN
B42: Veredicto | C42: HOLD. Spot $49.49 vs mediana modelo $45.99 = ~7% downside según mi base case. La tesis NO es asimétrica al alza; el rango $17-$63 muestra incertidumbre cíclica genuina. Para BUY requeriría margen de seguridad +20% (precio <$38) o convicción más alta en escenario bull (oil >$80 sostenido).
B43: Recomendación | C43: HOLD con preferencia táctica de añadir sub-$40 (margen seguridad ~15% vs mediana). Posición full size justificaría confianza alta en (a) execution sinergias, (b) deck oil >$70 mid-cycle, (c) capital allocation disciplinado. Target price 12 meses: $46-52.
B44: Catalizadores a 12 meses | C44: 1) Q2-Q3 2026 ER — primeros consolidated post-merger numbers; production guidance combined; integration update. 2) Sinergias 6-month progress report Nov-2026. 3) Capital returns framework update H2-2026 (dividend variable, $8B buyback pacing). 4) FY27 budget enero-2027 — capex split mainten/growth. 5) Oil deck OPEC+ — meeting jun-2026.

Sheet Fuentes
B2: DEVON ENERGY — FUENTES Y REFERENCIAS
B3: Cita SIEMPRE fuentes primarias (SEC EDGAR) para datos históricos. Damodaran/Fed para inputs de mercado.
B5: 1. FILINGS REGULATORIOS (Filings regulador) — fuentes primarias
B6: Documento | C6: Fecha | D6: URL | E6: Uso en modelo
B7: DVN 10-K FY2025 (Form 10-K) | C7: 20-feb-2026 | D7: https://www.sec.gov/Archives/edgar/data/0001090012/000119312526056485/dvn-20251231.htm | E7: Income Statement, BS, CF FY21-FY25; segmento commodity revenue (Oil/Gas/NGL/M&M); producción Boe; reservas YE25 (2,428 MMBoe); realized prices y costes producción
B8: DVN Q1 2026 earnings 8-K | C8: 5-may-2026 | D8: https://www.sec.gov/Archives/edgar/data/0001090012/000119312526206689/d947371dex992.htm | E8: Q1 26 IS/CF: Revenue $3,807M, NI $120M, OCF $1,655M, Capex $848M; producción 851 MBoe/d; realized prices Oil $69.66/Gas $1.66/NGL $17.80
B9: Devon/Coterra Merger Agreement (S-4) | C9: 2-feb-2026 | D9: https://www.sec.gov/Archives/edgar/data/0001090012/000119312526032720/d75203dex991.htm | E9: Términos del merger: 0.70 DVN/CTRA share, $1B sinergias target, $8B buyback authorization, Clay Gaspar CEO, Shannon Young III CFO
B10: DVN/CTRA Merger Closing 425 filing | C10: 7-may-2026 | D10: https://www.sec.gov/Archives/edgar/data/0001090012/000119312526204307/d150144d425.htm | E10: Confirmación cierre operación; shareholders aprobaron 4-may-2026; combined company keeps DVN ticker
B11: CTRA 10-K FY2025 (Coterra Energy) | C11: 24-feb-2026 | D11: https://www.sec.gov/Archives/edgar/data/0000858470/000085847026000073/cog-20251231.htm | E11: Datos Coterra FY25 standalone para construir pro-forma: Revenue $7,650M, NI $1,720M, debt $3.8B, producción 747 MBoe/d Marcellus-heavy
B12: DVN 10-K FY2023 (cross-check) | C12: feb-2024 | D12: https://www.sec.gov/cgi-bin/browse-edgar?action=getcompany&CIK=0001090012&type=10-K | E12: Cross-check FY22-FY23 históricos; segment volumes y precios para serie 5-year
B13: DVN 10-K FY2021 (cross-check) | C13: feb-2022 | D13: https://www.sec.gov/cgi-bin/browse-edgar?action=getcompany&CIK=0001090012&type=10-K | E13: FY21 base year — Revenue $12.2B (NO $6.2B como aparecía en PDF original); confirma cifras XBRL
B15: 2. MERCADO Y MACRO
B16: Fuente | C16: Dato (15-may-2026) | D16: URL | E16: Uso en modelo
B17: Tipo libre de riesgo (bono soberano 10Y) | C17: DGS10: 4.5% (19-may-2026, Fed H.15) | D17: https://www.federalreserve.gov/releases/h15/ | E17: Risk-free rate input (Hipotesis!$C$9)
B18: Equity Risk Premium (recomendado: Damodaran) | C18: ERP 2026 Edition (Damodaran): ~4.5% | D18: https://pages.stern.nyu.edu/~adamodar/ | E18: Equity Risk Premium (Hipotesis!$C$10)
B19: Cotización spot DVN | C19: DVN $49.49 (19-may-2026 close estimado) | D19: Yahoo Finance / Google Finance | E19: Spot price (Hipotesis!$C$6)
B20: Rango 52 semanas DVN | C20: $30.24 (apr-2026 low) – $52.71 (peak) | D20: Yahoo Finance | E20: Contexto histórico Resumen
B21: Beta sectorial (recomendado: Damodaran Industry Beta) | C21: Beta sectorial E&P (Damodaran 2026): 1.10-1.30 range, usamos 1.20 | D21: https://pages.stern.nyu.edu/~adamodar/New_Home_Page/datafile/Betas.html | E21: Beta sector E&P (Hipotesis!$C$11) — NO usar beta Google 0.43 que sub-estima riesgo cíclico
B23: 3. PEERS Y CROSS-CHECKS
B24: Peer | C24: Métrica clave | D24: URL | E24: Uso
B25: EOG Resources — 10-K FY25 | C25: Market cap ~$70B, P/E ~10×, FCF yield ~9% | D25: https://investors.eogresources.com/ | E25: Comparable pure-play oil-weighted E&P; benchmark capital discipline
B26: Diamondback Energy (FANG) — 10-K FY25 | C26: Market cap ~$45B, P/E ~12×, FCF yield ~10% | D26: https://ir.diamondbackenergy.com/ | E26: Permian pure-play; benchmark unit economics, capex/Boe
B27: ConocoPhillips (COP) — 10-K FY25 | C27: Market cap ~$140B, P/E ~13×, dividend yield 3%+ | D27: https://www.conocophillips.com/investor-information/ | E27: Multi-basin large-cap E&P; benchmark diversification y capital allocation
B28: Occidental Petroleum (OXY) — 10-K FY25 | C28: Market cap ~$50B, P/E ~14×, Berkshire stake | D28: https://www.oxy.com/investors/ | E28: Permian + Gulf of Mexico + DAC; benchmark balance sheet recovery post-CrownRock
B30: 4. DOCUMENTOS INTERNOS / RESEARCH USADOS
B31: Documento | C31: Fecha | D31: Origen | E31: Uso
B32: DVN-research-prevaluation-v0.2 (PDF) | C32: 15-may-2026 | D32: Documento aportado por usuario | E32: Marco analítico inicial. NOTA: las cifras históricas del PDF eran incorrectas (Revenue FY21 $6.2B vs real $12.2B; revenue FY25 $15.3B vs real $17.2B). Usamos SEC primary sources directamente.
B33: Modelo MSFT previo (plantilla 8-sheet de referencia) | C33: 14-may-2026 | D33: Repositorio interno | E33: Plantilla 8-sheet replicada (Resumen/Hipotesis/Historico/Modelo/DuPont_WC/Reverse_DCF/Conclusiones/Fuentes) para consistencia metodológica
B35: 5. NOTAS METODOLÓGICAS
B36: Todas las cifras históricas DVN verificadas contra 10-K originales (SEC EDGAR). Las cifras del PDF inicial v0.2 contenían errores materiales (revenue FY21 $6.2B vs real $12.2B; capex FY23 $11.3B vs real $3.8B) — se descartaron y se reconstruyó desde fuentes primarias.
B37: Tasa fiscal efectiva: usamos 22% para modelo (promedio FY23-FY25 normalizado, vs 23% en FY25). En E&P el effective rate varia con depletion/IDC deductions, suele estar 18-25%.
B38: Descomposición P×Q: Revenue = Production (volumen MMBoe) × Realized Price ($/unit). Tres "segmentos": Oil, Gas, NGL. Marketing & Midstream se trata como pass-through (~0% margen) y se excluye del segment math.
B39: Pro-forma combined Devon+Coterra: FY25 base combinada $24.8B revenue (DVN $17.2B + CTRA $7.7B). Las proyecciones FY26E asumen año completo combinado vs DVN standalone (de ahí el step-up +45% oil/+215% gas en FY26E growth).
B40: Maintenance vs Growth capex: split 85/15% FY26E, 95/5% terminal. Maintenance ≈ F&D cost ($10/Boe target). Growth ≈ inversion para expansión de producción. Justificación: ciclo maduro Permian/Marcellus, decline rates altos requieren capex sostenido solo para mantener producción.
B41: Damodaran ERP: edition Jan-2026, ~4.5% implied basada en S&P 500 dividend + buyback yields. Alternativa histórica geo-arith mean 4-6%. Usamos 4.5% punto medio.
B42: Cost of debt: DVN BBB+/Baa1 rated, spread ~100bp sobre 10Y UST. Calculado como Rf 4.5% + 100bp = 5.5% pre-tax. After-tax 5.5%×(1−22%) = 4.29%.
B43: Beta sectorial 1.20: Damodaran "Oil/Gas (Production and Exploration)" 2026 estimate. NO usar beta Yahoo/Google 0.43 (DVN standalone 5Y monthly), sub-estima dramatically el riesgo cíclico post-merger.
B44: 8 métodos de valoración: 5 DCF (Gordon, H-Model, Exit EV/EBITDA, Exit EV/EBIT, Exit EV/Revenue) + 3 NTM multiples (P/E, EV/EBITDA, EV/Revenue). La mediana ($45.99) se usa como punto central; el rango ($17.63-$63.10) refleja la incertidumbre cíclica real.
B45: Sensibilidades embebidas (Tablas A-D en Modelo cols L-R): recompute completo, no TABLE() de Excel. Highlight verde > spot, rojo < spot. Rangos recalibrados a niveles E&P (Capex/Rev 17-30%, Op margin 20-40%, WACC 7.5-12%).
B47: Modelo construido 19-may-2026. Auditable end-to-end vía formulas. 774 formulas totales, 0 errors en recalc completo.
