Workbook

Sheet Instrucciones
B2: NETFLIX, INC. (NFLX) — MODELO DE VALORACION v1.0 (basado en Plantilla v1)
B3: Modelo multi-método (8 metodologías) con sensibilidades y reverse-DCF. Fecha de corte: 18-may-2026. Datos verificados contra 10-K FY2025 (filed 23-ene-2026) y 10-Q Q1 2026 (filed 17-abr-2026).
B5: ▶ QUICK START — los 4 pasos para usar la plantilla
B7: Paso 1 | C7: Edita la hoja Hipotesis (azul = inputs). Empieza por: Spot price, shares outstanding, WACC components (Rf, ERP, Beta, Kd), y tasa fiscal. El WACC se calcula automáticamente.
B8: Paso 2 | C8: Rellena la hoja Historico con datos reales de la empresa (5 años de P&L + Cash Flow + Balance, más el último parcial YTD si aplica). Todos los datos hardcodeados están en color azul. Los ratios y % se calculan solos.
B9: Paso 3 | C9: Vuelve a Hipotesis y ajusta las suposiciones de proyección: crecimiento por segmento (rows 30-32), margen operativo por segmento (rows 33-35), Capex/Rev y D&A/Rev (rows 39-42). 5 años de proyección, columnas C-G + Terminal en H.
B10: Paso 4 | C10: Revisa la hoja Modelo (8 metodologías + tabla de sensibilidades en cols L-R). Luego la hoja Reverse_DCF para ver qué pricea el mercado al spot actual. Termina con Conclusiones y Resumen escribiendo tu tesis.
B12: ▶ ESTRUCTURA DEL ARCHIVO — 8 hojas + esta guía
B14: Instrucciones | C14: Esta hoja (guía de uso). Borrar antes de entregar al cliente, mantener para iteración interna.
B15: Resumen | C15: Output ejecutivo. Recomendación, precio objetivo, drivers clave. Aquí pegas tu tesis cuando el modelo esté terminado. Contiene un chart de barras con los 8 precios implícitos.
B16: Hipotesis | C16: INPUTS CRÍTICOS. 5 secciones: (1) Mercado/Coste de capital + WACC, (2) Crecimiento por segmento × año, (3) Capex/D&A/SBC/WC ratios, (4) Valores terminales (g, exit multiples), (5) Inversiones estratégicas opcionales.
B17: Historico | C17: 5 años de financials + YTD parcial. Estructura: A=P&L, B=Cash Flow, C=Balance, D=Segmentos, E=KPIs trimestrales. Cada línea principal tiene su YoY% / margen INLINE debajo.
B18: Modelo | C18: Forecast operativo + 8 metodologías de valoración: 5 DCF (Gordon, H-Model, Exit EV/EBITDA, Exit EV/EBIT, Exit EV/Rev) + 3 NTM multiples (P/E, EV/EBITDA, EV/Rev). Incluye 4 tablas de sensibilidad embebidas (cols L-R).
B19: DuPont_WC | C19: Descomposición ROE/ROIC en 5 factores + análisis de working capital y cash conversion cycle. Para detectar si el ROE viene de margen, asset turnover o leverage.
B20: Reverse_DCF | C20: Dado el spot, qué assumptions implica el mercado (g terminal, WACC, EBIT margin, Capex/Rev, Revenue CAGR). 5 análisis closed-form, no iterativos.
B21: Conclusiones | C21: Narrativa cualitativa: tesis, debate bear/bull, escenarios, drivers ranked, riesgos, veredicto final con catalizadores a 12 meses.
B22: Fuentes | C22: Listado de fuentes citadas. CRÍTICO mantener fuentes primarias (filings) para auditabilidad.
B24: ▶ CÓDIGO DE COLORES Y CONVENCIONES
B26: Texto azul | C26: Input hardcoded — EDITAS tú
B27: Texto negro | C27: Cálculo (formula) — NO TOCAR
B28: Texto gris itálico | C28: Ratio inline (debajo de la línea principal — margen/growth %)
B29: Texto azul itálico | C29: Prompt — sustituir por contenido propio (Conclusiones/Resumen)
B30: Fondo amarillo (FFE699) | C30: Header de tabla o input clave
B31: Fondo verde (E2EFDA) | C31: Output relevante o resultado clave
B32: Fondo azul claro (DDEBF7) | C32: Subtotal o métrica de control
B33: Fondo rojo claro | C33: Advertencia o assumption importante
B35: ▶ LAS 8 METODOLOGÍAS — qué hace cada una y cuándo confiar en ella
B37: M1 — DCF Gordon Growth | C37: Suma PV de FCFF explícito (5 años, mid-year convention) + PV del valor terminal en perpetuidad FCFF_t × (1+g) / (WACC − g). El método más teórico pero EXTREMADAMENTE sensible a (WACC − g). Diferencias de 50bp en g cambian el precio 15-20%. Trade-off: pureza teórica vs sensibilidad.
B38: M2 — DCF H-Model (fade) | C38: Variante de Gordon donde el crecimiento decae linealmente de g_inicial (high-growth) a g_terminal durante n años. Más realista para compañías que aún están en fase de crecimiento. Útil cuando crees que el crecimiento no es estable sino transicional.
B39: M3 — DCF Exit EV/EBITDA | C39: PV del FCFF explícito + EV terminal calculado como múltiplo × EBITDA FY-final. Evita el problema de WACC−g del Gordon. Trade-off: el multiple aplicado debe ser DEFENDIBLE (comparable a peers o histórico de la empresa).
B40: M4 — DCF Exit EV/EBIT | C40: Igual que M3 pero usando EBIT × multiple. Más conservador (excluye D&A). Útil para empresas asset-heavy donde EBITDA infla la valoración por D&A alto.
B41: M5 — DCF Exit EV/Revenue | C41: Cross-check: EV terminal = revenue × P/S multiple. Útil para compañías sin profitability estable (early-stage, turnaround). En compañías maduras, es la metodología MÁS débil — no respeta unit economics.
B42: M6 — NTM P/E × FY27 EPS | C42: Equity = P/E × NI_FY27. Atajo basado en multiples NTM. Útil cuando tu peer set cotiza a un P/E claro y la convergencia es la tesis. Ignora el balance (cash, debt) — usar con cuidado en empresas net-cash.
B43: M7 — NTM EV/EBITDA × FY27 EBITDA | C43: EV = multiple × EBITDA_FY27. Bridge a equity con cash y debt actuales. Muy usado por sell-side. El más comparable cross-empresa porque normaliza capital structure.
B44: M8 — NTM EV/Revenue × FY27 Revenue | C44: Cross-check rapido. Útil en sectores con métricas operativas claras (SaaS, software). Combinar con tasa de growth — un multiple alto solo justifica con growth alto.
B46: Lectura | C46: La MEDIANA de las 8 metodologías es la referencia central (más robusta que el promedio frente a outliers). El RANGO (mín-máx) indica nivel de incertidumbre: si los 8 métodos rinden $80-$120, el precio justo es $100 ± 20%. Si rinden $50-$200, la valoración es altamente sensible a assumptions.
B48: ▶ CHECKLIST DE CALIDAD — ANTES DE PRESENTAR EL MODELO
C50: ✓ Todos los datos históricos referenciados a fuente primaria (memoria anual, reporte trimestral, etc.) — ver hoja Fuentes
C51: ✓ Tasa libre de riesgo y ERP actualizadas a fecha actual (Damodaran refresh mensual)
C52: ✓ Beta justificada: 5Y regression vs índice relevante O sectorial (Damodaran Industry Beta)
C53: ✓ WACC en rango razonable (typically 7-12% para large-caps desarrollados, mayor para emerging)
C54: ✓ Tasa terminal g ≤ crecimiento PIB nominal esperado (3-4% USD, 2% EUR)
C55: ✓ Margen operativo terminal NO superior al máximo histórico del sector (industry leadership)
C56: ✓ Capex/Revenue normalizado refleja D&A en estado estacionario (Capex ≈ D&A en steady state)
C57: ✓ Mediana 8 métodos cae dentro del rango P25-P75 — si está fuera, revisar outliers
C58: ✓ Sensibilidades (Tablas A-D en Modelo cols L-R) tienen el spot SOMEWHERE EN LA TABLA — si está fuera del rango, ajustar
C59: ✓ Reverse DCF revela implícitas RAZONABLES (no requiere assumptions extremas)
C60: ✓ Recomendación coherente con upside: typically BUY si mediana >+15%, HOLD si ±15%, SELL si <-15%
C61: ✓ Riesgos identificados son CONCRETOS (no boilerplate) — sector-específicos y cuantificables
C62: ✓ Spelling/typos revisados — el modelo es una entrega profesional
B64: ▶ ERRORES COMUNES — DO NOT
C66: × NO inflar el margen operativo terminal por encima del máximo histórico del sector. Reversion to the mean es real.
C67: × NO usar Capex/Rev = D&A/Rev en estado terminal — debe haber CONVERGENCIA hacia steady state.
C68: × NO confiar SOLO en una metodología. Las 8 sirven justamente para triangular la incertidumbre.
C69: × NO ignorar la SBC (stock-based comp) si es relevante. En tech, descontarla del FCFF puede cambiar 5-15% el precio.
C70: × NO usar el promedio de 8 métodos si hay un outlier obvio (ej. M5 EV/Revenue da 3x el resto) — usar mediana.
C71: × NO escribir conclusiones sin haber pasado por TODAS las sensibilidades y el reverse DCF.
C72: × NO entregar el modelo con la hoja Instrucciones visible al cliente final — es trabajo interno.
C73: × NO confundir Cash & STI con todo el cash (long-term equity investments, treasury bonds van separados).
C74: × NO olvidar el efecto del impuesto sobre Kd (siempre after-tax) ni el efecto de capital structure en WACC.
C75: × NO usar beta de regression cuando la empresa ha cambiado su perfil de riesgo dramáticamente (ej. post-merger).
B77: ▶ REFERENCIAS METODOLOGICAS
B79: Damodaran | C79: NYU Stern. Implied ERP mensual, betas sectoriales, multiples comparativos. Ref: https://pages.stern.nyu.edu/~adamodar/
B80: Federal Reserve | C80: FRED — Risk-free rates (10Y UST). Ref: https://fred.stlouisfed.org/series/DGS10
B81: McKinsey | C81: Valuation: Measuring and Managing the Value of Companies (Koller). Standard de la industria para metodologías DCF y WACC.
B82: CFA Institute | C82: Equity Asset Valuation (Stowe, Robinson, Pinto). Base de las metodologías de multiples y DCF Gordon/H-Model.
B83: SEC EDGAR / CNMV | C83: Filings públicos para datos históricos. USA: sec.gov/edgar. ES: cnmv.es. UK: gov.uk/government/organisations/companies-house.
B85: ▶ NOTAS DE VERSION
B87: v1.0 | C87: Plantilla inicial. 8 hojas, 684 fórmulas, 8 charts nativos. Basada en metodología MSFT valuation model. Soporta 3 segmentos, 5 años de proyección + Terminal, 8 métodos de valoración, 4 tablas de sensibilidad bidimensional, Reverse DCF closed-form en 5 dimensiones.
B90: ▶ FLAGS CRITICOS ESPECIFICOS DE ESTE MODELO NFLX (leer antes de interpretar valoracion)
B92: 1. WBD acquisition FALLO. Netflix retiro su oferta el 26-feb-2026. Paramount Skydance adquirio WBD el 27-feb-2026. El modelo es STANDALONE — el deep dive original referencia un bridge facility $42.2bn que YA NO APLICA.
B93: 2. Stock split 10:1 efectivo 17-nov-2025. Todas las cifras por accion (EPS, precio objetivo, spot) son POST-SPLIT. Spot al cierre 15-may-2026: $87.02.
B94: 3. Net income Q1 2026 ($5,283M) incluye ~$2.85bn de "Interest and other income" no recurrente. NO anualizar linealmente. La guia de margen FY26 (31.5%) sigue siendo el ancla.
B95: 4. Los 3 segmentos en Hipotesis/Modelo son CONCEPTUALES (Suscripcion / Publicidad / Otros). Netflix reporta como un unico segmento operativo. Los splits son estimaciones del modelista basadas en disclosures de shareholder letters y guias publicas.
B96: 5. Capex PP&E es marginal (~1.5% revenue). El verdadero "capex economico" es el contenido, que se contabiliza en COR (amortizacion) y en OCF (pagos). FCF de Netflix YA descuenta el contenido — es mas limpio que un capex tradicional.

Sheet Resumen
B2: NETFLIX, INC. (NFLX) — RESUMEN EJECUTIVO DE VALORACION
B3: Modelo valoración integral · Fecha valoración: 18-may-2026 · Cierre FY: 31-dic (calendar year)
B5: 1. COMPANY SNAPSHOT / MARKET DATA (15-may-2026)
B6: Co-CEOs | C6: Ted Sarandos, Greg Peters | E6: Spot ($) | F6: =Hipotesis!$C$6 -> 87.02
B7: CFO | C7: Spencer Neumann | E7: Market Cap ($B) | F7: =Hipotesis!$C$21/1000 -> 366.59786
B8: Headquarters | C8: Los Gatos, CA, USA | E8: Enterprise Value ($B) | F8: =(Hipotesis!$C$21+Hipotesis!$C$14-Hipotesis!$C$15)/1000 -> 370.99986
B9: Fundada | C9: 1997 (DVD); streaming desde 2007 | E9: Shares Outstanding (M) | F9: =Hipotesis!$C$8 -> 4212.8
B10: Empleados (FY25) | C10: ~16,000 (TradingView) | E10: 52-week range | F10: $75.01 – $134.12 (post-split)
B11: Año fiscal | C11: Cierre 31-dic (calendar year) | E11: All-time high (close, post-split) | F11: $133.91 (30-jun-2025)
B12: Sector | C12: Streaming / Media / Entertainment | E12: P/E TTM | F12: ~27-46x (rango Trefis 27.6x / Robinhood 46.5x)
B13: Segmentos reportados | C13: 1 segmento operativo (streaming). Conceptuales: subscripción, ads, otros | E13: EPS TTM | F13: ~$2.55 (post-split, FY25)
B14: Ticker / Exchange | C14: NFLX / NASDAQ-GS | E14: Beta (5Y) | F14: =Hipotesis!$C$11 -> 1.25
B15: Index | C15: S&P 500, NASDAQ-100 | E15: Dividend Yield | F15: 0% (NFLX no paga dividendos)
B16: Stock split reciente | C16: 10-for-1 efectivo 17-nov-2025
B17: 2. Q1 2026 EARNINGS HIGHLIGHTS (trimestre cerrado 31-mar-2026; filing 17-abr-2026)
B18: Revenue Q1 2026 | C18: $12,250M | E18: +16.2% YoY (vs $10,543M Q1 2025)
B19: Operating Income Q1 2026 | C19: $3,957M | E19: Op margin 32.3% (vs guide 32.1%)
B20: Net Income Q1 2026 | C20: $5,283M | E20: Diluted EPS $1.23 — INCLUYE $2.85bn one-off (Other income)
B21: Paid memberships (Q4 2025 último report) | C21: >325M | E21: Q1 2026 ya no reporta member adds (mgmt decision)
B22: Advertising revenue (Q1 run-rate) | C22: ~$2.0-2.5bn anualizado | E22: Mgmt guía ~2x FY26 (vs >$1.5bn FY25)
B23: Engagement | C23: ~2h+ per member/day | E23: Estable; clave para retención + ad ROI
B24: Content additions FY25 | C24: $17.1bn | E24: Content amortization $16.4bn (alineadas)
B25: Content obligations no reconocidas BS | C25: $18.4bn | E25: Compromisos operativos (no deuda)
B26: PP&E Capex Q1 2026 | C26: $196M | E26: Capex clásico minimal (1.5% rev)
B27: FCF Q1 2026 | C27: $5,094M | E27: OCF $5,290M − Capex $196M
B28: Buyback Q1 2026 | C28: $1,271M | E28: Bajo vs Q1 2025 ($3.5bn) — preserve cash en bid WBD (fallido)
B29: Dividends Q1 2026 | C29: $0 | E29: No dividend policy
B30: ⚠ Operación Warner Bros. (WBD) | C30: NETFLIX SE RETIRÓ 26-feb-2026 | E30: Paramount Skydance ganó @ $31/share ($110.9bn). Modelo es STANDALONE.
B31: Dividends Q3 | C31: $6.2B
B33: 3. 5-YEAR HISTORICAL FINANCIALS (FY21-FY25, $mm except per-share / ratios)
B34: Metric | C34: FY21 | D34: FY22 | E34: FY23 | F34: FY24 | G34: FY25
B35: Revenue ($mm) | C35: 29698 | D35: 31616 | E35: 33723 | F35: 39001 | G35: 45183
B36: YoY growth | C36: +18.8% | D36: +6.5% | E36: +6.7% | F36: +15.6% | G36: +15.8%
B37: Operating Income | C37: 6195 | D37: 5633 | E37: 6954 | F37: 10418 | G37: 13327
B38: Operating margin | C38: 20.9% | D38: 17.8% | E38: 20.6% | F38: 26.7% | G38: 29.5%
B39: Net Income | C39: 5116 | D39: 4492 | E39: 5408 | F39: 8712 | G39: 10981
B40: Diluted EPS (post-split) | C40: 1.13 | D40: 1 | E40: 1.22 | F40: 2 | G40: 2.55
B41: OCF | C41: 393 | D41: 2026 | E41: 7274 | F41: 7361 | G41: 10149
B42: PP&E Capex | C42: -525 | D42: -408 | E42: -349 | F42: -440 | G42: -688
B43: Free Cash Flow | C43: -132 | D43: 1619 | E43: 6925 | F43: 6921 | G43: 9461
B44: Buybacks | C44: -600 | D44: 0 | E44: -6045 | F44: -6264 | G44: -9127
B45: Dividends | C45: 0 | D45: 0 | E45: 0 | F45: 0 | G45: 0
B47: 4. VALUATION RESULTS — 8 metodologías (live link to Modelo)
B48: Method | C48: Implied Price | D48: [Completar con narrativa específica de la empresa]
B49: 1. DCF Gordon Growth | C49: =Modelo!J52 -> 61.719816 | D49: =Modelo!J52/Hipotesis!$C$6-1 -> -0.29073988
B50: 2. DCF H-Model (fade) | C50: =Modelo!J53 -> 54.229768 | D50: =Modelo!J53/Hipotesis!$C$6-1 -> -0.3768126
B51: 3. DCF Exit EV/EBITDA | C51: =Modelo!J54 -> 86.20895 | D51: =Modelo!J54/Hipotesis!$C$6-1 -> -0.0093202725
B52: 4. DCF Exit EV/EBIT | C52: =Modelo!J55 -> 100.26481 | D52: =Modelo!J55/Hipotesis!$C$6-1 -> 0.15220421
B53: 5. DCF Exit EV/Revenue | C53: =Modelo!J56 -> 75.909436 | D53: =Modelo!J56/Hipotesis!$C$6-1 -> -0.12767828
B54: 6. NTM P/E × FY27E EPS | C54: =Modelo!J57 -> 86.423956 | D54: =Modelo!J57/Hipotesis!$C$6-1 -> -0.0068495109
B55: 7. NTM EV/EBITDA × FY27E EBITDA | C55: =Modelo!J58 -> 78.677173 | D55: =Modelo!J58/Hipotesis!$C$6-1 -> -0.095872524
B56: 8. NTM EV/Revenue × FY27E Revenue | C56: =Modelo!J59 -> 73.072315 | D56: =Modelo!J59/Hipotesis!$C$6-1 -> -0.16028137
B57: MEDIANA (target price central) | C57: =MEDIAN(C49:C56) -> 77.293304 | D57: =C57/Hipotesis!$C$6-1 -> -0.1117754
B58: Promedio (8 métodos) | C58: =AVERAGE(C49:C56) -> 77.063278 | D58: =C58/Hipotesis!$C$6-1 -> -0.11441878
B59: Rango Min – Max | C59: =TEXT(MIN(C49:C56),"$#,##0")&" – "&TEXT(MAX(C49:C56),"$#,##0") -> $54 – $100
B61: 5. INVESTMENT THESIS (resumen ejecutivo — ver Conclusiones para narrativa completa)
B62: Target price (mediana, sin descuento) | C62: =C57 -> 77.293304 | D62: vs spot: | E62: =C57/Hipotesis!$C$6-1 -> -0.1117754
B64: ▸ Netflix entra en 2026 con la mejor calidad financiera de su historia: FY25 revenue $45.2bn (+16%), op margin 29.5% (vs 17.8% FY22), FCF $9.5bn. La conversión a caja cambió de régimen post-2023 (FCF/NI 80-128% vs negativo en 2021).
B65: ▸ Stock split 10:1 (17-nov-2025) ha hecho la acción más accesible. Cotiza a $87 con market cap ~$367bn. P/E TTM 27-28x (Trefis); 3Y avg 38x. Múltiplos comprimidos vs media histórica.
B66: ▸ Bid Warner Bros. (anunciado dic-2025 @ $27.75/share, $82.7bn) NO se materializó: Netflix se retiró 26-feb-2026; Paramount Skydance ganó. Esto ELIMINA la incertidumbre de balance/integración y libera capital para buybacks. Es POSITIVO neto para la tesis standalone.
B67: ▸ Drivers FY26: (1) subida de precios marzo 2026 sin guidance increase posterior — Mar Mahaney (TD Cowen) y otros analistas Upfront positivos; (2) publicidad: 250M MAVs en tier ads (vs 190M nov-2025), guía ~2x FY26 vs >$1.5bn FY25; (3) NFL deportivos, contenido coreano (KPop Demon Hunters tour), theatrical "Narnia" 2026.
B68: ▸ Riesgo de modelización clave: Q1 2026 NI $5.28bn incluye $2.85bn one-off (interest and other income). Ajustando, run-rate NI Q1 ≈ $3.1bn (~10.0% effective tax adjusting). No anualizar lineal.
B69: ▸ Sensibilidades clave: cada +100bp WACC ≈ -$10-13 precio; cada +100bp en op margin terminal ≈ +$5-7 precio; cada +50bp en g terminal ≈ +$8-10 precio. Ver Tablas A-D en Modelo cols L-R.
B70: ▸ Tesis base (mediana 8 métodos): ~$77 vs spot $87 = -11% (HOLD/UNDERWEIGHT en base). El mercado pricea assumptions más optimistas (Reverse_DCF muestra Revenue CAGR implícita ~12% vs base 9.7%). Range valoración $54-$100; rango amplio refleja sensibilidad a hipótesis de margen terminal y growth.
B72: Detalle metodológico en hojas Hipotesis, Historico, Modelo, DuPont_WC, Reverse_DCF, Conclusiones. Fuentes en hoja Fuentes.

Sheet Hipotesis
B1: NETFLIX, INC. (NFLX) — HIPOTESIS Y SUPUESTOS DE VALORACION
B2: LEYENDA: | C2: Input (hardcoded) | D2: Driver clave | E2: Formula | F2: Link a otra hoja | G2: Resultado/output
B4: 1. MERCADO Y COSTE DE CAPITAL
B5: Concepto | C5: Valor | D5: Fuente / Nota
B6: Spot price ($) | C6: 87.02 | D6: Source: Morningstar/Macrotrends close 15-may-2026; 10:1 stock split efectivo 17-nov-2025
B7: Diluted shares outstanding (M) | C7: 4298.4 | D7: Source: NFLX 10-Q Q1 2026 (period 31-mar-2026), Statements of Operations, Note 2 EPS; filed 17-abr-2026
B8: Shares outstanding actual (M) | C8: 4212.8 | D8: Source: NFLX 10-Q Q1 2026 cover, shares outstanding as of 31-mar-2026: 4,212,794,271
B9: Risk-free rate (10Y bono soberano, %) | C9: 0.0454 | D9: Source: FRED DGS10 (10Y UST), mid-may-2026 ~4.50-4.55% range
B10: Equity Risk Premium implícita (%) | C10: 0.0423 | D10: Source: Damodaran ERP 2026 Edition (jan-2026 implied ERP S&P500). Ref: https://pages.stern.nyu.edu/~adamodar/
B11: Beta (5Y o regression sectorial) | C11: 1.25 | D11: Source: Yahoo Finance / 5Y monthly regression vs S&P500 (rango histórico 1.15-1.40); usado punto medio
B12: Pre-tax cost of debt (%) | C12: 0.0525 | D12: Source: NFLX corporate bonds (5Y senior unsec) yielding ~5.0-5.5%, BBB- rating (S&P/Moody) + ~70bp spread over 10Y UST
B13: Effective tax rate (%) | C13: 0.2 | D13: Source: NFLX 10-K FY2025 + 10-Q Q1 2026; tax rate efectivo FY24=18.0%, FY25=~20.0%, Q1 2026=19.3%. Use 20% baseline.
B14: Total Debt ($mm, book) | C14: 13464 | D14: Source: NFLX 10-K FY2025 BS, long-term debt total $13,464M (filed 23-ene-2026)
B15: Cash + STI ($mm, book) | C15: 9062 | D15: Source: NFLX 10-K FY2025 BS, cash + short-term investments $9,062M
B16: Equity & other investments ($mm) | C16: 0 | D16: Source: NFLX no tiene equity investments materiales en BS (no incluye stakes estratégicos como MSFT/OpenAI)
B18: WACC computado
B19: Cost of equity Ke = Rf + Beta × ERP | C19: =Hipotesis!$C$9 + Hipotesis!$C$11*Hipotesis!$C$10 -> 0.098275
B20: After-tax cost of debt Kd = Kd*(1-T) | C20: =Hipotesis!$C$12 * (1 - Hipotesis!$C$13) -> 0.042
B21: Market cap = Spot × Shares ($mm) | C21: =Hipotesis!$C$6 * Hipotesis!$C$8 -> 366597.86
B22: Total enterprise capital = MC + Debt | C22: =Hipotesis!$C$21 + Hipotesis!$C$14 -> 380061.86
B23: Weight equity E/V | C23: =Hipotesis!$C$21 / Hipotesis!$C$22 -> 0.96457419
B24: Weight debt D/V | C24: =Hipotesis!$C$14 / Hipotesis!$C$22 -> 0.035425812
B25: WACC = E/V × Ke + D/V × Kd*(1-T) | C25: =Hipotesis!$C$23*Hipotesis!$C$19 + Hipotesis!$C$24*Hipotesis!$C$20 -> 0.096281412
B28: 2. CRECIMIENTO POR SEGMENTO (forecast horizon = años fiscales junio)
B29: Segmento / Driver | C29: FY2026E | D29: FY2027E | E29: FY2028E | F29: FY2029E | G29: FY2030E | H29: Terminal
B30: S1 — Suscripción core (membership) | C30: 0.1 | D30: 0.08 | E30: 0.07 | F30: 0.06 | G30: 0.05 | H30: 0.03 | J30: Q4 2025: 325M paid members. FY25 +16%. Paid sharing tailwind madura. Pricing power compensa parcialmente. Mar-2026 price hikes ayudan FY26.
B31: S2 — Publicidad (ad tier) | C31: 1 | D31: 0.6 | E31: 0.4 | F31: 0.25 | G31: 0.15 | H31: 0.05 | J31: Source: Shareholder Letter Q4 2025 — ad revenue >$1.5bn FY25, mgmt guía ~2x en FY26. Fade gradual con maduración del inventario y CPMs
B32: S3 — Otros (games, live events, theatrical, partnerships) | C32: 0.5 | D32: 0.4 | E32: 0.3 | F32: 0.2 | G32: 0.15 | H32: 0.05 | J32: Source: Mgmt commentary FY26 — expansión categorías (games, live events, video podcasts, "Narnia" theatrical 2026). Base pequeña, alto growth %
B33: S1 op margin % | C33: 0.33 | D33: 0.34 | E33: 0.35 | F33: 0.355 | G33: 0.36 | H33: 0.36 | J33: Subscription margin expandiendo por escala. Implícito vs op margin consolidado FY25 29.5% (incluye ads en fase inversión)
B34: S2 op margin % | C34: 0.05 | D34: 0.12 | E34: 0.18 | F34: 0.23 | G34: 0.28 | H34: 0.3 | J34: Negocio publicitario en fase inversión (ad-tech, ventas, medición). Margen escala con fill rate, CPMs, partners. Terminal vs peers CTV ~25-30%
B35: S3 op margin % | C35: 0.05 | D35: 0.1 | E35: 0.12 | F35: 0.15 | G35: 0.18 | H35: 0.2 | J35: Games + live events + theatrical: heavy upfront investment, margin maduración lenta. Conservador.
B37: 3. CAPEX, D&A Y CAPITAL ALLOCATION
B38: Driver | C38: FY2026E | D38: FY2027E | E38: FY2028E | F38: FY2029E | G38: FY2030E | H38: Terminal
B39: Capex / Revenue % | C39: 0.015 | D39: 0.015 | E39: 0.015 | F39: 0.014 | G39: 0.014 | H39: 0.013 | J39: PP&E capex únicamente (clásico). Contenido va vía OCF (amortizado en cost of revenues). FY25 actual 1.5%; estable.
B40: D&A / Revenue % | C40: 0.008 | D40: 0.008 | E40: 0.008 | F40: 0.008 | G40: 0.008 | H40: 0.008 | J40: PP&E D&A únicamente (~$99M Q1 2026 = ~$396M anualizado / $50bn rev ~ 0.8%). Content amortization YA está dentro de cost of revenues (FY25: $16.4bn)
B41: SBC / Revenue % | C41: 0.012 | D41: 0.012 | E41: 0.012 | F41: 0.012 | G41: 0.012 | H41: 0.012 | J41: Source: 10-Q Q1 2026 SBC $140M / Q rev $12.25bn ~ 1.15%. NFLX SBC moderada vs tech peers
B42: ΔWC / Revenue % | C42: -0.005 | D42: -0.005 | E42: -0.005 | F42: 0 | G42: 0 | H42: 0 | J42: NFLX subscription model: cobros adelantados → WC favorable (deferred revenue +$32M Q1 2026). Pequeño beneficio.
B43: Buybacks / FCF % | C43: 0.85 | D43: 0.85 | E43: 0.85 | F43: 0.8 | G43: 0.8 | H43: 0.75 | J43: FY25 96.5% FCF. Mgmt ha mantenido buybacks como vehículo principal de capital return. Sin dividendos.
B45: 4. VALORES TERMINALES (TV) Y CROSS-CHECKS
B46: Concepto | C46: Valor | D46: Justificación
B47: Terminal growth rate g (perpetuidad, %) | C47: 0.03 | D47: Gordon: g ≤ inflación + GDP real US ≈ 3%; NFLX como compounder global a largo plazo, igual a tasa nominal GDP
B48: H-Model: años fase alta (n) | C48: 5 | D48: Periodo high-growth explícito antes de fade lineal
B49: H-Model: g inicial (%) | C49: 0.07 | D49: g final FY30 estimada ~6-7% (post peak paid sharing/ads); fade linear hasta 3% terminal
B50: Exit EV/EBITDA múltiple (x) | C50: 18 | D50: FY2030 exit. NFLX TTM EV/EBITDA ~14-15x (post-correction); peers: SPOT 28x, GOOGL 22x, DIS 12x. Premium moderado
B51: Exit EV/EBIT múltiple (x) | C51: 22 | D51: FY2030 exit. NFLX TTM EV/EBIT ~16x; premium vs growth + margin expansion
B52: Exit EV/Revenue múltiple (x) | C52: 5.5 | D52: FY2030 exit. NFLX TTM EV/Rev ~8x; mature target lower; cross-check con NFLX histórico mediano 6-7x
B53: Exit P/E (x) | C53: 25 | D53: Cross-check; NFLX TTM P/E ~28x (Trefis 27.6x). Mediano histórico 30-40x. Conservador a 25x
B54: FCF conversion normalizada (post-pico capex) | C54: 0.85 | D54: FCF/NI: histórico 80-128% (2023-2025); normalización a 80-90%
B56: 5. INVERSIONES ESTRATEGICAS (n/a para NFLX — no tiene equity stakes materiales)
B57: Equity stake en partner estratégico ($mm) | C57: 0 | D57: Source: NFLX 10-K FY2025 — no equity investments materiales (a diferencia de MSFT/OpenAI o GOOGL/Anthropic)
B58: Equity stake ownership (%) | C58: 0 | D58: n/a
B59: Inversiones estratégicas (excluidas de EV) | C59: 0 | D59: n/a — no equity investments en BS de NFLX

Sheet Historico
B1: NETFLIX, INC. (NFLX) — HISTORICO FINANCIERO (FY2021 a FY2025 + Q1 2026)
B2: LEYENDA: | C2: Input (hardcoded) | D2: Cálculo (margen/growth) | E2: Inline ratio
B4: $ millions | C4: FY2021 | D4: FY2022 | E4: FY2023 | F4: FY2024 | G4: FY2025 | H4: Q1 2026
B5: A. CUENTA DE RESULTADOS ($mm except per-share)
B6: Revenue | C6: 29698 | D6: 31616 | E6: 33723 | F6: 39001 | G6: 45183 | H6: 12250 | I6: Source: NFLX 10-K FY2025 + 10-Q Q1 2026; CAGR FY21-FY25 = 11.0%
B7: Revenue YoY % | C7: n/a | D7: =D6/C6-1 -> 0.064583474 | E7: =E6/D6-1 -> 0.066643472 | F7: =F6/E6-1 -> 0.15651039 | G7: =G6/F6-1 -> 0.15850876 | H7: ytd | I7: CAGR FY21-FY25 ≈ 13.8%
B8: Cost of revenue | C8: 17332 | D8: 19169 | E8: 19715 | F8: 21034 | G8: 22045 | H8: 5888 | I8: Source: 10-K FY2025 + 10-Q Q1 2026; CoR incluye content amortization + delivery costs. FY21-FY24 estimados; FY25/Q1 2026 directos
B9: Cost of revenue / Revenue % | C9: =C8/C6 -> 0.58360832 | D9: =D8/D6 -> 0.60630693 | E9: =E8/E6 -> 0.58461584 | F9: =F8/F6 -> 0.5393195 | G9: =G8/G6 -> 0.48790474 | H9: =H8/H6 -> 0.48065306 | I9: Subiendo por [Driver de crecimiento] infra
B10: Gross profit | C10: 12366 | D10: 12447 | E10: 14008 | F10: 17967 | G10: 23138 | H10: 6362
B11: Gross margin % | C11: =C10/C6 -> 0.41639168 | D11: =D10/D6 -> 0.39369307 | E11: =E10/E6 -> 0.41538416 | F11: =F10/F6 -> 0.4606805 | G11: =G10/G6 -> 0.51209526 | H11: =H10/H6 -> 0.51934694 | I11: 69-70% [Plataforma cloud] GM en Último trimestre
B12: Technology and development (R&D equivalent) | C12: 2273 | D12: 2711 | E12: 2674 | F12: 2925 | G12: 3464 | H12: 960 | I12: Tech & dev (R&D equivalent) per 10-K; Q1 2026 $960M; FY21-FY24 estimados from filings
B13: R&D / Revenue % | C13: =C12/C6 -> 0.076537141 | D13: =D12/D6 -> 0.085747723 | E13: =E12/E6 -> 0.079293064 | F13: =F12/F6 -> 0.074998077 | G13: =G12/G6 -> 0.076666003 | H13: =H12/H6 -> 0.078367347 | I13: Estable ~12% — leverage del modelo
B14: S&M | C14: 2545 | D14: 2530 | E14: 2554 | F14: 2884 | G14: 3057 | H14: 842 | I14: Sales & marketing per 10-K; Q1 2026 $842M directo
B15: S&M / Revenue % | C15: =C14/C6 -> 0.085696006 | D15: =D14/D6 -> 0.080022773 | E15: =E14/E6 -> 0.075734662 | F15: =F14/F6 -> 0.073946822 | G15: =G14/G6 -> 0.06765819 | H15: =H14/H6 -> 0.068734694 | I15: Bajando con scale (de 12% → 9%)
B16: G&A | C16: 1351 | D16: 1572 | E16: 1626 | F16: 1741 | G16: 2245 | H16: 603 | I16: G&A per 10-K; Q1 2026 $603M directo
B17: G&A / Revenue % | C17: =C16/C6 -> 0.045491279 | D17: =D16/D6 -> 0.04972166 | E17: =E16/E6 -> 0.048216351 | F17: =F16/F6 -> 0.044639881 | G17: =G16/G6 -> 0.049686829 | H17: =H16/H6 -> 0.04922449 | I17: ~3% estable
B18: Operating income | C18: 6195 | D18: 5633 | E18: 6954 | F18: 10418 | G18: 13327 | H18: 3957 | I18: Source: NFLX 10-K FY2025 + 10-Q Q1 2026 directo. Op margin FY25 29.5%, Q1 2026 32.3%
B19: Operating margin % | C19: =C18/C6 -> 0.20859991 | D19: =D18/D6 -> 0.17816928 | E19: =E18/E6 -> 0.20620941 | F19: =F18/F6 -> 0.26712136 | G19: =G18/G6 -> 0.29495607 | H19: =H18/H6 -> 0.32302041 | I19: 📈 +330bp FY21-FY25, +200bp más en 9M parcial (47%)
B20: Op income YoY % | C20: n/a | D20: =D18/C18-1 -> -0.090718321 | E20: =E18/D18-1 -> 0.23451092 | F20: =F18/E18-1 -> 0.49813057 | G20: =G18/F18-1 -> 0.27922826 | H20: ytd
B21: Other income (expense), net | C21: 411 | D21: -353 | E21: 56 | F21: 869 | G21: 553 | H21: 2590 | I21: NB Q1 2026: $2,852M en "Interest and other income (expense)" — ONE-OFF (FX gains/divest gains/hedging). El NI ajustado excluyendo este ítem ~$3,1bn
B22: Income before taxes | C22: 6606 | D22: 5280 | E22: 7010 | F22: 11287 | G22: 13880 | H22: 6547
B23: Provision for income taxes | C23: 1490 | D23: 788 | E23: 1602 | F23: 2575 | G23: 2899 | H23: 1264
B24: Effective tax rate | C24: =C23/C22 -> 0.22555253 | D24: =D23/D22 -> 0.14924242 | E24: =E23/E22 -> 0.22853067 | F24: =F23/F22 -> 0.22813857 | G24: =G23/G22 -> 0.20886167 | H24: =H23/H22 -> 0.19306553 | I24: 18% FY24-FY25, ligero uptick Último trimestre
B25: Net income | C25: 5116 | D25: 4492 | E25: 5408 | F25: 8712 | G25: 10981 | H25: 5283 | I25: Source: 10-K FY2025 + 10-Q Q1 2026. Q1 2026 incluye $2.85bn one-off (Other income)
B26: Net margin % | C26: =C25/C6 -> 0.17226749 | D26: =D25/D6 -> 0.14207996 | E26: =E25/E6 -> 0.16036533 | F26: =F25/F6 -> 0.22337889 | G26: =G25/G6 -> 0.24303388 | H26: =H25/H6 -> 0.43126531 | I26: ~36% — quality of earnings alto
B27: Net income YoY % | C27: n/a | D27: =D25/C25-1 -> -0.12197029 | E27: =E25/D25-1 -> 0.20391808 | F27: =F25/E25-1 -> 0.61094675 | G27: =G25/F25-1 -> 0.26044536 | H27: ytd
B28: Diluted EPS ($) | C28: 1.13 | D28: 1 | E28: 1.22 | F28: 2 | G28: 2.55 | H28: 1.23 | I28: EPS post-split 10:1 (efectivo 17-nov-2025). Historical retroactively adjusted. Q1 2026 inflado por one-off
B29: Diluted EPS YoY % | C29: n/a | D29: =D28/C28-1 -> -0.11504425 | E29: =E28/D28-1 -> 0.22 | F29: =F28/E28-1 -> 0.63934426 | G29: =G28/F28-1 -> 0.275 | H29: ytd | I29: Buybacks ayudan ~50bp/año al EPS growth
B30: Diluted shares (M) | C30: 4520 | D30: 4500 | E30: 4450 | F30: 4368 | G30: 4318 | H30: 4298.4 | I30: Diluted weighted-avg shares post-10:1 split. Buybacks reducen count
B32: B. CASH FLOW ($mm)
B33: Net cash from operations (OCF) | C33: 393 | D33: 2026 | E33: 7274 | F33: 7361 | G33: 10149 | H33: 5290 | I33: Source: NFLX 10-K + 10-Q Q1 2026 Cash Flow Statement. OCF YA NETO de pagos de contenido
B34: OCF / Revenue % | C34: =C33/C6 -> 0.013233214 | D34: =D33/D6 -> 0.064081478 | E34: =E33/E6 -> 0.21569848 | F34: =F33/F6 -> 0.18873875 | G34: =G33/G6 -> 0.22461988 | H34: =H33/H6 -> 0.43183673 | I34: ~48% — cash conversion alta
B35: OCF YoY % | C35: n/a | D35: =D33/C33-1 -> 4.1552163 | E35: =E33/D33-1 -> 2.5903258 | F35: =F33/E33-1 -> 0.011960407 | G35: =G33/F33-1 -> 0.37875289 | H35: ytd
B36: Capex (Additions to P&E) | C36: 525 | D36: 408 | E36: 349 | F36: 440 | G36: 688 | H36: 196 | I36: PP&E capex únicamente (no contenido). FY25 1.5% revenue
B37: Capex / Revenue % | C37: =C36/C6 -> 0.017677958 | D37: =D36/D6 -> 0.012904858 | E37: =E36/E6 -> 0.01034902 | F37: =F36/F6 -> 0.011281762 | G37: =G36/G6 -> 0.015226966 | H37: =H36/H6 -> 0.016 | I37: 📈 12% → 23% TTM → 33% 9M parcial (inversión productiva)
B38: Capex YoY % | C38: n/a | D38: =D36/C36-1 -> -0.22285714 | E38: =E36/D36-1 -> -0.14460784 | F38: =F36/E36-1 -> 0.26074499 | G38: =G36/F36-1 -> 0.56363636 | H38: ytd | I38: +213% acumulado FY21-FY25
B39: FCF simple = OCF − Capex | C39: -132 | D39: 1619 | E39: 6925 | F39: 6921 | G39: 9461 | H39: 5094 | I39: FCF simple = OCF - PP&E capex. Para NFLX el contenido YA está en OCF (a diferencia de empresas asset-heavy donde contenido sería capex)
B40: FCF / Revenue % | C40: =C39/C6 -> -0.0044447438 | D40: =D39/D6 -> 0.051208249 | E40: =E39/E6 -> 0.20534946 | F40: =F39/F6 -> 0.17745699 | G40: =G39/G6 -> 0.20939291 | H40: =H39/H6 -> 0.41583673 | I40: Bajando 33% → 25% por capex inversión
B41: FCF / Net Income % | C41: =C39/C25 -> -0.025801407 | D41: =D39/D25 -> 0.36041852 | E41: =E39/E25 -> 1.2805104 | F41: =F39/F25 -> 0.79442149 | G41: =G39/G25 -> 0.86157909 | H41: =H39/H25 -> 0.96422487 | I41: <70% confirma que la depreciación NO captura todo el outflow
B42: FCF YoY % | C42: n/a | D42: =D39/C39-1 -> -13.265152 | E42: =E39/D39-1 -> 3.2773317 | F42: =F39/E39-1 -> -0.00057761733 | G42: =G39/F39-1 -> 0.36699899 | H42: ytd
B43: D&A | C43: 208 | D43: 336 | E43: 297 | F43: 320 | G43: 350 | H43: 99 | I43: PP&E D&A únicamente (content amortization YA está en cost of revenues; FY25 content amort $16.4bn)
B44: D&A / Revenue % | C44: =C43/C6 -> 0.0070038386 | D44: =D43/D6 -> 0.01062753 | E44: =E43/E6 -> 0.0088070456 | F44: =F43/F6 -> 0.0082049178 | G44: =G43/G6 -> 0.0077462763 | H44: =H43/H6 -> 0.0080816327 | I44: Subiendo con el capex (lag de 2-3 años)
B45: Stock-based compensation | C45: 404 | D45: 553 | E45: 416 | F45: 437 | G45: 514 | H45: 140 | I45: SBC per CF statement; moderada vs tech peers (~1% revenue)
B46: SBC / Revenue % | C46: =C45/C6 -> 0.01360361 | D46: =D45/D6 -> 0.017491144 | E46: =E45/E6 -> 0.012335795 | F46: =F45/F6 -> 0.011204841 | G46: =G45/G6 -> 0.01137596 | H46: =H45/H6 -> 0.011428571 | I46: Estable ~4%
B47: Dividends paid | C47: 0 | D47: 0 | E47: 0 | F47: 0 | G47: 0 | H47: 0 | I47: NFLX no paga dividendos. Capital return 100% vía buybacks
B48: Common stock repurchased | C48: 600 | D48: 0 | E48: 6045 | F48: 6264 | G48: 9127 | H48: 1271 | I48: Buybacks FY23-25 acumulados $21.4bn. Q1 2026 reducido vs Q1 2025 ($3.5bn) por reserva de capital para bid WBD (fallido)
B49: Capital returns total ($mm) | C49: =C47+C48 -> 600 | D49: =D47+D48 -> 0 | E49: =E47+E48 -> 6045 | F49: =F47+F48 -> 6264 | G49: =G47+G48 -> 9127 | H49: =H47+H48 -> 1271
B50: Capital returns / FCF % | C50: =C49/C39 -> -4.5454545 | D50: =D49/D39 -> 0 | E50: =E49/E39 -> 0.87292419 | F50: =F49/F39 -> 0.90507152 | G50: =G49/G39 -> 0.96469718 | H50: =H49/H39 -> 0.24950923 | I50: ~70-80%, sostenible
B52: C. BALANCE SHEET (fin de periodo)
B53: Cash + STI | C53: 6028 | D53: 6058 | E53: 7138 | F53: 9584 | G53: 9062 | H53: 12267 | I53: Source: 10-K + 10-Q Q1 2026 BS. Q1 2026 alza por menor buyback Q1 (vs $1.1bn net debt). Deep dive nota cash+STI mucho mayor por bid WBD
B54: Equity & other investments (LT) | C54: 0 | D54: 0 | E54: 0 | F54: 0 | G54: 0 | H54: 0 | I54: NFLX no tiene equity investments materiales en BS
B55: Accounts receivable, net | C55: 0 | D55: 0 | E55: 0 | F55: 0 | G55: 0 | H55: 0 | I55: NFLX subscription model: cobros adelantados, AR mínimo/nulo
B56: PP&E, net | C56: 1324 | D56: 1399 | E56: 1432 | F56: 1546 | G56: 1750 | H56: 1850 | I56: PP&E neto modesto (offices, servers). Content assets (~$32bn) van separados como intangible operativo
B57: Goodwill + Intangibles | C57: 0 | D57: 0 | E57: 0 | F57: 0 | G57: 0 | H57: 0 | I57: NFLX goodwill mínimo. Content assets $32bn YA están como activo operativo, no goodwill
B58: Total assets | C58: 44585 | D58: 48595 | E58: 48732 | F58: 53630 | G58: 55597 | H58: 60000 | I58: Source: NFLX 10-K + Q1 estimate; Q1 2026 ramp por cash buildup
B59: Total debt (current + long-term) | C59: 14693 | D59: 14353 | E59: 14143 | F59: 13798 | G59: 13464 | H59: 13400 | I59: Source: NFLX 10-K + Q1 2026; no new debt en Q1 2026 (Repayments = 0)
B60: Stockholders' equity | C60: 15849 | D60: 20777 | E60: 20588 | F60: 24744 | G60: 26615 | H60: 30700
B61: Common stock + APIC | C61: 5026 | D61: 4638 | E61: 5145 | F61: 5660 | G61: 6000 | H61: 6100
B62: Retained earnings | C62: 10823 | D62: 16139 | E62: 15443 | F62: 19084 | G62: 20615 | H62: 24600
B63: Unearned revenue (current + LT) | C63: 1209 | D63: 1503 | E63: 1442 | F63: 1564 | G63: 1530 | H63: 1500 | I63: NFLX deferred revenue limitado (prepaid 1 mes típico). ΔWC ligeramente favorable
B64: Obligaciones contenido no reconocidas en BS ($bn) | C64: n/d | D64: n/d | E64: n/d | F64: n/d | G64: 18.4 | H64: n/d | I64: Source: 10-K FY2025 — obligaciones contenido no en BS $18.4bn (compromisos op, no deuda)
B65: Pasivos contenido reconocidos en BS ($bn) | G65: 5.7 | I65: Source: 10-K FY2025, $5.664bn
B66: Capital structure / leverage
B67: Net cash position ($mm) | C67: =C53-C59 -> -8665 | D67: =D53-D59 -> -8295 | E67: =E53-E59 -> -7005 | F67: =F53-F59 -> -4214 | G67: =G53-G59 -> -4402 | H67: =H53-H59 -> -1133
B68: Debt / Equity (x) | C68: =C59/C60 -> 0.92706164 | D68: =D59/D60 -> 0.69081196 | E68: =E59/E60 -> 0.68695357 | F68: =F59/F60 -> 0.55763013 | G68: =G59/G60 -> 0.50588014 | H68: =H59/H60 -> 0.43648208 | I68: Desapalancando: 0.55 → 0.10
B69: PP&E / Revenue % | C69: =C56/C6 -> 0.044582127 | D69: =D56/D6 -> 0.044249747 | E69: =E56/E6 -> 0.042463601 | F69: =F56/F6 -> 0.039640009 | G69: =G56/G6 -> 0.038731381 | H69: =H56/H6 -> 0.15102041 | I69: 📈 36% → 73% → 117% (inversión capex stack)
B70: Asset turnover (Rev / Avg Assets, proxy con end-of-period) | C70: =C6/C58 -> 0.66609846 | D70: =D6/D58 -> 0.65060191 | E70: =E6/E58 -> 0.69200936 | F70: =F6/F58 -> 0.72722357 | G70: =G6/G58 -> 0.81268773 | H70: =H6/H58 -> 0.20416667 | I70: Bajando 0.50 → 0.46 → 0.35 (inversión capex)
B72: D. SEGMENTOS CONCEPTUALES (estimados — NFLX reporta como 1 segmento operativo)
B73: (Estimación propia basada en disclosure shareholder letters; no es segmentación reportada)
B74: S1 revenue | C74: n/d | D74: n/d | E74: n/d | F74: 38400 | G74: 43600 | H74: n/d | I74: Est. subscription revenue: FY25 = total ($45.2bn) - ads ($1.5bn) - other ($83M); FY24 ads estimated $0.55bn (~2.5x growth)
B75: Segmento 2 (motor crecimiento) revenue | C75: n/d | D75: n/d | E75: n/d | F75: 550 | G75: 1500 | H75: n/d | I75: Source: Shareholder Letter Q4 2025 — ad revenue >$1.5bn FY25, "2.5x growth" implica ~$600M FY24; estimación
B76: S3 revenue | C76: n/d | D76: n/d | E76: n/d | F76: 51 | G76: 83 | H76: n/d | I76: Est. other revenue residual (games, theatrical, partnerships, legacy DVD); pequeño
B77: S1 operating income | C77: n/d | D77: n/d | E77: n/d | F77: 11000 | G77: 13500 | H77: n/d | I77: Estimación: subscription es el motor de margen. FY25 subscription op margin ~31%
B78: S2 operating income | C78: n/d | D78: n/d | E78: n/d | F78: -528 | G78: -140 | H78: n/d | I78: Ads en fase inversión (ad-tech, ventas, medición). Estimación: -$0.1-0.5bn drag en 2024-25
B79: S3 operating income | C79: n/d | D79: n/d | E79: n/d | F79: -54 | G79: -33 | H79: n/d | I79: Other (games, live events, theatrical) en fase inversión. Drag pequeño
B81: Margen operativo por segmento
B82: S1 op margin % | C82: n/d | D82: n/d | E82: n/d | F82: =IFERROR(F77/F74,"n/d") -> 0.28645833 | G82: =IFERROR(G77/G74,"n/d") -> 0.30963303 | H82: n/d
B83: S2 op margin % | C83: n/d | D83: n/d | E83: n/d | F83: =IFERROR(F78/F75,"n/d") -> -0.96 | G83: =IFERROR(G78/G75,"n/d") -> -0.093333333 | H83: n/d
B84: S3 op margin % | C84: n/d | D84: n/d | E84: n/d | F84: =IFERROR(F79/F76,"n/d") -> -1.0588235 | G84: =IFERROR(G79/G76,"n/d") -> -0.39759036 | H84: n/d
B86: Crecimiento YoY por segmento (FY25 vs FY24)
B87: S1 revenue YoY % | C87: n/d | D87: n/d | E87: n/d | F87: n/a | G87: =IFERROR(G74/F74-1,"n/d") -> 0.13541667 | H87: ytd
B88: S2 revenue YoY % | C88: n/d | D88: n/d | E88: n/d | F88: n/a | G88: =IFERROR(G75/F75-1,"n/d") -> 1.7272727 | H88: ytd
B89: S3 revenue YoY % | C89: n/d | D89: n/d | E89: n/d | F89: n/a | G89: =IFERROR(G76/F76-1,"n/d") -> 0.62745098 | H89: ytd
B92: E. METRICAS CLAVE (KPIs trimestrales específicos del sector)
B93: Métrica | C93: Valor
B94: Último trimestre Revenue YoY | C94: +12.5% YoY (Q1 2026 reported)
B95: Crecimiento orgánico (CC) | C95: Paid memberships >325M (Q4 2025); ~$3.0bn ads revenue run-rate FY26 (~2x FY25)
B96: Segmento estratégico crecimiento | C96: Ad revenue +100% FY26 (mgmt guide)
B97: Métrica KPI específica del sector | C97: Engagement: 2h+/day per member (mgmt disclosure)
B98: Backlog comercial total | C98: Obligaciones contenido no reconocidas $18.4bn (FY25 10-K)
B99: Ratio crecimiento orgánico | C99: Revenue / paid member FY25 ~$139 (vs $128 FY24)
B100: Capex + finance leases último trimestre | C100: PP&E capex Q1 2026 $196M (low; trim del 1.5% rev)
B101: Guía próximo trimestre capex | C101: No formal capex guidance — content spend $17.1bn FY25
B102: Guía anual capex | C102: Operating margin FY26 guide 31.5%
B103: Guía revenue próximo trimestre | C103: Q2 2026 revenue guide ~$13.0bn (mgmt outlook FY26 $50.7-51.7bn)
B104: Guía crecimiento por segmento | C104: Advertising ~2x FY26 (per Q4 2025 Shareholder Letter)
B105: Guía margen operativo implícito | C105: ~32% operating margin FY26 implícito

Sheet Modelo
B1: NETFLIX, INC. (NFLX) — MODELO OPERATIVO + FCFF + VALORACION (segmentado conceptual, FY26-FY30)
B2: LEYENDA: | C2: Input (azul) | D2: Cálculo (negro) | E2: Inline ratio | F2: Total (negrita) | G2: Terminal
B4: $ millions | C4: FY2026E | D4: FY2027E | E4: FY2028E | F4: FY2029E | G4: FY2030E | H4: Terminal
L5: Tabla A — Precio (Gordon DCF) vs WACC × g_terminal
B6: A. PROYECCION DE INGRESOS POR SEGMENTO
B7: S1 Suscripcion core revenue | C7: =Historico!G74*(1+Hipotesis!C30) -> 47960 | D7: =C7*(1+Hipotesis!D30) -> 51796.8 | E7: =D7*(1+Hipotesis!E30) -> 55422.576 | F7: =E7*(1+Hipotesis!F30) -> 58747.931 | G7: =F7*(1+Hipotesis!G30) -> 61685.327 | H7: =G7*(1+Hipotesis!H30) -> 63535.887 | L7: WACC ↓ \ g → | M7: 0.02 | N7: 0.025 | O7: 0.03 | P7: 0.035 | Q7: 0.04
B8: S1 Suscripcion core — revenue YoY % | C8: =C7/Historico!G74-1 -> 0.1 | D8: =D7/C7-1 -> 0.08 | E8: =E7/D7-1 -> 0.07 | F8: =F7/E7-1 -> 0.06 | G8: =G7/F7-1 -> 0.05 | H8: =H7/G7-1 -> 0.03 | L8: 0.075 | M8: =((C33/(1+$L$8)^0.5 + D33/(1+$L$8)^1.5 + E33/(1+$L$8)^2.5 + F33/(1+$L$8)^3.5 + G33/(1+$L$8)^4.5)+(G33*(1+M$7)/($L$8-M$7))/(1+$L$8)^5+Hipotesis!$C$15+Hipotesis!$C$16-Hipotesis!$C$14)/Hipotesis!$C$8 -> 74.753654 | N8: =((C33/(1+$L$8)^0.5 + D33/(1+$L$8)^1.5 + E33/(1+$L$8)^2.5 + F33/(1+$L$8)^3.5 + G33/(1+$L$8)^4.5)+(G33*(1+N$7)/($L$8-N$7))/(1+$L$8)^5+Hipotesis!$C$15+Hipotesis!$C$16-Hipotesis!$C$14)/Hipotesis!$C$8 -> 81.069806 | O8: =((C33/(1+$L$8)^0.5 + D33/(1+$L$8)^1.5 + E33/(1+$L$8)^2.5 + F33/(1+$L$8)^3.5 + G33/(1+$L$8)^4.5)+(G33*(1+O$7)/($L$8-O$7))/(1+$L$8)^5+Hipotesis!$C$15+Hipotesis!$C$16-Hipotesis!$C$14)/Hipotesis!$C$8 -> 88.789548 | P8: =((C33/(1+$L$8)^0.5 + D33/(1+$L$8)^1.5 + E33/(1+$L$8)^2.5 + F33/(1+$L$8)^3.5 + G33/(1+$L$8)^4.5)+(G33*(1+P$7)/($L$8-P$7))/(1+$L$8)^5+Hipotesis!$C$15+Hipotesis!$C$16-Hipotesis!$C$14)/Hipotesis!$C$8 -> 98.439225 | Q8: =((C33/(1+$L$8)^0.5 + D33/(1+$L$8)^1.5 + E33/(1+$L$8)^2.5 + F33/(1+$L$8)^3.5 + G33/(1+$L$8)^4.5)+(G33*(1+Q$7)/($L$8-Q$7))/(1+$L$8)^5+Hipotesis!$C$15+Hipotesis!$C$16-Hipotesis!$C$14)/Hipotesis!$C$8 -> 110.84595
B9: S2 Publicidad revenue | C9: =Historico!G75*(1+Hipotesis!C31) -> 3000 | D9: =C9*(1+Hipotesis!D31) -> 4800 | E9: =D9*(1+Hipotesis!E31) -> 6720 | F9: =E9*(1+Hipotesis!F31) -> 8400 | G9: =F9*(1+Hipotesis!G31) -> 9660 | H9: =G9*(1+Hipotesis!H31) -> 10143 | L9: 0.085 | M9: =((C33/(1+$L$9)^0.5 + D33/(1+$L$9)^1.5 + E33/(1+$L$9)^2.5 + F33/(1+$L$9)^3.5 + G33/(1+$L$9)^4.5)+(G33*(1+M$7)/($L$9-M$7))/(1+$L$9)^5+Hipotesis!$C$15+Hipotesis!$C$16-Hipotesis!$C$14)/Hipotesis!$C$8 -> 62.867657 | N9: =((C33/(1+$L$9)^0.5 + D33/(1+$L$9)^1.5 + E33/(1+$L$9)^2.5 + F33/(1+$L$9)^3.5 + G33/(1+$L$9)^4.5)+(G33*(1+N$7)/($L$9-N$7))/(1+$L$9)^5+Hipotesis!$C$15+Hipotesis!$C$16-Hipotesis!$C$14)/Hipotesis!$C$8 -> 67.159418 | O9: =((C33/(1+$L$9)^0.5 + D33/(1+$L$9)^1.5 + E33/(1+$L$9)^2.5 + F33/(1+$L$9)^3.5 + G33/(1+$L$9)^4.5)+(G33*(1+O$7)/($L$9-O$7))/(1+$L$9)^5+Hipotesis!$C$15+Hipotesis!$C$16-Hipotesis!$C$14)/Hipotesis!$C$8 -> 72.2315 | P9: =((C33/(1+$L$9)^0.5 + D33/(1+$L$9)^1.5 + E33/(1+$L$9)^2.5 + F33/(1+$L$9)^3.5 + G33/(1+$L$9)^4.5)+(G33*(1+P$7)/($L$9-P$7))/(1+$L$9)^5+Hipotesis!$C$15+Hipotesis!$C$16-Hipotesis!$C$14)/Hipotesis!$C$8 -> 78.317999 | Q9: =((C33/(1+$L$9)^0.5 + D33/(1+$L$9)^1.5 + E33/(1+$L$9)^2.5 + F33/(1+$L$9)^3.5 + G33/(1+$L$9)^4.5)+(G33*(1+Q$7)/($L$9-Q$7))/(1+$L$9)^5+Hipotesis!$C$15+Hipotesis!$C$16-Hipotesis!$C$14)/Hipotesis!$C$8 -> 85.757052
B10: S2 Publicidad — revenue YoY % | C10: =C9/Historico!G75-1 -> 1 | D10: =D9/C9-1 -> 0.6 | E10: =E9/D9-1 -> 0.4 | F10: =F9/E9-1 -> 0.25 | G10: =G9/F9-1 -> 0.15 | H10: =H9/G9-1 -> 0.05 | L10: 0.0912 | M10: =((C33/(1+$L$10)^0.5 + D33/(1+$L$10)^1.5 + E33/(1+$L$10)^2.5 + F33/(1+$L$10)^3.5 + G33/(1+$L$10)^4.5)+(G33*(1+M$7)/($L$10-M$7))/(1+$L$10)^5+Hipotesis!$C$15+Hipotesis!$C$16-Hipotesis!$C$14)/Hipotesis!$C$8 -> 57.187006 | N10: =((C33/(1+$L$10)^0.5 + D33/(1+$L$10)^1.5 + E33/(1+$L$10)^2.5 + F33/(1+$L$10)^3.5 + G33/(1+$L$10)^4.5)+(G33*(1+N$7)/($L$10-N$7))/(1+$L$10)^5+Hipotesis!$C$15+Hipotesis!$C$16-Hipotesis!$C$14)/Hipotesis!$C$8 -> 60.658079 | O10: =((C33/(1+$L$10)^0.5 + D33/(1+$L$10)^1.5 + E33/(1+$L$10)^2.5 + F33/(1+$L$10)^3.5 + G33/(1+$L$10)^4.5)+(G33*(1+O$7)/($L$10-O$7))/(1+$L$10)^5+Hipotesis!$C$15+Hipotesis!$C$16-Hipotesis!$C$14)/Hipotesis!$C$8 -> 64.696321 | P10: =((C33/(1+$L$10)^0.5 + D33/(1+$L$10)^1.5 + E33/(1+$L$10)^2.5 + F33/(1+$L$10)^3.5 + G33/(1+$L$10)^4.5)+(G33*(1+P$7)/($L$10-P$7))/(1+$L$10)^5+Hipotesis!$C$15+Hipotesis!$C$16-Hipotesis!$C$14)/Hipotesis!$C$8 -> 69.453111 | Q10: =((C33/(1+$L$10)^0.5 + D33/(1+$L$10)^1.5 + E33/(1+$L$10)^2.5 + F33/(1+$L$10)^3.5 + G33/(1+$L$10)^4.5)+(G33*(1+Q$7)/($L$10-Q$7))/(1+$L$10)^5+Hipotesis!$C$15+Hipotesis!$C$16-Hipotesis!$C$14)/Hipotesis!$C$8 -> 75.138961
B11: S3 Otros (games/live/licensing) revenue | C11: =Historico!G76*(1+Hipotesis!C32) -> 124.5 | D11: =C11*(1+Hipotesis!D32) -> 174.3 | E11: =D11*(1+Hipotesis!E32) -> 226.59 | F11: =E11*(1+Hipotesis!F32) -> 271.908 | G11: =F11*(1+Hipotesis!G32) -> 312.6942 | H11: =G11*(1+Hipotesis!H32) -> 328.32891 | L11: 0.1 | M11: =((C33/(1+$L$11)^0.5 + D33/(1+$L$11)^1.5 + E33/(1+$L$11)^2.5 + F33/(1+$L$11)^3.5 + G33/(1+$L$11)^4.5)+(G33*(1+M$7)/($L$11-M$7))/(1+$L$11)^5+Hipotesis!$C$15+Hipotesis!$C$16-Hipotesis!$C$14)/Hipotesis!$C$8 -> 50.649023 | N11: =((C33/(1+$L$11)^0.5 + D33/(1+$L$11)^1.5 + E33/(1+$L$11)^2.5 + F33/(1+$L$11)^3.5 + G33/(1+$L$11)^4.5)+(G33*(1+N$7)/($L$11-N$7))/(1+$L$11)^5+Hipotesis!$C$15+Hipotesis!$C$16-Hipotesis!$C$14)/Hipotesis!$C$8 -> 53.289589 | O11: =((C33/(1+$L$11)^0.5 + D33/(1+$L$11)^1.5 + E33/(1+$L$11)^2.5 + F33/(1+$L$11)^3.5 + G33/(1+$L$11)^4.5)+(G33*(1+O$7)/($L$11-O$7))/(1+$L$11)^5+Hipotesis!$C$15+Hipotesis!$C$16-Hipotesis!$C$14)/Hipotesis!$C$8 -> 56.30738 | P11: =((C33/(1+$L$11)^0.5 + D33/(1+$L$11)^1.5 + E33/(1+$L$11)^2.5 + F33/(1+$L$11)^3.5 + G33/(1+$L$11)^4.5)+(G33*(1+P$7)/($L$11-P$7))/(1+$L$11)^5+Hipotesis!$C$15+Hipotesis!$C$16-Hipotesis!$C$14)/Hipotesis!$C$8 -> 59.789446 | Q11: =((C33/(1+$L$11)^0.5 + D33/(1+$L$11)^1.5 + E33/(1+$L$11)^2.5 + F33/(1+$L$11)^3.5 + G33/(1+$L$11)^4.5)+(G33*(1+Q$7)/($L$11-Q$7))/(1+$L$11)^5+Hipotesis!$C$15+Hipotesis!$C$16-Hipotesis!$C$14)/Hipotesis!$C$8 -> 63.851857
B12: S3 Otros — revenue YoY % | C12: =C11/Historico!G76-1 -> 0.5 | D12: =D11/C11-1 -> 0.4 | E12: =E11/D11-1 -> 0.3 | F12: =F11/E11-1 -> 0.2 | G12: =G11/F11-1 -> 0.15 | H12: =H11/G11-1 -> 0.05 | L12: 0.11 | M12: =((C33/(1+$L$12)^0.5 + D33/(1+$L$12)^1.5 + E33/(1+$L$12)^2.5 + F33/(1+$L$12)^3.5 + G33/(1+$L$12)^4.5)+(G33*(1+M$7)/($L$12-M$7))/(1+$L$12)^5+Hipotesis!$C$15+Hipotesis!$C$16-Hipotesis!$C$14)/Hipotesis!$C$8 -> 44.786981 | N12: =((C33/(1+$L$12)^0.5 + D33/(1+$L$12)^1.5 + E33/(1+$L$12)^2.5 + F33/(1+$L$12)^3.5 + G33/(1+$L$12)^4.5)+(G33*(1+N$7)/($L$12-N$7))/(1+$L$12)^5+Hipotesis!$C$15+Hipotesis!$C$16-Hipotesis!$C$14)/Hipotesis!$C$8 -> 46.784384 | O12: =((C33/(1+$L$12)^0.5 + D33/(1+$L$12)^1.5 + E33/(1+$L$12)^2.5 + F33/(1+$L$12)^3.5 + G33/(1+$L$12)^4.5)+(G33*(1+O$7)/($L$12-O$7))/(1+$L$12)^5+Hipotesis!$C$15+Hipotesis!$C$16-Hipotesis!$C$14)/Hipotesis!$C$8 -> 49.031463 | P12: =((C33/(1+$L$12)^0.5 + D33/(1+$L$12)^1.5 + E33/(1+$L$12)^2.5 + F33/(1+$L$12)^3.5 + G33/(1+$L$12)^4.5)+(G33*(1+P$7)/($L$12-P$7))/(1+$L$12)^5+Hipotesis!$C$15+Hipotesis!$C$16-Hipotesis!$C$14)/Hipotesis!$C$8 -> 51.578152 | Q12: =((C33/(1+$L$12)^0.5 + D33/(1+$L$12)^1.5 + E33/(1+$L$12)^2.5 + F33/(1+$L$12)^3.5 + G33/(1+$L$12)^4.5)+(G33*(1+Q$7)/($L$12-Q$7))/(1+$L$12)^5+Hipotesis!$C$15+Hipotesis!$C$16-Hipotesis!$C$14)/Hipotesis!$C$8 -> 54.488655
B13: Total Revenue | C13: =C7+C9+C11 -> 51084.5 | D13: =D7+D9+D11 -> 56771.1 | E13: =E7+E9+E11 -> 62369.166 | F13: =F7+F9+F11 -> 67419.839 | G13: =G7+G9+G11 -> 71658.021 | H13: =H7+H9+H11 -> 74007.216
B14: Revenue growth YoY % | C14: =C13/Historico!G6-1 -> 0.13061328 | D14: =D13/C13-1 -> 0.11131752 | E14: =E13/D13-1 -> 0.098607672 | F14: =F13/E13-1 -> 0.080980281 | G14: =G13/F13-1 -> 0.062862546 | H14: =H13/G13-1 -> 0.032783413
L15: Tabla B — Precio (Gordon DCF) vs WACC × Op margin terminal
B16: B. OPERATING INCOME POR SEGMENTO
B17: S1 Suscripcion core — operating income | C17: =C7*Hipotesis!C33 -> 15826.8 | D17: =D7*Hipotesis!D33 -> 17610.912 | E17: =E7*Hipotesis!E33 -> 19397.902 | F17: =F7*Hipotesis!F33 -> 20855.515 | G17: =G7*Hipotesis!G33 -> 22206.718 | H17: =H7*Hipotesis!H33 -> 22872.919 | L17: WACC ↓ \ margin → | M17: 0.4 | N17: 0.43 | O17: 0.46 | P17: 0.49 | Q17: 0.52
B18: S1 Suscripcion core — op margin % | C18: =C17/C7 -> 0.33 | D18: =D17/D7 -> 0.34 | E18: =E17/E7 -> 0.35 | F18: =F17/F7 -> 0.355 | G18: =G17/G7 -> 0.36 | H18: =H17/H7 -> 0.36 | L18: 0.075 | M18: =(C41+((G13*M$17*(1-Hipotesis!$C$13)+G28+G30+G32)*(1+Hipotesis!$C$47)/($L$18-Hipotesis!$C$47))/(1+$L$18)^5+Hipotesis!$C$15+Hipotesis!$C$16-Hipotesis!$C$14)/Hipotesis!$C$8 -> 99.203977 | N18: =(C41+((G13*N$17*(1-Hipotesis!$C$13)+G28+G30+G32)*(1+Hipotesis!$C$47)/($L$18-Hipotesis!$C$47))/(1+$L$18)^5+Hipotesis!$C$15+Hipotesis!$C$16-Hipotesis!$C$14)/Hipotesis!$C$8 -> 105.71258 | O18: =(C41+((G13*O$17*(1-Hipotesis!$C$13)+G28+G30+G32)*(1+Hipotesis!$C$47)/($L$18-Hipotesis!$C$47))/(1+$L$18)^5+Hipotesis!$C$15+Hipotesis!$C$16-Hipotesis!$C$14)/Hipotesis!$C$8 -> 112.22118 | P18: =(C41+((G13*P$17*(1-Hipotesis!$C$13)+G28+G30+G32)*(1+Hipotesis!$C$47)/($L$18-Hipotesis!$C$47))/(1+$L$18)^5+Hipotesis!$C$15+Hipotesis!$C$16-Hipotesis!$C$14)/Hipotesis!$C$8 -> 118.72978 | Q18: =(C41+((G13*Q$17*(1-Hipotesis!$C$13)+G28+G30+G32)*(1+Hipotesis!$C$47)/($L$18-Hipotesis!$C$47))/(1+$L$18)^5+Hipotesis!$C$15+Hipotesis!$C$16-Hipotesis!$C$14)/Hipotesis!$C$8 -> 125.23838
B19: S2 Publicidad (motor crecimiento) operating income | C19: =C9*Hipotesis!C34 -> 150 | D19: =D9*Hipotesis!D34 -> 576 | E19: =E9*Hipotesis!E34 -> 1209.6 | F19: =F9*Hipotesis!F34 -> 1932 | G19: =G9*Hipotesis!G34 -> 2704.8 | H19: =H9*Hipotesis!H34 -> 3042.9 | L19: 0.085 | M19: =(C41+((G13*M$17*(1-Hipotesis!$C$13)+G28+G30+G32)*(1+Hipotesis!$C$47)/($L$19-Hipotesis!$C$47))/(1+$L$19)^5+Hipotesis!$C$15+Hipotesis!$C$16-Hipotesis!$C$14)/Hipotesis!$C$8 -> 80.569364 | N19: =(C41+((G13*N$17*(1-Hipotesis!$C$13)+G28+G30+G32)*(1+Hipotesis!$C$47)/($L$19-Hipotesis!$C$47))/(1+$L$19)^5+Hipotesis!$C$15+Hipotesis!$C$16-Hipotesis!$C$14)/Hipotesis!$C$8 -> 85.653663 | O19: =(C41+((G13*O$17*(1-Hipotesis!$C$13)+G28+G30+G32)*(1+Hipotesis!$C$47)/($L$19-Hipotesis!$C$47))/(1+$L$19)^5+Hipotesis!$C$15+Hipotesis!$C$16-Hipotesis!$C$14)/Hipotesis!$C$8 -> 90.737962 | P19: =(C41+((G13*P$17*(1-Hipotesis!$C$13)+G28+G30+G32)*(1+Hipotesis!$C$47)/($L$19-Hipotesis!$C$47))/(1+$L$19)^5+Hipotesis!$C$15+Hipotesis!$C$16-Hipotesis!$C$14)/Hipotesis!$C$8 -> 95.82226 | Q19: =(C41+((G13*Q$17*(1-Hipotesis!$C$13)+G28+G30+G32)*(1+Hipotesis!$C$47)/($L$19-Hipotesis!$C$47))/(1+$L$19)^5+Hipotesis!$C$15+Hipotesis!$C$16-Hipotesis!$C$14)/Hipotesis!$C$8 -> 100.90656
B20: S2 Publicidad — op margin % | C20: =C19/C9 -> 0.05 | D20: =D19/D9 -> 0.12 | E20: =E19/E9 -> 0.18 | F20: =F19/F9 -> 0.23 | G20: =G19/G9 -> 0.28 | H20: =H19/H9 -> 0.3 | L20: 0.0912 | M20: =(C41+((G13*M$17*(1-Hipotesis!$C$13)+G28+G30+G32)*(1+Hipotesis!$C$47)/($L$20-Hipotesis!$C$47))/(1+$L$20)^5+Hipotesis!$C$15+Hipotesis!$C$16-Hipotesis!$C$14)/Hipotesis!$C$8 -> 72.151328 | N20: =(C41+((G13*N$17*(1-Hipotesis!$C$13)+G28+G30+G32)*(1+Hipotesis!$C$47)/($L$20-Hipotesis!$C$47))/(1+$L$20)^5+Hipotesis!$C$15+Hipotesis!$C$16-Hipotesis!$C$14)/Hipotesis!$C$8 -> 76.59221 | O20: =(C41+((G13*O$17*(1-Hipotesis!$C$13)+G28+G30+G32)*(1+Hipotesis!$C$47)/($L$20-Hipotesis!$C$47))/(1+$L$20)^5+Hipotesis!$C$15+Hipotesis!$C$16-Hipotesis!$C$14)/Hipotesis!$C$8 -> 81.033092 | P20: =(C41+((G13*P$17*(1-Hipotesis!$C$13)+G28+G30+G32)*(1+Hipotesis!$C$47)/($L$20-Hipotesis!$C$47))/(1+$L$20)^5+Hipotesis!$C$15+Hipotesis!$C$16-Hipotesis!$C$14)/Hipotesis!$C$8 -> 85.473974 | Q20: =(C41+((G13*Q$17*(1-Hipotesis!$C$13)+G28+G30+G32)*(1+Hipotesis!$C$47)/($L$20-Hipotesis!$C$47))/(1+$L$20)^5+Hipotesis!$C$15+Hipotesis!$C$16-Hipotesis!$C$14)/Hipotesis!$C$8 -> 89.914856
B21: S3 Otros — operating income | C21: =C11*Hipotesis!C35 -> 6.225 | D21: =D11*Hipotesis!D35 -> 17.43 | E21: =E11*Hipotesis!E35 -> 27.1908 | F21: =F11*Hipotesis!F35 -> 40.7862 | G21: =G11*Hipotesis!G35 -> 56.284956 | H21: =H11*Hipotesis!H35 -> 65.665782 | L21: 0.1 | M21: =(C41+((G13*M$17*(1-Hipotesis!$C$13)+G28+G30+G32)*(1+Hipotesis!$C$47)/($L$21-Hipotesis!$C$47))/(1+$L$21)^5+Hipotesis!$C$15+Hipotesis!$C$16-Hipotesis!$C$14)/Hipotesis!$C$8 -> 62.847492 | N21: =(C41+((G13*N$17*(1-Hipotesis!$C$13)+G28+G30+G32)*(1+Hipotesis!$C$47)/($L$21-Hipotesis!$C$47))/(1+$L$21)^5+Hipotesis!$C$15+Hipotesis!$C$16-Hipotesis!$C$14)/Hipotesis!$C$8 -> 66.577253 | O21: =(C41+((G13*O$17*(1-Hipotesis!$C$13)+G28+G30+G32)*(1+Hipotesis!$C$47)/($L$21-Hipotesis!$C$47))/(1+$L$21)^5+Hipotesis!$C$15+Hipotesis!$C$16-Hipotesis!$C$14)/Hipotesis!$C$8 -> 70.307014 | P21: =(C41+((G13*P$17*(1-Hipotesis!$C$13)+G28+G30+G32)*(1+Hipotesis!$C$47)/($L$21-Hipotesis!$C$47))/(1+$L$21)^5+Hipotesis!$C$15+Hipotesis!$C$16-Hipotesis!$C$14)/Hipotesis!$C$8 -> 74.036775 | Q21: =(C41+((G13*Q$17*(1-Hipotesis!$C$13)+G28+G30+G32)*(1+Hipotesis!$C$47)/($L$21-Hipotesis!$C$47))/(1+$L$21)^5+Hipotesis!$C$15+Hipotesis!$C$16-Hipotesis!$C$14)/Hipotesis!$C$8 -> 77.766535
B22: S3 Otros — op margin % | C22: =C21/C11 -> 0.05 | D22: =D21/D11 -> 0.1 | E22: =E21/E11 -> 0.12 | F22: =F21/F11 -> 0.15 | G22: =G21/G11 -> 0.18 | H22: =H21/H11 -> 0.2 | L22: 0.11 | M22: =(C41+((G13*M$17*(1-Hipotesis!$C$13)+G28+G30+G32)*(1+Hipotesis!$C$47)/($L$22-Hipotesis!$C$47))/(1+$L$22)^5+Hipotesis!$C$15+Hipotesis!$C$16-Hipotesis!$C$14)/Hipotesis!$C$8 -> 54.858791 | N22: =(C41+((G13*N$17*(1-Hipotesis!$C$13)+G28+G30+G32)*(1+Hipotesis!$C$47)/($L$22-Hipotesis!$C$47))/(1+$L$22)^5+Hipotesis!$C$15+Hipotesis!$C$16-Hipotesis!$C$14)/Hipotesis!$C$8 -> 57.97795 | O22: =(C41+((G13*O$17*(1-Hipotesis!$C$13)+G28+G30+G32)*(1+Hipotesis!$C$47)/($L$22-Hipotesis!$C$47))/(1+$L$22)^5+Hipotesis!$C$15+Hipotesis!$C$16-Hipotesis!$C$14)/Hipotesis!$C$8 -> 61.097109 | P22: =(C41+((G13*P$17*(1-Hipotesis!$C$13)+G28+G30+G32)*(1+Hipotesis!$C$47)/($L$22-Hipotesis!$C$47))/(1+$L$22)^5+Hipotesis!$C$15+Hipotesis!$C$16-Hipotesis!$C$14)/Hipotesis!$C$8 -> 64.216269 | Q22: =(C41+((G13*Q$17*(1-Hipotesis!$C$13)+G28+G30+G32)*(1+Hipotesis!$C$47)/($L$22-Hipotesis!$C$47))/(1+$L$22)^5+Hipotesis!$C$15+Hipotesis!$C$16-Hipotesis!$C$14)/Hipotesis!$C$8 -> 67.335428
B23: Total Operating Income (EBIT) | C23: =C17+C19+C21 -> 15983.025 | D23: =D17+D19+D21 -> 18204.342 | E23: =E17+E19+E21 -> 20634.692 | F23: =F17+F19+F21 -> 22828.302 | G23: =G17+G19+G21 -> 24967.803 | H23: =H17+H19+H21 -> 25981.485
B24: Operating margin % | C24: =C23/C13 -> 0.31287426 | D24: =D23/D13 -> 0.32066213 | E24: =E23/E13 -> 0.33084766 | F24: =F23/F13 -> 0.33859917 | G24: =G23/G13 -> 0.34842998 | H24: =H23/H13 -> 0.35106692 | L24: Tabla C — Precio (Gordon DCF) vs Capex/Rev terminal × g_terminal
B26: C. PUENTE DE EBIT A FREE CASH FLOW (FCFF) | L26: Capex/Rev ↓ \ g → | M26: 0.02 | N26: 0.025 | O26: 0.03 | P26: 0.035 | Q26: 0.04
B27: NOPAT = EBIT × (1 − tax rate) | C27: =C23*(1-Hipotesis!$C$13) -> 12786.42 | D27: =D23*(1-Hipotesis!$C$13) -> 14563.474 | E27: =E23*(1-Hipotesis!$C$13) -> 16507.754 | F27: =F23*(1-Hipotesis!$C$13) -> 18262.641 | G27: =G23*(1-Hipotesis!$C$13) -> 19974.242 | H27: =H23*(1-Hipotesis!$C$13) -> 20785.188 | L27: 0.1 | M27: =(C41+((G27+G28+(-G13*$L$27)+G32)*(1+M$26)/(Hipotesis!$C$25-M$26))/(1+Hipotesis!$C$25)^5+Hipotesis!$C$15+Hipotesis!$C$16-Hipotesis!$C$14)/Hipotesis!$C$8 -> 40.873063 | N27: =(C41+((G27+G28+(-G13*$L$27)+G32)*(1+N$26)/(Hipotesis!$C$25-N$26))/(1+Hipotesis!$C$25)^5+Hipotesis!$C$15+Hipotesis!$C$16-Hipotesis!$C$14)/Hipotesis!$C$8 -> 42.895278 | O27: =(C41+((G27+G28+(-G13*$L$27)+G32)*(1+O$26)/(Hipotesis!$C$25-O$26))/(1+Hipotesis!$C$25)^5+Hipotesis!$C$15+Hipotesis!$C$16-Hipotesis!$C$14)/Hipotesis!$C$8 -> 45.222589 | P27: =(C41+((G27+G28+(-G13*$L$27)+G32)*(1+P$26)/(Hipotesis!$C$25-P$26))/(1+Hipotesis!$C$25)^5+Hipotesis!$C$15+Hipotesis!$C$16-Hipotesis!$C$14)/Hipotesis!$C$8 -> 47.929674 | Q27: =(C41+((G27+G28+(-G13*$L$27)+G32)*(1+Q$26)/(Hipotesis!$C$25-Q$26))/(1+Hipotesis!$C$25)^5+Hipotesis!$C$15+Hipotesis!$C$16-Hipotesis!$C$14)/Hipotesis!$C$8 -> 51.117749
B28: (+) D&A | C28: =C13*Hipotesis!C40 -> 408.676 | D28: =D13*Hipotesis!D40 -> 454.1688 | E28: =E13*Hipotesis!E40 -> 498.95333 | F28: =F13*Hipotesis!F40 -> 539.35871 | G28: =G13*Hipotesis!G40 -> 573.26417 | H28: =H13*Hipotesis!H40 -> 592.05773 | L28: 0.125 | M28: =(C41+((G27+G28+(-G13*$L$28)+G32)*(1+M$26)/(Hipotesis!$C$25-M$26))/(1+Hipotesis!$C$25)^5+Hipotesis!$C$15+Hipotesis!$C$16-Hipotesis!$C$14)/Hipotesis!$C$8 -> 37.282148 | N28: =(C41+((G27+G28+(-G13*$L$28)+G32)*(1+N$26)/(Hipotesis!$C$25-N$26))/(1+Hipotesis!$C$25)^5+Hipotesis!$C$15+Hipotesis!$C$16-Hipotesis!$C$14)/Hipotesis!$C$8 -> 39.033643 | O28: =(C41+((G27+G28+(-G13*$L$28)+G32)*(1+O$26)/(Hipotesis!$C$25-O$26))/(1+Hipotesis!$C$25)^5+Hipotesis!$C$15+Hipotesis!$C$16-Hipotesis!$C$14)/Hipotesis!$C$8 -> 41.049389 | P28: =(C41+((G27+G28+(-G13*$L$28)+G32)*(1+P$26)/(Hipotesis!$C$25-P$26))/(1+Hipotesis!$C$25)^5+Hipotesis!$C$15+Hipotesis!$C$16-Hipotesis!$C$14)/Hipotesis!$C$8 -> 43.394068 | Q28: =(C41+((G27+G28+(-G13*$L$28)+G32)*(1+Q$26)/(Hipotesis!$C$25-Q$26))/(1+Hipotesis!$C$25)^5+Hipotesis!$C$15+Hipotesis!$C$16-Hipotesis!$C$14)/Hipotesis!$C$8 -> 46.155346
B29: D&A / Revenue % | C29: =C28/C13 -> 0.008 | D29: =D28/D13 -> 0.008 | E29: =E28/E13 -> 0.008 | F29: =F28/F13 -> 0.008 | G29: =G28/G13 -> 0.008 | H29: =H28/H13 -> 0.008 | L29: 0.15 | M29: =(C41+((G27+G28+(-G13*$L$29)+G32)*(1+M$26)/(Hipotesis!$C$25-M$26))/(1+Hipotesis!$C$25)^5+Hipotesis!$C$15+Hipotesis!$C$16-Hipotesis!$C$14)/Hipotesis!$C$8 -> 33.691232 | N29: =(C41+((G27+G28+(-G13*$L$29)+G32)*(1+N$26)/(Hipotesis!$C$25-N$26))/(1+Hipotesis!$C$25)^5+Hipotesis!$C$15+Hipotesis!$C$16-Hipotesis!$C$14)/Hipotesis!$C$8 -> 35.172007 | O29: =(C41+((G27+G28+(-G13*$L$29)+G32)*(1+O$26)/(Hipotesis!$C$25-O$26))/(1+Hipotesis!$C$25)^5+Hipotesis!$C$15+Hipotesis!$C$16-Hipotesis!$C$14)/Hipotesis!$C$8 -> 36.876189 | P29: =(C41+((G27+G28+(-G13*$L$29)+G32)*(1+P$26)/(Hipotesis!$C$25-P$26))/(1+Hipotesis!$C$25)^5+Hipotesis!$C$15+Hipotesis!$C$16-Hipotesis!$C$14)/Hipotesis!$C$8 -> 38.858462 | Q29: =(C41+((G27+G28+(-G13*$L$29)+G32)*(1+Q$26)/(Hipotesis!$C$25-Q$26))/(1+Hipotesis!$C$25)^5+Hipotesis!$C$15+Hipotesis!$C$16-Hipotesis!$C$14)/Hipotesis!$C$8 -> 41.192942
B30: (−) Capex | C30: =-C13*Hipotesis!C39 -> -766.2675 | D30: =-D13*Hipotesis!D39 -> -851.5665 | E30: =-E13*Hipotesis!E39 -> -935.53749 | F30: =-F13*Hipotesis!F39 -> -943.87774 | G30: =-G13*Hipotesis!G39 -> -1003.2123 | H30: =-H13*Hipotesis!H39 -> -962.09381 | L30: 0.175 | M30: =(C41+((G27+G28+(-G13*$L$30)+G32)*(1+M$26)/(Hipotesis!$C$25-M$26))/(1+Hipotesis!$C$25)^5+Hipotesis!$C$15+Hipotesis!$C$16-Hipotesis!$C$14)/Hipotesis!$C$8 -> 30.100317 | N30: =(C41+((G27+G28+(-G13*$L$30)+G32)*(1+N$26)/(Hipotesis!$C$25-N$26))/(1+Hipotesis!$C$25)^5+Hipotesis!$C$15+Hipotesis!$C$16-Hipotesis!$C$14)/Hipotesis!$C$8 -> 31.310371 | O30: =(C41+((G27+G28+(-G13*$L$30)+G32)*(1+O$26)/(Hipotesis!$C$25-O$26))/(1+Hipotesis!$C$25)^5+Hipotesis!$C$15+Hipotesis!$C$16-Hipotesis!$C$14)/Hipotesis!$C$8 -> 32.702989 | P30: =(C41+((G27+G28+(-G13*$L$30)+G32)*(1+P$26)/(Hipotesis!$C$25-P$26))/(1+Hipotesis!$C$25)^5+Hipotesis!$C$15+Hipotesis!$C$16-Hipotesis!$C$14)/Hipotesis!$C$8 -> 34.322856 | Q30: =(C41+((G27+G28+(-G13*$L$30)+G32)*(1+Q$26)/(Hipotesis!$C$25-Q$26))/(1+Hipotesis!$C$25)^5+Hipotesis!$C$15+Hipotesis!$C$16-Hipotesis!$C$14)/Hipotesis!$C$8 -> 36.230539
B31: Capex / Revenue % | C31: =-C30/C13 -> 0.015 | D31: =-D30/D13 -> 0.015 | E31: =-E30/E13 -> 0.015 | F31: =-F30/F13 -> 0.014 | G31: =-G30/G13 -> 0.014 | H31: =-H30/H13 -> 0.013 | L31: 0.2 | M31: =(C41+((G27+G28+(-G13*$L$31)+G32)*(1+M$26)/(Hipotesis!$C$25-M$26))/(1+Hipotesis!$C$25)^5+Hipotesis!$C$15+Hipotesis!$C$16-Hipotesis!$C$14)/Hipotesis!$C$8 -> 26.509402 | N31: =(C41+((G27+G28+(-G13*$L$31)+G32)*(1+N$26)/(Hipotesis!$C$25-N$26))/(1+Hipotesis!$C$25)^5+Hipotesis!$C$15+Hipotesis!$C$16-Hipotesis!$C$14)/Hipotesis!$C$8 -> 27.448736 | O31: =(C41+((G27+G28+(-G13*$L$31)+G32)*(1+O$26)/(Hipotesis!$C$25-O$26))/(1+Hipotesis!$C$25)^5+Hipotesis!$C$15+Hipotesis!$C$16-Hipotesis!$C$14)/Hipotesis!$C$8 -> 28.529789 | P31: =(C41+((G27+G28+(-G13*$L$31)+G32)*(1+P$26)/(Hipotesis!$C$25-P$26))/(1+Hipotesis!$C$25)^5+Hipotesis!$C$15+Hipotesis!$C$16-Hipotesis!$C$14)/Hipotesis!$C$8 -> 29.78725 | Q31: =(C41+((G27+G28+(-G13*$L$31)+G32)*(1+Q$26)/(Hipotesis!$C$25-Q$26))/(1+Hipotesis!$C$25)^5+Hipotesis!$C$15+Hipotesis!$C$16-Hipotesis!$C$14)/Hipotesis!$C$8 -> 31.268135
B32: (−) ΔWorking Capital | C32: =-C13*Hipotesis!C42 -> 255.4225 | D32: =-D13*Hipotesis!D42 -> 283.8555 | E32: =-E13*Hipotesis!E42 -> 311.84583 | F32: =-F13*Hipotesis!F42 -> 0 | G32: =-G13*Hipotesis!G42 -> 0 | H32: =-H13*Hipotesis!H42 -> 0
B33: Free Cash Flow to Firm (FCFF) | C33: =C27+C28+C30+C32 -> 12684.251 | D33: =D27+D28+D30+D32 -> 14449.931 | E33: =E27+E28+E30+E32 -> 16383.016 | F33: =F27+F28+F30+F32 -> 17858.122 | G33: =G27+G28+G30+G32 -> 19544.294 | H33: =H27+H28+H30+H32 -> 20415.152 | L33: Tabla D — Precio (Exit EV/EBITDA) vs WACC × Exit EV/EBITDA
B34: FCFF / Revenue % | C34: =C33/C13 -> 0.24829941 | D34: =D33/D13 -> 0.25452971 | E34: =E33/E13 -> 0.26267813 | F34: =F33/F13 -> 0.26487934 | G34: =G33/G13 -> 0.27274398 | H34: =H33/H13 -> 0.27585353
B35: FCFF / NOPAT % (conversion) | C35: =C33/C27 -> 0.99200957 | D35: =D33/D27 -> 0.99220363 | E35: =E33/E27 -> 0.99244365 | F35: =F33/F27 -> 0.97784992 | G35: =G33/G27 -> 0.97847487 | H35: =H33/H27 -> 0.98219713 | L35: WACC ↓ \ EV/EBITDA → | M35: 16 | N35: 18 | O35: 20 | P35: 22 | Q35: 24
L36: 0.075 | M36: =((C33/(1+$L$36)^0.5 + D33/(1+$L$36)^1.5 + E33/(1+$L$36)^2.5 + F33/(1+$L$36)^3.5 + G33/(1+$L$36)^4.5)+(M$35*(G23+G28))/(1+$L$36)^5+Hipotesis!$C$15+Hipotesis!$C$16-Hipotesis!$C$14)/Hipotesis!$C$8 -> 82.392395 | N36: =((C33/(1+$L$36)^0.5 + D33/(1+$L$36)^1.5 + E33/(1+$L$36)^2.5 + F33/(1+$L$36)^3.5 + G33/(1+$L$36)^4.5)+(N$35*(G23+G28))/(1+$L$36)^5+Hipotesis!$C$15+Hipotesis!$C$16-Hipotesis!$C$14)/Hipotesis!$C$8 -> 90.838488 | O36: =((C33/(1+$L$36)^0.5 + D33/(1+$L$36)^1.5 + E33/(1+$L$36)^2.5 + F33/(1+$L$36)^3.5 + G33/(1+$L$36)^4.5)+(O$35*(G23+G28))/(1+$L$36)^5+Hipotesis!$C$15+Hipotesis!$C$16-Hipotesis!$C$14)/Hipotesis!$C$8 -> 99.284581 | P36: =((C33/(1+$L$36)^0.5 + D33/(1+$L$36)^1.5 + E33/(1+$L$36)^2.5 + F33/(1+$L$36)^3.5 + G33/(1+$L$36)^4.5)+(P$35*(G23+G28))/(1+$L$36)^5+Hipotesis!$C$15+Hipotesis!$C$16-Hipotesis!$C$14)/Hipotesis!$C$8 -> 107.73067 | Q36: =((C33/(1+$L$36)^0.5 + D33/(1+$L$36)^1.5 + E33/(1+$L$36)^2.5 + F33/(1+$L$36)^3.5 + G33/(1+$L$36)^4.5)+(Q$35*(G23+G28))/(1+$L$36)^5+Hipotesis!$C$15+Hipotesis!$C$16-Hipotesis!$C$14)/Hipotesis!$C$8 -> 116.17677
B37: D. DCF DISCOUNTING & VALUE BRIDGE | L37: 0.085 | M37: =((C33/(1+$L$37)^0.5 + D33/(1+$L$37)^1.5 + E33/(1+$L$37)^2.5 + F33/(1+$L$37)^3.5 + G33/(1+$L$37)^4.5)+(M$35*(G23+G28))/(1+$L$37)^5+Hipotesis!$C$15+Hipotesis!$C$16-Hipotesis!$C$14)/Hipotesis!$C$8 -> 78.963687 | N37: =((C33/(1+$L$37)^0.5 + D33/(1+$L$37)^1.5 + E33/(1+$L$37)^2.5 + F33/(1+$L$37)^3.5 + G33/(1+$L$37)^4.5)+(N$35*(G23+G28))/(1+$L$37)^5+Hipotesis!$C$15+Hipotesis!$C$16-Hipotesis!$C$14)/Hipotesis!$C$8 -> 87.027668 | O37: =((C33/(1+$L$37)^0.5 + D33/(1+$L$37)^1.5 + E33/(1+$L$37)^2.5 + F33/(1+$L$37)^3.5 + G33/(1+$L$37)^4.5)+(O$35*(G23+G28))/(1+$L$37)^5+Hipotesis!$C$15+Hipotesis!$C$16-Hipotesis!$C$14)/Hipotesis!$C$8 -> 95.091649 | P37: =((C33/(1+$L$37)^0.5 + D33/(1+$L$37)^1.5 + E33/(1+$L$37)^2.5 + F33/(1+$L$37)^3.5 + G33/(1+$L$37)^4.5)+(P$35*(G23+G28))/(1+$L$37)^5+Hipotesis!$C$15+Hipotesis!$C$16-Hipotesis!$C$14)/Hipotesis!$C$8 -> 103.15563 | Q37: =((C33/(1+$L$37)^0.5 + D33/(1+$L$37)^1.5 + E33/(1+$L$37)^2.5 + F33/(1+$L$37)^3.5 + G33/(1+$L$37)^4.5)+(Q$35*(G23+G28))/(1+$L$37)^5+Hipotesis!$C$15+Hipotesis!$C$16-Hipotesis!$C$14)/Hipotesis!$C$8 -> 111.21961
B38: Período (años desde valoración) | C38: 0.5 | D38: 1.5 | E38: 2.5 | F38: 3.5 | G38: 4.5 | H38: TV at end FY30 | L38: 0.0912 | M38: =((C33/(1+$L$38)^0.5 + D33/(1+$L$38)^1.5 + E33/(1+$L$38)^2.5 + F33/(1+$L$38)^3.5 + G33/(1+$L$38)^4.5)+(M$35*(G23+G28))/(1+$L$38)^5+Hipotesis!$C$15+Hipotesis!$C$16-Hipotesis!$C$14)/Hipotesis!$C$8 -> 76.928495 | N38: =((C33/(1+$L$38)^0.5 + D33/(1+$L$38)^1.5 + E33/(1+$L$38)^2.5 + F33/(1+$L$38)^3.5 + G33/(1+$L$38)^4.5)+(N$35*(G23+G28))/(1+$L$38)^5+Hipotesis!$C$15+Hipotesis!$C$16-Hipotesis!$C$14)/Hipotesis!$C$8 -> 84.765974 | O38: =((C33/(1+$L$38)^0.5 + D33/(1+$L$38)^1.5 + E33/(1+$L$38)^2.5 + F33/(1+$L$38)^3.5 + G33/(1+$L$38)^4.5)+(O$35*(G23+G28))/(1+$L$38)^5+Hipotesis!$C$15+Hipotesis!$C$16-Hipotesis!$C$14)/Hipotesis!$C$8 -> 92.603454 | P38: =((C33/(1+$L$38)^0.5 + D33/(1+$L$38)^1.5 + E33/(1+$L$38)^2.5 + F33/(1+$L$38)^3.5 + G33/(1+$L$38)^4.5)+(P$35*(G23+G28))/(1+$L$38)^5+Hipotesis!$C$15+Hipotesis!$C$16-Hipotesis!$C$14)/Hipotesis!$C$8 -> 100.44093 | Q38: =((C33/(1+$L$38)^0.5 + D33/(1+$L$38)^1.5 + E33/(1+$L$38)^2.5 + F33/(1+$L$38)^3.5 + G33/(1+$L$38)^4.5)+(Q$35*(G23+G28))/(1+$L$38)^5+Hipotesis!$C$15+Hipotesis!$C$16-Hipotesis!$C$14)/Hipotesis!$C$8 -> 108.27841
B39: Discount factor (mid-year) | C39: =1/(1+Hipotesis!$C$25)^C38 -> 0.95507829 | D39: =1/(1+Hipotesis!$C$25)^D38 -> 0.87119811 | E39: =1/(1+Hipotesis!$C$25)^E38 -> 0.79468474 | F39: =1/(1+Hipotesis!$C$25)^F38 -> 0.72489119 | G39: =1/(1+Hipotesis!$C$25)^G38 -> 0.66122729 | H39: — | L39: 0.1 | M39: =((C33/(1+$L$39)^0.5 + D33/(1+$L$39)^1.5 + E33/(1+$L$39)^2.5 + F33/(1+$L$39)^3.5 + G33/(1+$L$39)^4.5)+(M$35*(G23+G28))/(1+$L$39)^5+Hipotesis!$C$15+Hipotesis!$C$16-Hipotesis!$C$14)/Hipotesis!$C$8 -> 74.152787 | N39: =((C33/(1+$L$39)^0.5 + D33/(1+$L$39)^1.5 + E33/(1+$L$39)^2.5 + F33/(1+$L$39)^3.5 + G33/(1+$L$39)^4.5)+(N$35*(G23+G28))/(1+$L$39)^5+Hipotesis!$C$15+Hipotesis!$C$16-Hipotesis!$C$14)/Hipotesis!$C$8 -> 81.681743 | O39: =((C33/(1+$L$39)^0.5 + D33/(1+$L$39)^1.5 + E33/(1+$L$39)^2.5 + F33/(1+$L$39)^3.5 + G33/(1+$L$39)^4.5)+(O$35*(G23+G28))/(1+$L$39)^5+Hipotesis!$C$15+Hipotesis!$C$16-Hipotesis!$C$14)/Hipotesis!$C$8 -> 89.2107 | P39: =((C33/(1+$L$39)^0.5 + D33/(1+$L$39)^1.5 + E33/(1+$L$39)^2.5 + F33/(1+$L$39)^3.5 + G33/(1+$L$39)^4.5)+(P$35*(G23+G28))/(1+$L$39)^5+Hipotesis!$C$15+Hipotesis!$C$16-Hipotesis!$C$14)/Hipotesis!$C$8 -> 96.739656 | Q39: =((C33/(1+$L$39)^0.5 + D33/(1+$L$39)^1.5 + E33/(1+$L$39)^2.5 + F33/(1+$L$39)^3.5 + G33/(1+$L$39)^4.5)+(Q$35*(G23+G28))/(1+$L$39)^5+Hipotesis!$C$15+Hipotesis!$C$16-Hipotesis!$C$14)/Hipotesis!$C$8 -> 104.26861
B40: PV of FCFF (explicit period) | C40: =C33*C39 -> 12114.453 | D40: =D33*D39 -> 12588.753 | E40: =E33*E39 -> 13019.332 | F40: =F33*F39 -> 12945.195 | G40: =G33*G39 -> 12923.221 | H40: (see TV below) | L40: 0.11 | M40: =((C33/(1+$L$40)^0.5 + D33/(1+$L$40)^1.5 + E33/(1+$L$40)^2.5 + F33/(1+$L$40)^3.5 + G33/(1+$L$40)^4.5)+(M$35*(G23+G28))/(1+$L$40)^5+Hipotesis!$C$15+Hipotesis!$C$16-Hipotesis!$C$14)/Hipotesis!$C$8 -> 71.151257 | N40: =((C33/(1+$L$40)^0.5 + D33/(1+$L$40)^1.5 + E33/(1+$L$40)^2.5 + F33/(1+$L$40)^3.5 + G33/(1+$L$40)^4.5)+(N$35*(G23+G28))/(1+$L$40)^5+Hipotesis!$C$15+Hipotesis!$C$16-Hipotesis!$C$14)/Hipotesis!$C$8 -> 78.347127 | O40: =((C33/(1+$L$40)^0.5 + D33/(1+$L$40)^1.5 + E33/(1+$L$40)^2.5 + F33/(1+$L$40)^3.5 + G33/(1+$L$40)^4.5)+(O$35*(G23+G28))/(1+$L$40)^5+Hipotesis!$C$15+Hipotesis!$C$16-Hipotesis!$C$14)/Hipotesis!$C$8 -> 85.542997 | P40: =((C33/(1+$L$40)^0.5 + D33/(1+$L$40)^1.5 + E33/(1+$L$40)^2.5 + F33/(1+$L$40)^3.5 + G33/(1+$L$40)^4.5)+(P$35*(G23+G28))/(1+$L$40)^5+Hipotesis!$C$15+Hipotesis!$C$16-Hipotesis!$C$14)/Hipotesis!$C$8 -> 92.738867 | Q40: =((C33/(1+$L$40)^0.5 + D33/(1+$L$40)^1.5 + E33/(1+$L$40)^2.5 + F33/(1+$L$40)^3.5 + G33/(1+$L$40)^4.5)+(Q$35*(G23+G28))/(1+$L$40)^5+Hipotesis!$C$15+Hipotesis!$C$16-Hipotesis!$C$14)/Hipotesis!$C$8 -> 99.934736
B41: Σ PV of explicit FCFF | C41: =SUM(C40:G40) -> 63590.954
B43: Cálculos de Valor Terminal (4 métodos)
B44: Method 1: Gordon Growth perpetuity | C44: =G33*(1+Hipotesis!$C$47)/(Hipotesis!$C$25-Hipotesis!$C$47) -> 303714.45 | D44: TV nominal | G44: =C44*G39 -> 200824.29 | H44: (PV)
B45: Method 2: Exit EV/EBITDA × FY30 EBITDA | C45: =Hipotesis!$C$50*(G23+G28) -> 459739.2 | D45: EV exit | G45: =C45*G39 -> 303992.11
B46: Method 3: Exit EV/EBIT × FY30 EBIT | C46: =Hipotesis!$C$51*G23 -> 549291.66 | D46: EV exit | G46: =C46*G39 -> 363206.64
B47: Method 4: H-Model (fade gST → gLT) | C47: =(G33*(1+Hipotesis!$C$47)+G33*Hipotesis!$C$48*(G14-Hipotesis!$C$47))/(Hipotesis!$C$25-Hipotesis!$C$47) -> 352165.08 | D47: EV total | G47: =C47*G39 -> 232861.17
B48: Method 5: Exit EV/Revenue × FY30 Revenue | C48: =Hipotesis!$C$52*G13 -> 394119.12 | D48: Cross-check | G48: =C48*G39 -> 260602.32
B50: F. PUENTE EV → EQUITY → PRICE TARGET (8 metodologías)
B51: Método | C51: EV ($mm) | D51: (+) Cash | E51: (−) Debt | F51: (+) Eq.inv | G51: Equity ($mm) | H51: Shares (M) | I51: Price ($)
B52: 1. DCF Gordon Growth | C52: =C41+G44 -> 264415.24 | D52: =Hipotesis!$C$15 -> 9062 | E52: =-Hipotesis!$C$14 -> -13464 | F52: =Hipotesis!$C$16 -> 0 | G52: =C52+D52+E52+F52 -> 260013.24 | H52: =Hipotesis!$C$8 -> 4212.8 | I52: =G52/H52 -> 61.719816 | J52: =I52 -> 61.719816
B53: 2. DCF H-Model (fade) | C53: =G47 -> 232861.17 | D53: =Hipotesis!$C$15 -> 9062 | E53: =-Hipotesis!$C$14 -> -13464 | F53: =Hipotesis!$C$16 -> 0 | G53: =C53+D53+E53+F53 -> 228459.17 | H53: =Hipotesis!$C$8 -> 4212.8 | I53: =G53/H53 -> 54.229768 | J53: =I53 -> 54.229768
B54: 3. DCF Exit EV/EBITDA | C54: =C41+G45 -> 367583.06 | D54: =Hipotesis!$C$15 -> 9062 | E54: =-Hipotesis!$C$14 -> -13464 | F54: =Hipotesis!$C$16 -> 0 | G54: =C54+D54+E54+F54 -> 363181.06 | H54: =Hipotesis!$C$8 -> 4212.8 | I54: =G54/H54 -> 86.20895 | J54: =I54 -> 86.20895
B55: 4. DCF Exit EV/EBIT | C55: =C41+G46 -> 426797.59 | D55: =Hipotesis!$C$15 -> 9062 | E55: =-Hipotesis!$C$14 -> -13464 | F55: =Hipotesis!$C$16 -> 0 | G55: =C55+D55+E55+F55 -> 422395.59 | H55: =Hipotesis!$C$8 -> 4212.8 | I55: =G55/H55 -> 100.26481 | J55: =I55 -> 100.26481
B56: 5. DCF Exit EV/Revenue | C56: =C41+G48 -> 324193.27 | D56: =Hipotesis!$C$15 -> 9062 | E56: =-Hipotesis!$C$14 -> -13464 | F56: =Hipotesis!$C$16 -> 0 | G56: =C56+D56+E56+F56 -> 319791.27 | H56: =Hipotesis!$C$8 -> 4212.8 | I56: =G56/H56 -> 75.909436 | J56: =I56 -> 75.909436
B57: 6. NTM P/E × FY27E EPS | C57: — | D57: — | E57: — | F57: — | G57: =Hipotesis!$C$53*D27 -> 364086.84 | H57: =Hipotesis!$C$8 -> 4212.8 | I57: =G57/H57 -> 86.423956 | J57: =I57 -> 86.423956
B58: 7. NTM EV/EBITDA × FY27E EBITDA | C58: =Hipotesis!$C$50*(D23+D28) -> 335853.19 | D58: =Hipotesis!$C$15 -> 9062 | E58: =-Hipotesis!$C$14 -> -13464 | F58: =Hipotesis!$C$16 -> 0 | G58: =C58+D58+E58+F58 -> 331451.19 | H58: =Hipotesis!$C$8 -> 4212.8 | I58: =G58/H58 -> 78.677173 | J58: =I58 -> 78.677173
B59: 8. NTM EV/Revenue × FY27E Revenue | C59: =Hipotesis!$C$52*D13 -> 312241.05 | D59: =Hipotesis!$C$15 -> 9062 | E59: =-Hipotesis!$C$14 -> -13464 | F59: =Hipotesis!$C$16 -> 0 | G59: =C59+D59+E59+F59 -> 307839.05 | H59: =Hipotesis!$C$8 -> 4212.8 | I59: =G59/H59 -> 73.072315 | J59: =I59 -> 73.072315
B61: G. ESTADISTICAS DE LAS 8 VALORACIONES
B62: Promedio | J62: =AVERAGE(J52:J59) -> 77.063278
B63: Mediana | J63: =MEDIAN(J52:J59) -> 77.293304
B64: Mínimo | J64: =MIN(J52:J59) -> 54.229768
B65: Máximo | J65: =MAX(J52:J59) -> 100.26481
B66: Spot price | J66: =Hipotesis!$C$6 -> 87.02
B67: Upside (Mediana vs Spot) | J67: =J63/J66-1 -> -0.1117754

Sheet DuPont_WC
B2: NETFLIX, INC. (NFLX) — DuPont Decomposition + Working Capital Analysis
B3: Periodo FY21-FY25 + Q1 2026. Datos en $mm except ratios. NFLX fiscal year = calendar year.
B5: 1. INPUTS HISTORICOS (Source: NFLX 10-K FY2025 + 10-Q Q1 2026, SEC EDGAR)
C6: FY2021 | D6: FY2022 | E6: FY2023 | F6: FY2024 | G6: FY2025 | H6: Q1 2026
B7: Revenue ($mm) | C7: 29698 | D7: 31616 | E7: 33723 | F7: 39001 | G7: 45183 | H7: 12250 | I7: 10-K Income Statement + 10-Q
B8: Operating Income ($mm) | C8: 6195 | D8: 5633 | E8: 6954 | F8: 10418 | G8: 13327 | H8: 3957
B9: Net Income ($mm) | C9: 5116 | D9: 4492 | E9: 5408 | F9: 8712 | G9: 10981 | H9: 5283
B10: Total Assets ($mm) | C10: 44585 | D10: 48595 | E10: 48732 | F10: 53630 | G10: 55597 | H10: 60000 | I10: Balance Sheet; Q1 2026 estimate (no full BS disclosure in 10-Q yet released)
B11: Stockholders' Equity ($mm) | C11: 15849 | D11: 20777 | E11: 20588 | F11: 24744 | G11: 26615 | H11: 30700
B12: Total Debt (incl. current portion) ($mm) | C12: 14693 | D12: 14353 | E12: 14143 | F12: 13798 | G12: 13464 | H12: 13400
B13: Cash + STI ($mm) | C13: 6028 | D13: 6058 | E13: 7138 | F13: 9584 | G13: 9062 | H13: 12267
B14: Operating Cash Flow ($mm) | C14: 393 | D14: 2026 | E14: 7274 | F14: 7361 | G14: 10149 | H14: 5290 | I14: Cash Flow Statement
B15: Capex ($mm) | C15: 525 | D15: 408 | E15: 349 | F15: 440 | G15: 688 | H15: 196
B16: Free Cash Flow ($mm) | C16: -132 | D16: 1619 | E16: 6925 | F16: 6921 | G16: 9461 | H16: 5094
B17: D&A ($mm) | C17: 208 | D17: 336 | E17: 297 | F17: 320 | G17: 350 | H17: 99
B18: Effective Tax Rate | C18: 0.226 | D18: 0.149 | E18: 0.229 | F18: 0.228 | G18: 0.209 | H18: 0.193 | I18: 10-K Note Income Taxes. FY22 menor por FX y créditos. Promedio FY23-25 ≈ 22%
B20: 2. DUPONT DECOMPOSITION (ROE = Tax Burden × Interest Burden × OpMargin × Asset Turnover × Equity Multiplier)
C21: FY2021 | D21: FY2022 | E21: FY2023 | F21: FY2024 | G21: FY2025 | H21: 9M parcial
B22: Tax Burden = 1 − effective tax rate | C22: =1-C18 -> 0.774 | D22: =1-D18 -> 0.851 | E22: =1-E18 -> 0.771 | F22: =1-F18 -> 0.772 | G22: =1-G18 -> 0.791 | H22: =1-H18 -> 0.807 | I22: Cuanto retiene la empresa del pretax income
B23: Interest Burden = EBT / EBIT (proxy: (NI/(1-T)) / OI) | C23: =(C9/(1-C18))/C8 -> 1.0669603 | D23: =(D9/(1-D18))/D8 -> 0.93706655 | E23: =(E9/(1-E18))/E8 -> 1.0086665 | F23: =(F9/(1-F18))/F8 -> 1.0832189 | G23: =(G9/(1-G18))/G8 -> 1.0416768 | H23: =(H9/(1-H18))/H8 -> 1.6544019 | I23: >1 indica non-op income positivo (intereses, equity inv gains)
B24: Operating Margin = EBIT / Revenue | C24: =C8/C7 -> 0.20859991 | D24: =D8/D7 -> 0.17816928 | E24: =E8/E7 -> 0.20620941 | F24: =F8/F7 -> 0.26712136 | G24: =G8/G7 -> 0.29495607 | H24: =H8/H7 -> 0.32302041 | I24: Core profitability — clave del bull case
B25: Asset Turnover = Revenue / Total Assets | C25: =C7/C10 -> 0.66609846 | D25: =D7/D10 -> 0.65060191 | E25: =E7/E10 -> 0.69200936 | F25: =F7/F10 -> 0.72722357 | G25: =G7/G10 -> 0.81268773 | H25: =H7/H10 -> 0.20416667 | I25: Cuán eficientemente generan revenue. Cae con $200B+ inversión capex
B26: Equity Multiplier = Total Assets / Equity | C26: =C10/C11 -> 2.8131112 | D26: =D10/D11 -> 2.3388843 | E26: =E10/E11 -> 2.3670099 | F26: =F10/F11 -> 2.1673941 | G26: =G10/G11 -> 2.0889348 | H26: =H10/H11 -> 1.9543974 | I26: Leverage — [EMPRESA] está sobrecapitalizada, declining
B28: ROE (DuPont) = product of 5 factors | C28: =C22*C23*C24*C25*C26 -> 0.32279639 | D28: =D22*D23*D24*D25*D26 -> 0.21620061 | E28: =E22*E23*E24*E25*E26 -> 0.26267729 | F28: =F22*F23*F24*F25*F26 -> 0.35208535 | G28: =G22*G23*G24*G25*G26 -> 0.41258689 | H28: =H22*H23*H24*H25*H26 -> 0.17208469 | I28: Cross-check vs NI/avg Equity ▼
B29: ROE cross-check = NI / period-end Equity | C29: =C9/C11 -> 0.32279639 | D29: =D9/D11 -> 0.21620061 | E29: =E9/E11 -> 0.26267729 | F29: =F9/F11 -> 0.35208535 | G29: =G9/G11 -> 0.41258689 | H29: =H9/H11 -> 0.17208469 | I29: 9M parcial anualizado: ×4/3
B31: 3. ROS2 OPERATIVO (NOPAT / Invested Capital) — métrica relevante para valoración DCF
C32: FY2021 | D32: FY2022 | E32: FY2023 | F32: FY2024 | G32: FY2025 | H32: 9M parcial
B33: NOPAT = EBIT × (1 − effective tax rate) | C33: =C8*(1-C18) -> 4794.93 | D33: =D8*(1-D18) -> 4793.683 | E33: =E8*(1-E18) -> 5361.534 | F33: =F8*(1-F18) -> 8042.696 | G33: =G8*(1-G18) -> 10541.657 | H33: =H8*(1-H18) -> 3193.299 | I33: Excluye non-op income (más conservador que NI)
B34: Invested Capital = Equity + Debt − Excess Cash/STI | C34: =C11+C12-C13 -> 24514 | D34: =D11+D12-D13 -> 29072 | E34: =E11+E12-E13 -> 27593 | F34: =F11+F12-F13 -> 28958 | G34: =G11+G12-G13 -> 31017 | H34: =H11+H12-H13 -> 31833 | I34: Capital efectivamente desplegado en operaciones
B35: ROS2 operativo = NOPAT / S2 | C35: =C33/C34 -> 0.19559966 | D35: =D33/D34 -> 0.16489003 | E35: =E33/E34 -> 0.19430776 | F35: =F33/F34 -> 0.27773658 | G35: =G33/G34 -> 0.33986707 | H35: =H33/H34 -> 0.10031411 | I35: Si baja por capex inversión, valor terminal afectado
B37: ROS2 − WACC spread (WACC=9.12% from Hipotesis!$C$25) | C37: =C35-Hipotesis!$C$25 -> 0.099318245 | D37: =D35-Hipotesis!$C$25 -> 0.068608619 | E37: =E35-Hipotesis!$C$25 -> 0.098026347 | F37: =F35-Hipotesis!$C$25 -> 0.18145517 | G37: =G35-Hipotesis!$C$25 -> 0.24358566 | H37: =H35-Hipotesis!$C$25 -> 0.0040326956 | I37: Spread positivo = creación de valor ([EMPRESA] crónicamente >+20pp)
B39: 4. WORKING CAPITAL DYNAMICS — DSO, DPO, CCC + Backlog visibility
C40: FY2021 | D40: FY2022 | E40: FY2023 | F40: FY2024 | G40: FY2025 | H40: 9M parcial
B41: Accounts Receivable (net, $mm) | C41: 0 | D41: 0 | E41: 0 | F41: 0 | G41: 0 | H41: 0 | I41: NFLX subscription model: cobros prepaid. AR tradicional mínimo
B42: Inventory ($mm) | C42: 0 | D42: 0 | E42: 0 | F42: 0 | G42: 0 | H42: 0 | I42: NFLX digital streaming: inventory mínimo
B43: Accounts Payable ($mm) | C43: 837 | D43: 871 | E43: 747 | F43: 825 | G43: 850 | H43: 850 | I43: AP modesto (NFLX paga rápido a content suppliers)
B44: Unearned Revenue (current, $mm) | C44: 1209 | D44: 1503 | E44: 1442 | F44: 1564 | G44: 1530 | H44: 1500 | I44: Deferred revenue: prepayments ~1 mes promedio. Refleja modelo subscription
B46: DSO = (AR / Revenue) × 365 (annualized for 9M) | C46: =C41/C7*365 -> 0 | D46: =D41/D7*365 -> 0 | E46: =E41/E7*365 -> 0 | F46: =F41/F7*365 -> 0 | G46: =G41/G7*365 -> 0 | H46: =H41/(H7*4/3)*365 -> 0 | I46: Estable ~78-85 días. Sin signos de stretch en collections
B47: DPO = (AP / Revenue) × 365 (proxy; ideal usa COGS) | C47: =C43/C7*365 -> 10.287056 | D47: =D43/D7*365 -> 10.05551 | E47: =E43/E7*365 -> 8.0851348 | F47: =F43/F7*365 -> 7.7209559 | G47: =G43/G7*365 -> 6.8665206 | H47: =H43/(H7*4/3)*365 -> 18.994898 | I47: 9M parcial: AP +$15.8B vs Jun-25 por componentes operativos (en realidad oculta capex)
B48: DIO = (Inventory / Revenue) × 365 | C48: =C42/C7*365 -> 0 | D48: =D42/D7*365 -> 0 | E48: =E42/E7*365 -> 0 | F48: =F42/F7*365 -> 0 | G48: =G42/G7*365 -> 0 | H48: =H42/(H7*4/3)*365 -> 0 | I48: [EMPRESA] software-heavy → inventory minimal
B49: Cash Conversion Cycle = DSO + DIO − DPO | C49: =C46+C48-C47 -> -10.287056 | D49: =D46+D48-D47 -> -10.05551 | E49: =E46+E48-E47 -> -8.0851348 | F49: =F46+F48-F47 -> -7.7209559 | G49: =G46+G48-G47 -> -6.8665206 | H49: =H46+H48-H47 -> -18.994898 | I49: CCC bajo o negativo = ventaja competitiva (clientes pagan rápido, proveedores tarde)
B51: Content obligations (no recon. en BS) ($mm) — proxy de "Backlog" | C51: — | D51: — | E51: — | F51: — | G51: 18400 | H51: n/d | I51: Source: 10-K FY2025 — obligaciones de contenido NO reconocidas en BS = $18.4bn. Es compromiso operativo, no deuda
B52: Content obligations / Revenue (años) | C52: n/d | D52: n/d | E52: n/d | F52: n/d | G52: =G51/G7 -> 0.40723281 | H52: n/d | I52: FY25: 0.41× revenue = ~5 meses de contenido ya comprometido. Visibility moderada
B55: 5. SÍNTESIS — Lectura de DuPont y WC
B56: ▸ ROE GAAP sube de ~32% (FY21) a ~41% (FY25): mejora driven por margin expansion + asset productivity con equity creciendo más lento que earnings.
B57: ▸ Operating margin sube +870 bp (FY21 20.9% → FY25 29.5%): la mejor expansión de la industria streaming. Q1 2026 ya 32.3%. Driver: scale + paid sharing + pricing + content discipline.
B58: ▸ Asset turnover sube 0.67→0.81 (FY21→FY25): mejor utilización de activos. NFLX no es asset-heavy en sentido clásico (PP&E ~$1.8bn vs $284bn de MSFT).
B59: ▸ Equity multiplier baja de 2.81→2.09 (FY21→FY25): balance se desapalanca con buybacks contenidos por debt repayment. Q1 2026 net debt ~$1.1bn (vs $8.7bn FY21).
B60: ▸ ROS2 operativo (NOPAT/IC) FY25 = 34.0%; FY21 = 19.6%. Mejora +1440bp. Spread vs WACC 9.6% = +24.4pp en FY25 (creación de valor sostenida).
B61: ▸ AR / DSO no aplica para NFLX (subscription model con cobros prepaid). Deferred revenue stable ~$1.5bn = 12 días de revenue.
B62: ▸ Content obligations no en BS = $18.4bn (FY25). Si capitalizáramos estas obligaciones como deuda económica, debt/equity ajustado ~1.2x (vs 0.5x reported).
B63: ▸ FCF/NI: FY21 -2.6% → FY22 36% → FY23 128% (sobre-conversión post-content peak) → FY24 80% → FY25 86%. La conversión es ahora estable y de alta calidad.
B64: ▸ Net debt cae de $8.7bn (FY21) a $1.1bn (Q1 2026): NFLX virtualmente sin apalancamiento neto. Esto soporta buybacks pero presiona ROE GAAP.
B65: ▸ Conclusión: la calidad operativa de NFLX ha EXPANDIDO significativamente desde el ciclo content-peak 2021-22. ROIC > WACC en spread amplio sostiene creación de valor mientras el modelo siga escalando rentablemente.

Sheet Reverse_DCF
B2: NETFLIX, INC. (NFLX) — REVERSE DCF: ¿Qué pricea el mercado a $87?
B3: Dado spot=$87, ¿qué suposiciones tendrían que ser ciertas? Closed-form solutions — no goal seek manual.
B5: INPUTS COMUNES (link a Modelo/Hipotesis)
B6: Spot price ($) | C6: =Hipotesis!$C$6 -> 87.02
B7: Shares diluidas (M) | C7: =Hipotesis!$C$8 -> 4212.8
B8: Cash + STI ($mm) | C8: =Hipotesis!$C$15 -> 9062
B9: Equity & other investments ($mm) | C9: =Hipotesis!$C$16 -> 0
B10: Total Debt ($mm) | C10: =Hipotesis!$C$14 -> 13464
B11: WACC (caso base) | C11: =Hipotesis!$C$25 -> 0.096281412
B12: Terminal g (caso base) | C12: =Hipotesis!$C$47 -> 0.03
B13: Σ PV explicit FCFF FY26-FY30 (Modelo) | C13: =Modelo!$C$41 -> 63590.954
B14: FY30E FCFF (Modelo) | C14: =Modelo!$G$33 -> 19544.294
B15: FY30E EBIT (Modelo) | C15: =Modelo!$G$23 -> 24967.803
B16: FY30E D&A (Modelo) | C16: =Modelo!$G$28 -> 573.26417
B17: FY30E Revenue (Modelo) | C17: =Modelo!$G$13 -> 71658.021
B18: FY30E NOPAT (Modelo) | C18: =Modelo!$G$27 -> 19974.242
B19: Effective tax rate | C19: =Hipotesis!$C$13 -> 0.2
B21: CÁLCULOS INTERMEDIOS (Δ implícita vs caso base)
B22: Equity target = Spot × Shares ($mm) | C22: =C6*C7 -> 366597.86
B23: (+) Debt | C23: =C10 -> 13464
B24: (−) Cash + STI | C24: =-C8 -> -9062
B25: (−) Equity & other investments | C25: =-C9 -> 0
B26: Enterprise Value target ($mm) | C26: =C22+C10-C8-C9 -> 370999.86
B27: (−) Σ PV explicit FCFF | C27: =-C13 -> -63590.954
B28: PV(TV) implícito ($mm) | C28: =C26-C13 -> 307408.9
B29: TV nominal implícito (×(1+WACC)^5) | C29: =C28*(1+C11)^5 -> 486773.24
B31: A. ¿Qué g_terminal implica el spot? (manteniendo WACC, FCFF base, bridge)
B32: Fórmula: g = (TV·WACC − FCFF_30) / (TV + FCFF_30)
B33: g_terminal implícito (Gordon) | C33: =(C29*C11-C14)/(C29+C14) -> 0.053964003 | D33: vs base 3.0%: | E33: =C33-C12 -> 0.023964003 | G33: Si >0 ↑ → mercado más optimista que base. Si <0 → más pesimista.
B35: B. ¿Qué WACC implica el spot? (manteniendo g_terminal=3%, FCFF base, bridge)
B36: Aproximación: como WACC afecta TV y descuento, no hay fórmula cerrada. Tabla de precios implícitos:
B37: WACC → | C37: 0.075 | D37: 0.085 | E37: 0.0912 | F37: 0.095 | G37: 0.105 | H37: 0.115
B38: Precio implícito ($) | C38: =((Modelo!C33/(1+C$37)^0.5 + Modelo!D33/(1+C$37)^1.5 + Modelo!E33/(1+C$37)^2.5 + Modelo!F33/(1+C$37)^3.5 + Modelo!G33/(1+C$37)^4.5)+(Modelo!G33*(1+C12)/(C$37-C12))/(1+C$37)^5+C8+C9-C10)/C7 -> 88.789548 | D38: =((Modelo!C33/(1+D$37)^0.5 + Modelo!D33/(1+D$37)^1.5 + Modelo!E33/(1+D$37)^2.5 + Modelo!F33/(1+D$37)^3.5 + Modelo!G33/(1+D$37)^4.5)+(Modelo!G33*(1+C12)/(D$37-C12))/(1+D$37)^5+C8+C9-C10)/C7 -> 72.2315 | E38: =((Modelo!C33/(1+E$37)^0.5 + Modelo!D33/(1+E$37)^1.5 + Modelo!E33/(1+E$37)^2.5 + Modelo!F33/(1+E$37)^3.5 + Modelo!G33/(1+E$37)^4.5)+(Modelo!G33*(1+C12)/(E$37-C12))/(1+E$37)^5+C8+C9-C10)/C7 -> 64.696321 | F38: =((Modelo!C33/(1+F$37)^0.5 + Modelo!D33/(1+F$37)^1.5 + Modelo!E33/(1+F$37)^2.5 + Modelo!F33/(1+F$37)^3.5 + Modelo!G33/(1+F$37)^4.5)+(Modelo!G33*(1+C12)/(F$37-C12))/(1+F$37)^5+C8+C9-C10)/C7 -> 60.793005 | G38: =((Modelo!C33/(1+G$37)^0.5 + Modelo!D33/(1+G$37)^1.5 + Modelo!E33/(1+G$37)^2.5 + Modelo!F33/(1+G$37)^3.5 + Modelo!G33/(1+G$37)^4.5)+(Modelo!G33*(1+C12)/(G$37-C12))/(1+G$37)^5+C8+C9-C10)/C7 -> 52.424602 | H38: =((Modelo!C33/(1+H$37)^0.5 + Modelo!D33/(1+H$37)^1.5 + Modelo!E33/(1+H$37)^2.5 + Modelo!F33/(1+H$37)^3.5 + Modelo!G33/(1+H$37)^4.5)+(Modelo!G33*(1+C12)/(H$37-C12))/(1+H$37)^5+C8+C9-C10)/C7 -> 46.041401
B39: WACC implícito (interpolado vs spot) | C39: =SLOPE(C37:H37,C38:H38)*C6+INTERCEPT(C37:H37,C38:H38) -> 0.073385314 | D39: vs base 9.12%: | E39: =C39-C11 -> -0.022896098 | G39: (FORECAST.LINEAR sobre la tabla — aproximación lineal, válida en el entorno del spot)
B41: C. ¿Qué margen EBIT FY30E implica el spot? (manteniendo Rev FY30E, Capex/Rev, g, WACC)
B42: Aprox: terminal margin solo afecta TV (PV explícito a caso base).
B43: FCFF terminal implícito ($mm) | C43: =C29*(C11-C12)/(1+C12) -> 31324.289 | D43: vs base: | E43: =C43/C14-1 -> 0.6027332
B44: NOPAT terminal implícito = FCFF − D&A − Capex_signed − ΔWC_signed | C44: =C43-C16-Modelo!G30-Modelo!G32 -> 31754.237
B45: EBIT terminal implícito = NOPAT / (1−T) | C45: =C44/(1-C19) -> 39692.796
B46: EBIT margin FY30E implícito | C46: =C45/C17 -> 0.55391979 | D46: vs base 45.8%: | E46: =C46-C15/C17 -> 0.20548982 | G46: Si <base, el mercado descuenta margen presionado (capex inversión persistente).
B48: D. ¿Qué Capex/Rev terminal implica el spot? (manteniendo EBIT margin base, g, WACC)
B49: Capex terminal implícito ($mm) | C49: =C18+C16-C43-Modelo!G32 -> -10776.783
B50: Capex/Rev terminal implícito | C50: =C49/C17 -> -0.15039185 | D50: vs base 1.3%: | E50: =C50-Hipotesis!$H$39 -> -0.16339185 | G50: Si >base, el mercado descuenta capex inversión sostenido (overinvest).
B52: E. ¿Qué Revenue CAGR FY25→FY30 implica el spot? (escala uniforme, margenes y Capex/Rev fijos)
B53: Base EV = PV_explicit + PV(TV_base) (from Modelo) | C53: =C13 + C14*(1+C12)/(C11-C12)/(1+C11)^5 -> 255393.87
B54: Scaling factor k = Target EV / Base EV | C54: =C26/C53 -> 1.4526576
B55: Implied FY30E Revenue = Base × k | C55: =C17*C54 -> 104094.57
B56: Revenue CAGR FY25→FY30 implícito | C56: =(C55/Historico!G6)^(1/5)-1 -> 0.18165475 | D56: vs base ~9.7%: | E56: =C56-((C17/Historico!G6)^(1/5)-1) -> 0.085030234 | G56: Es la 'tasa de crecimiento' que necesita [EMPRESA] para que $408 sea justo, manteniendo todos los ratios.
B58: F. SÍNTESIS — qué pricea el mercado vs caso base
B59: Variable | C59: Base case | D59: Implícito (ceteris paribus) | E59: Δ | F59: Lectura
B60: Terminal g (perpetuidad) | C60: =C12 -> 0.03 | D60: =C33 -> 0.053964003 | E60: =D60-C60 -> 0.023964003 | F60: Mercado pricea g terminal 5.4% (vs base 3%) — alto, requiere growth premium permanente
B61: WACC | C61: =C11 -> 0.096281412 | D61: =C39 -> 0.073385314 | E61: =D61-C61 -> -0.022896098 | F61: Mercado pricea WACC 7.3% (vs base 9.6%) — muy bajo, asume risk premium BBB-tech mínimo
B62: EBIT margin FY30E | C62: =C15/C17 -> 0.34842998 | D62: =C45/C17 -> 0.55391979 | E62: =D62-C62 -> 0.20548982 | F62: Mercado pricea EBIT margin FY30 55% (vs base 35%) — IRREAL aislado; refleja combinación con otros levers
B63: Capex/Rev terminal | C63: =Hipotesis!$H$39 -> 0.013 | D63: =C49/C17 -> -0.15039185 | E63: =D63-C63 -> -0.16339185 | F63: Mercado pricea Capex/Rev -15% (vs base 1.3%) — ABSURDO aislado; el spot NO se justifica con 1 solo lever
B64: Revenue CAGR FY25→FY30 | C64: =(C17/Historico!G6)^(1/5)-1 -> 0.096624513 | D64: =(C55/Historico!G6)^(1/5)-1 -> 0.18165475 | E64: =D64-C64 -> 0.085030234 | F64: Mercado pricea CAGR FY25-FY30 18.2% (vs base 9.7%) — agresivo; superior al guide implícito FY26 +13%
B66: G. LECTURA INTEGRAL
B67: ▸ El spot $87 implica una combinación de assumptions más optimistas que mi base. Ningún lever aislado justifica el precio: g implícito 5.4% (alto); WACC 7.3% (muy bajo); margin 55% (irreal); CAGR 18% (agresivo).
B68: ▸ Lectura correcta: el mercado pricea un MIX de mejores assumptions — quizá margin terminal 38-40% + CAGR 12-14% + WACC 8.5%. No un único lever extremo.
B69: ▸ La mediana de mis 8 métodos es $77 (–11% vs spot). Esto significa que CON MIS HIPÓTESIS BASE el spot está caro. Para llegar a fair value $87 necesitaría margin terminal ~38% o CAGR ~12%.
B70: ▸ El reverse-DCF expone que NFLX a $87 requiere creer en EXPANSIÓN MATERIAL de margin (>34%) Y crecimiento sostenido (>10% CAGR) Y normalización de risk premium. Es la apuesta agregada por la "high-quality compounder" thesis.
B71: ▸ Test crítico para la tesis bullish: ¿qué probabilidad asignar a margen FY30 >36%? El historial dice que NFLX ya ha hecho +870bp en 4 años (FY21-FY25), y +200bp más en Q1 2026 (32.3%). Posible, pero no consensual.

Sheet Conclusiones
B2: NETFLIX, INC. (NFLX) — CONCLUSIONES Y TESIS DE INVERSION
B3: Síntesis cualitativa. Compañera de Modelo (números) + DuPont_WC (returns) + Reverse_DCF (market-implied).
B5: 1. TESIS CENTRAL
B6: Tesis | C6: Netflix es un compounder de alta calidad con economía de escala global probada (FY25 op margin 29.5% vs 17.8% FY22; FCF $9.5bn; conversión >85%). El bid fallido por WBD (feb-2026) ELIMINA el riesgo de integración/balance y refuerza la tesis standalone. Sin embargo, el precio $87 incorpora assumptions optimistas en margen terminal (>36%) y crecimiento (>11% CAGR). Mediana de 8 métodos = $77 (-11% vs spot). HOLD con sesgo a UNDERWEIGHT en niveles actuales; reevaluar BUY en caídas a $70-75 o si guidance FY26 se eleva post-Q2.
B8: 2. EL DEBATE CENTRAL — ¿Es la expansión de margen estructural o cíclica?
B9: Bear case | C9: Paid sharing fue un tailwind one-off que ya ha sido cosechado: 60M-100M cuentas convertidas en 2024-25 difícil de repetir. Pricing power se erosionará con elasticidad mayor en mercados emerging. Ad revenue $1.5bn FY25 todavía no genera margen positivo material. Competencia (YouTube +60% del watch time global TV, Amazon Prime Video subsidiado, Disney+ ROIC negativo pero contenido premium) mantiene presión sobre el content spend ($17.1bn FY25 vs $13bn FY22). Margen FY26 31.5% es CEILING, no piso. Precio bear: $55-65 (DCF Gordon/H-Model floor).
B11: Bull case | C11: La transición de Netflix a "global ad-supported entertainment platform" está EN CURSO: 250M MAUs en tier ads (vs 190M nov-2025), ad revenue duplica en FY26 a ~$3bn. Cada $1bn de ad revenue añade ~$300-500M de operating income a partir de 2027-28. Live events (NFL deportivos, KPop Demon Hunters tour, eventos box) crean nuevo inventory premium. Theatrical pipeline (Narnia 2026) demuestra opcionalidad. Engagement >2h/día por miembro es defensible. Margen terminal puede sostener 35-38%. Precio bull: $100-130 (exit multiples generosos).
B13: Mi lectura | C13: El bull case es plausible pero el mercado YA pricea ~75% de él. Mi base 35% terminal margin + 9.7% CAGR rinde $77, vs spot $87. Para que $87 sea fair value se necesita 38%+ margen Y 12%+ CAGR — agresivo pero no imposible. Mejor risk-reward: comprar en correcciones tipo Mar-Abr 2026 (low $75) cuando el mercado prediga sub-guidance. ALT: si NFL/live events demuestran ROI claro en Q3-Q4 2026, levantar target hacia $100-110.
B15: 3. ESCENARIOS DE VALORACIÓN
B16: Escenario | C16: Drivers clave | D16: Precio implícito
B17: Bear (25%) | C17: Margin terminal 30-31% (no expansion further); CAGR FY25-FY30 7-8%; ad revenue plateau $4bn; competencia eleva content spend +20% adicional | D17: $55-65 (-25% to -35%)
B18: Base (50%) | C18: Margin terminal 34-35%; CAGR FY25-FY30 9-10%; ad revenue $6bn FY30; content spend disciplinado | D18: $75-85 (-10% to -2%)
B19: Bull (25%) | C19: Margin terminal 37-38%; CAGR FY25-FY30 11-13%; ad revenue $8-10bn FY30; live sports/events scale | D19: $100-130 (+15% to +50%)
B20: Probabilistic mean | C20: 0.25×$60 + 0.50×$80 + 0.25×$115 = $83.75 | D20: $84 (-3% vs spot)
B22: 4. DRIVERS CLAVE — RANKED BY SENSITIVITY
B23: #1 — Margen operativo terminal (S1 subscription) | C23: El single driver más importante. Cada +100bp en margin terminal ≈ +$5-7 en precio. NFLX ya ha demostrado +870bp expansion (FY21→FY25). Pregunta: ¿hay más palancas? Sí: (1) ads scale; (2) content efficiency (catálogo global reusable); (3) tech leverage. Ver Tabla B (Modelo cols L-R).
B24: #2 — WACC / Risk premium | C24: Cada +100bp WACC ≈ -$10-13 precio (Tabla A en Modelo). NFLX beta 1.25 razonable dado historial volátil. Inverso: si bonos NFLX consiguen IG upgrade (BBB → A) y Fed cuts en 2026-2027, WACC podría caer a 8.5-9.0% → +$15-20 precio. Sensibilidad implícita en spot: WACC 7.3% (irreal aislado).
B25: #3 — Revenue growth FY26-FY30 | C25: Mgmt guía FY26 +12-14%. Mi base 9.7% CAGR FY25-FY30 implica fade de ~13% (FY26) a ~6% (FY30). Reverse-DCF implícito 18% — agresivo. Si paid sharing tailwind agotado y ad ramp menor que esperado, el growth se acerca a 8-9%. Si live events e international expansion funcionan, 11-12% sostenido es posible.
B26: #4 — Ad revenue scale and monetization | C26: De $1.5bn FY25 (3.3% revenue) a posible $6-10bn FY30 (12-17% revenue). Si ads margin terminal es 30% (vs 70%+ que algunos peers CTV consiguen), cada $1bn ad revenue añade ~$300M operating income. Pregunta: ¿Netflix escalará ad infrastructure interna (vs Microsoft/Xandr partner inicialmente)?
B27: #5 — Terminal g (perpetuidad) | C27: Asumo 3% (alineado con GDP nominal US). Reverse-DCF implica 5.4% — alto. Sensibilidad alta: cada +50bp en g terminal ≈ +$8-10 precio (Tabla A en Modelo). 3% es defendible si NFLX mantiene pricing power y expansion internacional (mid-tier markets aún sub-penetrados).
B28: #6 — M&A risk (mitigado post-WBD fail) | C28: El bid WBD (dic 2025-feb 2026) fue UNA SEÑAL de que mgmt estaba dispuesto a deal-make grande ($82.7bn, $42bn bridge facility). Aunque fallido, abre preguntas: ¿próximo target? Posibles: gaming asset (no probable corto plazo), regional streamer, tech/ad capability. Lectura: capital allocation discipline a observar trimestralmente.
B30: 5. RIESGOS PRINCIPALES
B31: Riesgo | C31: Magnitud / Impacto
B32: #1 Saturación de growth (paid sharing maduro + price hike fatigue) | C32: Si el growth FY26 cae a <10% (vs guide 12-14%) y mgmt revisa guidance a la baja en Q2 2026: -$15-20 precio. Probabilidad: 25-30%. Impacto: alto.
B33: #2 Competencia YouTube + plataformas verticales (TikTok) | C33: YouTube ya tiene mayor share of TV time (>9% vs Netflix ~8%, Nielsen Apr-2026). Si NFLX lanza Clips (vertical mobile video) sin tracción, concede engagement strategy a TikTok/YouTube Shorts. Implicación: ad CPMs presionados.
B34: #3 Content hit-rate y costes de producción/sports | C34: Live sports requires high contract costs (NFL fees, F1 rights). Si Netflix paga premium sin recuperar via ads/subs uplift, content spend/revenue se eleva del 38% actual al 42%+ — comprime FCF 200-300bp.
B35: #4 Riesgo regulatorio / antitrust | C35: EU Digital Services Act + Audiovisual Media Services Directive: cuota cultural europea (30% local content) impone cost. Posible antitrust en ad market si NFLX escala >$10bn/año en advertising. Magnitud: -3-5% margin posible.
B36: #5 FX exposure | C36: NFLX >50% revenue internacional. Fortaleza USD (DXY ~104-106 mid-2026) comprime revenue reported. Hedging via cash flow hedges modera pero no elimina. FY26 FX-neutral growth +17% vs reported +16% (Q4 2025 letter).
B37: #6 Macro / consumer recession | C37: Streaming subs son cuasi-discrecionales. En recesión 2026-27, churn en lower tiers podría +200-400bp. Mitigación: ad-tier $5-7/mes captura downgraders. Pero ARPU mix downgrade comprime revenue/member 5-10%.
B38: #7 Stock split makes shares more retail-driven | C38: Post 10:1 split (nov 2025), volume y volatilidad subieron. Drawdown -35% YTD (de $134 high a $87 ahora) puede acelerar en cualquier signo de margin compression. Lectura: market multiple sensitivity elevada.
B39: #8 Key-person risk (co-CEOs Sarandos/Peters) | C39: Reed Hastings stepped back 2023; co-CEO structure ha funcionado. Cualquier salida o desacuerdo materially negative. Probabilidad: baja, impacto: alto.
B41: 6. CONCLUSIÓN — DECISIÓN DE INVERSIÓN
B42: Veredicto | C42: Netflix a $87 está fairly valued con sesgo a ligero sobre-valor. Mi base $77 (mediana 8 métodos) implica -11% downside; mi probability-weighted blended $84 implica -3%. Risk-reward asimétrico moderado a la baja en el spot actual.
B43: Recomendación | C43: HOLD con sesgo a UNDERWEIGHT. Target central $80 (12 meses). Comprar en $70-75 (drawdown). Vender en >$110.
B44: Catalizadores a 12 meses | C44: (1) Q2 2026 results jul-2026: ¿se eleva guidance FY26 op margin >31.5%? Bullish trigger. (2) NFL Christmas Day games dic-2026: monetización demonstrable? (3) Ad upfront 2027 (mayo 2027): ¿se confirma run-rate $3.5bn+? (4) Próxima M&A: si NFLX lanza otro bid grande post-WBD, gauge market reaction. (5) Macroeconomic: 10Y UST rate dynamics (Fed path 2026-27); Rf 4.5%→3.5% reduce WACC 50bp ≈ +$7-10 precio.

Sheet Fuentes
B2: [EMPRESA] — FUENTES Y REFERENCIAS
B3: Cita SIEMPRE fuentes primarias (filings regulador) para datos históricos. Damodaran y bancos centrales para inputs de mercado.
B5: 1. FILINGS REGULATORIOS (Filings regulador) — fuentes primarias
B6: Documento | C6: Fecha | D6: URL | E6: Uso en modelo
B7: [EMPRESA] Memoria anual FY-1 (último ejercicio cerrado) | C7: 30-jun-2025 | D7: [URL al filing oficial] | E7: Income Statement, BS, CF, segmentos FY21-FY25; effective tax rate Nota 12; buyback authorization Nota 17
B8: [EMPRESA] Reporte trimestral más reciente | C8: 31-mar-2026 | D8: [URL al filing oficial] | E8: 9M parcial IS/BS/CF; [Producto cloud] +40%; Backlog $627B; capex 9M $80.1B; PP&E $283B; [Inversión estratégica] Recap dilution gain $5.9B
B9: [EMPRESA] Press release último resultado | C9: 29-abr-2026 | D9: [URL al filing oficial] | E9: Detail métricas operativas: MS Cloud $45.5B (+22%), [Driver de crecimiento] ARR $37B (+123%), [Producto AI] seats >20M
B10: [EMPRESA] Memoria anual FY-2 | C10: 30-jun-2024 | D10: [URL al filing oficial] | E10: FY24 históricos para comparativa y series largas; Activision close detalles
B11: [EMPRESA] Memoria anual FY-3 | C11: 30-jun-2023 | D11: [URL al filing oficial] | E11: FY23 históricos; primer reporting Backlog ($222B); Activision pending
B12: [EMPRESA] Memoria anual FY-4 | C12: 30-jun-2022 | D12: [URL al filing oficial] | E12: FY22 históricos; pre-inversión capex baseline
B13: [EMPRESA] Memoria anual FY-5 | C13: 30-jun-2021 | D13: [URL al filing oficial] | E13: FY21 base year para series 5-year
B15: 2. MERCADO Y MACRO
B16: Fuente | C16: Dato (15-may-2026) | D16: URL | E16: Uso en modelo
B17: Tipo libre de riesgo (bono soberano 10Y) | C17: DGS10 series — daily, 15-may-2026: 4.54% | D17: [Completar fuente/URL] | E17: Risk-free rate input (Hipotesis!$C$9)
B18: Equity Risk Premium (recomendado: Damodaran) | C18: ERP 2026 Edition, January 2026 update: 4.23% | D18: https://pages.stern.nyu.edu/~adamodar/ | E18: Equity Risk Premium input (Hipotesis!$C$10)
B19: Cotización spot [EMPRESA] | C19: Yahoo Finance / Google Finance 15-may-2026 EOD ~$408 | D19: [Completar fuente/URL] | E19: Spot price (Hipotesis!$C$6) — verificación cross-source
B20: Rango 52 semanas [EMPRESA] | C20: $356.28 (Apr-2026 low) – $555.45 (Oct-2025 high) | D20: [Completar fuente/URL] | E20: Resumen sheet — context histórico
B21: Beta sectorial (recomendado: Damodaran Industry Beta) | C21: Software (System & Application) 2026: 1.05-1.15 range | D21: https://pages.stern.nyu.edu/~adamodar/New_Home_Page/datafile/Betas.html | E21: Beta cross-check (Hipotesis!$C$11)
B23: 3. PEERS Y CROSS-CHECKS
B24: Peer | C24: Métrica clave | D24: URL | E24: Uso
B25: [Peer 1] — último Reporte trimestral | C25: Market cap $4.86T, P/E 30.4× TTM | D25: https://abc.xyz/investor/ | E25: Multiple peer comparison para EV/EBITDA y P/E ranges
B26: [Peer 2] — último Reporte trimestral | C26: Market cap $2.87T, P/E 31.5× TTM, AWS focus | D26: https://ir.aboutamazon.com/ | E26: Hyperscaler cross-check capex/revenue ratio
B27: [Peer 3] — último Reporte trimestral | C27: Market cap $555B, P/E ~33× post sell-off (Sep-25 high $345 → $185) | D27: https://investor.oracle.com/ | E27: Comparable cloud transition / multiple compression case study
B28: [Activist / Inversor relevante] — últimas posiciones 13F | C28: Position initiated in [EMPRESA] during Mar-Apr-2026 drawdown | D28: https://www.sec.gov/cgi-bin/browse-edgar?action=getcompany&CIK=0001336528 | E28: Sentiment / institutional positioning context
B30: 4. DOCUMENTOS INTERNOS / RESEARCH USADOS
B31: Documento | C31: Fecha | D31: Origen | E31: Uso
B32: [Documentos internos / notas / research previo] | C32: 13-may-2026 | D32: Documento aportado por usuario | E32: Estructura inicial de tesis, marco analítico segmentación, decisión de capex inversión como centro narrativo
B33: [Modelos comparables sectoriales] | C33: previo (referencia) | D33: Repositorio interno del usuario | E33: Estructura 7-sheet replicada para consistencia metodológica (Resumen/Hipotesis/Historico/Modelo/DuPont_WC/Conclusiones/Fuentes)
B35: 5. NOTAS METODOLÓGICAS
B36: Todas las cifras históricas verificadas contra filings oficiales (memoria anual + reportes trimestrales).
B37: Tasa fiscal efectiva: usar el promedio de los últimos 2 años fiscales como guía para terminal.
B38: Segmentación: usar la estructura reportada por la empresa en sus filings. Reclasificar si cambia.
B39: Backlog / RPO: si la empresa reporta esta métrica, es excelente proxy de visibilidad futura.
B40: [Inversión estratégica] Recapitalization (Oct-2025): [EMPRESA] pasa de ~49% profit-sharing rights a ~27% as-converted equity stake. $13B total commitment, $11.8B funded as of Último trimestre. Reportado en Reporte trimestral Q1 FY26 Note 9.
B41: Damodaran ERP: implied ERP basado en S&P 500 dividend + buyback yields proyectados. Edición enero-2026. Alternativa: historical ERP arithmetic mean 5.8% (1928-2025) — no usada por preferencia de método implied.
B42: Cost of debt: AAA-rated MSFT, spread ~25bp sobre 10Y UST. Calculado como Rf 4.54% + 26bp = 4.80%. [EMPRESA] prácticamente sin nuevo debt issuance reciente (Total Debt cae de $79B en FY24 a $40B en Último trimestre).
B43: Discount factors: convención mid-year (0.5, 1.5, 2.5, ...) — más realista que end-of-year para flujos uniformemente distribuidos.
B44: 8 métodos de valoración (DCF Gordon, H-Model, Exit EBITDA/EBIT/Rev + NTM P/E/EBITDA/Rev cross-checks): la mediana se usa como target central por robustez vs outliers.
B45: Sensibilidades embebidas (Tablas A-D en Modelo cols L-R): recompute completo, no TABLE() de Excel. Highlight verde > spot, rojo < spot.
B47: Modelo construido el 15-may-2026. Auditable end-to-end vía formulas. 506+ formulas, 0 errors en recalc.
