Workbook

Sheet Resumen
A1: UBER / CUADRO DE MANDO - RESUMEN EJECUTIVO Y SNAPSHOT
B2: LEYENDA: | C2: AZUL+AMARILLO | D2: Input hardcoded (editable) | E2: AMARILLO FUERTE | F2: Input clave (driver de sensibilidad) | G2: NEGRO | H2: Formula (calculado) | I2: VERDE | J2: Link a otra hoja | K2: VERDE CLARO | L2: Resultado / output
A4: SNAPSHOT - resumen ejecutivo del libro completo
B6: STOCK / MERCADO | D6: VALORACION DCF | F6: OPERATIONS (FY25) | H6: QUALITY / RETURNS
B7: Spot ($) | C7: =Hipotesis!D55 -> 77.11 | D7: DCF mediana | E7: =MEDIAN(Modelo!D128:G128) -> 103.38241 | F7: Revenue 2025 | G7: =Historico!I7 -> 52017 | H7: ROIC operativo'25 | I7: =DuPont_WC!I37 -> 0.14503325
B8: Market Cap ($M) | C8: =Hipotesis!D55*Hipotesis!D46/1000 -> 159724.96 | D8: DCF promedio | E8: =AVERAGE(Modelo!D128:G128) -> 101.50039 | F8: EBIT 2025 | G8: =Historico!I17 -> 5565 | H8: EBIT margin '25 | I8: =Historico!I18 -> 0.10698426
B9: Enterprise Value | C9: =Hipotesis!D55*Hipotesis!D46/1000+Hipotesis!D51-Hipotesis!D49-Hipotesis!D50-Hipotesis!D52-Hipotesis!D53+Hipotesis!D54 -> 156831.96 | D9: Upside vs spot | E9: =MEDIAN(Modelo!D128:G128)/Hipotesis!D55-1 -> 0.34071343 | F9: Adj EBITDA 2025 | G9: =Historico!I26 -> 8730 | H9: FCF margin '25 | I9: =Historico!I63 -> 0.18768864
B10: 52w range ($) | C10: $68.46 - $101.99 | D10: EV/EBITDA NTM | E10: =$C$9/Modelo!F72 -> 16.88 | F10: FCF 2025 | G10: =Historico!I62 -> 9763 | H10: NWC 2025 ($M) | I10: =DuPont_WC!I64 -> -4613
B11: Acciones dil. (k) | C11: =Hipotesis!D46 -> 2071391 | D11: EV/EBIT NTM | E11: =$C$9/Modelo!F62 -> 18.479252 | F11: Q1'26 Revenue | G11: 13203 | H11: Insurance res. '25 | I11: =DuPont_WC!I57 -> 7450
B13: Tesis: | C13: "Scale Efficiency over Monetization Aggression" - depende de Mobility margin, no de take-rate heroics
B14: Critico Q1'26: | C14: Take rate Mobility paso 30.7% -> 25.8% por cambio UK (merchant->agency); ~9pp del cambio es contable
A16: 1. Q1 2026 HIGHLIGHTS (8-K filed May 6, 2026)
B17: Total Gross Bookings | D17: 53720 | E17: +18% YoY cc
B18: Total Revenue | D18: 13203 | E18: +21% YoY cc
B19: GAAP Operating Income | D19: 1923 | E19: +105% YoY
B20: Adj EBITDA | D20: 2481 | E20: +24% YoY
B21: Non-GAAP Operating Income | D21: 1883 | E21: Nueva metrica primaria
B22: Free Cash Flow | D22: 2286 | E22: +44% YoY
B23: Mobility - Gross Bookings | D23: 26394 | E23: +25% YoY cc
B24: Mobility - Revenue | D24: 6798 | E24: +5% YoY (UK accounting -9pp)
B25: Mobility - Segment Op Income | D25: 2029 | E25: +28% YoY
B26: Delivery - Gross Bookings | D26: 25992 | E26: +23% YoY cc
B27: Delivery - Revenue | D27: 5068 | E27: +25% YoY
B28: Delivery - Segment Op Income | D28: 961 | E28: +43% YoY
... B30: Buybacks (capital returned) | D30: 3000 | E30: $20B program total
A33: 2. HISTORIA FINANCIERA (5 anos)
D34: 2021A | E34: 2022A | F34: 2023A | G34: 2024A | H34: 2025A
B35: Revenue ($M) | D35: =Historico!E7 -> 17455 | E35: =Historico!F7 -> 31877 | F35: =Historico!G7 -> 37281 | G35: =Historico!H7 -> 43978 | H35: =Historico!I7 -> 52017
B36: YoY % | D36: =Historico!E8 -> 0.56701679 | E36: =Historico!F8 -> 0.8262389 | F36: =Historico!G8 -> 0.16952662 | G36: =Historico!H8 -> 0.17963574 | H36: =Historico!I8 -> 0.18279594
B37: Adj EBITDA ($M) | D37: =Historico!E26 -> -774 | E37: =Historico!F26 -> 1713 | F37: =Historico!G26 -> 4052 | G37: =Historico!H26 -> 6484 | H37: =Historico!I26 -> 8730
B38: Adj EBITDA margin | D38: =Historico!E27 -> -0.044342595 | E38: =Historico!F27 -> 0.053737805 | F38: =Historico!G27 -> 0.10868807 | G38: =Historico!H27 -> 0.14743736 | H38: =Historico!I27 -> 0.16782975
B39: FCF ($M) | D39: =Historico!E62 -> 238 | E39: =Historico!F62 -> 390 | F39: =Historico!G62 -> 3361 | G39: =Historico!H62 -> 6895 | H39: =Historico!I62 -> 9763
B40: FCF margin | D40: =Historico!E63 -> 0.013635062 | E40: =Historico!F63 -> 0.012234526 | F40: =Historico!G63 -> 0.090153161 | G40: =Historico!H63 -> 0.15678294 | H40: =Historico!I63 -> 0.18768864
B41: Total Assets ($M) | D41: =Historico!E49 -> 38774 | E41: =Historico!F49 -> 32109 | F41: =Historico!G49 -> 38699 | G41: =Historico!H49 -> 51244 | H41: =Historico!I49 -> 61802
B42: Total Equity ($M) | D42: =Historico!E50 -> 14458 | E42: =Historico!F50 -> 7340 | F42: =Historico!G50 -> 11249 | G42: =Historico!H50 -> 21558 | H42: =Historico!I50 -> 27041
B43: LT Debt ($M) | D43: =Historico!E52 -> 9276 | E43: =Historico!F52 -> 9265 | F43: =Historico!G52 -> 9456 | G43: =Historico!H52 -> 10579 | H43: =Historico!I52 -> 10521
B44: Diluted shares (k) | D44: =Historico!E65 -> 1903053 | E44: =Historico!F65 -> 1992188 | F44: =Historico!G65 -> 2068999 | G44: =Historico!H65 -> 2096810 | H44: =Historico!I65 -> 2119689
A47: 3. MULTIPLOS DE NEGOCIACION (current)
B48: EV / Revenue (NTM 2026E) | D48: =$C$9/Modelo!F55 -> 2.7306628
B49: EV / EBITDA (NTM 2026E) | D49: =$C$9/Modelo!F72 -> 16.88
B50: EV / EBIT (NTM 2026E) | D50: =$C$9/Modelo!F62 -> 18.479252
B51: EV / FCFF (NTM 2026E) | D51: =$C$9/Modelo!F75 -> 28.284171
B52: EV / GB (NTM 2026E) | D52: =$C$9/Modelo!F38 -> 0.67238134
B53: P / FCF (LTM 2025A) | D53: =(Hipotesis!D55*Hipotesis!D46/1000)/Historico!I62 -> 16.360234
A56: 4. PRECIOS IMPLICITOS (todos los metodos)
B57: Metodo | D57: Precio impl. | E57: Upside | F57: Comentario
B58: DCF Gordon Growth | D58: =Modelo!D128 -> 72.978709 | E58: =D58/Hipotesis!$D$55-1 -> -0.053576595 | F58: Perpetuidad estandar
B59: DCF H-Model | D59: =Modelo!E128 -> 86.288402 | E59: =D59/Hipotesis!$D$55-1 -> 0.11902999 | F59: Crecimiento decadente
B60: DCF Exit Multiple EV/EBITDA | D60: =Modelo!F128 -> 120.47642 | E60: =D60/Hipotesis!$D$55-1 -> 0.56239687 | F60: Salida 16x EBITDA
B61: DCF Exit Multiple EV/EBIT | D61: =Modelo!G128 -> 126.25804 | E61: =D61/Hipotesis!$D$55-1 -> 0.6373757 | F61: Salida 18x EBIT
B62: DCF Promedio (4 metodos) | D62: =Modelo!H128 -> 101.50039 | E62: =D62/Hipotesis!$D$55-1 -> 0.31630649 | F62: Punto medio razonable
B64: PROMEDIO (5 metodos) | D64: =AVERAGE(D58:D62) -> 101.50039 | E64: =D64/Hipotesis!$D$55-1 -> 0.31630649
B65: MEDIANA | D65: =MEDIAN(D58:D62) -> 101.50039 | E65: =D65/Hipotesis!$D$55-1 -> 0.31630649
B66: MIN / MAX | D66: =MIN(D58:D62) -> 72.978709 | E66: =MAX(D58:D62) -> 126.25804
A68: Rango de referencia analistas:
B69: Bear case | D69: $62 - $70
B70: Base case | D70: $84 - $96
B71: Bull case | D71: $102 - $118
B72: Centro consenso (May 2026) | D72: $88 - $92 (analyst PT ~$104)
A74: 5. DRIVERS CLAVE (modificar en hoja HIPOTESIS)
B75: Driver | D75: 2026E | E75: 2030E | F75: Comentario
B76: Mobility GB growth | D76: =Hipotesis!G22 -> 0.2 | E76: =Hipotesis!K22 -> 0.09 | F76: Driver de actividad core
B77: Mobility Take Rate | D77: =Hipotesis!G23 -> 0.26 | E77: =Hipotesis!K23 -> 0.28 | F77: Q1 26 reportado 25.8% (UK -9pp); normalizado ~27-28%
B78: Mobility Op Margin | D78: =Hipotesis!G24 -> 0.3 | E78: =Hipotesis!K24 -> 0.335 | F78: * DRIVER PRINCIPAL DE VALOR (Sens A en Modelo)
B79: Delivery Op Margin | D79: =Hipotesis!G29 -> 0.19 | E79: =Hipotesis!K29 -> 0.225 | F79: Mejorando con publicidad
B80: Corporate overhead (% GB) | D80: =Hipotesis!G37 -> 0.02 | E80: =Hipotesis!K37 -> 0.014 | F80: * Overhead dilution lever (Sens D)
B81: Sales-to-Capital | D81: =Hipotesis!D40 -> 5 | E81: =Hipotesis!D40 -> 5 | F81: 5x asset-light moderado (Sens F)
B82: SBC % rev | D82: =Hipotesis!G44 -> 0.03 | E82: =Hipotesis!K44 -> 0.024 | F82: Q1 26 = 3.6% rev
B83: Net buyback % | D83: =Hipotesis!G45 -> 0.03 | E83: =Hipotesis!K45 -> 0.018 | F83: Programa $20B activo
B84: WACC | D84: =Hipotesis!D14 -> 0.104564 | E84: =Hipotesis!D14 -> 0.104564 | F84: Ke 10.85% + Kd post-tax 4.29%
B85: Crecimiento perpetuo (g) | D85: =Hipotesis!D15 -> 0.025 | E85: =Hipotesis!D15 -> 0.025 | F85: Conservador vs LT GDP nominal ~3.5-4%
B86: Exit Multiple EV/EBITDA | D86: =Hipotesis!D16 -> 16 | E86: =Hipotesis!D16 -> 16 | F86: 16x plataforma madura
B87: Exit Multiple EV/EBIT | D87: =Hipotesis!D17 -> 18 | E87: =Hipotesis!D17 -> 18 | F87: 18x consistente con 16x EBITDA
A89: 6. TESIS DE VALORACION
B90: "Scale Efficiency over Monetization Aggression"
B91: El caso funciona si UBER:
B92: 1. Mantiene posicion como demand aggregator asset-light
B93: 2. Convierte escala en operating leverage (Mobility margin sube)
B94: 3. Diluye overhead corporativo con escala (corporate % GB baja)
B95: 4. Disciplina en reinversion (S2C alto, capex razonable)
B96: 5. Captura valor por accion (buybacks netos > SBC)
B98: Lo que ROMPE la tesis:
B99: - Mobility margin no expande mas alla del actual ~24-25%
B100: - Take rate normalizado queda plano (no aparece operating leverage)
B101: - Reinversion sale mas pesada de lo esperado (S2C colapsa)
B102: - SBC y dilucion siguen altos; buybacks no compensan
B103: - Overhead no diluye con escala
B130: Chart helper data: | D130: 2020A | E130: 2021A | F130: 2022A | G130: 2023A | H130: 2024A | I130: 2025A
C131: Revenue | D131: =Historico!D7 -> 11139 | E131: =Historico!E7 -> 17455 | F131: =Historico!F7 -> 31877 | G131: =Historico!G7 -> 37281 | H131: =Historico!H7 -> 43978 | I131: =Historico!I7 -> 52017
C132: Adj EBITDA | D132: =Historico!D26 -> -2528 | E132: =Historico!E26 -> -774 | F132: =Historico!F26 -> 1713 | G132: =Historico!G26 -> 4052 | H132: =Historico!H26 -> 6484 | I132: =Historico!I26 -> 8730
C133: OCF | D133: =Historico!D61 -> -2745 | E133: =Historico!E61 -> 445 | F133: =Historico!F61 -> 642 | G133: =Historico!G61 -> 3585 | H133: =Historico!H61 -> 7137 | I133: =Historico!I61 -> 10099
C134: FCF | D134: =Historico!D62 -> -3361 | E134: =Historico!E62 -> 238 | F134: =Historico!F62 -> 390 | G134: =Historico!G62 -> 3361 | H134: =Historico!H62 -> 6895 | I134: =Historico!I62 -> 9763
C135: Mobility GB | D135: =Historico!D30 -> 26553 | E135: =Historico!E30 -> 38713 | F135: =Historico!F30 -> 49669 | G135: =Historico!G30 -> 64995 | H135: =Historico!H30 -> 81763 | I135: =Historico!I30 -> 97497
C136: Delivery GB | D136: =Historico!D35 -> 30227 | E136: =Historico!E35 -> 51635 | F136: =Historico!F35 -> 60048 | G136: =Historico!G35 -> 66331 | H136: =Historico!H35 -> 75144 | I136: =Historico!I35 -> 90864
C137: Freight GB | D137: =Historico!D40 -> 1051 | E137: =Historico!E40 -> 2132 | F137: =Historico!F40 -> 7058 | G137: =Historico!G40 -> 5245 | H137: =Historico!H40 -> 5277 | I137: =Historico!I40 -> 5141
C138: ROE GAAP | D138: =DuPont_WC!D25 -> -0.55176912 | E138: =DuPont_WC!E25 -> -0.037120192 | F138: =DuPont_WC!F25 -> -0.8387008 | G138: =DuPont_WC!G25 -> 0.20302329 | H138: =DuPont_WC!H25 -> 0.60084738 | I138: =DuPont_WC!I25 -> 0.41371222
C139: ROIC operativo | D139: =DuPont_WC!D37 -> -0.30503739 | E139: =DuPont_WC!E37 -> -0.18725093 | F139: =DuPont_WC!F37 -> -0.1276085 | G139: =DuPont_WC!G37 -> 0.05592662 | H139: =DuPont_WC!H37 -> 0.086980876 | I139: =DuPont_WC!I37 -> 0.14503325
B145: Implied prices helper:
C146: Method | D146: Precio
C147: Spot | D147: =Hipotesis!D55 -> 77.11
...

Sheet Hipotesis
A1: HIPOTESIS DEL MODELO / Inputs y Drivers
B2: LEYENDA: | C2: AZUL+AMARILLO | D2: Input hardcoded (editable) | E2: AMARILLO FUERTE | F2: Input clave (driver de sensibilidad) | G2: NEGRO | H2: Formula (calculado) | I2: VERDE | J2: Link a otra hoja | K2: VERDE CLARO | L2: Resultado / output
A4: 1. TASA DE DESCUENTO (WACC)
B5: Tasa libre de riesgo (10Y UST yield) | D5: 0.0435
B6: Equity Risk Premium (ERP) | D6: 0.05
B7: Beta apalancado (5Y) | D7: 1.3
B8: Coste del Equity (Ke = Rf + Beta x ERP) | D8: =D5+D7*D6 -> 0.1085
B9: Coste de deuda pre-impuestos (Kd) | D9: 0.055
B10: Tipo impositivo efectivo (Non-GAAP) | D10: 0.22
B11: Kd post-impuestos = Kd x (1-T) | D11: =D9*(1-D10) -> 0.0429
B12: Peso del Equity (E/EV) | D12: 0.94
B13: Peso de Deuda (D/EV) | D13: =1-D12 -> 0.06
B14: WACC | D14: =D8*D12+D11*D13 -> 0.104564
B15: Tasa de crecimiento perpetuo (g) | D15: 0.025
B16: Multiplo EV/EBITDA salida | D16: 16
B17: Multiplo EV/EBIT salida | D17: 18
D19: 2023A | E19: 2024A | F19: 2025A | G19: 2026E | H19: 2027E | I19: 2028E | J19: 2029E | K19: 2030E
A21: 2. MOBILITY (driver principal del valor)
B22: GB growth (% YoY) | G22: 0.2 | H22: 0.16 | I22: 0.13 | J22: 0.11 | K22: 0.09
B23: Take Rate (Revenue / GB) | G23: 0.26 | H23: 0.27 | I23: 0.275 | J23: 0.28 | K23: 0.28
B24: Margen Op. de Mobility (% revenue) | G24: 0.3 | H24: 0.315 | I24: 0.325 | J24: 0.33 | K24: 0.335
A26: 3. DELIVERY (bloque secundario)
B27: GB growth (% YoY) | G27: 0.22 | H27: 0.18 | I27: 0.14 | J27: 0.11 | K27: 0.09
B28: Take Rate | G28: 0.195 | H28: 0.198 | I28: 0.2 | J28: 0.2 | K28: 0.2
B29: Margen Op. de Delivery (% revenue) | G29: 0.19 | H29: 0.205 | I29: 0.215 | J29: 0.22 | K29: 0.225
A31: 4. FREIGHT (modelar conservador)
B32: GB growth (% YoY) | G32: 0.05 | H32: 0.05 | I32: 0.04 | J32: 0.03 | K32: 0.03
B33: Take Rate (~100%) | G33: 1 | H33: 1 | I33: 1 | J33: 1 | K33: 1
B34: Margen Op. de Freight (% revenue) | G34: -0.015 | H34: 0 | I34: 0.005 | J34: 0.01 | K34: 0.015
A36: 5. CORPORATE OVERHEAD (driver de overhead dilution)
B37: Corporate cost (% Gross Bookings) | G37: 0.02 | H37: 0.018 | I37: 0.016 | J37: 0.015 | K37: 0.014
A39: 6. REINVERSION
B40: Sales-to-Capital ratio | D40: 5
B41: ΔWC / ΔRevenue | D41: -0.005
A43: 7. CAPTURA POR ACCION
B44: SBC % revenue | G44: 0.03 | H44: 0.028 | I44: 0.026 | J44: 0.025 | K44: 0.024
B45: Buyback neto (% acciones anual) | G45: 0.03 | H45: 0.025 | I45: 0.022 | J45: 0.02 | K45: 0.018
B46: Acciones diluidas iniciales (k) | D46: 2071391
A48: 8. BALANCE SHEET (Q1 2026, $M)
B49: Cash + equivalents | D49: 5558
B50: Short-term investments | D50: 533
B51: Long-term debt | D51: 10514
B52: Equity stakes (Aurora, Grab, Didi, Lucid, etc.) | D52: 8109
B53: Equity method investments | D53: 268
B54: Non-controlling interests | D54: 1061
B55: Precio actual por accion ($) | D55: 77.11
A57: 9. INDICE DE INPUTS HARDCODED (mantenimiento)
B58: Todos los inputs editables estan en esta hoja, identificados por color azul + amarillo.
B59: Para actualizar el modelo: cambia solo aqui. El resto recalcula automaticamente.
B60: Inputs HARDCODED en otras hojas (deben mantenerse aqui idealmente):
B61: - Historico: cifras anuales 2020-2025 (publicadas SEC)

Sheet Historico
A1: HISTORICO 2020-2025 / fuente: SEC 10-K, 8-K, 10-Q
B2: LEYENDA: | C2: AZUL+AMARILLO | D2: Input hardcoded (editable) | E2: AMARILLO FUERTE | F2: Input clave (driver de sensibilidad) | G2: NEGRO | H2: Formula (calculado) | I2: VERDE | J2: Link a otra hoja | K2: VERDE CLARO | L2: Resultado / output
D4: 2020A | E4: 2021A | F4: 2022A | G4: 2023A | H4: 2024A | I4: 2025A
A6: INCOME STATEMENT ($M, source: 10-K)
B7: Revenue | D7: 11139 | E7: 17455 | F7: 31877 | G7: 37281 | H7: 43978 | I7: 52017
B8: YoY growth % | E8: =E7/D7-1 -> 0.56701679 | F8: =F7/E7-1 -> 0.8262389 | G8: =G7/F7-1 -> 0.16952662 | H8: =H7/G7-1 -> 0.17963574 | I8: =I7/H7-1 -> 0.18279594
B10: Cost of revenue (excl. D&A) | D10: 5154 | E10: 9351 | F10: 18748 | G10: 21513 | H10: 26494 | I10: 31288
B11: Operations and support | D11: 1819 | E11: 1877 | F11: 2392 | G11: 2526 | H11: 2604 | I11: 2716
B12: Sales and marketing | D12: 3583 | E12: 4789 | F12: 4286 | G12: 4248 | H12: 4525 | I12: 5158
B13: Research and development | D13: 2205 | E13: 2054 | F13: 2666 | G13: 2989 | H13: 3104 | I13: 3399
B14: General and administrative | D14: 2666 | E14: 2316 | F14: 2421 | G14: 2436 | H14: 2789 | I14: 3179
B15: Depreciation and amortization | D15: 575 | E15: 902 | F15: 947 | G15: 823 | H15: 663 | I15: 712
B17: GAAP Income from Operations | D17: -4863 | E17: -3824 | F17: -1832 | G17: 1110 | H17: 2799 | I17: 5565
B18: GAAP Op margin % | D18: =D17/D7 -> -0.4365742 | E18: =E17/E7 -> -0.21907763 | F18: =F17/F7 -> -0.057470904 | G18: =G17/G7 -> 0.029773879 | H18: =H17/H7 -> 0.063645459 | I18: =I17/I7 -> 0.10698426
B19: Stock-based compensation (memo) | D19: 827 | E19: 1168 | F19: 1793 | G19: 1935 | H19: 1925 | I19: 1826
B20: SBC % revenue | D20: =D19/D7 -> 0.074243648 | E20: =E19/E7 -> 0.066914924 | F20: =F19/F7 -> 0.056247451 | G20: =G19/G7 -> 0.051903114 | H20: =H19/H7 -> 0.043771886 | I20: =I19/I7 -> 0.035103908
B22: Net Income (GAAP) | D22: -6768 | E22: -496 | F22: -9141 | G22: 1887 | H22: 9856 | I22: 10053
B23: EPS diluted ($) | D23: -3.86 | E23: -0.26 | F23: -4.49 | G23: 0.87 | H23: 4.56 | I23: 4.73
A25: ADJ EBITDA (Non-GAAP, source: company press releases)
B26: Adj EBITDA | D26: -2528 | E26: -774 | F26: 1713 | G26: 4052 | H26: 6484 | I26: 8730
B27: Adj EBITDA margin % | D27: =D26/D7 -> -0.22695035 | E27: =E26/E7 -> -0.044342595 | F27: =F26/F7 -> 0.053737805 | G27: =G26/G7 -> 0.10868807 | H27: =H26/H7 -> 0.14743736 | I27: =I26/I7 -> 0.16782975
A29: SEGMENT DATA ($M)
B30: Mobility — Gross Bookings | D30: 26553 | E30: 38713 | F30: 49669 | G30: 64995 | H30: 81763 | I30: 97497
B31: Mobility — Revenue | D31: 6089 | E31: 6953 | F31: 14000 | G31: 19783 | H31: 25086 | I31: 29670
B32: Take rate (Rev/GB) | D32: =D31/D30 -> 0.22931495 | E32: =E31/E30 -> 0.17960375 | F32: =F31/F30 -> 0.28186595 | G32: =G31/G30 -> 0.30437726 | H32: =H31/H30 -> 0.3068136 | I32: =I31/I30 -> 0.30431706
B33: Mobility — Adj EBITDA | D33: 1169 | E33: 1604 | F33: 3133 | G33: 5174 | H33: 6546 | I33: 7899
B35: Delivery — Gross Bookings | D35: 30227 | E35: 51635 | F35: 60048 | G35: 66331 | H35: 75144 | I35: 90864
B36: Delivery — Revenue | D36: 3904 | E36: 8362 | F36: 10905 | G36: 12204 | H36: 13745 | I36: 17248
B37: Take rate | D37: =D36/D35 -> 0.12915605 | E37: =E36/E35 -> 0.16194442 | F37: =F36/F35 -> 0.18160472 | G37: =G36/G35 -> 0.18398637 | H37: =H36/H35 -> 0.18291547 | I37: =I36/I35 -> 0.18982215
B38: Delivery — Adj EBITDA | D38: -873 | E38: -348 | F38: 553 | G38: 1502 | H38: 2516 | I38: 3572
B40: Freight — Gross Bookings | D40: 1051 | E40: 2132 | F40: 7058 | G40: 5245 | H40: 5277 | I40: 5141
B41: Freight — Revenue | D41: 1146 | E41: 2132 | F41: 6952 | G41: 5245 | H41: 5147 | I41: 5099
B42: Freight — Adj EBITDA | D42: -118 | E42: -147 | F42: -92 | G42: -224 | H42: -107 | I42: -33
B44: Corporate G&A + Platform R&D | D44: -2706 | E44: -1883 | F44: -1881 | G44: -2400 | H44: -2471 | I44: -2708
B46: Sum of segments + Corporate (check vs Adj EBITDA) | D46: =D33+D38+D42+D44 -> -2528 | E46: =E33+E38+E42+E44 -> -774 | F46: =F33+F38+F42+F44 -> 1713 | G46: =G33+G38+G42+G44 -> 4052 | H46: =H33+H38+H42+H44 -> 6484 | I46: =I33+I38+I42+I44 -> 8730
A48: BALANCE SHEET HISTORICAL ($M, source: 10-K)
B49: Total Assets | D49: 33252 | E49: 38774 | F49: 32109 | G49: 38699 | H49: 51244 | I49: 61802
B50: Total Stockholders' Equity (UBER) | D50: 12266 | E50: 14458 | F50: 7340 | G50: 11249 | H50: 21558 | I50: 27041
B51: Total Equity (incl. NCI) | D51: 12721 | E51: 14997 | F51: 7656 | G51: 11614 | H51: 22383 | I51: 27918
B52: Long-term Debt | D52: 7561 | E52: 9276 | F52: 9265 | G52: 9456 | H52: 10579 | I52: 10521
B53: Cash + ST investments | D53: 7392 | E53: 7805 | F53: 5407 | G53: 5224 | H53: 7037 | I53: 7633
B54: Accounts Receivable, net | D54: 1110 | E54: 2439 | F54: 2477 | G54: 2779 | H54: 3399 | I54: 3850
B55: Accounts Payable | D55: 235 | E55: 396 | F55: 622 | G55: 712 | H55: 858 | I55: 1013
B56: ST Insurance reserves | D56: 1243 | E56: 1442 | F56: 2049 | G56: 2528 | H56: 2754 | I56: 3050
B57: LT Insurance reserves | D57: 2812 | E57: 2823 | F57: 3370 | G57: 3736 | H57: 4102 | I57: 4400
A59: CASH FLOW ($M, source: 10-K)
B60: CapEx | D60: 616 | E60: 207 | F60: 252 | G60: 224 | H60: 242 | I60: 336
B61: Operating Cash Flow | D61: -2745 | E61: 445 | F61: 642 | G61: 3585 | H61: 7137 | I61: 10099
B62: Free Cash Flow | D62: -3361 | E62: 238 | F62: 390 | G62: 3361 | H62: 6895 | I62: 9763
B63: FCF margin % | D63: =D62/D7 -> -0.30173265 | E63: =E62/E7 -> 0.013635062 | F63: =F62/F7 -> 0.012234526 | G63: =G62/G7 -> 0.090153161 | H63: =H62/H7 -> 0.15678294 | I63: =I62/I7 -> 0.18768864
B65: Diluted shares (k, weighted-avg) | D65: 1751952 | E65: 1903053 | F65: 1992188 | G65: 2068999 | H65: 2096810 | I65: 2119689
A67: NOTAS METODOLOGICAS
B68: Q4 2024 valuation allowance release: tax benefit no-cash de $6.4B distorsiona FY2024 NI
B69: FY2025 NI = $10.0B vs Op Income $5.6B: gap por interest income, equity gains, tax NOL
B70: Q1 2026: cambio UK Mobility (merchant -> agency) reduce ~350bps Mobility revenue margin
B71: Insurance reserves estimated for FY2025 (proporcion historica); confirmar con 10-K detalles
B72: Las cifras 2020-2024 son ya finales en filings posteriores; 2025 es ultimo 10-K

Sheet Modelo
A1: MODELO DE OPERACIONES + FCFF + VALORACION / sensibilidades a la derecha
B2: LEYENDA: | C2: AZUL+AMARILLO | D2: Input hardcoded (editable) | E2: AMARILLO FUERTE | F2: Input clave (driver de sensibilidad) | G2: NEGRO | H2: Formula (calculado) | I2: VERDE | J2: Link a otra hoja | K2: VERDE CLARO | L2: Resultado / output
D4: 2024A | E4: 2025A | F4: 2026E | G4: 2027E | H4: 2028E | I4: 2029E | J4: 2030E
L5: (Sensibilidad Mobility — pendiente posicion)
A6: A. MOBILITY (driver principal del valor) | L6: Sens A. Mobility Margin × Take Rate (precio implicito $)
B7: Gross Bookings ($M) | D7: =Historico!H30 -> 81763 | E7: =Historico!I30 -> 97497 | F7: =E7*(1+Hipotesis!G22) -> 116996.4 | G7: =F7*(1+Hipotesis!H22) -> 135715.82 | H7: =G7*(1+Hipotesis!I22) -> 153358.88 | I7: =H7*(1+Hipotesis!J22) -> 170228.36 | J7: =I7*(1+Hipotesis!K22) -> 185548.91 | L7: Op Margin ↓ Take Rate →
B8: YoY % | E8: =E7/D7-1 -> 0.19243423 | F8: =F7/E7-1 -> 0.2 | G8: =G7/F7-1 -> 0.16 | H8: =H7/G7-1 -> 0.13 | I8: =I7/H7-1 -> 0.11 | J8: =J7/I7-1 -> 0.09 | M8: 0.25 | N8: 0.26 | O8: 0.27 | P8: 0.28 | Q8: 0.29 | R8: 0.3
L9: 0.27 | M9: =(($D$82-$J$81+(((((($J$7*M$8)*$L9)+($J$62-$J$15))*(1-Hipotesis!$D$10))-((($J$67-$J$11+($J$7*M$8))-$I$67)/Hipotesis!$D$40))/(1+Hipotesis!$D$14)^5))+((((((($J$7*M$8)*$L9)+($J$62-$J$15))*(1-Hipotesis!$D$10))-((($J$67-$J$11+($J$7*M$8))-$I$67)/Hipotesis!$D$40))*(1+Hipotesis!$D$15)/(Hipotesis!$D$14-Hipotesis!$D$15))/(1+Hipotesis!$D$14)^5)+(Hipotesis!$D$49+Hipotesis!$D$50-Hipotesis!$D$51+Hipotesis!$D$52+Hipotesis!$D$53-Hipotesis!$D$54))/Hipotesis!$D$46*1000 -> 62.001213 | N9: =(($D$82-$J$81+(((((($J$7*N$8)*$L9)+($J$62-$J$15))*(1-Hipotesis!$D$10))-((($J$67-$J$11+($J$7*N$8))-$I$67)/Hipotesis!$D$40))/(1+Hipotesis!$D$14)^5))+((((((($J$7*N$8)*$L9)+($J$62-$J$15))*(1-Hipotesis!$D$10))-((($J$67-$J$11+($J$7*N$8))-$I$67)/Hipotesis!$D$40))*(1+Hipotesis!$D$15)/(Hipotesis!$D$14-Hipotesis!$D$15))/(1+Hipotesis!$D$14)^5)+(Hipotesis!$D$49+Hipotesis!$D$50-Hipotesis!$D$51+Hipotesis!$D$52+Hipotesis!$D$53-Hipotesis!$D$54))/Hipotesis!$D$46*1000 -> 62.081384 | O9: =(($D$82-$J$81+(((((($J$7*O$8)*$L9)+($J$62-$J$15))*(1-Hipotesis!$D$10))-((($J$67-$J$11+($J$7*O$8))-$I$67)/Hipotesis!$D$40))/(1+Hipotesis!$D$14)^5))+((((((($J$7*O$8)*$L9)+($J$62-$J$15))*(1-Hipotesis!$D$10))-((($J$67-$J$11+($J$7*O$8))-$I$67)/Hipotesis!$D$40))*(1+Hipotesis!$D$15)/(Hipotesis!$D$14-Hipotesis!$D$15))/(1+Hipotesis!$D$14)^5)+(Hipotesis!$D$49+Hipotesis!$D$50-Hipotesis!$D$51+Hipotesis!$D$52+Hipotesis!$D$53-Hipotesis!$D$54))/Hipotesis!$D$46*1000 -> 62.161556 | P9: =(($D$82-$J$81+(((((($J$7*P$8)*$L9)+($J$62-$J$15))*(1-Hipotesis!$D$10))-((($J$67-$J$11+($J$7*P$8))-$I$67)/Hipotesis!$D$40))/(1+Hipotesis!$D$14)^5))+((((((($J$7*P$8)*$L9)+($J$62-$J$15))*(1-Hipotesis!$D$10))-((($J$67-$J$11+($J$7*P$8))-$I$67)/Hipotesis!$D$40))*(1+Hipotesis!$D$15)/(Hipotesis!$D$14-Hipotesis!$D$15))/(1+Hipotesis!$D$14)^5)+(Hipotesis!$D$49+Hipotesis!$D$50-Hipotesis!$D$51+Hipotesis!$D$52+Hipotesis!$D$53-Hipotesis!$D$54))/Hipotesis!$D$46*1000 -> 62.241728 | Q9: =(($D$82-$J$81+(((((($J$7*Q$8)*$L9)+($J$62-$J$15))*(1-Hipotesis!$D$10))-((($J$67-$J$11+($J$7*Q$8))-$I$67)/Hipotesis!$D$40))/(1+Hipotesis!$D$14)^5))+((((((($J$7*Q$8)*$L9)+($J$62-$J$15))*(1-Hipotesis!$D$10))-((($J$67-$J$11+($J$7*Q$8))-$I$67)/Hipotesis!$D$40))*(1+Hipotesis!$D$15)/(Hipotesis!$D$14-Hipotesis!$D$15))/(1+Hipotesis!$D$14)^5)+(Hipotesis!$D$49+Hipotesis!$D$50-Hipotesis!$D$51+Hipotesis!$D$52+Hipotesis!$D$53-Hipotesis!$D$54))/Hipotesis!$D$46*1000 -> 62.3219 | R9: =(($D$82-$J$81+(((((($J$7*R$8)*$L9)+($J$62-$J$15))*(1-Hipotesis!$D$10))-((($J$67-$J$11+($J$7*R$8))-$I$67)/Hipotesis!$D$40))/(1+Hipotesis!$D$14)^5))+((((((($J$7*R$8)*$L9)+($J$62-$J$15))*(1-Hipotesis!$D$10))-((($J$67-$J$11+($J$7*R$8))-$I$67)/Hipotesis!$D$40))*(1+Hipotesis!$D$15)/(Hipotesis!$D$14-Hipotesis!$D$15))/(1+Hipotesis!$D$14)^5)+(Hipotesis!$D$49+Hipotesis!$D$50-Hipotesis!$D$51+Hipotesis!$D$52+Hipotesis!$D$53-Hipotesis!$D$54))/Hipotesis!$D$46*1000 -> 62.402072
B10: Take Rate (Rev/GB) | D10: =Historico!H32 -> 0.3068136 | E10: =Historico!I32 -> 0.30431706 | F10: =Hipotesis!G23 -> 0.26 | G10: =Hipotesis!H23 -> 0.27 | H10: =Hipotesis!I23 -> 0.275 | I10: =Hipotesis!J23 -> 0.28 | J10: =Hipotesis!K23 -> 0.28 | L10: 0.29 | M10: =(($D$82-$J$81+(((((($J$7*M$8)*$L10)+($J$62-$J$15))*(1-Hipotesis!$D$10))-((($J$67-$J$11+($J$7*M$8))-$I$67)/Hipotesis!$D$40))/(1+Hipotesis!$D$14)^5))+((((((($J$7*M$8)*$L10)+($J$62-$J$15))*(1-Hipotesis!$D$10))-((($J$67-$J$11+($J$7*M$8))-$I$67)/Hipotesis!$D$40))*(1+Hipotesis!$D$15)/(Hipotesis!$D$14-Hipotesis!$D$15))/(1+Hipotesis!$D$14)^5)+(Hipotesis!$D$49+Hipotesis!$D$50-Hipotesis!$D$51+Hipotesis!$D$52+Hipotesis!$D$53-Hipotesis!$D$54))/Hipotesis!$D$46*1000 -> 64.950933 | N10: =(($D$82-$J$81+(((((($J$7*N$8)*$L10)+($J$62-$J$15))*(1-Hipotesis!$D$10))-((($J$67-$J$11+($J$7*N$8))-$I$67)/Hipotesis!$D$40))/(1+Hipotesis!$D$14)^5))+((((((($J$7*N$8)*$L10)+($J$62-$J$15))*(1-Hipotesis!$D$10))-((($J$67-$J$11+($J$7*N$8))-$I$67)/Hipotesis!$D$40))*(1+Hipotesis!$D$15)/(Hipotesis!$D$14-Hipotesis!$D$15))/(1+Hipotesis!$D$14)^5)+(Hipotesis!$D$49+Hipotesis!$D$50-Hipotesis!$D$51+Hipotesis!$D$52+Hipotesis!$D$53-Hipotesis!$D$54))/Hipotesis!$D$46*1000 -> 65.149093 | O10: =(($D$82-$J$81+(((((($J$7*O$8)*$L10)+($J$62-$J$15))*(1-Hipotesis!$D$10))-((($J$67-$J$11+($J$7*O$8))-$I$67)/Hipotesis!$D$40))/(1+Hipotesis!$D$14)^5))+((((((($J$7*O$8)*$L10)+($J$62-$J$15))*(1-Hipotesis!$D$10))-((($J$67-$J$11+($J$7*O$8))-$I$67)/Hipotesis!$D$40))*(1+Hipotesis!$D$15)/(Hipotesis!$D$14-Hipotesis!$D$15))/(1+Hipotesis!$D$14)^5)+(Hipotesis!$D$49+Hipotesis!$D$50-Hipotesis!$D$51+Hipotesis!$D$52+Hipotesis!$D$53-Hipotesis!$D$54))/Hipotesis!$D$46*1000 -> 65.347254 | P10: =(($D$82-$J$81+(((((($J$7*P$8)*$L10)+($J$62-$J$15))*(1-Hipotesis!$D$10))-((($J$67-$J$11+($J$7*P$8))-$I$67)/Hipotesis!$D$40))/(1+Hipotesis!$D$14)^5))+((((((($J$7*P$8)*$L10)+($J$62-$J$15))*(1-Hipotesis!$D$10))-((($J$67-$J$11+($J$7*P$8))-$I$67)/Hipotesis!$D$40))*(1+Hipotesis!$D$15)/(Hipotesis!$D$14-Hipotesis!$D$15))/(1+Hipotesis!$D$14)^5)+(Hipotesis!$D$49+Hipotesis!$D$50-Hipotesis!$D$51+Hipotesis!$D$52+Hipotesis!$D$53-Hipotesis!$D$54))/Hipotesis!$D$46*1000 -> 65.545415 | Q10: =(($D$82-$J$81+(((((($J$7*Q$8)*$L10)+($J$62-$J$15))*(1-Hipotesis!$D$10))-((($J$67-$J$11+($J$7*Q$8))-$I$67)/Hipotesis!$D$40))/(1+Hipotesis!$D$14)^5))+((((((($J$7*Q$8)*$L10)+($J$62-$J$15))*(1-Hipotesis!$D$10))-((($J$67-$J$11+($J$7*Q$8))-$I$67)/Hipotesis!$D$40))*(1+Hipotesis!$D$15)/(Hipotesis!$D$14-Hipotesis!$D$15))/(1+Hipotesis!$D$14)^5)+(Hipotesis!$D$49+Hipotesis!$D$50-Hipotesis!$D$51+Hipotesis!$D$52+Hipotesis!$D$53-Hipotesis!$D$54))/Hipotesis!$D$46*1000 -> 65.743575 | R10: =(($D$82-$J$81+(((((($J$7*R$8)*$L10)+($J$62-$J$15))*(1-Hipotesis!$D$10))-((($J$67-$J$11+($J$7*R$8))-$I$67)/Hipotesis!$D$40))/(1+Hipotesis!$D$14)^5))+((((((($J$7*R$8)*$L10)+($J$62-$J$15))*(1-Hipotesis!$D$10))-((($J$67-$J$11+($J$7*R$8))-$I$67)/Hipotesis!$D$40))*(1+Hipotesis!$D$15)/(Hipotesis!$D$14-Hipotesis!$D$15))/(1+Hipotesis!$D$14)^5)+(Hipotesis!$D$49+Hipotesis!$D$50-Hipotesis!$D$51+Hipotesis!$D$52+Hipotesis!$D$53-Hipotesis!$D$54))/Hipotesis!$D$46*1000 -> 65.941736
B11: Revenue ($M) | D11: =D7*D10 -> 25086 | E11: =E7*E10 -> 29670 | F11: =F7*F10 -> 30419.064 | G11: =G7*G10 -> 36643.272 | H11: =H7*H10 -> 42173.692 | I11: =I7*I10 -> 47663.94 | J11: =J7*J10 -> 51953.695 | L11: 0.31 | M11: =(($D$82-$J$81+(((((($J$7*M$8)*$L11)+($J$62-$J$15))*(1-Hipotesis!$D$10))-((($J$67-$J$11+($J$7*M$8))-$I$67)/Hipotesis!$D$40))/(1+Hipotesis!$D$14)^5))+((((((($J$7*M$8)*$L11)+($J$62-$J$15))*(1-Hipotesis!$D$10))-((($J$67-$J$11+($J$7*M$8))-$I$67)/Hipotesis!$D$40))*(1+Hipotesis!$D$15)/(Hipotesis!$D$14-Hipotesis!$D$15))/(1+Hipotesis!$D$14)^5)+(Hipotesis!$D$49+Hipotesis!$D$50-Hipotesis!$D$51+Hipotesis!$D$52+Hipotesis!$D$53-Hipotesis!$D$54))/Hipotesis!$D$46*1000 -> 67.900652 | N11: =(($D$82-$J$81+(((((($J$7*N$8)*$L11)+($J$62-$J$15))*(1-Hipotesis!$D$10))-((($J$67-$J$11+($J$7*N$8))-$I$67)/Hipotesis!$D$40))/(1+Hipotesis!$D$14)^5))+((((((($J$7*N$8)*$L11)+($J$62-$J$15))*(1-Hipotesis!$D$10))-((($J$67-$J$11+($J$7*N$8))-$I$67)/Hipotesis!$D$40))*(1+Hipotesis!$D$15)/(Hipotesis!$D$14-Hipotesis!$D$15))/(1+Hipotesis!$D$14)^5)+(Hipotesis!$D$49+Hipotesis!$D$50-Hipotesis!$D$51+Hipotesis!$D$52+Hipotesis!$D$53-Hipotesis!$D$54))/Hipotesis!$D$46*1000 -> 68.216802 | O11: =(($D$82-$J$81+(((((($J$7*O$8)*$L11)+($J$62-$J$15))*(1-Hipotesis!$D$10))-((($J$67-$J$11+($J$7*O$8))-$I$67)/Hipotesis!$D$40))/(1+Hipotesis!$D$14)^5))+((((((($J$7*O$8)*$L11)+($J$62-$J$15))*(1-Hipotesis!$D$10))-((($J$67-$J$11+($J$7*O$8))-$I$67)/Hipotesis!$D$40))*(1+Hipotesis!$D$15)/(Hipotesis!$D$14-Hipotesis!$D$15))/(1+Hipotesis!$D$14)^5)+(Hipotesis!$D$49+Hipotesis!$D$50-Hipotesis!$D$51+Hipotesis!$D$52+Hipotesis!$D$53-Hipotesis!$D$54))/Hipotesis!$D$46*1000 -> 68.532951 | P11: =(($D$82-$J$81+(((((($J$7*P$8)*$L11)+($J$62-$J$15))*(1-Hipotesis!$D$10))-((($J$67-$J$11+($J$7*P$8))-$I$67)/Hipotesis!$D$40))/(1+Hipotesis!$D$14)^5))+((((((($J$7*P$8)*$L11)+($J$62-$J$15))*(1-Hipotesis!$D$10))-((($J$67-$J$11+($J$7*P$8))-$I$67)/Hipotesis!$D$40))*(1+Hipotesis!$D$15)/(Hipotesis!$D$14-Hipotesis!$D$15))/(1+Hipotesis!$D$14)^5)+(Hipotesis!$D$49+Hipotesis!$D$50-Hipotesis!$D$51+Hipotesis!$D$52+Hipotesis!$D$53-Hipotesis!$D$54))/Hipotesis!$D$46*1000 -> 68.849101 | Q11: =(($D$82-$J$81+(((((($J$7*Q$8)*$L11)+($J$62-$J$15))*(1-Hipotesis!$D$10))-((($J$67-$J$11+($J$7*Q$8))-$I$67)/Hipotesis!$D$40))/(1+Hipotesis!$D$14)^5))+((((((($J$7*Q$8)*$L11)+($J$62-$J$15))*(1-Hipotesis!$D$10))-((($J$67-$J$11+($J$7*Q$8))-$I$67)/Hipotesis!$D$40))*(1+Hipotesis!$D$15)/(Hipotesis!$D$14-Hipotesis!$D$15))/(1+Hipotesis!$D$14)^5)+(Hipotesis!$D$49+Hipotesis!$D$50-Hipotesis!$D$51+Hipotesis!$D$52+Hipotesis!$D$53-Hipotesis!$D$54))/Hipotesis!$D$46*1000 -> 69.16525 | R11: =(($D$82-$J$81+(((((($J$7*R$8)*$L11)+($J$62-$J$15))*(1-Hipotesis!$D$10))-((($J$67-$J$11+($J$7*R$8))-$I$67)/Hipotesis!$D$40))/(1+Hipotesis!$D$14)^5))+((((((($J$7*R$8)*$L11)+($J$62-$J$15))*(1-Hipotesis!$D$10))-((($J$67-$J$11+($J$7*R$8))-$I$67)/Hipotesis!$D$40))*(1+Hipotesis!$D$15)/(Hipotesis!$D$14-Hipotesis!$D$15))/(1+Hipotesis!$D$14)^5)+(Hipotesis!$D$49+Hipotesis!$D$50-Hipotesis!$D$51+Hipotesis!$D$52+Hipotesis!$D$53-Hipotesis!$D$54))/Hipotesis!$D$46*1000 -> 69.4814
B12: YoY % | E12: =E11/D11-1 -> 0.1827314 | F12: =F11/E11-1 -> 0.025246512 | G12: =G11/F11-1 -> 0.20461538 | H12: =H11/G11-1 -> 0.15092593 | I12: =I11/H11-1 -> 0.13018182 | J12: =J11/I11-1 -> 0.09 | L12: 0.33 | M12: =(($D$82-$J$81+(((((($J$7*M$8)*$L12)+($J$62-$J$15))*(1-Hipotesis!$D$10))-((($J$67-$J$11+($J$7*M$8))-$I$67)/Hipotesis!$D$40))/(1+Hipotesis!$D$14)^5))+((((((($J$7*M$8)*$L12)+($J$62-$J$15))*(1-Hipotesis!$D$10))-((($J$67-$J$11+($J$7*M$8))-$I$67)/Hipotesis!$D$40))*(1+Hipotesis!$D$15)/(Hipotesis!$D$14-Hipotesis!$D$15))/(1+Hipotesis!$D$14)^5)+(Hipotesis!$D$49+Hipotesis!$D$50-Hipotesis!$D$51+Hipotesis!$D$52+Hipotesis!$D$53-Hipotesis!$D$54))/Hipotesis!$D$46*1000 -> 70.850372 | N12: =(($D$82-$J$81+(((((($J$7*N$8)*$L12)+($J$62-$J$15))*(1-Hipotesis!$D$10))-((($J$67-$J$11+($J$7*N$8))-$I$67)/Hipotesis!$D$40))/(1+Hipotesis!$D$14)^5))+((((((($J$7*N$8)*$L12)+($J$62-$J$15))*(1-Hipotesis!$D$10))-((($J$67-$J$11+($J$7*N$8))-$I$67)/Hipotesis!$D$40))*(1+Hipotesis!$D$15)/(Hipotesis!$D$14-Hipotesis!$D$15))/(1+Hipotesis!$D$14)^5)+(Hipotesis!$D$49+Hipotesis!$D$50-Hipotesis!$D$51+Hipotesis!$D$52+Hipotesis!$D$53-Hipotesis!$D$54))/Hipotesis!$D$46*1000 -> 71.284511 | O12: =(($D$82-$J$81+(((((($J$7*O$8)*$L12)+($J$62-$J$15))*(1-Hipotesis!$D$10))-((($J$67-$J$11+($J$7*O$8))-$I$67)/Hipotesis!$D$40))/(1+Hipotesis!$D$14)^5))+((((((($J$7*O$8)*$L12)+($J$62-$J$15))*(1-Hipotesis!$D$10))-((($J$67-$J$11+($J$7*O$8))-$I$67)/Hipotesis!$D$40))*(1+Hipotesis!$D$15)/(Hipotesis!$D$14-Hipotesis!$D$15))/(1+Hipotesis!$D$14)^5)+(Hipotesis!$D$49+Hipotesis!$D$50-Hipotesis!$D$51+Hipotesis!$D$52+Hipotesis!$D$53-Hipotesis!$D$54))/Hipotesis!$D$46*1000 -> 71.718649 | P12: =(($D$82-$J$81+(((((($J$7*P$8)*$L12)+($J$62-$J$15))*(1-Hipotesis!$D$10))-((($J$67-$J$11+($J$7*P$8))-$I$67)/Hipotesis!$D$40))/(1+Hipotesis!$D$14)^5))+((((((($J$7*P$8)*$L12)+($J$62-$J$15))*(1-Hipotesis!$D$10))-((($J$67-$J$11+($J$7*P$8))-$I$67)/Hipotesis!$D$40))*(1+Hipotesis!$D$15)/(Hipotesis!$D$14-Hipotesis!$D$15))/(1+Hipotesis!$D$14)^5)+(Hipotesis!$D$49+Hipotesis!$D$50-Hipotesis!$D$51+Hipotesis!$D$52+Hipotesis!$D$53-Hipotesis!$D$54))/Hipotesis!$D$46*1000 -> 72.152787 | Q12: =(($D$82-$J$81+(((((($J$7*Q$8)*$L12)+($J$62-$J$15))*(1-Hipotesis!$D$10))-((($J$67-$J$11+($J$7*Q$8))-$I$67)/Hipotesis!$D$40))/(1+Hipotesis!$D$14)^5))+((((((($J$7*Q$8)*$L12)+($J$62-$J$15))*(1-Hipotesis!$D$10))-((($J$67-$J$11+($J$7*Q$8))-$I$67)/Hipotesis!$D$40))*(1+Hipotesis!$D$15)/(Hipotesis!$D$14-Hipotesis!$D$15))/(1+Hipotesis!$D$14)^5)+(Hipotesis!$D$49+Hipotesis!$D$50-Hipotesis!$D$51+Hipotesis!$D$52+Hipotesis!$D$53-Hipotesis!$D$54))/Hipotesis!$D$46*1000 -> 72.586925 | R12: =(($D$82-$J$81+(((((($J$7*R$8)*$L12)+($J$62-$J$15))*(1-Hipotesis!$D$10))-((($J$67-$J$11+($J$7*R$8))-$I$67)/Hipotesis!$D$40))/(1+Hipotesis!$D$14)^5))+((((((($J$7*R$8)*$L12)+($J$62-$J$15))*(1-Hipotesis!$D$10))-((($J$67-$J$11+($J$7*R$8))-$I$67)/Hipotesis!$D$40))*(1+Hipotesis!$D$15)/(Hipotesis!$D$14-Hipotesis!$D$15))/(1+Hipotesis!$D$14)^5)+(Hipotesis!$D$49+Hipotesis!$D$50-Hipotesis!$D$51+Hipotesis!$D$52+Hipotesis!$D$53-Hipotesis!$D$54))/Hipotesis!$D$46*1000 -> 73.021064
L13: 0.35 | M13: =(($D$82-$J$81+(((((($J$7*M$8)*$L13)+($J$62-$J$15))*(1-Hipotesis!$D$10))-((($J$67-$J$11+($J$7*M$8))-$I$67)/Hipotesis!$D$40))/(1+Hipotesis!$D$14)^5))+((((((($J$7*M$8)*$L13)+($J$62-$J$15))*(1-Hipotesis!$D$10))-((($J$67-$J$11+($J$7*M$8))-$I$67)/Hipotesis!$D$40))*(1+Hipotesis!$D$15)/(Hipotesis!$D$14-Hipotesis!$D$15))/(1+Hipotesis!$D$14)^5)+(Hipotesis!$D$49+Hipotesis!$D$50-Hipotesis!$D$51+Hipotesis!$D$52+Hipotesis!$D$53-Hipotesis!$D$54))/Hipotesis!$D$46*1000 -> 73.800092 | N13: =(($D$82-$J$81+(((((($J$7*N$8)*$L13)+($J$62-$J$15))*(1-Hipotesis!$D$10))-((($J$67-$J$11+($J$7*N$8))-$I$67)/Hipotesis!$D$40))/(1+Hipotesis!$D$14)^5))+((((((($J$7*N$8)*$L13)+($J$62-$J$15))*(1-Hipotesis!$D$10))-((($J$67-$J$11+($J$7*N$8))-$I$67)/Hipotesis!$D$40))*(1+Hipotesis!$D$15)/(Hipotesis!$D$14-Hipotesis!$D$15))/(1+Hipotesis!$D$14)^5)+(Hipotesis!$D$49+Hipotesis!$D$50-Hipotesis!$D$51+Hipotesis!$D$52+Hipotesis!$D$53-Hipotesis!$D$54))/Hipotesis!$D$46*1000 -> 74.352219 | O13: =(($D$82-$J$81+(((((($J$7*O$8)*$L13)+($J$62-$J$15))*(1-Hipotesis!$D$10))-((($J$67-$J$11+($J$7*O$8))-$I$67)/Hipotesis!$D$40))/(1+Hipotesis!$D$14)^5))+((((((($J$7*O$8)*$L13)+($J$62-$J$15))*(1-Hipotesis!$D$10))-((($J$67-$J$11+($J$7*O$8))-$I$67)/Hipotesis!$D$40))*(1+Hipotesis!$D$15)/(Hipotesis!$D$14-Hipotesis!$D$15))/(1+Hipotesis!$D$14)^5)+(Hipotesis!$D$49+Hipotesis!$D$50-Hipotesis!$D$51+Hipotesis!$D$52+Hipotesis!$D$53-Hipotesis!$D$54))/Hipotesis!$D$46*1000 -> 74.904346 | P13: =(($D$82-$J$81+(((((($J$7*P$8)*$L13)+($J$62-$J$15))*(1-Hipotesis!$D$10))-((($J$67-$J$11+($J$7*P$8))-$I$67)/Hipotesis!$D$40))/(1+Hipotesis!$D$14)^5))+((((((($J$7*P$8)*$L13)+($J$62-$J$15))*(1-Hipotesis!$D$10))-((($J$67-$J$11+($J$7*P$8))-$I$67)/Hipotesis!$D$40))*(1+Hipotesis!$D$15)/(Hipotesis!$D$14-Hipotesis!$D$15))/(1+Hipotesis!$D$14)^5)+(Hipotesis!$D$49+Hipotesis!$D$50-Hipotesis!$D$51+Hipotesis!$D$52+Hipotesis!$D$53-Hipotesis!$D$54))/Hipotesis!$D$46*1000 -> 75.456474 | Q13: =(($D$82-$J$81+(((((($J$7*Q$8)*$L13)+($J$62-$J$15))*(1-Hipotesis!$D$10))-((($J$67-$J$11+($J$7*Q$8))-$I$67)/Hipotesis!$D$40))/(1+Hipotesis!$D$14)^5))+((((((($J$7*Q$8)*$L13)+($J$62-$J$15))*(1-Hipotesis!$D$10))-((($J$67-$J$11+($J$7*Q$8))-$I$67)/Hipotesis!$D$40))*(1+Hipotesis!$D$15)/(Hipotesis!$D$14-Hipotesis!$D$15))/(1+Hipotesis!$D$14)^5)+(Hipotesis!$D$49+Hipotesis!$D$50-Hipotesis!$D$51+Hipotesis!$D$52+Hipotesis!$D$53-Hipotesis!$D$54))/Hipotesis!$D$46*1000 -> 76.008601 | R13: =(($D$82-$J$81+(((((($J$7*R$8)*$L13)+($J$62-$J$15))*(1-Hipotesis!$D$10))-((($J$67-$J$11+($J$7*R$8))-$I$67)/Hipotesis!$D$40))/(1+Hipotesis!$D$14)^5))+((((((($J$7*R$8)*$L13)+($J$62-$J$15))*(1-Hipotesis!$D$10))-((($J$67-$J$11+($J$7*R$8))-$I$67)/Hipotesis!$D$40))*(1+Hipotesis!$D$15)/(Hipotesis!$D$14-Hipotesis!$D$15))/(1+Hipotesis!$D$14)^5)+(Hipotesis!$D$49+Hipotesis!$D$50-Hipotesis!$D$51+Hipotesis!$D$52+Hipotesis!$D$53-Hipotesis!$D$54))/Hipotesis!$D$46*1000 -> 76.560728
B14: Op Margin (% revenue) | D14: 0.232 | E14: 0.241 | F14: =Hipotesis!G24 -> 0.3 | G14: =Hipotesis!H24 -> 0.315 | H14: =Hipotesis!I24 -> 0.325 | I14: =Hipotesis!J24 -> 0.33 | J14: =Hipotesis!K24 -> 0.335 | L14: 0.37 | M14: =(($D$82-$J$81+(((((($J$7*M$8)*$L14)+($J$62-$J$15))*(1-Hipotesis!$D$10))-((($J$67-$J$11+($J$7*M$8))-$I$67)/Hipotesis!$D$40))/(1+Hipotesis!$D$14)^5))+((((((($J$7*M$8)*$L14)+($J$62-$J$15))*(1-Hipotesis!$D$10))-((($J$67-$J$11+($J$7*M$8))-$I$67)/Hipotesis!$D$40))*(1+Hipotesis!$D$15)/(Hipotesis!$D$14-Hipotesis!$D$15))/(1+Hipotesis!$D$14)^5)+(Hipotesis!$D$49+Hipotesis!$D$50-Hipotesis!$D$51+Hipotesis!$D$52+Hipotesis!$D$53-Hipotesis!$D$54))/Hipotesis!$D$46*1000 -> 76.749812 | N14: =(($D$82-$J$81+(((((($J$7*N$8)*$L14)+($J$62-$J$15))*(1-Hipotesis!$D$10))-((($J$67-$J$11+($J$7*N$8))-$I$67)/Hipotesis!$D$40))/(1+Hipotesis!$D$14)^5))+((((((($J$7*N$8)*$L14)+($J$62-$J$15))*(1-Hipotesis!$D$10))-((($J$67-$J$11+($J$7*N$8))-$I$67)/Hipotesis!$D$40))*(1+Hipotesis!$D$15)/(Hipotesis!$D$14-Hipotesis!$D$15))/(1+Hipotesis!$D$14)^5)+(Hipotesis!$D$49+Hipotesis!$D$50-Hipotesis!$D$51+Hipotesis!$D$52+Hipotesis!$D$53-Hipotesis!$D$54))/Hipotesis!$D$46*1000 -> 77.419928 | O14: =(($D$82-$J$81+(((((($J$7*O$8)*$L14)+($J$62-$J$15))*(1-Hipotesis!$D$10))-((($J$67-$J$11+($J$7*O$8))-$I$67)/Hipotesis!$D$40))/(1+Hipotesis!$D$14)^5))+((((((($J$7*O$8)*$L14)+($J$62-$J$15))*(1-Hipotesis!$D$10))-((($J$67-$J$11+($J$7*O$8))-$I$67)/Hipotesis!$D$40))*(1+Hipotesis!$D$15)/(Hipotesis!$D$14-Hipotesis!$D$15))/(1+Hipotesis!$D$14)^5)+(Hipotesis!$D$49+Hipotesis!$D$50-Hipotesis!$D$51+Hipotesis!$D$52+Hipotesis!$D$53-Hipotesis!$D$54))/Hipotesis!$D$46*1000 -> 78.090044 | P14: =(($D$82-$J$81+(((((($J$7*P$8)*$L14)+($J$62-$J$15))*(1-Hipotesis!$D$10))-((($J$67-$J$11+($J$7*P$8))-$I$67)/Hipotesis!$D$40))/(1+Hipotesis!$D$14)^5))+((((((($J$7*P$8)*$L14)+($J$62-$J$15))*(1-Hipotesis!$D$10))-((($J$67-$J$11+($J$7*P$8))-$I$67)/Hipotesis!$D$40))*(1+Hipotesis!$D$15)/(Hipotesis!$D$14-Hipotesis!$D$15))/(1+Hipotesis!$D$14)^5)+(Hipotesis!$D$49+Hipotesis!$D$50-Hipotesis!$D$51+Hipotesis!$D$52+Hipotesis!$D$53-Hipotesis!$D$54))/Hipotesis!$D$46*1000 -> 78.76016 | Q14: =(($D$82-$J$81+(((((($J$7*Q$8)*$L14)+($J$62-$J$15))*(1-Hipotesis!$D$10))-((($J$67-$J$11+($J$7*Q$8))-$I$67)/Hipotesis!$D$40))/(1+Hipotesis!$D$14)^5))+((((((($J$7*Q$8)*$L14)+($J$62-$J$15))*(1-Hipotesis!$D$10))-((($J$67-$J$11+($J$7*Q$8))-$I$67)/Hipotesis!$D$40))*(1+Hipotesis!$D$15)/(Hipotesis!$D$14-Hipotesis!$D$15))/(1+Hipotesis!$D$14)^5)+(Hipotesis!$D$49+Hipotesis!$D$50-Hipotesis!$D$51+Hipotesis!$D$52+Hipotesis!$D$53-Hipotesis!$D$54))/Hipotesis!$D$46*1000 -> 79.430276 | R14: =(($D$82-$J$81+(((((($J$7*R$8)*$L14)+($J$62-$J$15))*(1-Hipotesis!$D$10))-((($J$67-$J$11+($J$7*R$8))-$I$67)/Hipotesis!$D$40))/(1+Hipotesis!$D$14)^5))+((((((($J$7*R$8)*$L14)+($J$62-$J$15))*(1-Hipotesis!$D$10))-((($J$67-$J$11+($J$7*R$8))-$I$67)/Hipotesis!$D$40))*(1+Hipotesis!$D$15)/(Hipotesis!$D$14-Hipotesis!$D$15))/(1+Hipotesis!$D$14)^5)+(Hipotesis!$D$49+Hipotesis!$D$50-Hipotesis!$D$51+Hipotesis!$D$52+Hipotesis!$D$53-Hipotesis!$D$54))/Hipotesis!$D$46*1000 -> 80.100392
B15: Segment Op Income ($M) | D15: =D11*D14 -> 5819.952 | E15: =E11*E14 -> 7150.47 | F15: =F11*F14 -> 9125.7192 | G15: =G11*G14 -> 11542.631 | H15: =H11*H14 -> 13706.45 | I15: =I11*I14 -> 15729.1 | J15: =J11*J14 -> 17404.488
B16: % de GB (margen sobre actividad) | D16: =D15/D7 -> 0.071180754 | E16: =E15/E7 -> 0.07334041 | F16: =F15/F7 -> 0.078 | G16: =G15/G7 -> 0.08505 | H16: =H15/H7 -> 0.089375 | I16: =I15/I7 -> 0.0924 | J16: =J15/J7 -> 0.0938 | L16: Caso base aprox: TR 28%, margen 33%. El resto de drivers se mantiene en base.
A18: B. DELIVERY (bloque secundario)
B19: Gross Bookings ($M) | D19: =Historico!H35 -> 75144 | E19: =Historico!I35 -> 90864 | F19: =E19*(1+Hipotesis!G27) -> 110854.08 | G19: =F19*(1+Hipotesis!H27) -> 130807.81 | H19: =G19*(1+Hipotesis!I27) -> 149120.91 | I19: =H19*(1+Hipotesis!J27) -> 165524.21 | J19: =I19*(1+Hipotesis!K27) -> 180421.39
B20: YoY % | E20: =E19/D19-1 -> 0.20919834 | F20: =F19/E19-1 -> 0.22 | G20: =G19/F19-1 -> 0.18 | H20: =H19/G19-1 -> 0.14 | I20: =I19/H19-1 -> 0.11 | J20: =J19/I19-1 -> 0.09
B22: Take Rate | D22: =Historico!H37 -> 0.18291547 | E22: =Historico!I37 -> 0.18982215 | F22: =Hipotesis!G28 -> 0.195 | G22: =Hipotesis!H28 -> 0.198 | H22: =Hipotesis!I28 -> 0.2 | I22: =Hipotesis!J28 -> 0.2 | J22: =Hipotesis!K28 -> 0.2
B23: Revenue ($M) | D23: =D19*D22 -> 13745 | E23: =E19*E22 -> 17248 | F23: =F19*F22 -> 21616.546 | G23: =G19*G22 -> 25899.947 | H23: =H19*H22 -> 29824.182 | I23: =I19*I22 -> 33104.842 | J23: =J19*J22 -> 36084.277
B25: Op Margin (% revenue) | D25: 0.183 | E25: 0.207 | F25: =Hipotesis!G29 -> 0.19 | G25: =Hipotesis!H29 -> 0.205 | H25: =Hipotesis!I29 -> 0.215 | I25: =Hipotesis!J29 -> 0.22 | J25: =Hipotesis!K29 -> 0.225
B26: Segment Op Income ($M) | D26: =D23*D25 -> 2515.335 | E26: =E23*E25 -> 3570.336 | F26: =F23*F25 -> 4107.1437 | G26: =G23*G25 -> 5309.4892 | H26: =H23*H25 -> 6412.1991 | I26: =I23*I25 -> 7283.0652 | J26: =J23*J25 -> 8118.9624
A28: C. FREIGHT (modelar conservador)
B29: Gross Bookings ($M) | D29: =Historico!H40 -> 5277 | E29: =Historico!I40 -> 5141 | F29: =E29*(1+Hipotesis!G32) -> 5398.05 | G29: =F29*(1+Hipotesis!H32) -> 5667.9525 | H29: =G29*(1+Hipotesis!I32) -> 5894.6706 | I29: =H29*(1+Hipotesis!J32) -> 6071.5107 | J29: =I29*(1+Hipotesis!K32) -> 6253.656
B31: Take Rate (~100%) | D31: =1 -> 1 | E31: =1 -> 1 | F31: =Hipotesis!G33 -> 1 | G31: =Hipotesis!H33 -> 1 | H31: =Hipotesis!I33 -> 1 | I31: =Hipotesis!J33 -> 1 | J31: =Hipotesis!K33 -> 1
B32: Revenue ($M) | D32: =D29*D31 -> 5277 | E32: =E29*E31 -> 5141 | F32: =F29*F31 -> 5398.05 | G32: =G29*G31 -> 5667.9525 | H32: =H29*H31 -> 5894.6706 | I32: =I29*I31 -> 6071.5107 | J32: =J29*J31 -> 6253.656
B34: Op Margin (% revenue) | D34: -0.021 | E34: -0.006 | F34: =Hipotesis!G34 -> -0.015 | G34: =Hipotesis!H34 -> 0 | H34: =Hipotesis!I34 -> 0.005 | I34: =Hipotesis!J34 -> 0.01 | J34: =Hipotesis!K34 -> 0.015
B35: Segment Op Income ($M) | D35: =D32*D34 -> -110.817 | E35: =E32*E34 -> -30.846 | F35: =F32*F34 -> -80.97075 | G35: =G32*G34 -> 0 | H35: =H32*H34 -> 29.473353 | I35: =I32*I34 -> 60.715107 | J35: =J32*J34 -> 93.804841
A37: D. CORPORATE OVERHEAD (driver de overhead dilution) | L37: Sens D. Overhead (% GB) × WACC (precio implicito $)
B38: Total Gross Bookings ($M) | D38: =D7+D19+D29 -> 162184 | E38: =E7+E19+E29 -> 193502 | F38: =F7+F19+F29 -> 233248.53 | G38: =G7+G19+G29 -> 272191.59 | H38: =H7+H19+H29 -> 308374.46 | I38: =I7+I19+I29 -> 341824.08 | J38: =J7+J19+J29 -> 372223.95 | L38: Overhead ↓ WACC →
B39: Corporate cost (% GB) | D39: 0.0207 | E39: 0.0206 | F39: =Hipotesis!G37 -> 0.02 | G39: =Hipotesis!H37 -> 0.018 | H39: =Hipotesis!I37 -> 0.016 | I39: =Hipotesis!J37 -> 0.015 | J39: =Hipotesis!K37 -> 0.014 | M39: 0.085 | N39: 0.092 | O39: 0.098 | P39: 0.105 | Q39: 0.112 | R39: 0.118
B40: Corporate cost ($M) | D40: =-D38*D39 -> -3357.2088 | E40: =-E38*E39 -> -3986.1412 | F40: =-F38*F39 -> -4664.9706 | G40: =-G38*G39 -> -4899.4486 | H40: =-H38*H39 -> -4933.9914 | I40: =-I38*I39 -> -5127.3612 | J40: =-J38*J39 -> -5211.1353 | L40: 0.005 | M40: =(($F$75/(1+M$39)^1+$G$75/(1+M$39)^2+$H$75/(1+M$39)^3+$I$75/(1+M$39)^4+((($J$62+(-$J$40-($L40*$J$38)))*(1-Hipotesis!$D$10))-(($J$67-$I$67)/Hipotesis!$D$40))/(1+M$39)^5)+((((($J$62+(-$J$40-($L40*$J$38)))*(1-Hipotesis!$D$10))-(($J$67-$I$67)/Hipotesis!$D$40))*(1+Hipotesis!$D$15)/(M$39-Hipotesis!$D$15))/(1+M$39)^5)+(Hipotesis!$D$49+Hipotesis!$D$50-Hipotesis!$D$51+Hipotesis!$D$52+Hipotesis!$D$53-Hipotesis!$D$54))/Hipotesis!$D$46*1000 -> 113.73861 | N40: =(($F$75/(1+N$39)^1+$G$75/(1+N$39)^2+$H$75/(1+N$39)^3+$I$75/(1+N$39)^4+((($J$62+(-$J$40-($L40*$J$38)))*(1-Hipotesis!$D$10))-(($J$67-$I$67)/Hipotesis!$D$40))/(1+N$39)^5)+((((($J$62+(-$J$40-($L40*$J$38)))*(1-Hipotesis!$D$10))-(($J$67-$I$67)/Hipotesis!$D$40))*(1+Hipotesis!$D$15)/(N$39-Hipotesis!$D$15))/(1+N$39)^5)+(Hipotesis!$D$49+Hipotesis!$D$50-Hipotesis!$D$51+Hipotesis!$D$52+Hipotesis!$D$53-Hipotesis!$D$54))/Hipotesis!$D$46*1000 -> 100.91974 | O40: =(($F$75/(1+O$39)^1+$G$75/(1+O$39)^2+$H$75/(1+O$39)^3+$I$75/(1+O$39)^4+((($J$62+(-$J$40-($L40*$J$38)))*(1-Hipotesis!$D$10))-(($J$67-$I$67)/Hipotesis!$D$40))/(1+O$39)^5)+((((($J$62+(-$J$40-($L40*$J$38)))*(1-Hipotesis!$D$10))-(($J$67-$I$67)/Hipotesis!$D$40))*(1+Hipotesis!$D$15)/(O$39-Hipotesis!$D$15))/(1+O$39)^5)+(Hipotesis!$D$49+Hipotesis!$D$50-Hipotesis!$D$51+Hipotesis!$D$52+Hipotesis!$D$53-Hipotesis!$D$54))/Hipotesis!$D$46*1000 -> 91.910078 | P40: =(($F$75/(1+P$39)^1+$G$75/(1+P$39)^2+$H$75/(1+P$39)^3+$I$75/(1+P$39)^4+((($J$62+(-$J$40-($L40*$J$38)))*(1-Hipotesis!$D$10))-(($J$67-$I$67)/Hipotesis!$D$40))/(1+P$39)^5)+((((($J$62+(-$J$40-($L40*$J$38)))*(1-Hipotesis!$D$10))-(($J$67-$I$67)/Hipotesis!$D$40))*(1+Hipotesis!$D$15)/(P$39-Hipotesis!$D$15))/(1+P$39)^5)+(Hipotesis!$D$49+Hipotesis!$D$50-Hipotesis!$D$51+Hipotesis!$D$52+Hipotesis!$D$53-Hipotesis!$D$54))/Hipotesis!$D$46*1000 -> 83.128776 | Q40: =(($F$75/(1+Q$39)^1+$G$75/(1+Q$39)^2+$H$75/(1+Q$39)^3+$I$75/(1+Q$39)^4+((($J$62+(-$J$40-($L40*$J$38)))*(1-Hipotesis!$D$10))-(($J$67-$I$67)/Hipotesis!$D$40))/(1+Q$39)^5)+((((($J$62+(-$J$40-($L40*$J$38)))*(1-Hipotesis!$D$10))-(($J$67-$I$67)/Hipotesis!$D$40))*(1+Hipotesis!$D$15)/(Q$39-Hipotesis!$D$15))/(1+Q$39)^5)+(Hipotesis!$D$49+Hipotesis!$D$50-Hipotesis!$D$51+Hipotesis!$D$52+Hipotesis!$D$53-Hipotesis!$D$54))/Hipotesis!$D$46*1000 -> 75.781525 | R40: =(($F$75/(1+R$39)^1+$G$75/(1+R$39)^2+$H$75/(1+R$39)^3+$I$75/(1+R$39)^4+((($J$62+(-$J$40-($L40*$J$38)))*(1-Hipotesis!$D$10))-(($J$67-$I$67)/Hipotesis!$D$40))/(1+R$39)^5)+((((($J$62+(-$J$40-($L40*$J$38)))*(1-Hipotesis!$D$10))-(($J$67-$I$67)/Hipotesis!$D$40))*(1+Hipotesis!$D$15)/(R$39-Hipotesis!$D$15))/(1+R$39)^5)+(Hipotesis!$D$49+Hipotesis!$D$50-Hipotesis!$D$51+Hipotesis!$D$52+Hipotesis!$D$53-Hipotesis!$D$54))/Hipotesis!$D$46*1000 -> 70.379306
L41: 0.01 | M41: =(($F$75/(1+M$39)^1+$G$75/(1+M$39)^2+$H$75/(1+M$39)^3+$I$75/(1+M$39)^4+((($J$62+(-$J$40-($L41*$J$38)))*(1-Hipotesis!$D$10))-(($J$67-$I$67)/Hipotesis!$D$40))/(1+M$39)^5)+((((($J$62+(-$J$40-($L41*$J$38)))*(1-Hipotesis!$D$10))-(($J$67-$I$67)/Hipotesis!$D$40))*(1+Hipotesis!$D$15)/(M$39-Hipotesis!$D$15))/(1+M$39)^5)+(Hipotesis!$D$49+Hipotesis!$D$50-Hipotesis!$D$51+Hipotesis!$D$52+Hipotesis!$D$53-Hipotesis!$D$54))/Hipotesis!$D$46*1000 -> 105.31037 | N41: =(($F$75/(1+N$39)^1+$G$75/(1+N$39)^2+$H$75/(1+N$39)^3+$I$75/(1+N$39)^4+((($J$62+(-$J$40-($L41*$J$38)))*(1-Hipotesis!$D$10))-(($J$67-$I$67)/Hipotesis!$D$40))/(1+N$39)^5)+((((($J$62+(-$J$40-($L41*$J$38)))*(1-Hipotesis!$D$10))-(($J$67-$I$67)/Hipotesis!$D$40))*(1+Hipotesis!$D$15)/(N$39-Hipotesis!$D$15))/(1+N$39)^5)+(Hipotesis!$D$49+Hipotesis!$D$50-Hipotesis!$D$51+Hipotesis!$D$52+Hipotesis!$D$53-Hipotesis!$D$54))/Hipotesis!$D$46*1000 -> 93.563739 | O41: =(($F$75/(1+O$39)^1+$G$75/(1+O$39)^2+$H$75/(1+O$39)^3+$I$75/(1+O$39)^4+((($J$62+(-$J$40-($L41*$J$38)))*(1-Hipotesis!$D$10))-(($J$67-$I$67)/Hipotesis!$D$40))/(1+O$39)^5)+((((($J$62+(-$J$40-($L41*$J$38)))*(1-Hipotesis!$D$10))-(($J$67-$I$67)/Hipotesis!$D$40))*(1+Hipotesis!$D$15)/(O$39-Hipotesis!$D$15))/(1+O$39)^5)+(Hipotesis!$D$49+Hipotesis!$D$50-Hipotesis!$D$51+Hipotesis!$D$52+Hipotesis!$D$53-Hipotesis!$D$54))/Hipotesis!$D$46*1000 -> 85.305051 | P41: =(($F$75/(1+P$39)^1+$G$75/(1+P$39)^2+$H$75/(1+P$39)^3+$I$75/(1+P$39)^4+((($J$62+(-$J$40-($L41*$J$38)))*(1-Hipotesis!$D$10))-(($J$67-$I$67)/Hipotesis!$D$40))/(1+P$39)^5)+((((($J$62+(-$J$40-($L41*$J$38)))*(1-Hipotesis!$D$10))-(($J$67-$I$67)/Hipotesis!$D$40))*(1+Hipotesis!$D$15)/(P$39-Hipotesis!$D$15))/(1+P$39)^5)+(Hipotesis!$D$49+Hipotesis!$D$50-Hipotesis!$D$51+Hipotesis!$D$52+Hipotesis!$D$53-Hipotesis!$D$54))/Hipotesis!$D$46*1000 -> 77.252966 | Q41: =(($F$75/(1+Q$39)^1+$G$75/(1+Q$39)^2+$H$75/(1+Q$39)^3+$I$75/(1+Q$39)^4+((($J$62+(-$J$40-($L41*$J$38)))*(1-Hipotesis!$D$10))-(($J$67-$I$67)/Hipotesis!$D$40))/(1+Q$39)^5)+((((($J$62+(-$J$40-($L41*$J$38)))*(1-Hipotesis!$D$10))-(($J$67-$I$67)/Hipotesis!$D$40))*(1+Hipotesis!$D$15)/(Q$39-Hipotesis!$D$15))/(1+Q$39)^5)+(Hipotesis!$D$49+Hipotesis!$D$50-Hipotesis!$D$51+Hipotesis!$D$52+Hipotesis!$D$53-Hipotesis!$D$54))/Hipotesis!$D$46*1000 -> 70.51325 | R41: =(($F$75/(1+R$39)^1+$G$75/(1+R$39)^2+$H$75/(1+R$39)^3+$I$75/(1+R$39)^4+((($J$62+(-$J$40-($L41*$J$38)))*(1-Hipotesis!$D$10))-(($J$67-$I$67)/Hipotesis!$D$40))/(1+R$39)^5)+((((($J$62+(-$J$40-($L41*$J$38)))*(1-Hipotesis!$D$10))-(($J$67-$I$67)/Hipotesis!$D$40))*(1+Hipotesis!$D$15)/(R$39-Hipotesis!$D$15))/(1+R$39)^5)+(Hipotesis!$D$49+Hipotesis!$D$50-Hipotesis!$D$51+Hipotesis!$D$52+Hipotesis!$D$53-Hipotesis!$D$54))/Hipotesis!$D$46*1000 -> 65.555868
L42: 0.014 | M42: =(($F$75/(1+M$39)^1+$G$75/(1+M$39)^2+$H$75/(1+M$39)^3+$I$75/(1+M$39)^4+((($J$62+(-$J$40-($L42*$J$38)))*(1-Hipotesis!$D$10))-(($J$67-$I$67)/Hipotesis!$D$40))/(1+M$39)^5)+((((($J$62+(-$J$40-($L42*$J$38)))*(1-Hipotesis!$D$10))-(($J$67-$I$67)/Hipotesis!$D$40))*(1+Hipotesis!$D$15)/(M$39-Hipotesis!$D$15))/(1+M$39)^5)+(Hipotesis!$D$49+Hipotesis!$D$50-Hipotesis!$D$51+Hipotesis!$D$52+Hipotesis!$D$53-Hipotesis!$D$54))/Hipotesis!$D$46*1000 -> 98.567786 | N42: =(($F$75/(1+N$39)^1+$G$75/(1+N$39)^2+$H$75/(1+N$39)^3+$I$75/(1+N$39)^4+((($J$62+(-$J$40-($L42*$J$38)))*(1-Hipotesis!$D$10))-(($J$67-$I$67)/Hipotesis!$D$40))/(1+N$39)^5)+((((($J$62+(-$J$40-($L42*$J$38)))*(1-Hipotesis!$D$10))-(($J$67-$I$67)/Hipotesis!$D$40))*(1+Hipotesis!$D$15)/(N$39-Hipotesis!$D$15))/(1+N$39)^5)+(Hipotesis!$D$49+Hipotesis!$D$50-Hipotesis!$D$51+Hipotesis!$D$52+Hipotesis!$D$53-Hipotesis!$D$54))/Hipotesis!$D$46*1000 -> 87.678943 | O42: =(($F$75/(1+O$39)^1+$G$75/(1+O$39)^2+$H$75/(1+O$39)^3+$I$75/(1+O$39)^4+((($J$62+(-$J$40-($L42*$J$38)))*(1-Hipotesis!$D$10))-(($J$67-$I$67)/Hipotesis!$D$40))/(1+O$39)^5)+((((($J$62+(-$J$40-($L42*$J$38)))*(1-Hipotesis!$D$10))-(($J$67-$I$67)/Hipotesis!$D$40))*(1+Hipotesis!$D$15)/(O$39-Hipotesis!$D$15))/(1+O$39)^5)+(Hipotesis!$D$49+Hipotesis!$D$50-Hipotesis!$D$51+Hipotesis!$D$52+Hipotesis!$D$53-Hipotesis!$D$54))/Hipotesis!$D$46*1000 -> 80.021029 | P42: =(($F$75/(1+P$39)^1+$G$75/(1+P$39)^2+$H$75/(1+P$39)^3+$I$75/(1+P$39)^4+((($J$62+(-$J$40-($L42*$J$38)))*(1-Hipotesis!$D$10))-(($J$67-$I$67)/Hipotesis!$D$40))/(1+P$39)^5)+((((($J$62+(-$J$40-($L42*$J$38)))*(1-Hipotesis!$D$10))-(($J$67-$I$67)/Hipotesis!$D$40))*(1+Hipotesis!$D$15)/(P$39-Hipotesis!$D$15))/(1+P$39)^5)+(Hipotesis!$D$49+Hipotesis!$D$50-Hipotesis!$D$51+Hipotesis!$D$52+Hipotesis!$D$53-Hipotesis!$D$54))/Hipotesis!$D$46*1000 -> 72.552318 | Q42: =(($F$75/(1+Q$39)^1+$G$75/(1+Q$39)^2+$H$75/(1+Q$39)^3+$I$75/(1+Q$39)^4+((($J$62+(-$J$40-($L42*$J$38)))*(1-Hipotesis!$D$10))-(($J$67-$I$67)/Hipotesis!$D$40))/(1+Q$39)^5)+((((($J$62+(-$J$40-($L42*$J$38)))*(1-Hipotesis!$D$10))-(($J$67-$I$67)/Hipotesis!$D$40))*(1+Hipotesis!$D$15)/(Q$39-Hipotesis!$D$15))/(1+Q$39)^5)+(Hipotesis!$D$49+Hipotesis!$D$50-Hipotesis!$D$51+Hipotesis!$D$52+Hipotesis!$D$53-Hipotesis!$D$54))/Hipotesis!$D$46*1000 -> 66.29863 | R42: =(($F$75/(1+R$39)^1+$G$75/(1+R$39)^2+$H$75/(1+R$39)^3+$I$75/(1+R$39)^4+((($J$62+(-$J$40-($L42*$J$38)))*(1-Hipotesis!$D$10))-(($J$67-$I$67)/Hipotesis!$D$40))/(1+R$39)^5)+((((($J$62+(-$J$40-($L42*$J$38)))*(1-Hipotesis!$D$10))-(($J$67-$I$67)/Hipotesis!$D$40))*(1+Hipotesis!$D$15)/(R$39-Hipotesis!$D$15))/(1+R$39)^5)+(Hipotesis!$D$49+Hipotesis!$D$50-Hipotesis!$D$51+Hipotesis!$D$52+Hipotesis!$D$53-Hipotesis!$D$54))/Hipotesis!$D$46*1000 -> 61.697118
L43: 0.018 | M43: =(($F$75/(1+M$39)^1+$G$75/(1+M$39)^2+$H$75/(1+M$39)^3+$I$75/(1+M$39)^4+((($J$62+(-$J$40-($L43*$J$38)))*(1-Hipotesis!$D$10))-(($J$67-$I$67)/Hipotesis!$D$40))/(1+M$39)^5)+((((($J$62+(-$J$40-($L43*$J$38)))*(1-Hipotesis!$D$10))-(($J$67-$I$67)/Hipotesis!$D$40))*(1+Hipotesis!$D$15)/(M$39-Hipotesis!$D$15))/(1+M$39)^5)+(Hipotesis!$D$49+Hipotesis!$D$50-Hipotesis!$D$51+Hipotesis!$D$52+Hipotesis!$D$53-Hipotesis!$D$54))/Hipotesis!$D$46*1000 -> 91.825198 | N43: =(($F$75/(1+N$39)^1+$G$75/(1+N$39)^2+$H$75/(1+N$39)^3+$I$75/(1+N$39)^4+((($J$62+(-$J$40-($L43*$J$38)))*(1-Hipotesis!$D$10))-(($J$67-$I$67)/Hipotesis!$D$40))/(1+N$39)^5)+((((($J$62+(-$J$40-($L43*$J$38)))*(1-Hipotesis!$D$10))-(($J$67-$I$67)/Hipotesis!$D$40))*(1+Hipotesis!$D$15)/(N$39-Hipotesis!$D$15))/(1+N$39)^5)+(Hipotesis!$D$49+Hipotesis!$D$50-Hipotesis!$D$51+Hipotesis!$D$52+Hipotesis!$D$53-Hipotesis!$D$54))/Hipotesis!$D$46*1000 -> 81.794146 | O43: =(($F$75/(1+O$39)^1+$G$75/(1+O$39)^2+$H$75/(1+O$39)^3+$I$75/(1+O$39)^4+((($J$62+(-$J$40-($L43*$J$38)))*(1-Hipotesis!$D$10))-(($J$67-$I$67)/Hipotesis!$D$40))/(1+O$39)^5)+((((($J$62+(-$J$40-($L43*$J$38)))*(1-Hipotesis!$D$10))-(($J$67-$I$67)/Hipotesis!$D$40))*(1+Hipotesis!$D$15)/(O$39-Hipotesis!$D$15))/(1+O$39)^5)+(Hipotesis!$D$49+Hipotesis!$D$50-Hipotesis!$D$51+Hipotesis!$D$52+Hipotesis!$D$53-Hipotesis!$D$54))/Hipotesis!$D$46*1000 -> 74.737007 | P43: =(($F$75/(1+P$39)^1+$G$75/(1+P$39)^2+$H$75/(1+P$39)^3+$I$75/(1+P$39)^4+((($J$62+(-$J$40-($L43*$J$38)))*(1-Hipotesis!$D$10))-(($J$67-$I$67)/Hipotesis!$D$40))/(1+P$39)^5)+((((($J$62+(-$J$40-($L43*$J$38)))*(1-Hipotesis!$D$10))-(($J$67-$I$67)/Hipotesis!$D$40))*(1+Hipotesis!$D$15)/(P$39-Hipotesis!$D$15))/(1+P$39)^5)+(Hipotesis!$D$49+Hipotesis!$D$50-Hipotesis!$D$51+Hipotesis!$D$52+Hipotesis!$D$53-Hipotesis!$D$54))/Hipotesis!$D$46*1000 -> 67.85167 | Q43: =(($F$75/(1+Q$39)^1+$G$75/(1+Q$39)^2+$H$75/(1+Q$39)^3+$I$75/(1+Q$39)^4+((($J$62+(-$J$40-($L43*$J$38)))*(1-Hipotesis!$D$10))-(($J$67-$I$67)/Hipotesis!$D$40))/(1+Q$39)^5)+((((($J$62+(-$J$40-($L43*$J$38)))*(1-Hipotesis!$D$10))-(($J$67-$I$67)/Hipotesis!$D$40))*(1+Hipotesis!$D$15)/(Q$39-Hipotesis!$D$15))/(1+Q$39)^5)+(Hipotesis!$D$49+Hipotesis!$D$50-Hipotesis!$D$51+Hipotesis!$D$52+Hipotesis!$D$53-Hipotesis!$D$54))/Hipotesis!$D$46*1000 -> 62.08401 | R43: =(($F$75/(1+R$39)^1+$G$75/(1+R$39)^2+$H$75/(1+R$39)^3+$I$75/(1+R$39)^4+((($J$62+(-$J$40-($L43*$J$38)))*(1-Hipotesis!$D$10))-(($J$67-$I$67)/Hipotesis!$D$40))/(1+R$39)^5)+((((($J$62+(-$J$40-($L43*$J$38)))*(1-Hipotesis!$D$10))-(($J$67-$I$67)/Hipotesis!$D$40))*(1+Hipotesis!$D$15)/(R$39-Hipotesis!$D$15))/(1+R$39)^5)+(Hipotesis!$D$49+Hipotesis!$D$50-Hipotesis!$D$51+Hipotesis!$D$52+Hipotesis!$D$53-Hipotesis!$D$54))/Hipotesis!$D$46*1000 -> 57.838368
L44: 0.022 | M44: =(($F$75/(1+M$39)^1+$G$75/(1+M$39)^2+$H$75/(1+M$39)^3+$I$75/(1+M$39)^4+((($J$62+(-$J$40-($L44*$J$38)))*(1-Hipotesis!$D$10))-(($J$67-$I$67)/Hipotesis!$D$40))/(1+M$39)^5)+((((($J$62+(-$J$40-($L44*$J$38)))*(1-Hipotesis!$D$10))-(($J$67-$I$67)/Hipotesis!$D$40))*(1+Hipotesis!$D$15)/(M$39-Hipotesis!$D$15))/(1+M$39)^5)+(Hipotesis!$D$49+Hipotesis!$D$50-Hipotesis!$D$51+Hipotesis!$D$52+Hipotesis!$D$53-Hipotesis!$D$54))/Hipotesis!$D$46*1000 -> 85.08261 | N44: =(($F$75/(1+N$39)^1+$G$75/(1+N$39)^2+$H$75/(1+N$39)^3+$I$75/(1+N$39)^4+((($J$62+(-$J$40-($L44*$J$38)))*(1-Hipotesis!$D$10))-(($J$67-$I$67)/Hipotesis!$D$40))/(1+N$39)^5)+((((($J$62+(-$J$40-($L44*$J$38)))*(1-Hipotesis!$D$10))-(($J$67-$I$67)/Hipotesis!$D$40))*(1+Hipotesis!$D$15)/(N$39-Hipotesis!$D$15))/(1+N$39)^5)+(Hipotesis!$D$49+Hipotesis!$D$50-Hipotesis!$D$51+Hipotesis!$D$52+Hipotesis!$D$53-Hipotesis!$D$54))/Hipotesis!$D$46*1000 -> 75.909349 | O44: =(($F$75/(1+O$39)^1+$G$75/(1+O$39)^2+$H$75/(1+O$39)^3+$I$75/(1+O$39)^4+((($J$62+(-$J$40-($L44*$J$38)))*(1-Hipotesis!$D$10))-(($J$67-$I$67)/Hipotesis!$D$40))/(1+O$39)^5)+((((($J$62+(-$J$40-($L44*$J$38)))*(1-Hipotesis!$D$10))-(($J$67-$I$67)/Hipotesis!$D$40))*(1+Hipotesis!$D$15)/(O$39-Hipotesis!$D$15))/(1+O$39)^5)+(Hipotesis!$D$49+Hipotesis!$D$50-Hipotesis!$D$51+Hipotesis!$D$52+Hipotesis!$D$53-Hipotesis!$D$54))/Hipotesis!$D$46*1000 -> 69.452985 | P44: =(($F$75/(1+P$39)^1+$G$75/(1+P$39)^2+$H$75/(1+P$39)^3+$I$75/(1+P$39)^4+((($J$62+(-$J$40-($L44*$J$38)))*(1-Hipotesis!$D$10))-(($J$67-$I$67)/Hipotesis!$D$40))/(1+P$39)^5)+((((($J$62+(-$J$40-($L44*$J$38)))*(1-Hipotesis!$D$10))-(($J$67-$I$67)/Hipotesis!$D$40))*(1+Hipotesis!$D$15)/(P$39-Hipotesis!$D$15))/(1+P$39)^5)+(Hipotesis!$D$49+Hipotesis!$D$50-Hipotesis!$D$51+Hipotesis!$D$52+Hipotesis!$D$53-Hipotesis!$D$54))/Hipotesis!$D$46*1000 -> 63.151022 | Q44: =(($F$75/(1+Q$39)^1+$G$75/(1+Q$39)^2+$H$75/(1+Q$39)^3+$I$75/(1+Q$39)^4+((($J$62+(-$J$40-($L44*$J$38)))*(1-Hipotesis!$D$10))-(($J$67-$I$67)/Hipotesis!$D$40))/(1+Q$39)^5)+((((($J$62+(-$J$40-($L44*$J$38)))*(1-Hipotesis!$D$10))-(($J$67-$I$67)/Hipotesis!$D$40))*(1+Hipotesis!$D$15)/(Q$39-Hipotesis!$D$15))/(1+Q$39)^5)+(Hipotesis!$D$49+Hipotesis!$D$50-Hipotesis!$D$51+Hipotesis!$D$52+Hipotesis!$D$53-Hipotesis!$D$54))/Hipotesis!$D$46*1000 -> 57.86939 | R44: =(($F$75/(1+R$39)^1+$G$75/(1+R$39)^2+$H$75/(1+R$39)^3+$I$75/(1+R$39)^4+((($J$62+(-$J$40-($L44*$J$38)))*(1-Hipotesis!$D$10))-(($J$67-$I$67)/Hipotesis!$D$40))/(1+R$39)^5)+((((($J$62+(-$J$40-($L44*$J$38)))*(1-Hipotesis!$D$10))-(($J$67-$I$67)/Hipotesis!$D$40))*(1+Hipotesis!$D$15)/(R$39-Hipotesis!$D$15))/(1+R$39)^5)+(Hipotesis!$D$49+Hipotesis!$D$50-Hipotesis!$D$51+Hipotesis!$D$52+Hipotesis!$D$53-Hipotesis!$D$54))/Hipotesis!$D$46*1000 -> 53.979617
L45: 0.026 | M45: =(($F$75/(1+M$39)^1+$G$75/(1+M$39)^2+$H$75/(1+M$39)^3+$I$75/(1+M$39)^4+((($J$62+(-$J$40-($L45*$J$38)))*(1-Hipotesis!$D$10))-(($J$67-$I$67)/Hipotesis!$D$40))/(1+M$39)^5)+((((($J$62+(-$J$40-($L45*$J$38)))*(1-Hipotesis!$D$10))-(($J$67-$I$67)/Hipotesis!$D$40))*(1+Hipotesis!$D$15)/(M$39-Hipotesis!$D$15))/(1+M$39)^5)+(Hipotesis!$D$49+Hipotesis!$D$50-Hipotesis!$D$51+Hipotesis!$D$52+Hipotesis!$D$53-Hipotesis!$D$54))/Hipotesis!$D$46*1000 -> 78.340022 | N45: =(($F$75/(1+N$39)^1+$G$75/(1+N$39)^2+$H$75/(1+N$39)^3+$I$75/(1+N$39)^4+((($J$62+(-$J$40-($L45*$J$38)))*(1-Hipotesis!$D$10))-(($J$67-$I$67)/Hipotesis!$D$40))/(1+N$39)^5)+((((($J$62+(-$J$40-($L45*$J$38)))*(1-Hipotesis!$D$10))-(($J$67-$I$67)/Hipotesis!$D$40))*(1+Hipotesis!$D$15)/(N$39-Hipotesis!$D$15))/(1+N$39)^5)+(Hipotesis!$D$49+Hipotesis!$D$50-Hipotesis!$D$51+Hipotesis!$D$52+Hipotesis!$D$53-Hipotesis!$D$54))/Hipotesis!$D$46*1000 -> 70.024552 | O45: =(($F$75/(1+O$39)^1+$G$75/(1+O$39)^2+$H$75/(1+O$39)^3+$I$75/(1+O$39)^4+((($J$62+(-$J$40-($L45*$J$38)))*(1-Hipotesis!$D$10))-(($J$67-$I$67)/Hipotesis!$D$40))/(1+O$39)^5)+((((($J$62+(-$J$40-($L45*$J$38)))*(1-Hipotesis!$D$10))-(($J$67-$I$67)/Hipotesis!$D$40))*(1+Hipotesis!$D$15)/(O$39-Hipotesis!$D$15))/(1+O$39)^5)+(Hipotesis!$D$49+Hipotesis!$D$50-Hipotesis!$D$51+Hipotesis!$D$52+Hipotesis!$D$53-Hipotesis!$D$54))/Hipotesis!$D$46*1000 -> 64.168963 | P45: =(($F$75/(1+P$39)^1+$G$75/(1+P$39)^2+$H$75/(1+P$39)^3+$I$75/(1+P$39)^4+((($J$62+(-$J$40-($L45*$J$38)))*(1-Hipotesis!$D$10))-(($J$67-$I$67)/Hipotesis!$D$40))/(1+P$39)^5)+((((($J$62+(-$J$40-($L45*$J$38)))*(1-Hipotesis!$D$10))-(($J$67-$I$67)/Hipotesis!$D$40))*(1+Hipotesis!$D$15)/(P$39-Hipotesis!$D$15))/(1+P$39)^5)+(Hipotesis!$D$49+Hipotesis!$D$50-Hipotesis!$D$51+Hipotesis!$D$52+Hipotesis!$D$53-Hipotesis!$D$54))/Hipotesis!$D$46*1000 -> 58.450374 | Q45: =(($F$75/(1+Q$39)^1+$G$75/(1+Q$39)^2+$H$75/(1+Q$39)^3+$I$75/(1+Q$39)^4+((($J$62+(-$J$40-($L45*$J$38)))*(1-Hipotesis!$D$10))-(($J$67-$I$67)/Hipotesis!$D$40))/(1+Q$39)^5)+((((($J$62+(-$J$40-($L45*$J$38)))*(1-Hipotesis!$D$10))-(($J$67-$I$67)/Hipotesis!$D$40))*(1+Hipotesis!$D$15)/(Q$39-Hipotesis!$D$15))/(1+Q$39)^5)+(Hipotesis!$D$49+Hipotesis!$D$50-Hipotesis!$D$51+Hipotesis!$D$52+Hipotesis!$D$53-Hipotesis!$D$54))/Hipotesis!$D$46*1000 -> 53.65477 | R45: =(($F$75/(1+R$39)^1+$G$75/(1+R$39)^2+$H$75/(1+R$39)^3+$I$75/(1+R$39)^4+((($J$62+(-$J$40-($L45*$J$38)))*(1-Hipotesis!$D$10))-(($J$67-$I$67)/Hipotesis!$D$40))/(1+R$39)^5)+((((($J$62+(-$J$40-($L45*$J$38)))*(1-Hipotesis!$D$10))-(($J$67-$I$67)/Hipotesis!$D$40))*(1+Hipotesis!$D$15)/(R$39-Hipotesis!$D$15))/(1+R$39)^5)+(Hipotesis!$D$49+Hipotesis!$D$50-Hipotesis!$D$51+Hipotesis!$D$52+Hipotesis!$D$53-Hipotesis!$D$54))/Hipotesis!$D$46*1000 -> 50.120867
L47: Q1 2026: 2.0%. Tesis pide bajar a ~1.4% para 2030. Cada 50bps mueve precio notablemente.
A49: E. CONSOLIDADO - EBIT y EBITDA
B50: Mobility Op Income | D50: =D15 -> 5819.952 | E50: =E15 -> 7150.47 | F50: =F15 -> 9125.7192 | G50: =G15 -> 11542.631 | H50: =H15 -> 13706.45 | I50: =I15 -> 15729.1 | J50: =J15 -> 17404.488
B51: Delivery Op Income | D51: =D26 -> 2515.335 | E51: =E26 -> 3570.336 | F51: =F26 -> 4107.1437 | G51: =G26 -> 5309.4892 | H51: =H26 -> 6412.1991 | I51: =I26 -> 7283.0652 | J51: =J26 -> 8118.9624
B52: Freight Op Income | D52: =D35 -> -110.817 | E52: =E35 -> -30.846 | F52: =F35 -> -80.97075 | G52: =G35 -> 0 | H52: =H35 -> 29.473353 | I52: =I35 -> 60.715107 | J52: =J35 -> 93.804841
B53: Sum Segments | D53: =SUM(D50:D52) -> 8224.47 | E53: =SUM(E50:E52) -> 10689.96 | F53: =SUM(F50:F52) -> 13151.892 | G53: =SUM(G50:G52) -> 16852.12 | H53: =SUM(H50:H52) -> 20148.122 | I53: =SUM(I50:I52) -> 23072.881 | J53: =SUM(J50:J52) -> 25617.255
B54: Corporate overhead | D54: =D40 -> -3357.2088 | E54: =E40 -> -3986.1412 | F54: =F40 -> -4664.9706 | G54: =G40 -> -4899.4486 | H54: =H40 -> -4933.9914 | I54: =I40 -> -5127.3612 | J54: =J40 -> -5211.1353
B55: Total Revenue ($M) | D55: =D11+D23+D32 -> 44108 | E55: =E11+E23+E32 -> 52059 | F55: =F11+F23+F32 -> 57433.66 | G55: =G11+G23+G32 -> 68211.172 | H55: =H11+H23+H32 -> 77892.545 | I55: =I11+I23+I32 -> 86840.293 | J55: =J11+J23+J32 -> 94291.628
B62: EBIT (Non-GAAP Op Income) | D62: =D53+D54 -> 4867.2612 | E62: =E53+E54 -> 6703.8188 | F62: =F53+F54 -> 8486.9215 | G62: =G53+G54 -> 11952.671 | H62: =H53+H54 -> 15214.131 | I62: =I53+I54 -> 17945.519 | J62: =J53+J54 -> 20406.12
B63: EBIT margin (% revenue) | D63: =D62/D55 -> 0.11034872 | E63: =E62/E55 -> 0.12877348 | F63: =F62/F55 -> 0.14776912 | G63: =G62/G55 -> 0.17523041 | H63: =H62/H55 -> 0.19532204 | I63: =I62/I55 -> 0.20664969 | J63: =J62/J55 -> 0.21641497
B64: EBIT % sobre GB | D64: =D62/D38 -> 0.030010736 | E64: =E62/E38 -> 0.0346447 | F64: =F62/F38 -> 0.036385745 | G64: =G62/G38 -> 0.043912714 | H64: =H62/H38 -> 0.049336547 | I64: =I62/I38 -> 0.052499284 | J64: =J62/J38 -> 0.054822156
B67: Total Revenue (= Mob+Del+Frt) | D67: =D55 -> 44108 | E67: =E55 -> 52059 | F67: =F55 -> 57433.66 | G67: =G55 -> 68211.172 | H67: =H55 -> 77892.545 | I67: =I55 -> 86840.293 | J67: =J55 -> 94291.628
B70: (+) D&A estimado (% revenue) | D70: 0.014 | E70: 0.014 | F70: =$E$70 -> 0.014 | G70: =$E$70 -> 0.014 | H70: =$E$70 -> 0.014 | I70: =$E$70 -> 0.014 | J70: =$E$70 -> 0.014
B71: D&A ($M) | D71: =D70*D55 -> 617.512 | E71: =E70*E55 -> 728.826 | F71: =F70*F55 -> 804.07123 | G71: =G70*G55 -> 954.95641 | H71: =H70*H55 -> 1090.4956 | I71: =I70*I55 -> 1215.7641 | J71: =J70*J55 -> 1320.0828
B72: EBITDA = EBIT + D&A | D72: =D62+D71 -> 5484.7732 | E72: =E62+E71 -> 7432.6448 | F72: =F62+F71 -> 9290.9927 | G72: =G62+G71 -> 12907.628 | H72: =H62+H71 -> 16304.627 | I72: =I62+I71 -> 19161.283 | J72: =J62+J71 -> 21726.202
A74: F. FREE CASH FLOW TO FIRM (Damodaran Sales-to-Capital) | L74: Sens F. Mobility Margin × Sales-to-Capital (precio $)
B75: FCFF (NOPAT - Reinversion) | F75: =F77+F79 -> 5544.8669 | G75: =G77+G79 -> 7167.5812 | H75: =H77+H79 -> 9930.7477 | I75: =I77+I79 -> 12207.956 | J75: =J77+J79 -> 14426.506 | L75: Op Margin ↓ S2C →
B76: Periodo (anos desde 2025) | D76: =0 -> 0 | E76: =0 -> 0 | F76: =1 -> 1 | G76: =2 -> 2 | H76: =3 -> 3 | I76: =4 -> 4 | J76: =5 -> 5 | M76: 3 | N76: 4 | O76: 5 | P76: 6 | Q76: 7 | R76: 8
B77: NOPAT = EBIT × (1-T) | D77: =D62*(1-Hipotesis!$D$10) -> 3796.4637 | E77: =E62*(1-Hipotesis!$D$10) -> 5228.9787 | F77: =F62*(1-Hipotesis!$D$10) -> 6619.7988 | G77: =G62*(1-Hipotesis!$D$10) -> 9323.0837 | H77: =H62*(1-Hipotesis!$D$10) -> 11867.022 | I77: =I62*(1-Hipotesis!$D$10) -> 13997.505 | J77: =J62*(1-Hipotesis!$D$10) -> 15916.773 | L77: 0.27 | M77: =(($D$82-$J$81+(((((($J$7*$J$10)*$L77)+($J$62-$J$15))*(1-Hipotesis!$D$10))-(($J$55-$I$55)/M$76))/(1+Hipotesis!$D$14)^5))+((((((($J$7*$J$10)*$L77)+($J$62-$J$15))*(1-Hipotesis!$D$10))-(($J$55-$I$55)/M$76))*(1+Hipotesis!$D$15)/(Hipotesis!$D$14-Hipotesis!$D$15))/(1+Hipotesis!$D$14)^5)+(Hipotesis!$D$49+Hipotesis!$D$50-Hipotesis!$D$51+Hipotesis!$D$52+Hipotesis!$D$53-Hipotesis!$D$54))/Hipotesis!$D$46*1000 -> 58.191956 | N77: =(($D$82-$J$81+(((((($J$7*$J$10)*$L77)+($J$62-$J$15))*(1-Hipotesis!$D$10))-(($J$55-$I$55)/N$76))/(1+Hipotesis!$D$14)^5))+((((((($J$7*$J$10)*$L77)+($J$62-$J$15))*(1-Hipotesis!$D$10))-(($J$55-$I$55)/N$76))*(1+Hipotesis!$D$15)/(Hipotesis!$D$14-Hipotesis!$D$15))/(1+Hipotesis!$D$14)^5)+(Hipotesis!$D$49+Hipotesis!$D$50-Hipotesis!$D$51+Hipotesis!$D$52+Hipotesis!$D$53-Hipotesis!$D$54))/Hipotesis!$D$46*1000 -> 60.723063 | O77: =(($D$82-$J$81+(((((($J$7*$J$10)*$L77)+($J$62-$J$15))*(1-Hipotesis!$D$10))-(($J$55-$I$55)/O$76))/(1+Hipotesis!$D$14)^5))+((((((($J$7*$J$10)*$L77)+($J$62-$J$15))*(1-Hipotesis!$D$10))-(($J$55-$I$55)/O$76))*(1+Hipotesis!$D$15)/(Hipotesis!$D$14-Hipotesis!$D$15))/(1+Hipotesis!$D$14)^5)+(Hipotesis!$D$49+Hipotesis!$D$50-Hipotesis!$D$51+Hipotesis!$D$52+Hipotesis!$D$53-Hipotesis!$D$54))/Hipotesis!$D$46*1000 -> 62.241728 | P77: =(($D$82-$J$81+(((((($J$7*$J$10)*$L77)+($J$62-$J$15))*(1-Hipotesis!$D$10))-(($J$55-$I$55)/P$76))/(1+Hipotesis!$D$14)^5))+((((((($J$7*$J$10)*$L77)+($J$62-$J$15))*(1-Hipotesis!$D$10))-(($J$55-$I$55)/P$76))*(1+Hipotesis!$D$15)/(Hipotesis!$D$14-Hipotesis!$D$15))/(1+Hipotesis!$D$14)^5)+(Hipotesis!$D$49+Hipotesis!$D$50-Hipotesis!$D$51+Hipotesis!$D$52+Hipotesis!$D$53-Hipotesis!$D$54))/Hipotesis!$D$46*1000 -> 63.254171 | Q77: =(($D$82-$J$81+(((((($J$7*$J$10)*$L77)+($J$62-$J$15))*(1-Hipotesis!$D$10))-(($J$55-$I$55)/Q$76))/(1+Hipotesis!$D$14)^5))+((((((($J$7*$J$10)*$L77)+($J$62-$J$15))*(1-Hipotesis!$D$10))-(($J$55-$I$55)/Q$76))*(1+Hipotesis!$D$15)/(Hipotesis!$D$14-Hipotesis!$D$15))/(1+Hipotesis!$D$14)^5)+(Hipotesis!$D$49+Hipotesis!$D$50-Hipotesis!$D$51+Hipotesis!$D$52+Hipotesis!$D$53-Hipotesis!$D$54))/Hipotesis!$D$46*1000 -> 63.977345 | R77: =(($D$82-$J$81+(((((($J$7*$J$10)*$L77)+($J$62-$J$15))*(1-Hipotesis!$D$10))-(($J$55-$I$55)/R$76))/(1+Hipotesis!$D$14)^5))+((((((($J$7*$J$10)*$L77)+($J$62-$J$15))*(1-Hipotesis!$D$10))-(($J$55-$I$55)/R$76))*(1+Hipotesis!$D$15)/(Hipotesis!$D$14-Hipotesis!$D$15))/(1+Hipotesis!$D$14)^5)+(Hipotesis!$D$49+Hipotesis!$D$50-Hipotesis!$D$51+Hipotesis!$D$52+Hipotesis!$D$53-Hipotesis!$D$54))/Hipotesis!$D$46*1000 -> 64.519725
B78: ΔRevenue ($M) | E78: =E55-D55 -> 7951 | F78: =F55-E55 -> 5374.6596 | G78: =G55-F55 -> 10777.513 | H78: =H55-G55 -> 9681.3724 | I78: =I55-H55 -> 8947.748 | J78: =J55-I55 -> 7451.3357 | L78: 0.29 | M78: =(($D$82-$J$81+(((((($J$7*$J$10)*$L78)+($J$62-$J$15))*(1-Hipotesis!$D$10))-(($J$55-$I$55)/M$76))/(1+Hipotesis!$D$14)^5))+((((((($J$7*$J$10)*$L78)+($J$62-$J$15))*(1-Hipotesis!$D$10))-(($J$55-$I$55)/M$76))*(1+Hipotesis!$D$15)/(Hipotesis!$D$14-Hipotesis!$D$15))/(1+Hipotesis!$D$14)^5)+(Hipotesis!$D$49+Hipotesis!$D$50-Hipotesis!$D$51+Hipotesis!$D$52+Hipotesis!$D$53-Hipotesis!$D$54))/Hipotesis!$D$46*1000 -> 61.495642 | N78: =(($D$82-$J$81+(((((($J$7*$J$10)*$L78)+($J$62-$J$15))*(1-Hipotesis!$D$10))-(($J$55-$I$55)/N$76))/(1+Hipotesis!$D$14)^5))+((((((($J$7*$J$10)*$L78)+($J$62-$J$15))*(1-Hipotesis!$D$10))-(($J$55-$I$55)/N$76))*(1+Hipotesis!$D$15)/(Hipotesis!$D$14-Hipotesis!$D$15))/(1+Hipotesis!$D$14)^5)+(Hipotesis!$D$49+Hipotesis!$D$50-Hipotesis!$D$51+Hipotesis!$D$52+Hipotesis!$D$53-Hipotesis!$D$54))/Hipotesis!$D$46*1000 -> 64.02675 | O78: =(($D$82-$J$81+(((((($J$7*$J$10)*$L78)+($J$62-$J$15))*(1-Hipotesis!$D$10))-(($J$55-$I$55)/O$76))/(1+Hipotesis!$D$14)^5))+((((((($J$7*$J$10)*$L78)+($J$62-$J$15))*(1-Hipotesis!$D$10))-(($J$55-$I$55)/O$76))*(1+Hipotesis!$D$15)/(Hipotesis!$D$14-Hipotesis!$D$15))/(1+Hipotesis!$D$14)^5)+(Hipotesis!$D$49+Hipotesis!$D$50-Hipotesis!$D$51+Hipotesis!$D$52+Hipotesis!$D$53-Hipotesis!$D$54))/Hipotesis!$D$46*1000 -> 65.545415 | P78: =(($D$82-$J$81+(((((($J$7*$J$10)*$L78)+($J$62-$J$15))*(1-Hipotesis!$D$10))-(($J$55-$I$55)/P$76))/(1+Hipotesis!$D$14)^5))+((((((($J$7*$J$10)*$L78)+($J$62-$J$15))*(1-Hipotesis!$D$10))-(($J$55-$I$55)/P$76))*(1+Hipotesis!$D$15)/(Hipotesis!$D$14-Hipotesis!$D$15))/(1+Hipotesis!$D$14)^5)+(Hipotesis!$D$49+Hipotesis!$D$50-Hipotesis!$D$51+Hipotesis!$D$52+Hipotesis!$D$53-Hipotesis!$D$54))/Hipotesis!$D$46*1000 -> 66.557858 | Q78: =(($D$82-$J$81+(((((($J$7*$J$10)*$L78)+($J$62-$J$15))*(1-Hipotesis!$D$10))-(($J$55-$I$55)/Q$76))/(1+Hipotesis!$D$14)^5))+((((((($J$7*$J$10)*$L78)+($J$62-$J$15))*(1-Hipotesis!$D$10))-(($J$55-$I$55)/Q$76))*(1+Hipotesis!$D$15)/(Hipotesis!$D$14-Hipotesis!$D$15))/(1+Hipotesis!$D$14)^5)+(Hipotesis!$D$49+Hipotesis!$D$50-Hipotesis!$D$51+Hipotesis!$D$52+Hipotesis!$D$53-Hipotesis!$D$54))/Hipotesis!$D$46*1000 -> 67.281031 | R78: =(($D$82-$J$81+(((((($J$7*$J$10)*$L78)+($J$62-$J$15))*(1-Hipotesis!$D$10))-(($J$55-$I$55)/R$76))/(1+Hipotesis!$D$14)^5))+((((((($J$7*$J$10)*$L78)+($J$62-$J$15))*(1-Hipotesis!$D$10))-(($J$55-$I$55)/R$76))*(1+Hipotesis!$D$15)/(Hipotesis!$D$14-Hipotesis!$D$15))/(1+Hipotesis!$D$14)^5)+(Hipotesis!$D$49+Hipotesis!$D$50-Hipotesis!$D$51+Hipotesis!$D$52+Hipotesis!$D$53-Hipotesis!$D$54))/Hipotesis!$D$46*1000 -> 67.823412
B79: Reinversion = ΔRev / S2C | F79: =-F78/Hipotesis!$D$40 -> -1074.9319 | G79: =-G78/Hipotesis!$D$40 -> -2155.5025 | H79: =-H78/Hipotesis!$D$40 -> -1936.2745 | I79: =-I78/Hipotesis!$D$40 -> -1789.5496 | J79: =-J78/Hipotesis!$D$40 -> -1490.2671 | L79: 0.31 | M79: =(($D$82-$J$81+(((((($J$7*$J$10)*$L79)+($J$62-$J$15))*(1-Hipotesis!$D$10))-(($J$55-$I$55)/M$76))/(1+Hipotesis!$D$14)^5))+((((((($J$7*$J$10)*$L79)+($J$62-$J$15))*(1-Hipotesis!$D$10))-(($J$55-$I$55)/M$76))*(1+Hipotesis!$D$15)/(Hipotesis!$D$14-Hipotesis!$D$15))/(1+Hipotesis!$D$14)^5)+(Hipotesis!$D$49+Hipotesis!$D$50-Hipotesis!$D$51+Hipotesis!$D$52+Hipotesis!$D$53-Hipotesis!$D$54))/Hipotesis!$D$46*1000 -> 64.799328 | N79: =(($D$82-$J$81+(((((($J$7*$J$10)*$L79)+($J$62-$J$15))*(1-Hipotesis!$D$10))-(($J$55-$I$55)/N$76))/(1+Hipotesis!$D$14)^5))+((((((($J$7*$J$10)*$L79)+($J$62-$J$15))*(1-Hipotesis!$D$10))-(($J$55-$I$55)/N$76))*(1+Hipotesis!$D$15)/(Hipotesis!$D$14-Hipotesis!$D$15))/(1+Hipotesis!$D$14)^5)+(Hipotesis!$D$49+Hipotesis!$D$50-Hipotesis!$D$51+Hipotesis!$D$52+Hipotesis!$D$53-Hipotesis!$D$54))/Hipotesis!$D$46*1000 -> 67.330436 | O79: =(($D$82-$J$81+(((((($J$7*$J$10)*$L79)+($J$62-$J$15))*(1-Hipotesis!$D$10))-(($J$55-$I$55)/O$76))/(1+Hipotesis!$D$14)^5))+((((((($J$7*$J$10)*$L79)+($J$62-$J$15))*(1-Hipotesis!$D$10))-(($J$55-$I$55)/O$76))*(1+Hipotesis!$D$15)/(Hipotesis!$D$14-Hipotesis!$D$15))/(1+Hipotesis!$D$14)^5)+(Hipotesis!$D$49+Hipotesis!$D$50-Hipotesis!$D$51+Hipotesis!$D$52+Hipotesis!$D$53-Hipotesis!$D$54))/Hipotesis!$D$46*1000 -> 68.849101 | P79: =(($D$82-$J$81+(((((($J$7*$J$10)*$L79)+($J$62-$J$15))*(1-Hipotesis!$D$10))-(($J$55-$I$55)/P$76))/(1+Hipotesis!$D$14)^5))+((((((($J$7*$J$10)*$L79)+($J$62-$J$15))*(1-Hipotesis!$D$10))-(($J$55-$I$55)/P$76))*(1+Hipotesis!$D$15)/(Hipotesis!$D$14-Hipotesis!$D$15))/(1+Hipotesis!$D$14)^5)+(Hipotesis!$D$49+Hipotesis!$D$50-Hipotesis!$D$51+Hipotesis!$D$52+Hipotesis!$D$53-Hipotesis!$D$54))/Hipotesis!$D$46*1000 -> 69.861544 | Q79: =(($D$82-$J$81+(((((($J$7*$J$10)*$L79)+($J$62-$J$15))*(1-Hipotesis!$D$10))-(($J$55-$I$55)/Q$76))/(1+Hipotesis!$D$14)^5))+((((((($J$7*$J$10)*$L79)+($J$62-$J$15))*(1-Hipotesis!$D$10))-(($J$55-$I$55)/Q$76))*(1+Hipotesis!$D$15)/(Hipotesis!$D$14-Hipotesis!$D$15))/(1+Hipotesis!$D$14)^5)+(Hipotesis!$D$49+Hipotesis!$D$50-Hipotesis!$D$51+Hipotesis!$D$52+Hipotesis!$D$53-Hipotesis!$D$54))/Hipotesis!$D$46*1000 -> 70.584718 | R79: =(($D$82-$J$81+(((((($J$7*$J$10)*$L79)+($J$62-$J$15))*(1-Hipotesis!$D$10))-(($J$55-$I$55)/R$76))/(1+Hipotesis!$D$14)^5))+((((((($J$7*$J$10)*$L79)+($J$62-$J$15))*(1-Hipotesis!$D$10))-(($J$55-$I$55)/R$76))*(1+Hipotesis!$D$15)/(Hipotesis!$D$14-Hipotesis!$D$15))/(1+Hipotesis!$D$14)^5)+(Hipotesis!$D$49+Hipotesis!$D$50-Hipotesis!$D$51+Hipotesis!$D$52+Hipotesis!$D$53-Hipotesis!$D$54))/Hipotesis!$D$46*1000 -> 71.127098
B80: Factor de descuento | F80: =1/(1+Hipotesis!$D$14)^F76 -> 0.90533459 | G80: =1/(1+Hipotesis!$D$14)^G76 -> 0.81963073 | H80: =1/(1+Hipotesis!$D$14)^H76 -> 0.74204005 | I80: =1/(1+Hipotesis!$D$14)^I76 -> 0.67179453 | J80: =1/(1+Hipotesis!$D$14)^J76 -> 0.60819883 | L80: 0.33 | M80: =(($D$82-$J$81+(((((($J$7*$J$10)*$L80)+($J$62-$J$15))*(1-Hipotesis!$D$10))-(($J$55-$I$55)/M$76))/(1+Hipotesis!$D$14)^5))+((((((($J$7*$J$10)*$L80)+($J$62-$J$15))*(1-Hipotesis!$D$10))-(($J$55-$I$55)/M$76))*(1+Hipotesis!$D$15)/(Hipotesis!$D$14-Hipotesis!$D$15))/(1+Hipotesis!$D$14)^5)+(Hipotesis!$D$49+Hipotesis!$D$50-Hipotesis!$D$51+Hipotesis!$D$52+Hipotesis!$D$53-Hipotesis!$D$54))/Hipotesis!$D$46*1000 -> 68.103015 | N80: =(($D$82-$J$81+(((((($J$7*$J$10)*$L80)+($J$62-$J$15))*(1-Hipotesis!$D$10))-(($J$55-$I$55)/N$76))/(1+Hipotesis!$D$14)^5))+((((((($J$7*$J$10)*$L80)+($J$62-$J$15))*(1-Hipotesis!$D$10))-(($J$55-$I$55)/N$76))*(1+Hipotesis!$D$15)/(Hipotesis!$D$14-Hipotesis!$D$15))/(1+Hipotesis!$D$14)^5)+(Hipotesis!$D$49+Hipotesis!$D$50-Hipotesis!$D$51+Hipotesis!$D$52+Hipotesis!$D$53-Hipotesis!$D$54))/Hipotesis!$D$46*1000 -> 70.634122 | O80: =(($D$82-$J$81+(((((($J$7*$J$10)*$L80)+($J$62-$J$15))*(1-Hipotesis!$D$10))-(($J$55-$I$55)/O$76))/(1+Hipotesis!$D$14)^5))+((((((($J$7*$J$10)*$L80)+($J$62-$J$15))*(1-Hipotesis!$D$10))-(($J$55-$I$55)/O$76))*(1+Hipotesis!$D$15)/(Hipotesis!$D$14-Hipotesis!$D$15))/(1+Hipotesis!$D$14)^5)+(Hipotesis!$D$49+Hipotesis!$D$50-Hipotesis!$D$51+Hipotesis!$D$52+Hipotesis!$D$53-Hipotesis!$D$54))/Hipotesis!$D$46*1000 -> 72.152787 | P80: =(($D$82-$J$81+(((((($J$7*$J$10)*$L80)+($J$62-$J$15))*(1-Hipotesis!$D$10))-(($J$55-$I$55)/P$76))/(1+Hipotesis!$D$14)^5))+((((((($J$7*$J$10)*$L80)+($J$62-$J$15))*(1-Hipotesis!$D$10))-(($J$55-$I$55)/P$76))*(1+Hipotesis!$D$15)/(Hipotesis!$D$14-Hipotesis!$D$15))/(1+Hipotesis!$D$14)^5)+(Hipotesis!$D$49+Hipotesis!$D$50-Hipotesis!$D$51+Hipotesis!$D$52+Hipotesis!$D$53-Hipotesis!$D$54))/Hipotesis!$D$46*1000 -> 73.16523 | Q80: =(($D$82-$J$81+(((((($J$7*$J$10)*$L80)+($J$62-$J$15))*(1-Hipotesis!$D$10))-(($J$55-$I$55)/Q$76))/(1+Hipotesis!$D$14)^5))+((((((($J$7*$J$10)*$L80)+($J$62-$J$15))*(1-Hipotesis!$D$10))-(($J$55-$I$55)/Q$76))*(1+Hipotesis!$D$15)/(Hipotesis!$D$14-Hipotesis!$D$15))/(1+Hipotesis!$D$14)^5)+(Hipotesis!$D$49+Hipotesis!$D$50-Hipotesis!$D$51+Hipotesis!$D$52+Hipotesis!$D$53-Hipotesis!$D$54))/Hipotesis!$D$46*1000 -> 73.888404 | R80: =(($D$82-$J$81+(((((($J$7*$J$10)*$L80)+($J$62-$J$15))*(1-Hipotesis!$D$10))-(($J$55-$I$55)/R$76))/(1+Hipotesis!$D$14)^5))+((((((($J$7*$J$10)*$L80)+($J$62-$J$15))*(1-Hipotesis!$D$10))-(($J$55-$I$55)/R$76))*(1+Hipotesis!$D$15)/(Hipotesis!$D$14-Hipotesis!$D$15))/(1+Hipotesis!$D$14)^5)+(Hipotesis!$D$49+Hipotesis!$D$50-Hipotesis!$D$51+Hipotesis!$D$52+Hipotesis!$D$53-Hipotesis!$D$54))/Hipotesis!$D$46*1000 -> 74.430784
B81: PV de FCFF | F81: =F75*F80 -> 5019.9598 | G81: =G75*G80 -> 5874.7697 | H81: =H75*H80 -> 7369.0126 | I81: =I75*I80 -> 8201.2377 | J81: =J75*J80 -> 8774.1841 | L81: 0.35 | M81: =(($D$82-$J$81+(((((($J$7*$J$10)*$L81)+($J$62-$J$15))*(1-Hipotesis!$D$10))-(($J$55-$I$55)/M$76))/(1+Hipotesis!$D$14)^5))+((((((($J$7*$J$10)*$L81)+($J$62-$J$15))*(1-Hipotesis!$D$10))-(($J$55-$I$55)/M$76))*(1+Hipotesis!$D$15)/(Hipotesis!$D$14-Hipotesis!$D$15))/(1+Hipotesis!$D$14)^5)+(Hipotesis!$D$49+Hipotesis!$D$50-Hipotesis!$D$51+Hipotesis!$D$52+Hipotesis!$D$53-Hipotesis!$D$54))/Hipotesis!$D$46*1000 -> 71.406701 | N81: =(($D$82-$J$81+(((((($J$7*$J$10)*$L81)+($J$62-$J$15))*(1-Hipotesis!$D$10))-(($J$55-$I$55)/N$76))/(1+Hipotesis!$D$14)^5))+((((((($J$7*$J$10)*$L81)+($J$62-$J$15))*(1-Hipotesis!$D$10))-(($J$55-$I$55)/N$76))*(1+Hipotesis!$D$15)/(Hipotesis!$D$14-Hipotesis!$D$15))/(1+Hipotesis!$D$14)^5)+(Hipotesis!$D$49+Hipotesis!$D$50-Hipotesis!$D$51+Hipotesis!$D$52+Hipotesis!$D$53-Hipotesis!$D$54))/Hipotesis!$D$46*1000 -> 73.937809 | O81: =(($D$82-$J$81+(((((($J$7*$J$10)*$L81)+($J$62-$J$15))*(1-Hipotesis!$D$10))-(($J$55-$I$55)/O$76))/(1+Hipotesis!$D$14)^5))+((((((($J$7*$J$10)*$L81)+($J$62-$J$15))*(1-Hipotesis!$D$10))-(($J$55-$I$55)/O$76))*(1+Hipotesis!$D$15)/(Hipotesis!$D$14-Hipotesis!$D$15))/(1+Hipotesis!$D$14)^5)+(Hipotesis!$D$49+Hipotesis!$D$50-Hipotesis!$D$51+Hipotesis!$D$52+Hipotesis!$D$53-Hipotesis!$D$54))/Hipotesis!$D$46*1000 -> 75.456474 | P81: =(($D$82-$J$81+(((((($J$7*$J$10)*$L81)+($J$62-$J$15))*(1-Hipotesis!$D$10))-(($J$55-$I$55)/P$76))/(1+Hipotesis!$D$14)^5))+((((((($J$7*$J$10)*$L81)+($J$62-$J$15))*(1-Hipotesis!$D$10))-(($J$55-$I$55)/P$76))*(1+Hipotesis!$D$15)/(Hipotesis!$D$14-Hipotesis!$D$15))/(1+Hipotesis!$D$14)^5)+(Hipotesis!$D$49+Hipotesis!$D$50-Hipotesis!$D$51+Hipotesis!$D$52+Hipotesis!$D$53-Hipotesis!$D$54))/Hipotesis!$D$46*1000 -> 76.468917 | Q81: =(($D$82-$J$81+(((((($J$7*$J$10)*$L81)+($J$62-$J$15))*(1-Hipotesis!$D$10))-(($J$55-$I$55)/Q$76))/(1+Hipotesis!$D$14)^5))+((((((($J$7*$J$10)*$L81)+($J$62-$J$15))*(1-Hipotesis!$D$10))-(($J$55-$I$55)/Q$76))*(1+Hipotesis!$D$15)/(Hipotesis!$D$14-Hipotesis!$D$15))/(1+Hipotesis!$D$14)^5)+(Hipotesis!$D$49+Hipotesis!$D$50-Hipotesis!$D$51+Hipotesis!$D$52+Hipotesis!$D$53-Hipotesis!$D$54))/Hipotesis!$D$46*1000 -> 77.19209 | R81: =(($D$82-$J$81+(((((($J$7*$J$10)*$L81)+($J$62-$J$15))*(1-Hipotesis!$D$10))-(($J$55-$I$55)/R$76))/(1+Hipotesis!$D$14)^5))+((((((($J$7*$J$10)*$L81)+($J$62-$J$15))*(1-Hipotesis!$D$10))-(($J$55-$I$55)/R$76))*(1+Hipotesis!$D$15)/(Hipotesis!$D$14-Hipotesis!$D$15))/(1+Hipotesis!$D$14)^5)+(Hipotesis!$D$49+Hipotesis!$D$50-Hipotesis!$D$51+Hipotesis!$D$52+Hipotesis!$D$53-Hipotesis!$D$54))/Hipotesis!$D$46*1000 -> 77.734471
B82: Suma PV FCFFs explicitos (anos 1-5) | D82: =SUM(F81:J81) -> 35239.164 | L82: 0.37 | M82: =(($D$82-$J$81+(((((($J$7*$J$10)*$L82)+($J$62-$J$15))*(1-Hipotesis!$D$10))-(($J$55-$I$55)/M$76))/(1+Hipotesis!$D$14)^5))+((((((($J$7*$J$10)*$L82)+($J$62-$J$15))*(1-Hipotesis!$D$10))-(($J$55-$I$55)/M$76))*(1+Hipotesis!$D$15)/(Hipotesis!$D$14-Hipotesis!$D$15))/(1+Hipotesis!$D$14)^5)+(Hipotesis!$D$49+Hipotesis!$D$50-Hipotesis!$D$51+Hipotesis!$D$52+Hipotesis!$D$53-Hipotesis!$D$54))/Hipotesis!$D$46*1000 -> 74.710387 | N82: =(($D$82-$J$81+(((((($J$7*$J$10)*$L82)+($J$62-$J$15))*(1-Hipotesis!$D$10))-(($J$55-$I$55)/N$76))/(1+Hipotesis!$D$14)^5))+((((((($J$7*$J$10)*$L82)+($J$62-$J$15))*(1-Hipotesis!$D$10))-(($J$55-$I$55)/N$76))*(1+Hipotesis!$D$15)/(Hipotesis!$D$14-Hipotesis!$D$15))/(1+Hipotesis!$D$14)^5)+(Hipotesis!$D$49+Hipotesis!$D$50-Hipotesis!$D$51+Hipotesis!$D$52+Hipotesis!$D$53-Hipotesis!$D$54))/Hipotesis!$D$46*1000 -> 77.241495 | O82: =(($D$82-$J$81+(((((($J$7*$J$10)*$L82)+($J$62-$J$15))*(1-Hipotesis!$D$10))-(($J$55-$I$55)/O$76))/(1+Hipotesis!$D$14)^5))+((((((($J$7*$J$10)*$L82)+($J$62-$J$15))*(1-Hipotesis!$D$10))-(($J$55-$I$55)/O$76))*(1+Hipotesis!$D$15)/(Hipotesis!$D$14-Hipotesis!$D$15))/(1+Hipotesis!$D$14)^5)+(Hipotesis!$D$49+Hipotesis!$D$50-Hipotesis!$D$51+Hipotesis!$D$52+Hipotesis!$D$53-Hipotesis!$D$54))/Hipotesis!$D$46*1000 -> 78.76016 | P82: =(($D$82-$J$81+(((((($J$7*$J$10)*$L82)+($J$62-$J$15))*(1-Hipotesis!$D$10))-(($J$55-$I$55)/P$76))/(1+Hipotesis!$D$14)^5))+((((((($J$7*$J$10)*$L82)+($J$62-$J$15))*(1-Hipotesis!$D$10))-(($J$55-$I$55)/P$76))*(1+Hipotesis!$D$15)/(Hipotesis!$D$14-Hipotesis!$D$15))/(1+Hipotesis!$D$14)^5)+(Hipotesis!$D$49+Hipotesis!$D$50-Hipotesis!$D$51+Hipotesis!$D$52+Hipotesis!$D$53-Hipotesis!$D$54))/Hipotesis!$D$46*1000 -> 79.772603 | Q82: =(($D$82-$J$81+(((((($J$7*$J$10)*$L82)+($J$62-$J$15))*(1-Hipotesis!$D$10))-(($J$55-$I$55)/Q$76))/(1+Hipotesis!$D$14)^5))+((((((($J$7*$J$10)*$L82)+($J$62-$J$15))*(1-Hipotesis!$D$10))-(($J$55-$I$55)/Q$76))*(1+Hipotesis!$D$15)/(Hipotesis!$D$14-Hipotesis!$D$15))/(1+Hipotesis!$D$14)^5)+(Hipotesis!$D$49+Hipotesis!$D$50-Hipotesis!$D$51+Hipotesis!$D$52+Hipotesis!$D$53-Hipotesis!$D$54))/Hipotesis!$D$46*1000 -> 80.495777 | R82: =(($D$82-$J$81+(((((($J$7*$J$10)*$L82)+($J$62-$J$15))*(1-Hipotesis!$D$10))-(($J$55-$I$55)/R$76))/(1+Hipotesis!$D$14)^5))+((((((($J$7*$J$10)*$L82)+($J$62-$J$15))*(1-Hipotesis!$D$10))-(($J$55-$I$55)/R$76))*(1+Hipotesis!$D$15)/(Hipotesis!$D$14-Hipotesis!$D$15))/(1+Hipotesis!$D$14)^5)+(Hipotesis!$D$49+Hipotesis!$D$50-Hipotesis!$D$51+Hipotesis!$D$52+Hipotesis!$D$53-Hipotesis!$D$54))/Hipotesis!$D$46*1000 -> 81.038157
L84: S2C alto = asset-light; subir de 5x a 7x mueve precio +$2-3.
A86: G. VALORACION - 4 metodos de Terminal Value | L86: Sens G. WACC × TGR (Gordon DCF, recomputo completo)
B87: Inputs comunes: | L87: TGR (g) ↓ WACC →
B88: WACC | D88: =Hipotesis!D14 -> 0.104564 | M88: 0.085 | N88: 0.092 | O88: 0.098 | P88: 0.105 | Q88: 0.112 | R88: 0.118
B89: TGR (g) | D89: =Hipotesis!D15 -> 0.025 | L89: 0.01 | M89: =(($F$75/(1+M$88)^1+$G$75/(1+M$88)^2+$H$75/(1+M$88)^3+$I$75/(1+M$88)^4+$J$75/(1+M$88)^5)+(($J$75*(1+$L89)/(M$88-$L89))/(1+M$88)^5)+(Hipotesis!$D$49+Hipotesis!$D$50-Hipotesis!$D$51+Hipotesis!$D$52+Hipotesis!$D$53-Hipotesis!$D$54))/Hipotesis!$D$46*1000 -> 81.816086 | N89: =(($F$75/(1+N$88)^1+$G$75/(1+N$88)^2+$H$75/(1+N$88)^3+$I$75/(1+N$88)^4+$J$75/(1+N$88)^5)+(($J$75*(1+$L89)/(N$88-$L89))/(1+N$88)^5)+(Hipotesis!$D$49+Hipotesis!$D$50-Hipotesis!$D$51+Hipotesis!$D$52+Hipotesis!$D$53-Hipotesis!$D$54))/Hipotesis!$D$46*1000 -> 74.306488 | O89: =(($F$75/(1+O$88)^1+$G$75/(1+O$88)^2+$H$75/(1+O$88)^3+$I$75/(1+O$88)^4+$J$75/(1+O$88)^5)+(($J$75*(1+$L89)/(O$88-$L89))/(1+O$88)^5)+(Hipotesis!$D$49+Hipotesis!$D$50-Hipotesis!$D$51+Hipotesis!$D$52+Hipotesis!$D$53-Hipotesis!$D$54))/Hipotesis!$D$46*1000 -> 68.832436 | P89: =(($F$75/(1+P$88)^1+$G$75/(1+P$88)^2+$H$75/(1+P$88)^3+$I$75/(1+P$88)^4+$J$75/(1+P$88)^5)+(($J$75*(1+$L89)/(P$88-$L89))/(1+P$88)^5)+(Hipotesis!$D$49+Hipotesis!$D$50-Hipotesis!$D$51+Hipotesis!$D$52+Hipotesis!$D$53-Hipotesis!$D$54))/Hipotesis!$D$46*1000 -> 63.332388 | Q89: =(($F$75/(1+Q$88)^1+$G$75/(1+Q$88)^2+$H$75/(1+Q$88)^3+$I$75/(1+Q$88)^4+$J$75/(1+Q$88)^5)+(($J$75*(1+$L89)/(Q$88-$L89))/(1+Q$88)^5)+(Hipotesis!$D$49+Hipotesis!$D$50-Hipotesis!$D$51+Hipotesis!$D$52+Hipotesis!$D$53-Hipotesis!$D$54))/Hipotesis!$D$46*1000 -> 58.599321 | R89: =(($F$75/(1+R$88)^1+$G$75/(1+R$88)^2+$H$75/(1+R$88)^3+$I$75/(1+R$88)^4+$J$75/(1+R$88)^5)+(($J$75*(1+$L89)/(R$88-$L89))/(1+R$88)^5)+(Hipotesis!$D$49+Hipotesis!$D$50-Hipotesis!$D$51+Hipotesis!$D$52+Hipotesis!$D$53-Hipotesis!$D$54))/Hipotesis!$D$46*1000 -> 55.039537
B90: FCFF 2030E (de seccion F) | D90: =J75 -> 14426.506 | L90: 0.015 | M90: =(($F$75/(1+M$88)^1+$G$75/(1+M$88)^2+$H$75/(1+M$88)^3+$I$75/(1+M$88)^4+$J$75/(1+M$88)^5)+(($J$75*(1+$L90)/(M$88-$L90))/(1+M$88)^5)+(Hipotesis!$D$49+Hipotesis!$D$50-Hipotesis!$D$51+Hipotesis!$D$52+Hipotesis!$D$53-Hipotesis!$D$54))/Hipotesis!$D$46*1000 -> 86.602286 | N90: =(($F$75/(1+N$88)^1+$G$75/(1+N$88)^2+$H$75/(1+N$88)^3+$I$75/(1+N$88)^4+$J$75/(1+N$88)^5)+(($J$75*(1+$L90)/(N$88-$L90))/(1+N$88)^5)+(Hipotesis!$D$49+Hipotesis!$D$50-Hipotesis!$D$51+Hipotesis!$D$52+Hipotesis!$D$53-Hipotesis!$D$54))/Hipotesis!$D$46*1000 -> 78.185079 | O90: =(($F$75/(1+O$88)^1+$G$75/(1+O$88)^2+$H$75/(1+O$88)^3+$I$75/(1+O$88)^4+$J$75/(1+O$88)^5)+(($J$75*(1+$L90)/(O$88-$L90))/(1+O$88)^5)+(Hipotesis!$D$49+Hipotesis!$D$50-Hipotesis!$D$51+Hipotesis!$D$52+Hipotesis!$D$53-Hipotesis!$D$54))/Hipotesis!$D$46*1000 -> 72.112626 | P90: =(($F$75/(1+P$88)^1+$G$75/(1+P$88)^2+$H$75/(1+P$88)^3+$I$75/(1+P$88)^4+$J$75/(1+P$88)^5)+(($J$75*(1+$L90)/(P$88-$L90))/(1+P$88)^5)+(Hipotesis!$D$49+Hipotesis!$D$50-Hipotesis!$D$51+Hipotesis!$D$52+Hipotesis!$D$53-Hipotesis!$D$54))/Hipotesis!$D$46*1000 -> 66.064219 | Q90: =(($F$75/(1+Q$88)^1+$G$75/(1+Q$88)^2+$H$75/(1+Q$88)^3+$I$75/(1+Q$88)^4+$J$75/(1+Q$88)^5)+(($J$75*(1+$L90)/(Q$88-$L90))/(1+Q$88)^5)+(Hipotesis!$D$49+Hipotesis!$D$50-Hipotesis!$D$51+Hipotesis!$D$52+Hipotesis!$D$53-Hipotesis!$D$54))/Hipotesis!$D$46*1000 -> 60.901176 | R90: =(($F$75/(1+R$88)^1+$G$75/(1+R$88)^2+$H$75/(1+R$88)^3+$I$75/(1+R$88)^4+$J$75/(1+R$88)^5)+(($J$75*(1+$L90)/(R$88-$L90))/(1+R$88)^5)+(Hipotesis!$D$49+Hipotesis!$D$50-Hipotesis!$D$51+Hipotesis!$D$52+Hipotesis!$D$53-Hipotesis!$D$54))/Hipotesis!$D$46*1000 -> 57.043275
B91: EBIT 2030E (de seccion E) | D91: =J62 -> 20406.12 | L91: 0.02 | M91: =(($F$75/(1+M$88)^1+$G$75/(1+M$88)^2+$H$75/(1+M$88)^3+$I$75/(1+M$88)^4+$J$75/(1+M$88)^5)+(($J$75*(1+$L91)/(M$88-$L91))/(1+M$88)^5)+(Hipotesis!$D$49+Hipotesis!$D$50-Hipotesis!$D$51+Hipotesis!$D$52+Hipotesis!$D$53-Hipotesis!$D$54))/Hipotesis!$D$46*1000 -> 92.124824 | N91: =(($F$75/(1+N$88)^1+$G$75/(1+N$88)^2+$H$75/(1+N$88)^3+$I$75/(1+N$88)^4+$J$75/(1+N$88)^5)+(($J$75*(1+$L91)/(N$88-$L91))/(1+N$88)^5)+(Hipotesis!$D$49+Hipotesis!$D$50-Hipotesis!$D$51+Hipotesis!$D$52+Hipotesis!$D$53-Hipotesis!$D$54))/Hipotesis!$D$46*1000 -> 82.602363 | O91: =(($F$75/(1+O$88)^1+$G$75/(1+O$88)^2+$H$75/(1+O$88)^3+$I$75/(1+O$88)^4+$J$75/(1+O$88)^5)+(($J$75*(1+$L91)/(O$88-$L91))/(1+O$88)^5)+(Hipotesis!$D$49+Hipotesis!$D$50-Hipotesis!$D$51+Hipotesis!$D$52+Hipotesis!$D$53-Hipotesis!$D$54))/Hipotesis!$D$46*1000 -> 75.813353 | P91: =(($F$75/(1+P$88)^1+$G$75/(1+P$88)^2+$H$75/(1+P$88)^3+$I$75/(1+P$88)^4+$J$75/(1+P$88)^5)+(($J$75*(1+$L91)/(P$88-$L91))/(1+P$88)^5)+(Hipotesis!$D$49+Hipotesis!$D$50-Hipotesis!$D$51+Hipotesis!$D$52+Hipotesis!$D$53-Hipotesis!$D$54))/Hipotesis!$D$46*1000 -> 69.117442 | Q91: =(($F$75/(1+Q$88)^1+$G$75/(1+Q$88)^2+$H$75/(1+Q$88)^3+$I$75/(1+Q$88)^4+$J$75/(1+Q$88)^5)+(($J$75*(1+$L91)/(Q$88-$L91))/(1+Q$88)^5)+(Hipotesis!$D$49+Hipotesis!$D$50-Hipotesis!$D$51+Hipotesis!$D$52+Hipotesis!$D$53-Hipotesis!$D$54))/Hipotesis!$D$46*1000 -> 63.453233 | R91: =(($F$75/(1+R$88)^1+$G$75/(1+R$88)^2+$H$75/(1+R$88)^3+$I$75/(1+R$88)^4+$J$75/(1+R$88)^5)+(($J$75*(1+$L91)/(R$88-$L91))/(1+R$88)^5)+(Hipotesis!$D$49+Hipotesis!$D$50-Hipotesis!$D$51+Hipotesis!$D$52+Hipotesis!$D$53-Hipotesis!$D$54))/Hipotesis!$D$46*1000 -> 59.251476
B92: EBITDA 2030E (de seccion E) | D92: =J72 -> 21726.202 | L92: 0.025 | M92: =(($F$75/(1+M$88)^1+$G$75/(1+M$88)^2+$H$75/(1+M$88)^3+$I$75/(1+M$88)^4+$J$75/(1+M$88)^5)+(($J$75*(1+$L92)/(M$88-$L92))/(1+M$88)^5)+(Hipotesis!$D$49+Hipotesis!$D$50-Hipotesis!$D$51+Hipotesis!$D$52+Hipotesis!$D$53-Hipotesis!$D$54))/Hipotesis!$D$46*1000 -> 98.567786 | N92: =(($F$75/(1+N$88)^1+$G$75/(1+N$88)^2+$H$75/(1+N$88)^3+$I$75/(1+N$88)^4+$J$75/(1+N$88)^5)+(($J$75*(1+$L92)/(N$88-$L92))/(1+N$88)^5)+(Hipotesis!$D$49+Hipotesis!$D$50-Hipotesis!$D$51+Hipotesis!$D$52+Hipotesis!$D$53-Hipotesis!$D$54))/Hipotesis!$D$46*1000 -> 87.678943 | O92: =(($F$75/(1+O$88)^1+$G$75/(1+O$88)^2+$H$75/(1+O$88)^3+$I$75/(1+O$88)^4+$J$75/(1+O$88)^5)+(($J$75*(1+$L92)/(O$88-$L92))/(1+O$88)^5)+(Hipotesis!$D$49+Hipotesis!$D$50-Hipotesis!$D$51+Hipotesis!$D$52+Hipotesis!$D$53-Hipotesis!$D$54))/Hipotesis!$D$46*1000 -> 80.021029 | P92: =(($F$75/(1+P$88)^1+$G$75/(1+P$88)^2+$H$75/(1+P$88)^3+$I$75/(1+P$88)^4+$J$75/(1+P$88)^5)+(($J$75*(1+$L92)/(P$88-$L92))/(1+P$88)^5)+(Hipotesis!$D$49+Hipotesis!$D$50-Hipotesis!$D$51+Hipotesis!$D$52+Hipotesis!$D$53-Hipotesis!$D$54))/Hipotesis!$D$46*1000 -> 72.552318 | Q92: =(($F$75/(1+Q$88)^1+$G$75/(1+Q$88)^2+$H$75/(1+Q$88)^3+$I$75/(1+Q$88)^4+$J$75/(1+Q$88)^5)+(($J$75*(1+$L92)/(Q$88-$L92))/(1+Q$88)^5)+(Hipotesis!$D$49+Hipotesis!$D$50-Hipotesis!$D$51+Hipotesis!$D$52+Hipotesis!$D$53-Hipotesis!$D$54))/Hipotesis!$D$46*1000 -> 66.29863 | R92: =(($F$75/(1+R$88)^1+$G$75/(1+R$88)^2+$H$75/(1+R$88)^3+$I$75/(1+R$88)^4+$J$75/(1+R$88)^5)+(($J$75*(1+$L92)/(R$88-$L92))/(1+R$88)^5)+(Hipotesis!$D$49+Hipotesis!$D$50-Hipotesis!$D$51+Hipotesis!$D$52+Hipotesis!$D$53-Hipotesis!$D$54))/Hipotesis!$D$46*1000 -> 61.697118
B93: Suma PV FCFF explicitos (de seccion F) | D93: =D82 -> 35239.164 | L93: 0.03 | M93: =(($F$75/(1+M$88)^1+$G$75/(1+M$88)^2+$H$75/(1+M$88)^3+$I$75/(1+M$88)^4+$J$75/(1+M$88)^5)+(($J$75*(1+$L93)/(M$88-$L93))/(1+M$88)^5)+(Hipotesis!$D$49+Hipotesis!$D$50-Hipotesis!$D$51+Hipotesis!$D$52+Hipotesis!$D$53-Hipotesis!$D$54))/Hipotesis!$D$46*1000 -> 106.18219 | N93: =(($F$75/(1+N$88)^1+$G$75/(1+N$88)^2+$H$75/(1+N$88)^3+$I$75/(1+N$88)^4+$J$75/(1+N$88)^5)+(($J$75*(1+$L93)/(N$88-$L93))/(1+N$88)^5)+(Hipotesis!$D$49+Hipotesis!$D$50-Hipotesis!$D$51+Hipotesis!$D$52+Hipotesis!$D$53-Hipotesis!$D$54))/Hipotesis!$D$46*1000 -> 93.574326 | O93: =(($F$75/(1+O$88)^1+$G$75/(1+O$88)^2+$H$75/(1+O$88)^3+$I$75/(1+O$88)^4+$J$75/(1+O$88)^5)+(($J$75*(1+$L93)/(O$88-$L93))/(1+O$88)^5)+(Hipotesis!$D$49+Hipotesis!$D$50-Hipotesis!$D$51+Hipotesis!$D$52+Hipotesis!$D$53-Hipotesis!$D$54))/Hipotesis!$D$46*1000 -> 84.84748 | P93: =(($F$75/(1+P$88)^1+$G$75/(1+P$88)^2+$H$75/(1+P$88)^3+$I$75/(1+P$88)^4+$J$75/(1+P$88)^5)+(($J$75*(1+$L93)/(P$88-$L93))/(1+P$88)^5)+(Hipotesis!$D$49+Hipotesis!$D$50-Hipotesis!$D$51+Hipotesis!$D$52+Hipotesis!$D$53-Hipotesis!$D$54))/Hipotesis!$D$46*1000 -> 76.445178 | Q93: =(($F$75/(1+Q$88)^1+$G$75/(1+Q$88)^2+$H$75/(1+Q$88)^3+$I$75/(1+Q$88)^4+$J$75/(1+Q$88)^5)+(($J$75*(1+$L93)/(Q$88-$L93))/(1+Q$88)^5)+(Hipotesis!$D$49+Hipotesis!$D$50-Hipotesis!$D$51+Hipotesis!$D$52+Hipotesis!$D$53-Hipotesis!$D$54))/Hipotesis!$D$46*1000 -> 69.491027 | R93: =(($F$75/(1+R$88)^1+$G$75/(1+R$88)^2+$H$75/(1+R$88)^3+$I$75/(1+R$88)^4+$J$75/(1+R$88)^5)+(($J$75*(1+$L93)/(R$88-$L93))/(1+R$88)^5)+(Hipotesis!$D$49+Hipotesis!$D$50-Hipotesis!$D$51+Hipotesis!$D$52+Hipotesis!$D$53-Hipotesis!$D$54))/Hipotesis!$D$46*1000 -> 64.420673
B94: PV factor año 5 | D94: =1/(1+D88)^5 -> 0.60819883 | L94: 0.035 | M94: =(($F$75/(1+M$88)^1+$G$75/(1+M$88)^2+$H$75/(1+M$88)^3+$I$75/(1+M$88)^4+$J$75/(1+M$88)^5)+(($J$75*(1+$L94)/(M$88-$L94))/(1+M$88)^5)+(Hipotesis!$D$49+Hipotesis!$D$50-Hipotesis!$D$51+Hipotesis!$D$52+Hipotesis!$D$53-Hipotesis!$D$54))/Hipotesis!$D$46*1000 -> 115.31949 | N94: =(($F$75/(1+N$88)^1+$G$75/(1+N$88)^2+$H$75/(1+N$88)^3+$I$75/(1+N$88)^4+$J$75/(1+N$88)^5)+(($J$75*(1+$L94)/(N$88-$L94))/(1+N$88)^5)+(Hipotesis!$D$49+Hipotesis!$D$50-Hipotesis!$D$51+Hipotesis!$D$52+Hipotesis!$D$53-Hipotesis!$D$54))/Hipotesis!$D$46*1000 -> 100.50399 | O94: =(($F$75/(1+O$88)^1+$G$75/(1+O$88)^2+$H$75/(1+O$88)^3+$I$75/(1+O$88)^4+$J$75/(1+O$88)^5)+(($J$75*(1+$L94)/(O$88-$L94))/(1+O$88)^5)+(Hipotesis!$D$49+Hipotesis!$D$50-Hipotesis!$D$51+Hipotesis!$D$52+Hipotesis!$D$53-Hipotesis!$D$54))/Hipotesis!$D$46*1000 -> 90.440035 | P94: =(($F$75/(1+P$88)^1+$G$75/(1+P$88)^2+$H$75/(1+P$88)^3+$I$75/(1+P$88)^4+$J$75/(1+P$88)^5)+(($J$75*(1+$L94)/(P$88-$L94))/(1+P$88)^5)+(Hipotesis!$D$49+Hipotesis!$D$50-Hipotesis!$D$51+Hipotesis!$D$52+Hipotesis!$D$53-Hipotesis!$D$54))/Hipotesis!$D$46*1000 -> 80.89416 | Q94: =(($F$75/(1+Q$88)^1+$G$75/(1+Q$88)^2+$H$75/(1+Q$88)^3+$I$75/(1+Q$88)^4+$J$75/(1+Q$88)^5)+(($J$75*(1+$L94)/(Q$88-$L94))/(1+Q$88)^5)+(Hipotesis!$D$49+Hipotesis!$D$50-Hipotesis!$D$51+Hipotesis!$D$52+Hipotesis!$D$53-Hipotesis!$D$54))/Hipotesis!$D$46*1000 -> 73.09802 | R94: =(($F$75/(1+R$88)^1+$G$75/(1+R$88)^2+$H$75/(1+R$88)^3+$I$75/(1+R$88)^4+$J$75/(1+R$88)^5)+(($J$75*(1+$L94)/(R$88-$L94))/(1+R$88)^5)+(Hipotesis!$D$49+Hipotesis!$D$50-Hipotesis!$D$51+Hipotesis!$D$52+Hipotesis!$D$53-Hipotesis!$D$54))/Hipotesis!$D$46*1000 -> 67.472368
A96: Metodo 1: Gordon Growth | L96: Sens más sensible al spread WACC-g. Cuanto menor, más explosivo el TV.
B97: TV = FCFF(t+1) / (WACC - g) | D97: =D90*(1+D89)/(D88-D89) -> 185852.51
B98: PV(TV) | D98: =D97*D94 -> 113035.28
A100: Metodo 2: H-Model (decadencia gradual)
B101: Crecimiento corto (g_s) | D101: 0.075
B102: Anos de transicion (H/2) | D102: 5
B103: TV = FCFF*(1+g)/(WACC-g) + FCFF*H*(g_s-g)/(WACC-g) | D103: =D90*(1+D89)/(D88-D89)+D90*D102*(D101-D89)/(D88-D89) -> 231182.39
B104: PV(TV) | D104: =D103*D94 -> 140604.86
A106: Metodo 3: Exit Multiple EV/EBITDA
B107: EV/EBITDA salida | D107: =Hipotesis!D16 -> 16
B108: TV = EBITDA(2030) × multiplo | D108: =D92*D107 -> 347619.24
B109: PV(TV) | D109: =D108*D94 -> 211421.61
A111: Metodo 4: Exit Multiple EV/EBIT
B112: EV/EBIT salida | D112: =Hipotesis!D17 -> 18
B113: TV = EBIT(2030) × multiplo | D113: =D91*D112 -> 367310.15
B114: PV(TV) | D114: =D113*D94 -> 223397.6
A116: PUENTE EV → EQUITY → PRECIO POR ACCION
D117: Gordon | E117: H-Model | F117: EV/EBITDA | G117: EV/EBIT | H117: Promedio
B118: Suma PV FCFFs explicitos | D118: =$D$93 -> 35239.164 | E118: =$D$93 -> 35239.164 | F118: =$D$93 -> 35239.164 | G118: =$D$93 -> 35239.164 | H118: =$D$93 -> 35239.164
B119: (+) PV(Terminal Value) | D119: =D98 -> 113035.28 | E119: =D104 -> 140604.86 | F119: =D109 -> 211421.61 | G119: =D114 -> 223397.6 | H119: =AVERAGE(D119:G119) -> 172114.84
B120: Enterprise Value | D120: =D118+D119 -> 148274.44 | E120: =E118+E119 -> 175844.02 | F120: =F118+F119 -> 246660.78 | G120: =G118+G119 -> 258636.77 | H120: =H118+H119 -> 207354
B121: (-) Total debt | D121: =-Hipotesis!$D$51 -> -10514 | E121: =-Hipotesis!$D$51 -> -10514 | F121: =-Hipotesis!$D$51 -> -10514 | G121: =-Hipotesis!$D$51 -> -10514 | H121: =-Hipotesis!$D$51 -> -10514
B122: (+) Cash + ST inv | D122: =Hipotesis!$D$49+Hipotesis!$D$50 -> 6091 | E122: =Hipotesis!$D$49+Hipotesis!$D$50 -> 6091 | F122: =Hipotesis!$D$49+Hipotesis!$D$50 -> 6091 | G122: =Hipotesis!$D$49+Hipotesis!$D$50 -> 6091 | H122: =Hipotesis!$D$49+Hipotesis!$D$50 -> 6091
B123: (+) Equity stakes | D123: =Hipotesis!$D$52 -> 8109 | E123: =Hipotesis!$D$52 -> 8109 | F123: =Hipotesis!$D$52 -> 8109 | G123: =Hipotesis!$D$52 -> 8109 | H123: =Hipotesis!$D$52 -> 8109
B124: (+) Equity method | D124: =Hipotesis!$D$53 -> 268 | E124: =Hipotesis!$D$53 -> 268 | F124: =Hipotesis!$D$53 -> 268 | G124: =Hipotesis!$D$53 -> 268 | H124: =Hipotesis!$D$53 -> 268
B125: (-) NCI | D125: =-Hipotesis!$D$54 -> -1061 | E125: =-Hipotesis!$D$54 -> -1061 | F125: =-Hipotesis!$D$54 -> -1061 | G125: =-Hipotesis!$D$54 -> -1061 | H125: =-Hipotesis!$D$54 -> -1061
B126: Equity Value | D126: =SUM(D120:D125) -> 151167.44 | E126: =SUM(E120:E125) -> 178737.02 | F126: =SUM(F120:F125) -> 249553.78 | G126: =SUM(G120:G125) -> 261529.77 | H126: =SUM(H120:H125) -> 210247
B128: Precio implicito por accion ($) | D128: =D126/Hipotesis!$D$46*1000 -> 72.978709 | E128: =E126/Hipotesis!$D$46*1000 -> 86.288402 | F128: =F126/Hipotesis!$D$46*1000 -> 120.47642 | G128: =G126/Hipotesis!$D$46*1000 -> 126.25804 | H128: =H126/Hipotesis!$D$46*1000 -> 101.50039
B129: Precio actual (spot) | D129: =Hipotesis!$D$55 -> 77.11 | E129: =Hipotesis!$D$55 -> 77.11 | F129: =Hipotesis!$D$55 -> 77.11 | G129: =Hipotesis!$D$55 -> 77.11 | H129: =Hipotesis!$D$55 -> 77.11
...

Sheet DuPont_WC
A1: DuPont ROE + WORKING CAPITAL ANALYSIS
B2: LEYENDA: | C2: AZUL+AMARILLO | D2: Input hardcoded (editable) | E2: AMARILLO FUERTE | F2: Input clave (driver de sensibilidad) | G2: NEGRO | H2: Formula (calculado) | I2: VERDE | J2: Link a otra hoja | K2: VERDE CLARO | L2: Resultado / output
D4: 2020A | E4: 2021A | F4: 2022A | G4: 2023A | H4: 2024A | I4: 2025A
A6: 1. DuPont 5-STEP DECOMPOSITION (datos historicos)
B7: ROE = Tax × Interest × Op Margin × Asset Turnover × Leverage
A9: Inputs (links Historico)
B10: Revenue | D10: =Historico!D7 -> 11139 | E10: =Historico!E7 -> 17455 | F10: =Historico!F7 -> 31877 | G10: =Historico!G7 -> 37281 | H10: =Historico!H7 -> 43978 | I10: =Historico!I7 -> 52017
B11: EBIT (GAAP Operating Income) | D11: =Historico!D17 -> -4863 | E11: =Historico!E17 -> -3824 | F11: =Historico!F17 -> -1832 | G11: =Historico!G17 -> 1110 | H11: =Historico!H17 -> 2799 | I11: =Historico!I17 -> 5565
B12: Non-operating income/(loss) - hardcode | D12: -2725 | E12: 3292 | F12: -7029 | G12: 738 | H12: 7350 | I12: 4500
B13: EBT = EBIT + Non-op | D13: =D11+D12 -> -7588 | E13: =E11+E12 -> -532 | F13: =F11+F12 -> -8861 | G13: =G11+G12 -> 1848 | H13: =H11+H12 -> 10149 | I13: =I11+I12 -> 10065
B14: Net Income (UBER) | D14: =Historico!D22 -> -6768 | E14: =Historico!E22 -> -496 | F14: =Historico!F22 -> -9141 | G14: =Historico!G22 -> 1887 | H14: =Historico!H22 -> 9856 | I14: =Historico!I22 -> 10053
B15: Total Assets (avg of beg+end) | D15: =Historico!D49 -> 33252 | E15: =(Historico!D49+Historico!E49)/2 -> 36013 | F15: =(Historico!E49+Historico!F49)/2 -> 35441.5 | G15: =(Historico!F49+Historico!G49)/2 -> 35404 | H15: =(Historico!G49+Historico!H49)/2 -> 44971.5 | I15: =(Historico!H49+Historico!I49)/2 -> 56523
B16: Stockholders' Equity (avg) | D16: =Historico!D50 -> 12266 | E16: =(Historico!D50+Historico!E50)/2 -> 13362 | F16: =(Historico!E50+Historico!F50)/2 -> 10899 | G16: =(Historico!F50+Historico!G50)/2 -> 9294.5 | H16: =(Historico!G50+Historico!H50)/2 -> 16403.5 | I16: =(Historico!H50+Historico!I50)/2 -> 24299.5
A18: Componentes de DuPont 5-step
B19: Tax Burden (NI / EBT) | D19: =IFERROR(D14/D13,0) -> 0.89193463 | E19: =IFERROR(E14/E13,0) -> 0.93233083 | F19: =IFERROR(F14/F13,0) -> 1.0315991 | G19: =IFERROR(G14/G13,0) -> 1.0211039 | H19: =IFERROR(H14/H13,0) -> 0.97113016 | I19: =IFERROR(I14/I13,0) -> 0.99880775
B20: Interest Burden (EBT / EBIT) | D20: =IFERROR(D13/D11,0) -> 1.5603537 | E20: =IFERROR(E13/E11,0) -> 0.13912134 | F20: =IFERROR(F13/F11,0) -> 4.8367904 | G20: =IFERROR(G13/G11,0) -> 1.6648649 | H20: =IFERROR(H13/H11,0) -> 3.6259378 | I20: =IFERROR(I13/I11,0) -> 1.8086253
B21: EBIT margin (EBIT / Revenue) | D21: =D11/D10 -> -0.4365742 | E21: =E11/E10 -> -0.21907763 | F21: =F11/F10 -> -0.057470904 | G21: =G11/G10 -> 0.029773879 | H21: =H11/H10 -> 0.063645459 | I21: =I11/I10 -> 0.10698426
B22: Asset Turnover (Revenue / Assets) | D22: =D10/D15 -> 0.33498737 | E22: =E10/E15 -> 0.48468609 | F22: =F10/F15 -> 0.89942581 | G22: =G10/G15 -> 1.0530166 | H22: =H10/H15 -> 0.97790823 | I22: =I10/I15 -> 0.92028024
B23: Equity Multiplier (Assets / Equity) | D23: =D15/D16 -> 2.7109082 | E23: =E15/E16 -> 2.6951804 | F23: =F15/F16 -> 3.2518121 | G23: =G15/G16 -> 3.8091344 | H23: =H15/H16 -> 2.7415795 | I23: =I15/I16 -> 2.3260972
B25: ROE (5-step product) | D25: =D19*D20*D21*D22*D23 -> -0.55176912 | E25: =E19*E20*E21*E22*E23 -> -0.037120192 | F25: =F19*F20*F21*F22*F23 -> -0.8387008 | G25: =G19*G20*G21*G22*G23 -> 0.20302329 | H25: =H19*H20*H21*H22*H23 -> 0.60084738 | I25: =I19*I20*I21*I22*I23 -> 0.41371222
B26: ROE (NI / Equity, check) | D26: =D14/D16 -> -0.55176912 | E26: =E14/E16 -> -0.037120192 | F26: =F14/F16 -> -0.8387008 | G26: =G14/G16 -> 0.20302329 | H26: =H14/H16 -> 0.60084738 | I26: =I14/I16 -> 0.41371222
B28: Comentario: | D28: ROE 2024-2025 distorsionado por valuation allowance release y ganancias en equity stakes.
A30: 2. ROE OPERATIVO (NOPAT-based, mas representativo)
B31: Limpia distorsiones de tax NOLs y equity investment marks
B33: EBIT (de arriba) | D33: =D11 -> -4863 | E33: =E11 -> -3824 | F33: =F11 -> -1832 | G33: =G11 -> 1110 | H33: =H11 -> 2799 | I33: =I11 -> 5565
B34: Tipo impositivo asumido (Hipotesis) | D34: =Hipotesis!$D$10 -> 0.22 | E34: =Hipotesis!$D$10 -> 0.22 | F34: =Hipotesis!$D$10 -> 0.22 | G34: =Hipotesis!$D$10 -> 0.22 | H34: =Hipotesis!$D$10 -> 0.22 | I34: =Hipotesis!$D$10 -> 0.22
B35: NOPAT = EBIT × (1-T) | D35: =D33*(1-D34) -> -3793.14 | E35: =E33*(1-E34) -> -2982.72 | F35: =F33*(1-F34) -> -1428.96 | G35: =G33*(1-G34) -> 865.8 | H35: =H33*(1-H34) -> 2183.22 | I35: =I33*(1-I34) -> 4340.7
B36: Capital invertido (Equity + LT debt - Cash) | D36: =Historico!D50+Historico!D52-Historico!D53 -> 12435 | E36: =Historico!E50+Historico!E52-Historico!E53 -> 15929 | F36: =Historico!F50+Historico!F52-Historico!F53 -> 11198 | G36: =Historico!G50+Historico!G52-Historico!G53 -> 15481 | H36: =Historico!H50+Historico!H52-Historico!H53 -> 25100 | I36: =Historico!I50+Historico!I52-Historico!I53 -> 29929
B37: ROIC operativo = NOPAT / Capital invertido | D37: =IFERROR(D35/D36,0) -> -0.30503739 | E37: =IFERROR(E35/E36,0) -> -0.18725093 | F37: =IFERROR(F35/F36,0) -> -0.1276085 | G37: =IFERROR(G35/G36,0) -> 0.05592662 | H37: =IFERROR(H35/H36,0) -> 0.086980876 | I37: =IFERROR(I35/I36,0) -> 0.14503325
B38: ROCE = EBIT / Capital invertido | D38: =IFERROR(D33/D36,0) -> -0.39107358 | E38: =IFERROR(E33/E36,0) -> -0.24006529 | F38: =IFERROR(F33/F36,0) -> -0.16360064 | G38: =IFERROR(G33/G36,0) -> 0.071700795 | H38: =IFERROR(H33/H36,0) -> 0.11151394 | I38: =IFERROR(I33/I36,0) -> 0.18594006
B40: Lectura:
B41: - ROE GAAP 2025 = ~37% pero distorsionado al alza
B42: - ROIC operativo subyacente = ~25-30% (FY2025) — un negocio con muy alto retorno sobre capital
B43: - La trayectoria 2020 → 2025 muestra el flip de quema de capital a generacion de valor
A46: 3. WORKING CAPITAL ANALYSIS
A48: Componentes de WC (links Historico)
B49: Accounts Receivable | D49: =Historico!D54 -> 1110 | E49: =Historico!E54 -> 2439 | F49: =Historico!F54 -> 2477 | G49: =Historico!G54 -> 2779 | H49: =Historico!H54 -> 3399 | I49: =Historico!I54 -> 3850
B50: Accounts Payable | D50: =Historico!D55 -> 235 | E50: =Historico!E55 -> 396 | F50: =Historico!F55 -> 622 | G50: =Historico!G55 -> 712 | H50: =Historico!H55 -> 858 | I50: =Historico!I55 -> 1013
B51: ST Insurance reserves | D51: =Historico!D56 -> 1243 | E51: =Historico!E56 -> 1442 | F51: =Historico!F56 -> 2049 | G51: =Historico!G56 -> 2528 | H51: =Historico!H56 -> 2754 | I51: =Historico!I56 -> 3050
B52: LT Insurance reserves | D52: =Historico!D57 -> 2812 | E52: =Historico!E57 -> 2823 | F52: =Historico!F57 -> 3370 | G52: =Historico!G57 -> 3736 | H52: =Historico!H57 -> 4102 | I52: =Historico!I57 -> 4400
A54: Ratios de eficiencia operativa
B55: DSO = AR / Revenue × 365 (días) | D55: =D49/Historico!D7*365 -> 36.372206 | E55: =E49/Historico!E7*365 -> 51.001719 | F55: =F49/Historico!F7*365 -> 28.362299 | G55: =G49/Historico!G7*365 -> 27.207827 | H55: =H49/Historico!H7*365 -> 28.210355 | I55: =I49/Historico!I7*365 -> 27.015207
B56: DPO = AP / Cost of Revenue × 365 (días) | D56: =D50/Historico!D10*365 -> 16.642414 | E56: =E50/Historico!E10*365 -> 15.45717 | F56: =F50/Historico!F10*365 -> 12.109558 | G56: =G50/Historico!G10*365 -> 12.080138 | H56: =H50/Historico!H10*365 -> 11.820412 | I56: =I50/Historico!I10*365 -> 11.81747
B57: Insurance reserves total | D57: =D51+D52 -> 4055 | E57: =E51+E52 -> 4265 | F57: =F51+F52 -> 5419 | G57: =G51+G52 -> 6264 | H57: =H51+H52 -> 6856 | I57: =I51+I52 -> 7450
B58: Insurance reserves / Revenue | D58: =D57/Historico!D7 -> 0.36403627 | E58: =E57/Historico!E7 -> 0.2443426 | F58: =F57/Historico!F7 -> 0.16999718 | G58: =G57/Historico!G7 -> 0.16802124 | H58: =H57/Historico!H7 -> 0.15589613 | I58: =I57/Historico!I7 -> 0.14322241
B59: Insurance reserves / Mobility GB | D59: =D57/Historico!D30 -> 0.15271344 | E59: =E57/Historico!E30 -> 0.11016971 | F59: =F57/Historico!F30 -> 0.10910226 | G59: =G57/Historico!G30 -> 0.096376644 | H59: =H57/Historico!H30 -> 0.083852109 | I59: =I57/Historico!I30 -> 0.076412608
A61: Working Capital implicado
B62: Working Capital simplificado
B63: = AR - AP - Insurance reserves
B64: Net Working Capital ($M) | D64: =D49-D50-D57 -> -3180 | E64: =E49-E50-E57 -> -2222 | F64: =F49-F50-F57 -> -3564 | G64: =G49-G50-G57 -> -4197 | H64: =H49-H50-H57 -> -4315 | I64: =I49-I50-I57 -> -4613
B65: NWC / Revenue | D65: =D64/Historico!D7 -> -0.28548344 | E65: =E64/Historico!E7 -> -0.12729877 | F65: =F64/Historico!F7 -> -0.11180475 | G65: =G64/Historico!G7 -> -0.11257745 | H65: =H64/Historico!H7 -> -0.09811724 | I65: =I64/Historico!I7 -> -0.088682546
B66: ΔNWC YoY ($M) | E66: =E64-D64 -> 958 | F66: =F64-E64 -> -1342 | G66: =G64-F64 -> -633 | H66: =H64-G64 -> -118 | I66: =I64-H64 -> -298
B67: ΔNWC / ΔRevenue (sales-to-capital reverso) | E67: =IFERROR(E66/(Historico!E7-Historico!D7),0) -> 0.15167828 | F67: =IFERROR(F66/(Historico!F7-Historico!E7),0) -> -0.093052281 | G67: =IFERROR(G66/(Historico!G7-Historico!F7),0) -> -0.11713546 | H67: =IFERROR(H66/(Historico!H7-Historico!G7),0) -> -0.01761983 | I67: =IFERROR(I66/(Historico!I7-Historico!H7),0) -> -0.037069287
A69: 4. CASH CONVERSION CYCLE (framework completo)
B70: CCC = DSO + DIO - DPO. Para UBER, DIO = 0 (no hay inventario).
A72: Inventario
B73: Inventory ($M) | D73: 0 | E73: 0 | F73: 0 | G73: 0 | H73: 0 | I73: 0
B74: Cost of Revenue (excl D&A) ($M) | D74: =Historico!D10 -> 5154 | E74: =Historico!E10 -> 9351 | F74: =Historico!F10 -> 18748 | G74: =Historico!G10 -> 21513 | H74: =Historico!H10 -> 26494 | I74: =Historico!I10 -> 31288
A76: Inventory metrics (N/A para UBER)
B77: DIO = Inventory / COGS x 365 (dias) | D77: =IFERROR(D73/D74*365,0) -> 0 | E77: =IFERROR(E73/E74*365,0) -> 0 | F77: =IFERROR(F73/F74*365,0) -> 0 | G77: =IFERROR(G73/G74*365,0) -> 0 | H77: =IFERROR(H73/H74*365,0) -> 0 | I77: =IFERROR(I73/I74*365,0) -> 0
B78: Inventory Turnover (x) | D78: =IF(D73>0,D74/D73,"N/A") -> N/A | E78: =IF(E73>0,E74/E73,"N/A") -> N/A | F78: =IF(F73>0,F74/F73,"N/A") -> N/A | G78: =IF(G73>0,G74/G73,"N/A") -> N/A | H78: =IF(H73>0,H74/H73,"N/A") -> N/A | I78: =IF(I73>0,I74/I73,"N/A") -> N/A
A80: Receivables & Payables turnover
B81: AR Turnover = Revenue / AR (x) | D81: =Historico!D7/D49 -> 10.035135 | E81: =Historico!E7/E49 -> 7.1566216 | F81: =Historico!F7/F49 -> 12.869197 | G81: =Historico!G7/G49 -> 13.415257 | H81: =Historico!H7/H49 -> 12.938511 | I81: =Historico!I7/I49 -> 13.510909
B82: AP Turnover = COGS / AP (x) | D82: =Historico!D10/D50 -> 21.931915 | E82: =Historico!E10/E50 -> 23.613636 | F82: =Historico!F10/F50 -> 30.141479 | G82: =Historico!G10/G50 -> 30.214888 | H82: =Historico!H10/H50 -> 30.878788 | I82: =Historico!I10/I50 -> 30.886476
B83: Asset Turnover = Revenue / Total Assets (x) | D83: =Historico!D7/Historico!D49 -> 0.33498737 | E83: =Historico!E7/Historico!E49 -> 0.4501728 | F83: =Historico!F7/Historico!F49 -> 0.99277461 | G83: =Historico!G7/Historico!G49 -> 0.96335823 | H83: =Historico!H7/Historico!H49 -> 0.85820779 | I83: =Historico!I7/Historico!I49 -> 0.84167179
A85: Operating Cycle y Cash Conversion Cycle
B86: Operating Cycle = DIO + DSO (dias) | D86: =D77+D55 -> 36.372206 | E86: =E77+E55 -> 51.001719 | F86: =F77+F55 -> 28.362299 | G86: =G77+G55 -> 27.207827 | H86: =H77+H55 -> 28.210355 | I86: =I77+I55 -> 27.015207
B87: Cash Conversion Cycle = DIO + DSO - DPO (dias) | D87: =D77+D55-D56 -> 19.729792 | E87: =E77+E55-E56 -> 35.544548 | F87: =F77+F55-F56 -> 16.25274 | G87: =G77+G55-G56 -> 15.127689 | H87: =H77+H55-H56 -> 16.389943 | I87: =I77+I55-I56 -> 15.197737
B89: Insurance reserves DAYS = Reserves / GB x 365 | D89: =D57/Historico!D30*365 -> 55.740406 | E89: =E57/Historico!E30*365 -> 40.211944 | F89: =F57/Historico!F30*365 -> 39.822324 | G89: =G57/Historico!G30*365 -> 35.177475 | H89: =H57/Historico!H30*365 -> 30.60602 | I89: =I57/Historico!I30*365 -> 27.890602
B90: CCC ajustado = CCC - Insurance reserves days | D90: =D87-D89 -> -36.010614 | E90: =E87-E89 -> -4.667396 | F90: =F87-F89 -> -23.569583 | G90: =G87-G89 -> -20.049786 | H90: =H87-H89 -> -14.216077 | I90: =I87-I89 -> -12.692865
B92: Lectura UBER:
B93: - CCC clasico = DSO - DPO ~ +15-20 dias (sin ajustar)
B94: - CCC ajustado por insurance reserves es FUERTEMENTE NEGATIVO
B95: - El framework CCC clasico no esta diseñado para asset-light platforms
B96: - Las insurance reserves actuan como linea de financiamiento gratuita
A98: 5. CONCLUSIONES Y INSIGHTS
B100: - ROIC operativo 2025 cerca del 14-15% — negocio asset-light en transicion a alto retorno
B101: - Insurance reserves crecen con escala (~3-4% sobre GB) — fuente estructural de financiamiento gratuito
B102: - Working Capital es NEGATIVO (NWC < 0) — el negocio se autofinancia: cobra rapido, paga reservas
B103: - Cada $1 incremental de revenue libera ~$0.05 de WC (ΔWC/ΔRev negativo) — tailwind de cash
B104: - DSO ~25-30 dias, DPO bajo — proveedores se pagan rapido, clientes aun mas rapido
B105: - DIO = 0 (sin inventario) — confirma modelo asset-light puro
B106: - ROE GAAP 2024-2025 (~37-60%) NO es replicable: depende de equity stakes marks y NOL releases
B107: - Para valoracion: usar ROIC operativo (~14-15%), no ROE GAAP
B110: Chart helper data: | D110: 2020A | E110: 2021A | F110: 2022A | G110: 2023A | H110: 2024A | I110: 2025A
C111: ROE GAAP | D111: =D25 -> -0.55176912 | E111: =E25 -> -0.037120192 | F111: =F25 -> -0.8387008 | G111: =G25 -> 0.20302329 | H111: =H25 -> 0.60084738 | I111: =I25 -> 0.41371222
C112: ROIC operativo | D112: =D37 -> -0.30503739 | E112: =E37 -> -0.18725093 | F112: =F37 -> -0.1276085 | G112: =G37 -> 0.05592662 | H112: =H37 -> 0.086980876 | I112: =I37 -> 0.14503325
C113: EBIT margin | D113: =D21 -> -0.4365742 | E113: =E21 -> -0.21907763 | F113: =F21 -> -0.057470904 | G113: =G21 -> 0.029773879 | H113: =H21 -> 0.063645459 | I113: =I21 -> 0.10698426
C114: Asset Turnover (x) | D114: =D22 -> 0.33498737 | E114: =E22 -> 0.48468609 | F114: =F22 -> 0.89942581 | G114: =G22 -> 1.0530166 | H114: =H22 -> 0.97790823 | I114: =I22 -> 0.92028024
C115: Accounts Receivable | D115: =D49 -> 1110 | E115: =E49 -> 2439 | F115: =F49 -> 2477 | G115: =G49 -> 2779 | H115: =H49 -> 3399 | I115: =I49 -> 3850
C116: Accounts Payable | D116: =D50 -> 235 | E116: =E50 -> 396 | F116: =F50 -> 622 | G116: =G50 -> 712 | H116: =H50 -> 858 | I116: =I50 -> 1013
C117: Insurance reserves | D117: =D57 -> 4055 | E117: =E57 -> 4265 | F117: =F57 -> 5419 | G117: =G57 -> 6264 | H117: =H57 -> 6856 | I117: =I57 -> 7450
C118: NWC (negativo) | D118: =D64 -> -3180 | E118: =E64 -> -2222 | F118: =F64 -> -3564 | G118: =G64 -> -4197 | H118: =H64 -> -4315 | I118: =I64 -> -4613
C119: DSO (dias) | D119: =D55 -> 36.372206 | E119: =E55 -> 51.001719 | F119: =F55 -> 28.362299 | G119: =G55 -> 27.207827 | H119: =H55 -> 28.210355 | I119: =I55 -> 27.015207
C120: DPO (dias) | D120: =D56 -> 16.642414 | E120: =E56 -> 15.45717 | F120: =F56 -> 12.109558 | G120: =G56 -> 12.080138 | H120: =H56 -> 11.820412 | I120: =I56 -> 11.81747
C121: CCC clasico | D121: =D87 -> 19.729792 | E121: =E87 -> 35.544548 | F121: =F87 -> 16.25274 | G121: =G87 -> 15.127689 | H121: =H87 -> 16.389943 | I121: =I87 -> 15.197737
C122: CCC ajustado (insur.) | D122: =D90 -> -36.010614 | E122: =E90 -> -4.667396 | F122: =F90 -> -23.569583 | G122: =G90 -> -20.049786 | H122: =H90 -> -14.216077 | I122: =I90 -> -12.692865

Sheet Reverse_DCF
A1: REVERSE DCF - que esta priceando el mercado
B2: LEYENDA: | C2: AZUL+AMARILLO | D2: Input hardcoded (editable) | E2: AMARILLO FUERTE | F2: Input clave (driver de sensibilidad) | G2: NEGRO | H2: Formula (calculado) | I2: VERDE | J2: Link a otra hoja | K2: VERDE CLARO | L2: Resultado / output
A4: Concepto: tomamos el spot price como dado y resolvemos hacia atras los inputs implicitos.
B5: Ayuda a contrastar tu tesis con lo que el mercado ya esta descontando.
A7: 1. ESTADO DE MERCADO + CASO BASE (links)
B8: Spot price ($) | D8: =Hipotesis!D55 -> 77.11
B9: Acciones diluidas (k) | D9: =Hipotesis!D46 -> 2071391
B10: Market Cap ($M) | D10: =D8*D9/1000 -> 159724.96
B11: (+) LT Debt | D11: =Hipotesis!D51 -> 10514
B12: (-) Cash + ST inv | D12: =-Hipotesis!D49-Hipotesis!D50 -> -6091
B13: (-) Equity stakes (Aurora, Grab, Didi, Lucid, etc.) | D13: =-Hipotesis!D52 -> -8109
B14: (-) Equity method investments | D14: =-Hipotesis!D53 -> -268
B15: (+) NCI | D15: =Hipotesis!D54 -> 1061
B16: OPERATING EV (lo que el mercado paga por las operaciones) | D16: =SUM(D10:D15) -> 156831.96
A18: Parametros del caso base (Hipotesis):
B19: WACC | D19: =Hipotesis!D14 -> 0.104564
B20: TGR (g) base | D20: =Hipotesis!D15 -> 0.025
B21: Tipo impositivo (T) | D21: =Hipotesis!D10 -> 0.22
B22: Sales-to-Capital (S2C) | D22: =Hipotesis!D40 -> 5
A24: Proyeccion del modelo (FCFF 2026-2030 en $M, link Modelo):
D25: 2026E | E25: 2027E | F25: 2028E | G25: 2029E | H25: 2030E
B26: FCFF base ($M) | D26: =Modelo!F75 -> 5544.8669 | E26: =Modelo!G75 -> 7167.5812 | F26: =Modelo!H75 -> 9930.7477 | G26: =Modelo!I75 -> 12207.956 | H26: =Modelo!J75 -> 14426.506
B27: EBIT base ($M) | D27: =Modelo!F62 -> 8486.9215 | E27: =Modelo!G62 -> 11952.671 | F27: =Modelo!H62 -> 15214.131 | G27: =Modelo!I62 -> 17945.519 | H27: =Modelo!J62 -> 20406.12
B28: EBITDA base ($M) | D28: =Modelo!F72 -> 9290.9927 | E28: =Modelo!G72 -> 12907.628 | F28: =Modelo!H72 -> 16304.627 | G28: =Modelo!I72 -> 19161.283 | H28: =Modelo!J72 -> 21726.202
B29: Revenue base ($M) | D29: =Modelo!F55 -> 57433.66 | E29: =Modelo!G55 -> 68211.172 | F29: =Modelo!H55 -> 77892.545 | G29: =Modelo!I55 -> 86840.293 | H29: =Modelo!J55 -> 94291.628
B30: Periodo de descuento | D30: =1 -> 1 | E30: =2 -> 2 | F30: =3 -> 3 | G30: =4 -> 4 | H30: =5 -> 5
B31: PV factor (1+WACC)^-t | D31: =1/(1+$D$19)^D30 -> 0.90533459 | E31: =1/(1+$D$19)^E30 -> 0.81963073 | F31: =1/(1+$D$19)^F30 -> 0.74204005 | G31: =1/(1+$D$19)^G30 -> 0.67179453 | H31: =1/(1+$D$19)^H30 -> 0.60819883
B32: PV de FCFF base | D32: =D26*D31 -> 5019.9598 | E32: =E26*E31 -> 5874.7697 | F32: =F26*F31 -> 7369.0126 | G32: =G26*G31 -> 8201.2377 | H32: =H26*H31 -> 8774.1841
B33: Suma PV FCFFs explicitos (5 anos) | D33: =SUM(D32:H32) -> 35239.164
B34: Required PV(TV) = Operating EV - Sum PV explicit | D34: =D16-D33 -> 121592.8
B35: Required Terminal Value @ Y5 = Required PV(TV) / PV factor Y5 | D35: =D34/H31 -> 199922.77
A37: 2. METODO A. Gordon single-stage - implied perpetual growth
B38: Formula: EV = FCFF*(1+g)/(WACC-g) --> g = (EV*WACC - FCFF)/(EV+FCFF)
A40: Resolviendo para distintos FCFF base:
D41: FCFF base ($M) | E41: Implied g (%) | F41: vs base 2.5% | G41: Lectura
B42: Usando FCFF 2025 (actual) | D42: =Historico!I62 -> 9763 | E42: =($D$16*$D$19-D42)/($D$16+D42) -> 0.039833 | F42: =E42-$D$20 -> 0.014833 | G42: Si crees que 2025 es el run-rate sostenible -> el mercado pide alto crecimiento
B43: Usando FCFF 2026E (modelo) | D43: =D26 -> 5544.8669 | E43: =($D$16*$D$19-D43)/($D$16+D43) -> 0.066845192 | F43: =E43-$D$20 -> 0.041845192 | G43: Si tomas el FCFF NTM como base -> g implicito alto (FCFF crecera)
B44: Usando FCFF 2030E (modelo) | D44: =H26 -> 14426.506 | E44: =($D$16*$D$19-D44)/($D$16+D44) -> 0.011517509 | F44: =E44-$D$20 -> -0.013482491 | G44: Si crees al modelo, el g implicito es bajo y compatible con perpetuidad madura
B46: Conclusion Metodo A:
B47: La eleccion del FCFF base cambia drasticamente el g implicito.
B48: Por eso un Gordon single-stage es POBRE para empresas en crecimiento como UBER.
B49: Mejor usar Metodo B (two-stage) que separa periodo explicito de perpetuidad.
A51: 3. METODO B. Two-stage - implied terminal growth (post-2030)
B52: Dado el modelo explicito 2026-2030, ¿que g perpetuo justifica el spot?
B53: Formula: g = (TV_required*WACC - FCFF_2030)/(TV_required + FCFF_2030)
A55: Calculo:
B56: Required TV at Y5 ($M) | D56: =D35 -> 199922.77
B57: FCFF 2030E base | D57: =H26 -> 14426.506
B58: Implied terminal g | D58: =(D56*D19-D57)/(D56+D57) -> 0.030222722
B59: vs base case g (2.5%) | D59: =D58-D20 -> 0.0052227219
B61: Lectura:
B62: Si implied g > 2.5% (base) -> mercado mas optimista que el modelo en perpetuidad
B63: Si implied g < 2.5% -> el modelo es mas optimista que el mercado
B64: Plausibilidad: g sostenible para perpetuidad debe estar <= LT GDP nominal (~3.5-4%)
A66: 4. METODO C. Implied exit multiple EV/EBITDA @ Year 5
B67: Asumiendo modelo explicito + WACC base, ¿que multiplo de salida pricea el mercado?
B68: Formula: multiple = Required TV @ Y5 / EBITDA 2030E
A70: Calculo:
B71: Required TV at Y5 ($M) | D71: =D35 -> 199922.77
B72: EBITDA 2030E base ($M) | D72: =H28 -> 21726.202
B73: Implied EV/EBITDA exit multiple | D73: =D71/D72 -> 9.2019198
B74: vs base case multiplo (16x) | D74: =D73-Hipotesis!D16 -> -6.7980802
B75: EBIT 2030E base ($M) | D75: =H27 -> 20406.12
B76: Implied EV/EBIT exit multiple | D76: =D71/D75 -> 9.7971969
B77: vs base case multiplo (18x) | D77: =D76-Hipotesis!D17 -> -8.2028031
B79: Lectura:
B80: UBER hoy cotiza ~17x EBITDA (NTM 2026E). Si implied exit < 17x, mercado espera CONTRACCION del multiplo.
B81: Contraccion del multiplo es razonable al madurar (de high-growth -> mature platform).
B82: Si implied exit < 10x EBITDA -> el mercado pricea madurez completa para 2030.
A84: 5. METODO D. Implied 2030E EBIT margin (fijando WACC, g, S2C, revenue al base)
B85: ¿Que margen operativo en 2030 se requiere para justificar el spot?
A87: Calculo:
B88: Sum PV FCFF 2026-2029 (excluding 2030) | D88: =D33-G32 -> 27037.926
B89: Required FCFF 2030E (implied) | D89: =(D16-D88)*(D19-D20)*(1+D19)^4 -> 15372.159
B90: vs FCFF 2030E base | D90: =H26 -> 14426.506
B91: Diferencia ($M) | D91: =D89-D90 -> 945.65309
B92: % diferencia vs base | D92: =D89/D90-1 -> 0.065549696
A94: Back-out del EBIT margin:
B95: Required FCFF 2030 (de arriba) | D95: =D89 -> 15372.159
B96: Reinversion 2030 base (ΔRev/S2C) | D96: =(H29-G29)/D22 -> 1490.2671
B97: NOPAT requerido 2030 = FCFF + Reinvest | D97: =D95+D96 -> 16862.426
B98: EBIT requerido 2030 = NOPAT/(1-T) | D98: =D97/(1-D21) -> 21618.495
B99: Revenue 2030 base | D99: =H29 -> 94291.628
B100: Implied EBIT margin 2030 | D100: =D98/D99 -> 0.22927269
B101: vs EBIT margin base 2030 | D101: =Modelo!J63 -> 0.21641497
B102: Diferencia (bps) | D102: =(D100-D101)*10000 -> 128.57724
B104: Lectura:
B105: Si implied margin > base (21.6%) -> mercado pide mas operating leverage
B106: Si implied margin < base -> mercado es escéptico sobre la expansion del modelo
B107: Comparar con Mobility Op Margin Q1 26 (29.8%), peers consumer tech (15-25%)
A109: 6. METODO E. Implied 5Y FCFF CAGR (2025 -> 2030 implied)
B110: Dado FCFF 2030 implied y FCFF 2025 actual, ¿que CAGR esta priceando?
A112: Calculo:
B113: FCFF 2025 actual ($M) | D113: =Historico!I62 -> 9763
B114: FCFF 2030 implied (Metodo D) | D114: =D89 -> 15372.159
B115: Implied 5Y FCFF CAGR 2025-2030 | D115: =(D114/D113)^(1/5)-1 -> 0.095040842
B116: Base case CAGR (modelo) | D116: =(H26/D113)^(1/5)-1 -> 0.081223747
B118: Lectura: si implied > base, mercado mas optimista en growth de FCFF que el modelo
A120: 7. RESUMEN - IMPLIED vs BASE (todos los metodos)
B121: Metodo / Variable | D121: Implied | E121: Base case | F121: Gap | G121: Plausibilidad
...

Sheet Fuentes
A1: FUENTES Y METODOLOGIA / trazabilidad completa
B2: LEYENDA: | C2: AZUL+AMARILLO | D2: Input hardcoded (editable) | E2: AMARILLO FUERTE | F2: Input clave (driver de sensibilidad) | G2: NEGRO | H2: Formula (calculado) | I2: VERDE | J2: Link a otra hoja | K2: VERDE CLARO | L2: Resultado / output
A4: 1. FUENTES FINANCIERAS PRIMARIAS (SEC EDGAR)
B5: Item | C5: Documento | D5: URL / Referencia
B6: FY2025 Q4 + Annual press release | C6: 8-K filed Feb 5, 2026 | D6: https://www.sec.gov/Archives/edgar/data/1543151/000154315126000011/uberq425earningspressrelea.htm
B7: Form 10-K FY2025 | C7: Filed Feb 13, 2026 | D7: https://www.sec.gov/Archives/edgar/data/1543151/000154315126000015/uber-20251231.htm
B8: Q4 2025 Prepared Remarks | C8: Earnings call materials | D8: https://s23.q4cdn.com/407969754/files/doc_earnings/2025/q4/transcript/Uber-Q4-25-Prepared-Remarks.pdf
B9: Q1 2026 Earnings press release | C9: 8-K filed May 6, 2026 | D9: https://www.sec.gov/Archives/edgar/data/1543151/000154315126000019/uberq126earningspressrelea.htm
B10: Q3 2025 10-Q | C10: Filed Nov 2025 | D10: https://www.sec.gov/cgi-bin/browse-edgar?action=getcompany&CIK=0001543151&type=10-Q
B11: Q2 2025 10-Q | C11: Filed Aug 2025 | D11: https://www.sec.gov/Archives/edgar/data/1543151/000154315125000023/uber-20250630.htm
B12: Q1 2025 10-Q | C12: Filed May 2025 | D12: https://www.sec.gov/Archives/edgar/data/1543151/000154315125000015/uber-20250331.htm
B13: Form 10-K FY2024 | C13: Filed Feb 2025 | D13: https://www.sec.gov/Archives/edgar/data/1543151/000154315125000008/uber-20241231.htm
B14: Investor Relations | C14: Quarterly materials & releases | D14: https://investor.uber.com/financials/default.aspx
A17: 2. DATOS DE MERCADO (precio, beta, tasas)
B18: Item | C18: Valor | D18: Fuente
B19: Precio UBER (spot) | C19: $77.11 al 8 May 2026 (NYSE close) | D19: Robinhood, CNBC, Bloomberg
B20: Beta apalancado 5Y | C20: 1.30 (midpoint rango 1.21-1.65) | D20: Yahoo Finance 5Y monthly, Walletinvestor, TradingView
B21: Risk-free rate (10Y UST) | C21: 4.35% (semana 4-7 May 2026) | D21: FRED DGS10: https://fred.stlouisfed.org/series/DGS10
B22: Equity Risk Premium | C22: 5.0% (USD ERP rango 4.5-5.5% 2025-26) | D22: Damodaran ERP: https://pages.stern.nyu.edu/~adamodar/
B23: Sales-to-Capital sector | C23: Online/platform tech: 4-6x | D23: Damodaran sector data: https://pages.stern.nyu.edu/~adamodar/
B24: Coste de deuda | C24: 5.4-5.6% (Sept 2025 senior notes) | D24: Per FY2025 10-K Note on Debt
B25: Analyst consensus PT | C25: ~$104 (May 2026) | D25: Yahoo Finance, MarketBeat consensus
B26: 52w range | C26: $68.46 — $101.99 | D26: NYSE consolidated tape
A28: 3. NOTAS METODOLOGICAS CRITICAS
B30: Cambio UK Mobility (Q1 2026) | C30: Merchant -> agency model. Resta ~350bps al margen de revenue Mobility, sin impacto profit.
C31: Q4 2025 prepared remarks. Explica casi por completo la caida del take rate de 30.7% a 25.8%.
B32: Take rate reportado vs normalizado | C32: Reportado Q1 2026: 25.8%. Normalizado (ajustando UK): ~28-29%.
C33: Modelo usa take rate normalizado en banda 26-28% para 2026E-2030E.
B34: Tax rate | C34: Non-GAAP ETR FY2026: 22-25%. Cash tax 10-15% (NOLs).
C35: Modelo usa 22% efectivo (conservador). Cash tax mas bajo da diferencia transitoria positiva.
B36: Tax valuation release FY2024 | C36: Q4 2024 libero valuation allowance con benefit no-cash $6.4B. Distorsiona NI 2024 GAAP.
C37: Para FY2024-25 usar Op Income / Adj EBITDA / Non-GAAP Op Income como anclas, no NI GAAP.
B38: Reporting transition 2026 | C38: Uber paso de Adj EBITDA a Non-GAAP Op Income como metrica primaria desde Q1 2026.
C39: Modelo reporta ambos; FCFF se construye sobre EBIT (Damodaran sales-to-capital).
B40: Equity stakes valoracion | C40: $8.1B Q1 2026 = mix marketable (Aurora, Grab) + non-marketable (Didi, Lucid, Waabi).
C41: Q1 2026 incluyo $1.5B mark-down. Modelo valora a 100% del valor en libros / mercado.
B42: FCFF approach | C42: Damodaran sales-to-capital primario; aproximacion: NOPAT - ΔRev/S2C.
C43: Genera FCFF anual; suma PV explicito + PV terminal.
B44: Terminal Value (4 metodos) | C44: Gordon, H-Model (decay 7.5%->2.5%), Exit EV/EBITDA (16x), Exit EV/EBIT (18x).
C45: Diversifica supuesto terminal; promedio sirve de punto medio.
B46: ROE distorsionado | C46: ROE GAAP 2024-25 (~37-60%) inflada por valuation release y equity stakes marks.
C47: Para evaluar calidad operativa: usar ROIC operativo (NOPAT/Capital invertido) ~15-25%.
B48: Working Capital negativo | C48: UBER NWC < 0 estructural: insurance reserves crecen con volumen.
C49: Cada $1 revenue libera $0.04-0.10 cash. Tailwind asset-light.
B50: Sensibilidad | C50: Tabla G (WACC×TGR): recomputo completo. Tablas A, D, F: aprox terminal.
C51: Anos explicitos 2026-2029 quedan en base. Adecuado dado que TV domina valor.
A54: 4. OBSERVACIONES CRITICAS / donde tener cuidado
B56: • Q1 2026 take rate compression NO es colapso economico. ~9 pts del cambio reportado proviene de UK accounting change.
B57: • Mobility Op Income Q1 2026 (segment) = $2,029M sobre revenue $6,798M = 29.8%. El profit margin se DEFENDIO.
B58: • Stock-based comp se trata como NO cash en FCFF pero SI dilutivo: el buyback neto debe compensar la SBC.
B59: • El equity stakes ($8.1B) anade ~$3.9/accion 'oculta'. No depende del DCF operativo.
B60: • Freight es valor cero en caso base; cualquier mejora es upside opcional.
B61: • Beta UBER ha bajado de ~1.7 a ~1.3. Si ancla en 1.0-1.1 (negocio defensivo), Ke baja ~50-100bps -> precio sube.
B62: • S2C de UBER puede ser >5x (asset-light). Subir a 7-8x mueve el precio notablemente (ver Sens F en Modelo).
B63: • Multiplo salida 16x EV/EBITDA es CONSERVADOR. Hoy cotiza ~22x trailing. Si terminal 18-20x, hay upside.
B64: • ROIC operativo ~15-25% (FY2025) — ya genera valor sobre capital. La etapa 'profitable growth' esta validada.
A67: 5. DISCLAIMER
B69: Este modelo es un ejercicio analitico, no un consejo de inversion.
B70: Los outputs dependen completamente de los inputs en HIPOTESIS.
B71: El objetivo es ENTENDER las palancas de valor, no predecir un precio teorico.
B72: Toda la informacion historica proviene de filings publicos (SEC EDGAR).
B73: Construido: May 2026 con datos hasta Q1 2026 reportados (8-K May 6, 2026).
