Workbook

Sheet Resumen
B2: MICROSOFT CORPORATION · MSFT · Valuation Snapshot
B3: Modelo valoración integral · Fecha valoración: 15-may-2026 · Cierre FY junio
B5: 1. COMPANY SNAPSHOT / MARKET DATA (15-may-2026)
B6: CEO | C6: Satya Nadella | E6: Spot ($) | F6: =Hipotesis!$C$6 -> 408
B7: CFO | C7: Amy Hood | E7: Market Cap ($B) | F7: =Hipotesis!$C$21/1000 -> 3030.7872
B8: Headquarters | C8: Redmond, WA, USA | E8: Enterprise Value ($B) | F8: =(Hipotesis!$C$21+Hipotesis!$C$14-Hipotesis!$C$15)/1000 -> 2992.7772
B9: Fundada | C9: 1975 | E9: Shares Outstanding (M) | F9: =Hipotesis!$C$8 -> 7428.4
B10: Empleados (FY25) | C10: ~228,000 | E10: 52-week range | F10: $356.28 – $555.45
B11: Año fiscal | C11: Cierre 30-jun | E11: All-time high (close) | F11: $539.83 (28-oct-2025)
B12: Sector | C12: Software / Cloud / IA | E12: P/E TTM | F12: 25.3x
B13: Segmentos reportados | C13: 3 (PBP, IC, MPC) | E13: EPS TTM | F13: $16.79
B14: Ticker / Exchange | C14: MSFT / NASDAQ-GS | E14: Beta (5Y) | F14: =Hipotesis!$C$11 -> 1.1
B15: Index | C15: S&P 500, NASDAQ-100 | E15: Dividend Yield | F15: ~0.82% ($3.32/sh annualized)
B17: 2. Q3 FY2026 EARNINGS HIGHLIGHTS (trimestre cerrado 31-mar-2026)
B18: Revenue Q3 | C18: $82,886M | E18: +15.5% YoY
B19: Operating Income Q3 | C19: $38,398M | E19: Margin 46.3%
B20: Net Income Q3 | C20: $31,778M | E20: Diluted EPS $4.27
B21: Azure & other cloud growth | C21: +40% cc | E21: Supply-constrained still
B22: Microsoft Cloud Q3 revenue | C22: $45.5B (+22%) | E22: MS Cloud GM 69%
B23: M365 Commercial Cloud | C23: +19% growth | E23: Copilot driving ARPU
B24: LinkedIn | C24: +12% growth
B25: Dynamics 365 | C25: +22% growth
B26: Commercial RPO | C26: $627B (+99% YoY) | E26: Backlog extraordinario
B27: AI ARR (annualized) | C27: $37B (+123%) | E27: >20M Copilot seats
B28: Capex Q3 | C28: $27.0B | E28: 9M total $80.1B
B29: FCF Q3 | C29: $17.6B | E29: 9M FCF $47.3B
B30: Buyback Q3 | C30: $5.6B
B31: Dividends Q3 | C31: $6.2B
B33: 3. 5-YEAR HISTORICAL FINANCIALS (FY21-FY25, $mm except per-share / ratios)
B34: Metric | C34: FY21 | D34: FY22 | E34: FY23 | F34: FY24 | G34: FY25
B35: Revenue ($mm) | C35: 168088 | D35: 198270 | E35: 211915 | F35: 245122 | G35: 281724
B36: YoY growth | C36: +18.0% | D36: +18.0% | E36: +6.9% | F36: +15.7% | G36: +14.9%
B37: Operating Income | C37: 69916 | D37: 83383 | E37: 88523 | F37: 109433 | G37: 128528
B38: Operating margin | C38: 41.6% | D38: 42.1% | E38: 41.8% | F38: 44.6% | G38: 45.6%
B39: Net Income | C39: 61271 | D39: 72738 | E39: 72361 | F39: 88136 | G39: 101832
B40: Diluted EPS | C40: 8.05 | D40: 9.65 | E40: 9.68 | F40: 11.8 | G40: 13.64
B41: OCF | C41: 76740 | D41: 89035 | E41: 87582 | F41: 118548 | G41: 136162
B42: Capex | C42: -20622 | D42: -23886 | E42: -28107 | F42: -44477 | G42: -64551
B43: Free Cash Flow | C43: 56118 | D43: 65149 | E43: 59475 | F43: 74071 | G43: 71611
B44: Buybacks | C44: -27385 | D44: -32696 | E44: -22245 | F44: -17254 | G44: -18420
B45: Dividends | C45: -16871 | D45: -18552 | E45: -19800 | F45: -21771 | G45: -24082
B47: 4. VALUATION RESULTS — 8 metodologías (live link to Modelo)
B48: Method | C48: Implied Price | D48: vs Spot $408
B49: 1. DCF Gordon Growth | C49: =Modelo!J52 -> 357.02941 | D49: =Modelo!J52/Hipotesis!$C$6-1 -> -0.12492791
B50: 2. DCF H-Model (fade) | C50: =Modelo!J53 -> 400.76589 | D50: =Modelo!J53/Hipotesis!$C$6-1 -> -0.017730672
B51: 3. DCF Exit EV/EBITDA | C51: =Modelo!J54 -> 604.43572 | D51: =Modelo!J54/Hipotesis!$C$6-1 -> 0.48146009
B52: 4. DCF Exit EV/EBIT | C52: =Modelo!J55 -> 566.35894 | D52: =Modelo!J55/Hipotesis!$C$6-1 -> 0.38813467
B53: 5. DCF Exit EV/Revenue | C53: =Modelo!J56 -> 464.0642 | D53: =Modelo!J56/Hipotesis!$C$6-1 -> 0.13741225
B54: 6. NTM P/E × FY27E EPS | C54: =Modelo!J57 -> 463.371 | D54: =Modelo!J57/Hipotesis!$C$6-1 -> 0.13571324
B55: 7. NTM EV/EBITDA × FY27E EBITDA | C55: =Modelo!J58 -> 539.70491 | D55: =Modelo!J58/Hipotesis!$C$6-1 -> 0.32280615
B56: 8. NTM EV/Revenue × FY27E Revenue | C56: =Modelo!J59 -> 415.21947 | D56: =Modelo!J59/Hipotesis!$C$6-1 -> 0.017694777
B57: MEDIANA (target price central) | C57: =MEDIAN(C49:C56) -> 463.7176 | D57: =C57/Hipotesis!$C$6-1 -> 0.13656275
B58: Promedio (8 métodos) | C58: =AVERAGE(C49:C56) -> 476.36869 | D58: =C58/Hipotesis!$C$6-1 -> 0.16757032
B59: Rango Min – Max | C59: =TEXT(MIN(C49:C56),"$#,##0")&" – "&TEXT(MAX(C49:C56),"$#,##0") -> $357 – $604
B61: 5. INVESTMENT THESIS (resumen ejecutivo)
B62: Target price (mediana, sin descuento) | C62: =C57 -> 463.7176 | D62: vs spot: | E62: =C57/Hipotesis!$C$6-1 -> 0.13656275
B64: ▸ Microsoft cotiza a ~25× P/E TTM, en línea con la última década pero por debajo del peer set tech ($GOOGL 30×, $AMZN 31×). El mercado descuenta una normalización de capex AI que aún no ha ocurrido.
B65: ▸ Azure +40% Q3 FY26 sigue capacity-constrained. El backlog comercial de $627B (~1.9× revenue) es histórico y reduce drásticamente el riesgo de proyección.
B66: ▸ La preocupación clave es el ciclo de capex AI: $80B en 9M FY26 vs $64B en todo FY25. La rentabilidad operativa (ROIC 25-36% vs WACC 9%) sigue +15-25pp por encima del coste, pero el spread es menor que pre-IA.
B67: ▸ Margins consolidados expandieron de 41.6% (FY21) a 47.4% (9M FY26) — la mayor expansión en una década. Copilot M365 (~$30/seat) y Azure mix shift son responsables.
B68: ▸ La participación 27% en OpenAI (post-Recap oct-2025, $11.8B funded) añade óptica adicional. Riesgos: dilución, dependencia hyperscaler, mismatch revenue cycle.
B69: ▸ Sensibilidades clave: cada +100bp WACC ≈ -$70 precio; cada +500bp en Capex/Rev terminal ≈ -$50 precio; cada +20bp en IC margin FY30 ≈ +$15 precio.
B70: ▸ Tesis base: mediana 8 métodos = $455, upside vs spot +12% — riesgo asimétrico moderado favorable. Risk-reward más atractivo en correcciones intra-año (drawdowns 10%+).
B72: Detalle metodológico en hojas Hipotesis, Historico, Modelo, DuPont_WC, Conclusiones. Fuentes en hoja Fuentes.

Sheet Hipotesis
B1: MSFT — HIPOTESIS Y SUPUESTOS DE VALORACION
B2: LEYENDA: | C2: Input (hardcoded) | D2: Driver clave | E2: Formula | F2: Link a otra hoja | G2: Resultado/output
B4: 1. MERCADO Y COSTE DE CAPITAL
B5: Concepto | C5: Valor | D5: Fuente / Nota
B6: Spot price MSFT ($) | C6: 408 | D6: Source: Robinhood/Google Finance, 15-may-2026, intraday ~$405-410
B7: Diluted shares outstanding (M) | C7: 7445 | D7: Source: MSFT 10-Q Q3 FY2026, diluted weighted-avg shares (Note 2 EPS)
B8: Shares outstanding actual (M, abr-26) | C8: 7428.4 | D8: Source: MSFT 10-Q Q3 FY26 cover, shares outstanding as of 23-abr-2026
B9: Risk-free rate (10Y UST, %) | C9: 0.0454 | D9: Source: FRED DGS10, 15-may-2026; máximo 1-año por tensiones Iran/inflación
B10: Equity Risk Premium implicita (%) | C10: 0.0423 | D10: Source: Damodaran ERP 2026 Edition, ene-2026, implied ERP S&P500
B11: Beta (5Y) | C11: 1.1 | D11: Source: Google Finance / Yahoo Finance, 15-may-2026
B12: Pre-tax cost of debt MSFT (%) | C12: 0.048 | D12: Source: 10-Q AAA rating + ~25bp spread over 10Y UST
B13: Effective tax rate (%) | C13: 0.18 | D13: Source: MSFT 10-K FY2025 Note 12, effective rate FY24=FY25=18%
B14: Total Debt ($mm, book) | C14: 40262 | D14: Source: MSFT 10-Q Q3 FY26 BS, current LTD $8,839 + LTD $31,423 = $40,262M
B15: Cash + STI ($mm, book) | C15: 78272 | D15: Source: MSFT 10-Q Q3 FY26 BS, Cash $32,105 + ST inv $46,167 = $78,272M
B16: Equity & other investments ($mm) | C16: 33683 | D16: Source: MSFT 10-Q Q3 FY26 BS; incluye OpenAI ~27% equity stake
B18: WACC computado
B19: Cost of equity Ke = Rf + Beta × ERP | C19: =Hipotesis!$C$9 + Hipotesis!$C$11*Hipotesis!$C$10 -> 0.09193
B20: After-tax cost of debt Kd = Kd*(1-T) | C20: =Hipotesis!$C$12 * (1 - Hipotesis!$C$13) -> 0.03936
B21: Market cap = Spot × Shares ($mm) | C21: =Hipotesis!$C$6 * Hipotesis!$C$8 -> 3030787.2
B22: Total enterprise capital = MC + Debt | C22: =Hipotesis!$C$21 + Hipotesis!$C$14 -> 3071049.2
B23: Weight equity E/V | C23: =Hipotesis!$C$21 / Hipotesis!$C$22 -> 0.98688982
B24: Weight debt D/V | C24: =Hipotesis!$C$14 / Hipotesis!$C$22 -> 0.013110177
B25: WACC = E/V × Ke + D/V × Kd*(1-T) | C25: =Hipotesis!$C$23*Hipotesis!$C$19 + Hipotesis!$C$24*Hipotesis!$C$20 -> 0.091240798
B28: 2. CRECIMIENTO POR SEGMENTO (forecast horizon = años fiscales junio)
B29: Segmento / Driver | C29: FY2026E | D29: FY2027E | E29: FY2028E | F29: FY2029E | G29: FY2030E | H29: Terminal
B30: PBP revenue growth % | C30: 0.142 | D30: 0.13 | E30: 0.115 | F30: 0.1 | G30: 0.09 | H30: 0.045 | J30: M365 Commercial Q3FY26 +19%, Consumer +33%, LinkedIn +12%, Dynamics +22%. Mix → 14% FY26
B31: Intelligent Cloud revenue growth % | C31: 0.225 | D31: 0.25 | E31: 0.22 | F31: 0.18 | G31: 0.14 | H31: 0.045 | J31: Azure +40% Q3FY26 (supply constrained). Capex permite mantener crecimiento alto 2-3 años
B32: MPC revenue growth % | C32: 0.02 | D32: 0.04 | E32: 0.04 | F32: 0.035 | G32: 0.03 | H32: 0.03 | J32: MPC -1% Q3FY26 YoY; Windows OEM -2%, Search ex-TAC +12%. Mature/cyclical.
B33: PBP operating margin % | C33: 0.575 | D33: 0.58 | E33: 0.58 | F33: 0.585 | G33: 0.585 | H33: 0.585 | J33: FY25 actual 57.8%. M365 Copilot puede expandir ARPU sin destruir margen si attach >50%
B34: IC operating margin % | C34: 0.39 | D34: 0.38 | E34: 0.385 | F34: 0.395 | G34: 0.405 | H34: 0.415 | J34: FY25 actual 42.0%; comprimido por D&A AI buildout, recupera al normalizarse capex
B35: MPC operating margin % | C35: 0.275 | D35: 0.27 | E35: 0.27 | F35: 0.27 | G35: 0.27 | H35: 0.27 | J35: FY25 actual 25.9%. Gaming + Search drivers; relativamente estable
B37: 3. CAPEX, D&A Y CAPITAL ALLOCATION
B38: Driver | C38: FY2026E | D38: FY2027E | E38: FY2028E | F38: FY2029E | G38: FY2030E | H38: Terminal
B39: Capex / Revenue % | C39: 0.33 | D39: 0.29 | E39: 0.235 | F39: 0.2 | G39: 0.175 | H39: 0.15 | J39: 9M FY26 ya 33%; mgmt guida >$190bn capex 2026CY. Normalización gradual hacia 15-17%
B40: D&A / Revenue % | C40: 0.117 | D40: 0.135 | E40: 0.15 | F40: 0.15 | G40: 0.145 | H40: 0.14 | J40: D&A FY25 12.1% ($34bn/$282bn). Sube con lag del capex; pico ~15% en FY28-29
B41: SBC / Revenue % | C41: 0.04 | D41: 0.04 | E41: 0.04 | F41: 0.04 | G41: 0.04 | H41: 0.04 | J41: FY25 SBC $12bn = 4.2%; estable como % revenue históricamente
B42: ΔWC / Revenue % | C42: -0.005 | D42: -0.005 | E42: 0 | F42: 0 | G42: 0 | H42: 0 | J42: MSFT unearned revenue genera WC favorable, mínimo en proyección
B43: Buybacks / FCF % | C43: 0.3 | D43: 0.35 | E43: 0.45 | F43: 0.5 | G43: 0.55 | H43: 0.5 | J43: FY25 buybacks $18.4bn = 26% FCF; mgmt mod era en fase capex alta
B45: 4. VALORES TERMINALES (TV) Y CROSS-CHECKS
B46: Concepto | C46: Valor | D46: Justificación
B47: Terminal growth rate g (perpetuidad, %) | C47: 0.03 | D47: Gordon: g ≤ inflación + crec real GDP US ≈ 2-3%
B48: H-Model: años fase alta (n) | C48: 5 | D48: Periodo de crecimiento explícito antes de fade lineal
B49: H-Model: g inicial (%) | C49: 0.15 | D49: Crecimiento al final del periodo explícito; fade linear hasta terminal
B50: Exit EV/EBITDA múltiple (x) | C50: 18 | D50: FY2030 exit. Peers cloud actuales: GOOGL ~22x EBITDA, AMZN ~16x, ORCL ~18x
B51: Exit EV/EBIT múltiple (x) | C51: 22 | D51: FY2030 exit. MSFT actual ~22x EV/EBIT; descontamos premium gradual
B52: Exit EV/Revenue múltiple (x) | C52: 8 | D52: FY2030 exit. Para cross-check; cloud-heavy en 6-10x
B53: Exit P/E (x) | C53: 25 | D53: Cross-check; MSFT TTM 25x, GOOGL 30x, AMZN 31x
B54: FCF conversion normalizada (post-pico capex) | C54: 0.75 | D54: FCF/NI: histórico 80-90%, 9M FY26 48%, normalización a 70-80% en fade
B56: 5. OPENAI & STRATEGIC INVESTMENTS (no afectan core operations)
B57: OpenAI equity stake total committed ($mm) | C57: 13000 | D57: Source: MSFT 10-Q Q3 FY26 Note 1, total commitment to OpenAI funded $11.8B
B58: OpenAI stake ownership (%, as-converted) | C58: 0.27 | D58: Source: MSFT 10-Q Q3 FY26 Note 1, OpenAI Recap Oct-2025
B59: Strategic investments value (excluído de EV) | C59: 33683 | D59: Equity & other investments en BS (incluye OpenAI); tratar como caja excedente

Sheet Historico
B1: MSFT — HISTORICO FINANCIERO (FY2021-FY2025 + 9M FY26)
B2: LEYENDA: | C2: Input (hardcoded) | D2: Cálculo (margen/growth) | E2: Inline ratio
B4: $ millions | C4: FY2021 | D4: FY2022 | E4: FY2023 | F4: FY2024 | G4: FY2025 | H4: 9M FY26
B5: A. CUENTA DE RESULTADOS ($mm except per-share)
B6: Revenue | C6: 168088 | D6: 198270 | E6: 211915 | F6: 245122 | G6: 281724 | H6: 241832 | I6: 10-K Income Statement (FY21-FY25), 10-Q 9M FY26
B7: Revenue YoY % | C7: n/a | D7: =D6/C6-1 -> 0.17956071 | E7: =E6/D6-1 -> 0.068820296 | F7: =F6/E6-1 -> 0.15669962 | G7: =G6/F6-1 -> 0.14932156 | H7: ytd | I7: CAGR FY21-FY25 ≈ 13.8%
B8: Cost of revenue | C8: 52232 | D8: 62650 | E8: 65863 | F8: 74114 | G8: 87831 | H8: 76849
B9: Cost of revenue / Revenue % | C9: =C8/C6 -> 0.31074199 | D9: =D8/D6 -> 0.31598326 | E9: =E8/E6 -> 0.31079914 | F9: =F8/F6 -> 0.30235556 | G9: =G8/G6 -> 0.31176258 | H9: =H8/H6 -> 0.31777846 | I9: Subiendo por AI infra
B10: Gross profit | C10: 115856 | D10: 135620 | E10: 146052 | F10: 171008 | G10: 193893 | H10: 164983
B11: Gross margin % | C11: =C10/C6 -> 0.68925801 | D11: =D10/D6 -> 0.68401674 | E11: =E10/E6 -> 0.68920086 | F11: =F10/F6 -> 0.69764444 | G11: =G10/G6 -> 0.68823742 | H11: =H10/H6 -> 0.68222154 | I11: 69-70% Microsoft Cloud GM en Q3 FY26
B12: R&D | C12: 20716 | D12: 24512 | E12: 27195 | F12: 29510 | G12: 32488 | H12: 25565
B13: R&D / Revenue % | C13: =C12/C6 -> 0.12324497 | D13: =D12/D6 -> 0.12362939 | E13: =E12/E6 -> 0.12832975 | F13: =F12/F6 -> 0.12038903 | G13: =G12/G6 -> 0.11531854 | H13: =H12/H6 -> 0.10571388 | I13: Estable ~12% — leverage del modelo
B14: S&M | C14: 20117 | D14: 21825 | E14: 22759 | F14: 24456 | G14: 25654 | H14: 19115
B15: S&M / Revenue % | C15: =C14/C6 -> 0.11968136 | D15: =D14/D6 -> 0.11007717 | E15: =E14/E6 -> 0.10739683 | F15: =F14/F6 -> 0.099770726 | G15: =G14/G6 -> 0.091060754 | H15: =H14/H6 -> 0.079042476 | I15: Bajando con scale (de 12% → 9%)
B16: G&A | C16: 5107 | D16: 5900 | E16: 7575 | F16: 7609 | G16: 7223 | H16: 5669
B17: G&A / Revenue % | C17: =C16/C6 -> 0.030382895 | D17: =D16/D6 -> 0.029757402 | E17: =E16/E6 -> 0.035745464 | F17: =F16/F6 -> 0.031041685 | G17: =G16/G6 -> 0.025638568 | H17: =H16/H6 -> 0.023441894 | I17: ~3% estable
B18: Operating income | C18: 69916 | D18: 83383 | E18: 88523 | F18: 109433 | G18: 128528 | H18: 114634
B19: Operating margin % | C19: =C18/C6 -> 0.41594879 | D19: =D18/D6 -> 0.42055278 | E19: =E18/E6 -> 0.41772881 | F19: =F18/F6 -> 0.446443 | G19: =G18/G6 -> 0.45621956 | H19: =H18/H6 -> 0.47402329 | I19: 📈 +330bp FY21-FY25, +200bp más en 9M FY26 (47%)
B20: Op income YoY % | C20: n/a | D20: =D18/C18-1 -> 0.19261685 | E20: =E18/D18-1 -> 0.061643261 | F20: =F18/E18-1 -> 0.2362098 | G20: =G18/F18-1 -> 0.17449033 | H20: ytd
B21: Other income (expense), net | C21: 1186 | D21: 333 | E21: 788 | F21: -1646 | G21: -4901 | H21: 7253
B22: Income before taxes | C22: 71102 | D22: 83716 | E22: 89311 | F22: 107787 | G22: 123627 | H22: 121887
B23: Provision for income taxes | C23: 9831 | D23: 10978 | E23: 16950 | F23: 19651 | G23: 21795 | H23: 23904
B24: Effective tax rate | C24: =C23/C22 -> 0.13826615 | D24: =D23/D22 -> 0.13113383 | E24: =E23/E22 -> 0.18978625 | F24: =F23/F22 -> 0.18231327 | G24: =G23/G22 -> 0.17629644 | H24: =H23/H22 -> 0.19611607 | I24: 18% FY24-FY25, ligero uptick Q3 FY26
B25: Net income | C25: 61271 | D25: 72738 | E25: 72361 | F25: 88136 | G25: 101832 | H25: 97983
B26: Net margin % | C26: =C25/C6 -> 0.3645174 | D26: =D25/D6 -> 0.36686337 | E26: =E25/E6 -> 0.34146238 | F26: =F25/F6 -> 0.35955973 | G26: =G25/G6 -> 0.36146015 | H26: =H25/H6 -> 0.4051697 | I26: ~36% — quality of earnings alto
B27: Net income YoY % | C27: n/a | D27: =D25/C25-1 -> 0.18715216 | E27: =E25/D25-1 -> -0.0051829855 | F27: =F25/E25-1 -> 0.21800417 | G27: =G25/F25-1 -> 0.15539621 | H27: ytd
B28: Diluted EPS ($) | C28: 8.05 | D28: 9.65 | E28: 9.68 | F28: 11.8 | G28: 13.64 | H28: 13.14
B29: Diluted EPS YoY % | C29: n/a | D29: =D28/C28-1 -> 0.19875776 | E29: =E28/D28-1 -> 0.0031088083 | F29: =F28/E28-1 -> 0.21900826 | G29: =G28/F28-1 -> 0.1559322 | H29: ytd | I29: Buybacks ayudan ~50bp/año al EPS growth
B30: Diluted shares (M) | C30: 7608 | D30: 7540 | E30: 7472 | F30: 7469 | G30: 7465 | H30: 7457
B32: B. CASH FLOW ($mm)
B33: Net cash from operations (OCF) | C33: 76740 | D33: 89035 | E33: 87582 | F33: 118548 | G33: 136162 | H33: 127494 | I33: 10-K CF Statement
B34: OCF / Revenue % | C34: =C33/C6 -> 0.45654657 | D34: =D33/D6 -> 0.44905936 | E34: =E33/E6 -> 0.41328835 | F34: =F33/F6 -> 0.48362856 | G34: =G33/G6 -> 0.48331701 | H34: =H33/H6 -> 0.5272007 | I34: ~48% — cash conversion alta
B35: OCF YoY % | C35: n/a | D35: =D33/C33-1 -> 0.16021631 | E35: =E33/D33-1 -> -0.016319425 | F35: =F33/E33-1 -> 0.3535658 | G35: =G33/F33-1 -> 0.14858117 | H35: ytd
B36: Capex (Additions to P&E) | C36: 20622 | D36: 23886 | E36: 28107 | F36: 44477 | G36: 64551 | H36: 80146
B37: Capex / Revenue % | C37: =C36/C6 -> 0.12268574 | D37: =D36/D6 -> 0.12047208 | E37: =E36/E6 -> 0.13263337 | F37: =F36/F6 -> 0.18144842 | G37: =G36/G6 -> 0.22912851 | H37: =H36/H6 -> 0.33141189 | I37: 📈 12% → 23% TTM → 33% 9M FY26 (AI build-out)
B38: Capex YoY % | C38: n/a | D38: =D36/C36-1 -> 0.15827757 | E38: =E36/D36-1 -> 0.17671439 | F38: =F36/E36-1 -> 0.58241719 | G38: =G36/F36-1 -> 0.4513344 | H38: ytd | I38: +213% acumulado FY21-FY25
B39: FCF simple = OCF − Capex | C39: 56118 | D39: 65149 | E39: 59475 | F39: 74071 | G39: 71611 | H39: 47348
B40: FCF / Revenue % | C40: =C39/C6 -> 0.33386083 | D40: =D39/D6 -> 0.32858728 | E40: =E39/E6 -> 0.28065498 | F40: =F39/F6 -> 0.30218014 | G40: =G39/G6 -> 0.2541885 | H40: =H39/H6 -> 0.19578881 | I40: Bajando 33% → 25% por capex AI
B41: FCF / Net Income % | C41: =C39/C25 -> 0.91589822 | D41: =D39/D25 -> 0.89566664 | E41: =E39/E25 -> 0.82192065 | F41: =F39/F25 -> 0.84041708 | G41: =G39/G25 -> 0.70322688 | H41: =H39/H25 -> 0.48322668 | I41: <70% confirma que la depreciación NO captura todo el outflow
B42: FCF YoY % | C42: n/a | D42: =D39/C39-1 -> 0.16092876 | E42: =E39/D39-1 -> -0.087092665 | F42: =F39/E39-1 -> 0.24541404 | G42: =G39/F39-1 -> -0.033211378 | H42: ytd
B43: D&A | C43: 11686 | D43: 14460 | E43: 13861 | F43: 22287 | G43: 34153 | H43: 27512
B44: D&A / Revenue % | C44: =C43/C6 -> 0.069523107 | D44: =D43/D6 -> 0.072930852 | E44: =E43/E6 -> 0.0654083 | F44: =F43/F6 -> 0.090922071 | G44: =G43/G6 -> 0.12122858 | H44: =H43/H6 -> 0.11376493 | I44: Subiendo con el capex (lag de 2-3 años)
B45: Stock-based compensation | C45: 6118 | D45: 7502 | E45: 9611 | F45: 10734 | G45: 11974 | H45: 9283
B46: SBC / Revenue % | C46: =C45/C6 -> 0.036397601 | D46: =D45/D6 -> 0.037837293 | E46: =E45/E6 -> 0.04535309 | F46: =F45/F6 -> 0.043790439 | G46: =G45/G6 -> 0.042502591 | H46: =H45/H6 -> 0.038386152 | I46: Estable ~4%
B47: Dividends paid | C47: 16521 | D47: 18552 | E47: 19800 | F47: 21771 | G47: 24082 | H47: 19687
B48: Common stock repurchased | C48: 27385 | D48: 32696 | E48: 22245 | F48: 17254 | G48: 18420 | H48: 17692
B49: Capital returns total ($mm) | C49: =C47+C48 -> 43906 | D49: =D47+D48 -> 51248 | E49: =E47+E48 -> 42045 | F49: =F47+F48 -> 39025 | G49: =G47+G48 -> 42502 | H49: =H47+H48 -> 37379
B50: Capital returns / FCF % | C50: =C49/C39 -> 0.78238711 | D50: =D49/D39 -> 0.78662758 | E50: =E49/E39 -> 0.70693569 | F50: =F49/F39 -> 0.52685936 | G50: =G49/G39 -> 0.59351217 | H50: =H49/H39 -> 0.78945256 | I50: ~70-80%, sostenible
B52: C. BALANCE SHEET (fin de periodo)
B53: Cash + STI | C53: 130334 | D53: 104757 | E53: 111262 | F53: 75531 | G53: 94565 | H53: 78272
B54: Equity & other investments (LT) | C54: 6047 | D54: 6891 | E54: 9879 | F54: 14600 | G54: 15405 | H54: 33683
B55: Accounts receivable, net | C55: 38043 | D55: 44261 | E55: 48688 | F55: 56924 | G55: 69905 | H55: 60041
B56: PP&E, net | C56: 59715 | D56: 74398 | E56: 95641 | F56: 135591 | G56: 204966 | H56: 283228
B57: Goodwill + Intangibles | C57: 60195 | D57: 78215 | E57: 78169 | F57: 146817 | G57: 142113 | H57: 138986
B58: Total assets | C58: 333779 | D58: 364840 | E58: 411976 | F58: 512163 | G58: 619003 | H58: 694228
B59: Total debt (current + long-term) | C59: 58146 | D59: 49781 | E59: 47237 | F59: 44937 | G59: 43151 | H59: 40262
B60: Stockholders' equity | C60: 141988 | D60: 166542 | E60: 206223 | F60: 268477 | G60: 343479 | H60: 414367
B61: Common stock + APIC | C61: 83111 | D61: 86939 | E61: 93718 | F61: 100923 | G61: 109095 | H61: 115069
B62: Retained earnings | C62: 57055 | D62: 84281 | E62: 118848 | F62: 173144 | G62: 237731 | H62: 302526
B63: Unearned revenue (current + LT) | C63: 47961 | D63: 48408 | E63: 53813 | F63: 60188 | G63: 67265 | H63: 53677
B64: Commercial RPO ($bn) | C64: n/d | D64: n/d | E64: n/d | F64: n/d | G64: >300 | H64: 627
B66: Capital structure / leverage
B67: Net cash position ($mm) | C67: =C53-C59 -> 72188 | D67: =D53-D59 -> 54976 | E67: =E53-E59 -> 64025 | F67: =F53-F59 -> 30594 | G67: =G53-G59 -> 51414 | H67: =H53-H59 -> 38010
B68: Debt / Equity (x) | C68: =C59/C60 -> 0.40951348 | D68: =D59/D60 -> 0.29890958 | E68: =E59/E60 -> 0.22905786 | F68: =F59/F60 -> 0.16737747 | G68: =G59/G60 -> 0.12562922 | H68: =H59/H60 -> 0.097165073 | I68: Desapalancando: 0.55 → 0.10
B69: PP&E / Revenue % | C69: =C56/C6 -> 0.35526034 | D69: =D56/D6 -> 0.37523579 | E69: =E56/E6 -> 0.45131775 | F69: =F56/F6 -> 0.5531572 | G69: =G56/G6 -> 0.72754185 | H69: =H56/H6 -> 1.1711767 | I69: 📈 36% → 73% → 117% (AI capex stack)
B70: Asset turnover (Rev / Avg Assets, proxy con end-of-period) | C70: =C6/C58 -> 0.5035907 | D70: =D6/D58 -> 0.5434437 | E70: =E6/E58 -> 0.51438676 | F70: =F6/F58 -> 0.47860154 | G70: =G6/G58 -> 0.45512542 | H70: =H6/H58 -> 0.34834665 | I70: Bajando 0.50 → 0.46 → 0.35 (AI capex)
B72: D. SEGMENTOS (new structure, recast FY24-FY25)
B73: (Pre-FY24: segmentos antiguos; ver Notes en 10-K para reconciliar)
B74: PBP revenue | C74: n/d | D74: n/d | E74: n/d | F74: 106820 | G74: 120810 | H74: n/d
B75: Intelligent Cloud revenue | C75: n/d | D75: n/d | E75: n/d | F75: 87464 | G75: 106265 | H75: n/d
B76: MPC revenue | C76: n/d | D76: n/d | E76: n/d | F76: 50838 | G76: 54649 | H76: n/d
B77: PBP operating income | C77: n/d | D77: n/d | E77: n/d | F77: 59661 | G77: 69773 | H77: n/d
B78: IC operating income | C78: n/d | D78: n/d | E78: n/d | F78: 37813 | G78: 44589 | H78: n/d
B79: MPC operating income | C79: n/d | D79: n/d | E79: n/d | F79: 11959 | G79: 14166 | H79: n/d
B81: Margen operativo por segmento
B82: PBP op margin % | C82: n/d | D82: n/d | E82: n/d | F82: =IFERROR(F77/F74,"n/d") -> 0.558519 | G82: =IFERROR(G77/G74,"n/d") -> 0.57754325 | H82: n/d
B83: IC op margin % | C83: n/d | D83: n/d | E83: n/d | F83: =IFERROR(F78/F75,"n/d") -> 0.43232644 | G83: =IFERROR(G78/G75,"n/d") -> 0.41960194 | H83: n/d
B84: MPC op margin % | C84: n/d | D84: n/d | E84: n/d | F84: =IFERROR(F79/F76,"n/d") -> 0.23523742 | G84: =IFERROR(G79/G76,"n/d") -> 0.25921792 | H84: n/d
B86: Crecimiento YoY por segmento (FY25 vs FY24)
B87: PBP revenue YoY % | C87: n/d | D87: n/d | E87: n/d | F87: n/a | G87: =IFERROR(G74/F74-1,"n/d") -> 0.13096798 | H87: ytd
B88: IC revenue YoY % | C88: n/d | D88: n/d | E88: n/d | F88: n/a | G88: =IFERROR(G75/F75-1,"n/d") -> 0.21495701 | H88: ytd
B89: MPC revenue YoY % | C89: n/d | D89: n/d | E89: n/d | F89: n/a | G89: =IFERROR(G76/F76-1,"n/d") -> 0.07496361 | H89: ytd
B92: E. METRICAS CLAVE (Q3 FY26 highlights, no aplicables YoY anual)
B93: Métrica | C93: Valor
B94: Q3 FY26 Revenue YoY | C94: +18% (CC +15%)
B95: Q3 FY26 Azure & other cloud growth | C95: +40% YoY
B96: Q3 FY26 Microsoft Cloud revenue | C96: $54.5bn (+29%)
B97: Q3 FY26 M365 Commercial cloud growth | C97: +19% YoY
B98: Q3 FY26 LinkedIn growth | C98: +12% YoY
B99: Q3 FY26 Dynamics 365 growth | C99: +22% YoY
B100: Q3 FY26 Commercial RPO | C100: $627bn (+99%)
B101: Q3 FY26 AI business ARR | C101: $37bn (+123%)
B102: Q3 FY26 M365 Copilot seats | C102: >20M paid
B103: Q3 FY26 Capex + finance leases | C103: $31.9bn (+49%)
B104: Q4 FY26 capex guide | C104: >$40bn
... B108: Q4 FY26 Op margin guidance (implied) | C108: ~44.0%

Sheet Modelo
B1: MSFT — MODELO OPERATIVO + FCFF + VALORACION (segmentado, FY26-FY30)
B2: LEYENDA: | C2: Input (azul) | D2: Cálculo (negro) | E2: Inline ratio | F2: Total (negrita) | G2: Terminal
B4: $ millions | C4: FY2026E | D4: FY2027E | E4: FY2028E | F4: FY2029E | G4: FY2030E | H4: Terminal
L5: Tabla A — Precio (Gordon DCF) vs WACC × g_terminal
B6: A. PROYECCION DE INGRESOS POR SEGMENTO
B7: PBP revenue | C7: =Historico!G74*(1+Hipotesis!C30) -> 137965.02 | D7: =C7*(1+Hipotesis!D30) -> 155900.47 | E7: =D7*(1+Hipotesis!E30) -> 173829.03 | F7: =E7*(1+Hipotesis!F30) -> 191211.93 | G7: =F7*(1+Hipotesis!G30) -> 208421 | H7: =G7*(1+Hipotesis!H30) -> 217799.95 | L7: WACC ↓ \ g → | M7: 0.02 | N7: 0.025 | O7: 0.03 | P7: 0.035 | Q7: 0.04
B8: PBP revenue YoY % | C8: =C7/Historico!G74-1 -> 0.142 | D8: =D7/C7-1 -> 0.13 | E8: =E7/D7-1 -> 0.115 | F8: =F7/E7-1 -> 0.1 | G8: =G7/F7-1 -> 0.09 | H8: =H7/G7-1 -> 0.045 | L8: 0.075 | M8: =((C33/(1+$L$8)^0.5 + D33/(1+$L$8)^1.5 + E33/(1+$L$8)^2.5 + F33/(1+$L$8)^3.5 + G33/(1+$L$8)^4.5)+(G33*(1+M$7)/($L$8-M$7))/(1+$L$8)^5+Hipotesis!$C$15+Hipotesis!$C$16-Hipotesis!$C$14)/Hipotesis!$C$8 -> 399.13105 | N8: =((C33/(1+$L$8)^0.5 + D33/(1+$L$8)^1.5 + E33/(1+$L$8)^2.5 + F33/(1+$L$8)^3.5 + G33/(1+$L$8)^4.5)+(G33*(1+N$7)/($L$8-N$7))/(1+$L$8)^5+Hipotesis!$C$15+Hipotesis!$C$16-Hipotesis!$C$14)/Hipotesis!$C$8 -> 433.34938 | O8: =((C33/(1+$L$8)^0.5 + D33/(1+$L$8)^1.5 + E33/(1+$L$8)^2.5 + F33/(1+$L$8)^3.5 + G33/(1+$L$8)^4.5)+(G33*(1+O$7)/($L$8-O$7))/(1+$L$8)^5+Hipotesis!$C$15+Hipotesis!$C$16-Hipotesis!$C$14)/Hipotesis!$C$8 -> 475.1718 | P8: =((C33/(1+$L$8)^0.5 + D33/(1+$L$8)^1.5 + E33/(1+$L$8)^2.5 + F33/(1+$L$8)^3.5 + G33/(1+$L$8)^4.5)+(G33*(1+P$7)/($L$8-P$7))/(1+$L$8)^5+Hipotesis!$C$15+Hipotesis!$C$16-Hipotesis!$C$14)/Hipotesis!$C$8 -> 527.44981 | Q8: =((C33/(1+$L$8)^0.5 + D33/(1+$L$8)^1.5 + E33/(1+$L$8)^2.5 + F33/(1+$L$8)^3.5 + G33/(1+$L$8)^4.5)+(G33*(1+Q$7)/($L$8-Q$7))/(1+$L$8)^5+Hipotesis!$C$15+Hipotesis!$C$16-Hipotesis!$C$14)/Hipotesis!$C$8 -> 594.6644
B9: Intelligent Cloud revenue | C9: =Historico!G75*(1+Hipotesis!C31) -> 130174.62 | D9: =C9*(1+Hipotesis!D31) -> 162718.28 | E9: =D9*(1+Hipotesis!E31) -> 198516.3 | F9: =E9*(1+Hipotesis!F31) -> 234249.24 | G9: =F9*(1+Hipotesis!G31) -> 267044.13 | H9: =G9*(1+Hipotesis!H31) -> 279061.12 | L9: 0.085 | M9: =((C33/(1+$L$9)^0.5 + D33/(1+$L$9)^1.5 + E33/(1+$L$9)^2.5 + F33/(1+$L$9)^3.5 + G33/(1+$L$9)^4.5)+(G33*(1+M$7)/($L$9-M$7))/(1+$L$9)^5+Hipotesis!$C$15+Hipotesis!$C$16-Hipotesis!$C$14)/Hipotesis!$C$8 -> 335.00796 | N9: =((C33/(1+$L$9)^0.5 + D33/(1+$L$9)^1.5 + E33/(1+$L$9)^2.5 + F33/(1+$L$9)^3.5 + G33/(1+$L$9)^4.5)+(G33*(1+N$7)/($L$9-N$7))/(1+$L$9)^5+Hipotesis!$C$15+Hipotesis!$C$16-Hipotesis!$C$14)/Hipotesis!$C$8 -> 358.25898 | O9: =((C33/(1+$L$9)^0.5 + D33/(1+$L$9)^1.5 + E33/(1+$L$9)^2.5 + F33/(1+$L$9)^3.5 + G33/(1+$L$9)^4.5)+(G33*(1+O$7)/($L$9-O$7))/(1+$L$9)^5+Hipotesis!$C$15+Hipotesis!$C$16-Hipotesis!$C$14)/Hipotesis!$C$8 -> 385.73745 | P9: =((C33/(1+$L$9)^0.5 + D33/(1+$L$9)^1.5 + E33/(1+$L$9)^2.5 + F33/(1+$L$9)^3.5 + G33/(1+$L$9)^4.5)+(G33*(1+P$7)/($L$9-P$7))/(1+$L$9)^5+Hipotesis!$C$15+Hipotesis!$C$16-Hipotesis!$C$14)/Hipotesis!$C$8 -> 418.71161 | Q9: =((C33/(1+$L$9)^0.5 + D33/(1+$L$9)^1.5 + E33/(1+$L$9)^2.5 + F33/(1+$L$9)^3.5 + G33/(1+$L$9)^4.5)+(G33*(1+Q$7)/($L$9-Q$7))/(1+$L$9)^5+Hipotesis!$C$15+Hipotesis!$C$16-Hipotesis!$C$14)/Hipotesis!$C$8 -> 459.01337
B10: IC revenue YoY % | C10: =C9/Historico!G75-1 -> 0.225 | D10: =D9/C9-1 -> 0.25 | E10: =E9/D9-1 -> 0.22 | F10: =F9/E9-1 -> 0.18 | G10: =G9/F9-1 -> 0.14 | H10: =H9/G9-1 -> 0.045 | L10: 0.0912 | M10: =((C33/(1+$L$10)^0.5 + D33/(1+$L$10)^1.5 + E33/(1+$L$10)^2.5 + F33/(1+$L$10)^3.5 + G33/(1+$L$10)^4.5)+(G33*(1+M$7)/($L$10-M$7))/(1+$L$10)^5+Hipotesis!$C$15+Hipotesis!$C$16-Hipotesis!$C$14)/Hipotesis!$C$8 -> 304.39644 | N10: =((C33/(1+$L$10)^0.5 + D33/(1+$L$10)^1.5 + E33/(1+$L$10)^2.5 + F33/(1+$L$10)^3.5 + G33/(1+$L$10)^4.5)+(G33*(1+N$7)/($L$10-N$7))/(1+$L$10)^5+Hipotesis!$C$15+Hipotesis!$C$16-Hipotesis!$C$14)/Hipotesis!$C$8 -> 323.20129 | O10: =((C33/(1+$L$10)^0.5 + D33/(1+$L$10)^1.5 + E33/(1+$L$10)^2.5 + F33/(1+$L$10)^3.5 + G33/(1+$L$10)^4.5)+(G33*(1+O$7)/($L$10-O$7))/(1+$L$10)^5+Hipotesis!$C$15+Hipotesis!$C$16-Hipotesis!$C$14)/Hipotesis!$C$8 -> 345.07884 | P10: =((C33/(1+$L$10)^0.5 + D33/(1+$L$10)^1.5 + E33/(1+$L$10)^2.5 + F33/(1+$L$10)^3.5 + G33/(1+$L$10)^4.5)+(G33*(1+P$7)/($L$10-P$7))/(1+$L$10)^5+Hipotesis!$C$15+Hipotesis!$C$16-Hipotesis!$C$14)/Hipotesis!$C$8 -> 370.84919 | Q10: =((C33/(1+$L$10)^0.5 + D33/(1+$L$10)^1.5 + E33/(1+$L$10)^2.5 + F33/(1+$L$10)^3.5 + G33/(1+$L$10)^4.5)+(G33*(1+Q$7)/($L$10-Q$7))/(1+$L$10)^5+Hipotesis!$C$15+Hipotesis!$C$16-Hipotesis!$C$14)/Hipotesis!$C$8 -> 401.65281
B11: MPC revenue | C11: =Historico!G76*(1+Hipotesis!C32) -> 55741.98 | D11: =C11*(1+Hipotesis!D32) -> 57971.659 | E11: =D11*(1+Hipotesis!E32) -> 60290.526 | F11: =E11*(1+Hipotesis!F32) -> 62400.694 | G11: =F11*(1+Hipotesis!G32) -> 64272.715 | H11: =G11*(1+Hipotesis!H32) -> 66200.896 | L11: 0.1 | M11: =((C33/(1+$L$11)^0.5 + D33/(1+$L$11)^1.5 + E33/(1+$L$11)^2.5 + F33/(1+$L$11)^3.5 + G33/(1+$L$11)^4.5)+(G33*(1+M$7)/($L$11-M$7))/(1+$L$11)^5+Hipotesis!$C$15+Hipotesis!$C$16-Hipotesis!$C$14)/Hipotesis!$C$8 -> 269.20423 | N11: =((C33/(1+$L$11)^0.5 + D33/(1+$L$11)^1.5 + E33/(1+$L$11)^2.5 + F33/(1+$L$11)^3.5 + G33/(1+$L$11)^4.5)+(G33*(1+N$7)/($L$11-N$7))/(1+$L$11)^5+Hipotesis!$C$15+Hipotesis!$C$16-Hipotesis!$C$14)/Hipotesis!$C$8 -> 283.50974 | O11: =((C33/(1+$L$11)^0.5 + D33/(1+$L$11)^1.5 + E33/(1+$L$11)^2.5 + F33/(1+$L$11)^3.5 + G33/(1+$L$11)^4.5)+(G33*(1+O$7)/($L$11-O$7))/(1+$L$11)^5+Hipotesis!$C$15+Hipotesis!$C$16-Hipotesis!$C$14)/Hipotesis!$C$8 -> 299.8589 | P11: =((C33/(1+$L$11)^0.5 + D33/(1+$L$11)^1.5 + E33/(1+$L$11)^2.5 + F33/(1+$L$11)^3.5 + G33/(1+$L$11)^4.5)+(G33*(1+P$7)/($L$11-P$7))/(1+$L$11)^5+Hipotesis!$C$15+Hipotesis!$C$16-Hipotesis!$C$14)/Hipotesis!$C$8 -> 318.72332 | Q11: =((C33/(1+$L$11)^0.5 + D33/(1+$L$11)^1.5 + E33/(1+$L$11)^2.5 + F33/(1+$L$11)^3.5 + G33/(1+$L$11)^4.5)+(G33*(1+Q$7)/($L$11-Q$7))/(1+$L$11)^5+Hipotesis!$C$15+Hipotesis!$C$16-Hipotesis!$C$14)/Hipotesis!$C$8 -> 340.7318
B12: MPC revenue YoY % | C12: =C11/Historico!G76-1 -> 0.02 | D12: =D11/C11-1 -> 0.04 | E12: =E11/D11-1 -> 0.04 | F12: =F11/E11-1 -> 0.035 | G12: =G11/F11-1 -> 0.03 | H12: =H11/G11-1 -> 0.03 | L12: 0.11 | M12: =((C33/(1+$L$12)^0.5 + D33/(1+$L$12)^1.5 + E33/(1+$L$12)^2.5 + F33/(1+$L$12)^3.5 + G33/(1+$L$12)^4.5)+(G33*(1+M$7)/($L$12-M$7))/(1+$L$12)^5+Hipotesis!$C$15+Hipotesis!$C$16-Hipotesis!$C$14)/Hipotesis!$C$8 -> 237.69854 | N12: =((C33/(1+$L$12)^0.5 + D33/(1+$L$12)^1.5 + E33/(1+$L$12)^2.5 + F33/(1+$L$12)^3.5 + G33/(1+$L$12)^4.5)+(G33*(1+N$7)/($L$12-N$7))/(1+$L$12)^5+Hipotesis!$C$15+Hipotesis!$C$16-Hipotesis!$C$14)/Hipotesis!$C$8 -> 248.51966 | O12: =((C33/(1+$L$12)^0.5 + D33/(1+$L$12)^1.5 + E33/(1+$L$12)^2.5 + F33/(1+$L$12)^3.5 + G33/(1+$L$12)^4.5)+(G33*(1+O$7)/($L$12-O$7))/(1+$L$12)^5+Hipotesis!$C$15+Hipotesis!$C$16-Hipotesis!$C$14)/Hipotesis!$C$8 -> 260.69341 | P12: =((C33/(1+$L$12)^0.5 + D33/(1+$L$12)^1.5 + E33/(1+$L$12)^2.5 + F33/(1+$L$12)^3.5 + G33/(1+$L$12)^4.5)+(G33*(1+P$7)/($L$12-P$7))/(1+$L$12)^5+Hipotesis!$C$15+Hipotesis!$C$16-Hipotesis!$C$14)/Hipotesis!$C$8 -> 274.49034 | Q12: =((C33/(1+$L$12)^0.5 + D33/(1+$L$12)^1.5 + E33/(1+$L$12)^2.5 + F33/(1+$L$12)^3.5 + G33/(1+$L$12)^4.5)+(G33*(1+Q$7)/($L$12-Q$7))/(1+$L$12)^5+Hipotesis!$C$15+Hipotesis!$C$16-Hipotesis!$C$14)/Hipotesis!$C$8 -> 290.25825
B13: Total Revenue | C13: =C7+C9+C11 -> 323881.62 | D13: =D7+D9+D11 -> 376590.41 | E13: =E7+E9+E11 -> 432635.86 | F13: =F7+F9+F11 -> 487861.86 | G13: =G7+G9+G11 -> 539737.85 | H13: =H7+H9+H11 -> 563061.96
B14: Revenue growth YoY % | C14: =C13/Historico!G6-1 -> 0.14964158 | D14: =D13/C13-1 -> 0.1627409 | E14: =E13/D13-1 -> 0.14882334 | F14: =F13/E13-1 -> 0.12765009 | G14: =G13/F13-1 -> 0.10633335 | H14: =H13/G13-1 -> 0.04321378
L15: Tabla B — Precio (Gordon DCF) vs WACC × Op margin terminal
B16: B. OPERATING INCOME POR SEGMENTO
B17: PBP operating income | C17: =C7*Hipotesis!C33 -> 79329.886 | D17: =D7*Hipotesis!D33 -> 90422.274 | E17: =E7*Hipotesis!E33 -> 100820.84 | F17: =F7*Hipotesis!F33 -> 111858.98 | G17: =G7*Hipotesis!G33 -> 121926.29 | H17: =H7*Hipotesis!H33 -> 127412.97 | L17: WACC ↓ \ margin → | M17: 0.4 | N17: 0.43 | O17: 0.46 | P17: 0.49 | Q17: 0.52
B18: PBP op margin % | C18: =C17/C7 -> 0.575 | D18: =D17/D7 -> 0.58 | E18: =E17/E7 -> 0.58 | F18: =F17/F7 -> 0.585 | G18: =G17/G7 -> 0.585 | H18: =H17/H7 -> 0.585 | L18: 0.075 | M18: =(C41+((G13*M$17*(1-Hipotesis!$C$13)+G28+G30+G32)*(1+Hipotesis!$C$47)/($L$18-Hipotesis!$C$47))/(1+$L$18)^5+Hipotesis!$C$15+Hipotesis!$C$16-Hipotesis!$C$14)/Hipotesis!$C$8 -> 416.87115 | N18: =(C41+((G13*N$17*(1-Hipotesis!$C$13)+G28+G30+G32)*(1+Hipotesis!$C$47)/($L$18-Hipotesis!$C$47))/(1+$L$18)^5+Hipotesis!$C$15+Hipotesis!$C$16-Hipotesis!$C$14)/Hipotesis!$C$8 -> 445.36854 | O18: =(C41+((G13*O$17*(1-Hipotesis!$C$13)+G28+G30+G32)*(1+Hipotesis!$C$47)/($L$18-Hipotesis!$C$47))/(1+$L$18)^5+Hipotesis!$C$15+Hipotesis!$C$16-Hipotesis!$C$14)/Hipotesis!$C$8 -> 473.86593 | P18: =(C41+((G13*P$17*(1-Hipotesis!$C$13)+G28+G30+G32)*(1+Hipotesis!$C$47)/($L$18-Hipotesis!$C$47))/(1+$L$18)^5+Hipotesis!$C$15+Hipotesis!$C$16-Hipotesis!$C$14)/Hipotesis!$C$8 -> 502.36332 | Q18: =(C41+((G13*Q$17*(1-Hipotesis!$C$13)+G28+G30+G32)*(1+Hipotesis!$C$47)/($L$18-Hipotesis!$C$47))/(1+$L$18)^5+Hipotesis!$C$15+Hipotesis!$C$16-Hipotesis!$C$14)/Hipotesis!$C$8 -> 530.86071
B19: Intelligent Cloud operating income | C19: =C9*Hipotesis!C34 -> 50768.104 | D19: =D9*Hipotesis!D34 -> 61832.947 | E19: =E9*Hipotesis!E34 -> 76428.777 | F19: =F9*Hipotesis!F34 -> 92528.449 | G19: =G9*Hipotesis!G34 -> 108152.87 | H19: =H9*Hipotesis!H34 -> 115810.36 | L19: 0.085 | M19: =(C41+((G13*M$17*(1-Hipotesis!$C$13)+G28+G30+G32)*(1+Hipotesis!$C$47)/($L$19-Hipotesis!$C$47))/(1+$L$19)^5+Hipotesis!$C$15+Hipotesis!$C$16-Hipotesis!$C$14)/Hipotesis!$C$8 -> 341.32704 | N19: =(C41+((G13*N$17*(1-Hipotesis!$C$13)+G28+G30+G32)*(1+Hipotesis!$C$47)/($L$19-Hipotesis!$C$47))/(1+$L$19)^5+Hipotesis!$C$15+Hipotesis!$C$16-Hipotesis!$C$14)/Hipotesis!$C$8 -> 363.58824 | O19: =(C41+((G13*O$17*(1-Hipotesis!$C$13)+G28+G30+G32)*(1+Hipotesis!$C$47)/($L$19-Hipotesis!$C$47))/(1+$L$19)^5+Hipotesis!$C$15+Hipotesis!$C$16-Hipotesis!$C$14)/Hipotesis!$C$8 -> 385.84944 | P19: =(C41+((G13*P$17*(1-Hipotesis!$C$13)+G28+G30+G32)*(1+Hipotesis!$C$47)/($L$19-Hipotesis!$C$47))/(1+$L$19)^5+Hipotesis!$C$15+Hipotesis!$C$16-Hipotesis!$C$14)/Hipotesis!$C$8 -> 408.11064 | Q19: =(C41+((G13*Q$17*(1-Hipotesis!$C$13)+G28+G30+G32)*(1+Hipotesis!$C$47)/($L$19-Hipotesis!$C$47))/(1+$L$19)^5+Hipotesis!$C$15+Hipotesis!$C$16-Hipotesis!$C$14)/Hipotesis!$C$8 -> 430.37184
B20: IC op margin % | C20: =C19/C9 -> 0.39 | D20: =D19/D9 -> 0.38 | E20: =E19/E9 -> 0.385 | F20: =F19/F9 -> 0.395 | G20: =G19/G9 -> 0.405 | H20: =H19/H9 -> 0.415 | L20: 0.0912 | M20: =(C41+((G13*M$17*(1-Hipotesis!$C$13)+G28+G30+G32)*(1+Hipotesis!$C$47)/($L$20-Hipotesis!$C$47))/(1+$L$20)^5+Hipotesis!$C$15+Hipotesis!$C$16-Hipotesis!$C$14)/Hipotesis!$C$8 -> 307.2006 | N20: =(C41+((G13*N$17*(1-Hipotesis!$C$13)+G28+G30+G32)*(1+Hipotesis!$C$47)/($L$20-Hipotesis!$C$47))/(1+$L$20)^5+Hipotesis!$C$15+Hipotesis!$C$16-Hipotesis!$C$14)/Hipotesis!$C$8 -> 326.64465 | O20: =(C41+((G13*O$17*(1-Hipotesis!$C$13)+G28+G30+G32)*(1+Hipotesis!$C$47)/($L$20-Hipotesis!$C$47))/(1+$L$20)^5+Hipotesis!$C$15+Hipotesis!$C$16-Hipotesis!$C$14)/Hipotesis!$C$8 -> 346.0887 | P20: =(C41+((G13*P$17*(1-Hipotesis!$C$13)+G28+G30+G32)*(1+Hipotesis!$C$47)/($L$20-Hipotesis!$C$47))/(1+$L$20)^5+Hipotesis!$C$15+Hipotesis!$C$16-Hipotesis!$C$14)/Hipotesis!$C$8 -> 365.53275 | Q20: =(C41+((G13*Q$17*(1-Hipotesis!$C$13)+G28+G30+G32)*(1+Hipotesis!$C$47)/($L$20-Hipotesis!$C$47))/(1+$L$20)^5+Hipotesis!$C$15+Hipotesis!$C$16-Hipotesis!$C$14)/Hipotesis!$C$8 -> 384.9768
B21: MPC operating income | C21: =C11*Hipotesis!C35 -> 15329.044 | D21: =D11*Hipotesis!D35 -> 15652.348 | E21: =E11*Hipotesis!E35 -> 16278.442 | F21: =F11*Hipotesis!F35 -> 16848.187 | G21: =G11*Hipotesis!G35 -> 17353.633 | H21: =H11*Hipotesis!H35 -> 17874.242 | L21: 0.1 | M21: =(C41+((G13*M$17*(1-Hipotesis!$C$13)+G28+G30+G32)*(1+Hipotesis!$C$47)/($L$21-Hipotesis!$C$47))/(1+$L$21)^5+Hipotesis!$C$15+Hipotesis!$C$16-Hipotesis!$C$14)/Hipotesis!$C$8 -> 269.48315 | N21: =(C41+((G13*N$17*(1-Hipotesis!$C$13)+G28+G30+G32)*(1+Hipotesis!$C$47)/($L$21-Hipotesis!$C$47))/(1+$L$21)^5+Hipotesis!$C$15+Hipotesis!$C$16-Hipotesis!$C$14)/Hipotesis!$C$8 -> 285.81361 | O21: =(C41+((G13*O$17*(1-Hipotesis!$C$13)+G28+G30+G32)*(1+Hipotesis!$C$47)/($L$21-Hipotesis!$C$47))/(1+$L$21)^5+Hipotesis!$C$15+Hipotesis!$C$16-Hipotesis!$C$14)/Hipotesis!$C$8 -> 302.14408 | P21: =(C41+((G13*P$17*(1-Hipotesis!$C$13)+G28+G30+G32)*(1+Hipotesis!$C$47)/($L$21-Hipotesis!$C$47))/(1+$L$21)^5+Hipotesis!$C$15+Hipotesis!$C$16-Hipotesis!$C$14)/Hipotesis!$C$8 -> 318.47454 | Q21: =(C41+((G13*Q$17*(1-Hipotesis!$C$13)+G28+G30+G32)*(1+Hipotesis!$C$47)/($L$21-Hipotesis!$C$47))/(1+$L$21)^5+Hipotesis!$C$15+Hipotesis!$C$16-Hipotesis!$C$14)/Hipotesis!$C$8 -> 334.805
B22: MPC op margin % | C22: =C21/C11 -> 0.275 | D22: =D21/D11 -> 0.27 | E22: =E21/E11 -> 0.27 | F22: =F21/F11 -> 0.27 | G22: =G21/G11 -> 0.27 | H22: =H21/H11 -> 0.27 | L22: 0.11 | M22: =(C41+((G13*M$17*(1-Hipotesis!$C$13)+G28+G30+G32)*(1+Hipotesis!$C$47)/($L$22-Hipotesis!$C$47))/(1+$L$22)^5+Hipotesis!$C$15+Hipotesis!$C$16-Hipotesis!$C$14)/Hipotesis!$C$8 -> 237.09722 | N22: =(C41+((G13*N$17*(1-Hipotesis!$C$13)+G28+G30+G32)*(1+Hipotesis!$C$47)/($L$22-Hipotesis!$C$47))/(1+$L$22)^5+Hipotesis!$C$15+Hipotesis!$C$16-Hipotesis!$C$14)/Hipotesis!$C$8 -> 250.75421 | O22: =(C41+((G13*O$17*(1-Hipotesis!$C$13)+G28+G30+G32)*(1+Hipotesis!$C$47)/($L$22-Hipotesis!$C$47))/(1+$L$22)^5+Hipotesis!$C$15+Hipotesis!$C$16-Hipotesis!$C$14)/Hipotesis!$C$8 -> 264.4112 | P22: =(C41+((G13*P$17*(1-Hipotesis!$C$13)+G28+G30+G32)*(1+Hipotesis!$C$47)/($L$22-Hipotesis!$C$47))/(1+$L$22)^5+Hipotesis!$C$15+Hipotesis!$C$16-Hipotesis!$C$14)/Hipotesis!$C$8 -> 278.06819 | Q22: =(C41+((G13*Q$17*(1-Hipotesis!$C$13)+G28+G30+G32)*(1+Hipotesis!$C$47)/($L$22-Hipotesis!$C$47))/(1+$L$22)^5+Hipotesis!$C$15+Hipotesis!$C$16-Hipotesis!$C$14)/Hipotesis!$C$8 -> 291.72518
B23: Total Operating Income (EBIT) | C23: =C17+C19+C21 -> 145427.03 | D23: =D17+D19+D21 -> 167907.57 | E23: =E17+E19+E21 -> 193528.05 | F23: =F17+F19+F21 -> 221235.62 | G23: =G17+G19+G21 -> 247432.79 | H23: =H17+H19+H21 -> 261097.58
B24: Operating margin % | C24: =C23/C13 -> 0.44901292 | D24: =D23/D13 -> 0.44586257 | E24: =E23/E13 -> 0.4473232 | F24: =F23/F13 -> 0.45348004 | G24: =G23/G13 -> 0.45843143 | H24: =H23/H13 -> 0.4637102 | L24: Tabla C — Precio (Gordon DCF) vs Capex/Rev terminal × g_terminal
B26: C. PUENTE DE EBIT A FREE CASH FLOW (FCFF) | L26: Capex/Rev ↓ \ g → | M26: 0.02 | N26: 0.025 | O26: 0.03 | P26: 0.035 | Q26: 0.04
B27: NOPAT = EBIT × (1 − tax rate) | C27: =C23*(1-Hipotesis!$C$13) -> 119250.17 | D27: =D23*(1-Hipotesis!$C$13) -> 137684.21 | E27: =E23*(1-Hipotesis!$C$13) -> 158693 | F27: =F23*(1-Hipotesis!$C$13) -> 181413.2 | G27: =G23*(1-Hipotesis!$C$13) -> 202894.89 | H27: =H23*(1-Hipotesis!$C$13) -> 214100.01 | L27: 0.1 | M27: =(C41+((G27+G28+(-G13*$L$27)+G32)*(1+M$26)/(Hipotesis!$C$25-M$26))/(1+Hipotesis!$C$25)^5+Hipotesis!$C$15+Hipotesis!$C$16-Hipotesis!$C$14)/Hipotesis!$C$8 -> 354.63457 | N27: =(C41+((G27+G28+(-G13*$L$27)+G32)*(1+N$26)/(Hipotesis!$C$25-N$26))/(1+Hipotesis!$C$25)^5+Hipotesis!$C$15+Hipotesis!$C$16-Hipotesis!$C$14)/Hipotesis!$C$8 -> 377.48603 | O27: =(C41+((G27+G28+(-G13*$L$27)+G32)*(1+O$26)/(Hipotesis!$C$25-O$26))/(1+Hipotesis!$C$25)^5+Hipotesis!$C$15+Hipotesis!$C$16-Hipotesis!$C$14)/Hipotesis!$C$8 -> 404.06891 | P27: =(C41+((G27+G28+(-G13*$L$27)+G32)*(1+P$26)/(Hipotesis!$C$25-P$26))/(1+Hipotesis!$C$25)^5+Hipotesis!$C$15+Hipotesis!$C$16-Hipotesis!$C$14)/Hipotesis!$C$8 -> 435.3784 | Q27: =(C41+((G27+G28+(-G13*$L$27)+G32)*(1+Q$26)/(Hipotesis!$C$25-Q$26))/(1+Hipotesis!$C$25)^5+Hipotesis!$C$15+Hipotesis!$C$16-Hipotesis!$C$14)/Hipotesis!$C$8 -> 472.79816
B28: (+) D&A | C28: =C13*Hipotesis!C40 -> 37894.15 | D28: =D13*Hipotesis!D40 -> 50839.706 | E28: =E13*Hipotesis!E40 -> 64895.378 | F28: =F13*Hipotesis!F40 -> 73179.279 | G28: =G13*Hipotesis!G40 -> 78261.988 | H28: =H13*Hipotesis!H40 -> 78828.675 | L28: 0.125 | M28: =(C41+((G27+G28+(-G13*$L$28)+G32)*(1+M$26)/(Hipotesis!$C$25-M$26))/(1+Hipotesis!$C$25)^5+Hipotesis!$C$15+Hipotesis!$C$16-Hipotesis!$C$14)/Hipotesis!$C$8 -> 337.82734 | N28: =(C41+((G27+G28+(-G13*$L$28)+G32)*(1+N$26)/(Hipotesis!$C$25-N$26))/(1+Hipotesis!$C$25)^5+Hipotesis!$C$15+Hipotesis!$C$16-Hipotesis!$C$14)/Hipotesis!$C$8 -> 359.32155 | O28: =(C41+((G27+G28+(-G13*$L$28)+G32)*(1+O$26)/(Hipotesis!$C$25-O$26))/(1+Hipotesis!$C$25)^5+Hipotesis!$C$15+Hipotesis!$C$16-Hipotesis!$C$14)/Hipotesis!$C$8 -> 384.32555 | P28: =(C41+((G27+G28+(-G13*$L$28)+G32)*(1+P$26)/(Hipotesis!$C$25-P$26))/(1+Hipotesis!$C$25)^5+Hipotesis!$C$15+Hipotesis!$C$16-Hipotesis!$C$14)/Hipotesis!$C$8 -> 413.77543 | Q28: =(C41+((G27+G28+(-G13*$L$28)+G32)*(1+Q$26)/(Hipotesis!$C$25-Q$26))/(1+Hipotesis!$C$25)^5+Hipotesis!$C$15+Hipotesis!$C$16-Hipotesis!$C$14)/Hipotesis!$C$8 -> 448.97266
B29: D&A / Revenue % | C29: =C28/C13 -> 0.117 | D29: =D28/D13 -> 0.135 | E29: =E28/E13 -> 0.15 | F29: =F28/F13 -> 0.15 | G29: =G28/G13 -> 0.145 | H29: =H28/H13 -> 0.14 | L29: 0.15 | M29: =(C41+((G27+G28+(-G13*$L$29)+G32)*(1+M$26)/(Hipotesis!$C$25-M$26))/(1+Hipotesis!$C$25)^5+Hipotesis!$C$15+Hipotesis!$C$16-Hipotesis!$C$14)/Hipotesis!$C$8 -> 321.02012 | N29: =(C41+((G27+G28+(-G13*$L$29)+G32)*(1+N$26)/(Hipotesis!$C$25-N$26))/(1+Hipotesis!$C$25)^5+Hipotesis!$C$15+Hipotesis!$C$16-Hipotesis!$C$14)/Hipotesis!$C$8 -> 341.15707 | O29: =(C41+((G27+G28+(-G13*$L$29)+G32)*(1+O$26)/(Hipotesis!$C$25-O$26))/(1+Hipotesis!$C$25)^5+Hipotesis!$C$15+Hipotesis!$C$16-Hipotesis!$C$14)/Hipotesis!$C$8 -> 364.58219 | P29: =(C41+((G27+G28+(-G13*$L$29)+G32)*(1+P$26)/(Hipotesis!$C$25-P$26))/(1+Hipotesis!$C$25)^5+Hipotesis!$C$15+Hipotesis!$C$16-Hipotesis!$C$14)/Hipotesis!$C$8 -> 392.17246 | Q29: =(C41+((G27+G28+(-G13*$L$29)+G32)*(1+Q$26)/(Hipotesis!$C$25-Q$26))/(1+Hipotesis!$C$25)^5+Hipotesis!$C$15+Hipotesis!$C$16-Hipotesis!$C$14)/Hipotesis!$C$8 -> 425.14715
B30: (−) Capex | C30: =-C13*Hipotesis!C39 -> -106880.94 | D30: =-D13*Hipotesis!D39 -> -109211.22 | E30: =-E13*Hipotesis!E39 -> -101669.43 | F30: =-F13*Hipotesis!F39 -> -97572.372 | G30: =-G13*Hipotesis!G39 -> -94454.124 | H30: =-H13*Hipotesis!H39 -> -84459.294 | L30: 0.175 | M30: =(C41+((G27+G28+(-G13*$L$30)+G32)*(1+M$26)/(Hipotesis!$C$25-M$26))/(1+Hipotesis!$C$25)^5+Hipotesis!$C$15+Hipotesis!$C$16-Hipotesis!$C$14)/Hipotesis!$C$8 -> 304.21289 | N30: =(C41+((G27+G28+(-G13*$L$30)+G32)*(1+N$26)/(Hipotesis!$C$25-N$26))/(1+Hipotesis!$C$25)^5+Hipotesis!$C$15+Hipotesis!$C$16-Hipotesis!$C$14)/Hipotesis!$C$8 -> 322.9926 | O30: =(C41+((G27+G28+(-G13*$L$30)+G32)*(1+O$26)/(Hipotesis!$C$25-O$26))/(1+Hipotesis!$C$25)^5+Hipotesis!$C$15+Hipotesis!$C$16-Hipotesis!$C$14)/Hipotesis!$C$8 -> 344.83883 | P30: =(C41+((G27+G28+(-G13*$L$30)+G32)*(1+P$26)/(Hipotesis!$C$25-P$26))/(1+Hipotesis!$C$25)^5+Hipotesis!$C$15+Hipotesis!$C$16-Hipotesis!$C$14)/Hipotesis!$C$8 -> 370.56948 | Q30: =(C41+((G27+G28+(-G13*$L$30)+G32)*(1+Q$26)/(Hipotesis!$C$25-Q$26))/(1+Hipotesis!$C$25)^5+Hipotesis!$C$15+Hipotesis!$C$16-Hipotesis!$C$14)/Hipotesis!$C$8 -> 401.32165
B31: Capex / Revenue % | C31: =-C30/C13 -> 0.33 | D31: =-D30/D13 -> 0.29 | E31: =-E30/E13 -> 0.235 | F31: =-F30/F13 -> 0.2 | G31: =-G30/G13 -> 0.175 | H31: =-H30/H13 -> 0.15 | L31: 0.2 | M31: =(C41+((G27+G28+(-G13*$L$31)+G32)*(1+M$26)/(Hipotesis!$C$25-M$26))/(1+Hipotesis!$C$25)^5+Hipotesis!$C$15+Hipotesis!$C$16-Hipotesis!$C$14)/Hipotesis!$C$8 -> 287.40567 | N31: =(C41+((G27+G28+(-G13*$L$31)+G32)*(1+N$26)/(Hipotesis!$C$25-N$26))/(1+Hipotesis!$C$25)^5+Hipotesis!$C$15+Hipotesis!$C$16-Hipotesis!$C$14)/Hipotesis!$C$8 -> 304.82812 | O31: =(C41+((G27+G28+(-G13*$L$31)+G32)*(1+O$26)/(Hipotesis!$C$25-O$26))/(1+Hipotesis!$C$25)^5+Hipotesis!$C$15+Hipotesis!$C$16-Hipotesis!$C$14)/Hipotesis!$C$8 -> 325.09548 | P31: =(C41+((G27+G28+(-G13*$L$31)+G32)*(1+P$26)/(Hipotesis!$C$25-P$26))/(1+Hipotesis!$C$25)^5+Hipotesis!$C$15+Hipotesis!$C$16-Hipotesis!$C$14)/Hipotesis!$C$8 -> 348.96651 | Q31: =(C41+((G27+G28+(-G13*$L$31)+G32)*(1+Q$26)/(Hipotesis!$C$25-Q$26))/(1+Hipotesis!$C$25)^5+Hipotesis!$C$15+Hipotesis!$C$16-Hipotesis!$C$14)/Hipotesis!$C$8 -> 377.49615
B32: (−) ΔWorking Capital | C32: =-C13*Hipotesis!C42 -> 1619.4081 | D32: =-D13*Hipotesis!D42 -> 1882.9521 | E32: =-E13*Hipotesis!E42 -> 0 | F32: =-F13*Hipotesis!F42 -> 0 | G32: =-G13*Hipotesis!G42 -> 0 | H32: =-H13*Hipotesis!H42 -> 0
B33: Free Cash Flow to Firm (FCFF) | C33: =C27+C28+C30+C32 -> 51882.79 | D33: =D27+D28+D30+D32 -> 81195.645 | E33: =E27+E28+E30+E32 -> 121918.96 | F33: =F27+F28+F30+F32 -> 157020.11 | G33: =G27+G28+G30+G32 -> 186702.75 | H33: =H27+H28+H30+H32 -> 208469.39 | L33: Tabla D — Precio (Exit EV/EBITDA) vs WACC × Exit EV/EBITDA
B34: FCFF / Revenue % | C34: =C33/C13 -> 0.1601906 | D34: =D33/D13 -> 0.21560731 | E34: =E33/E13 -> 0.28180502 | F34: =F33/F13 -> 0.32185363 | G34: =G33/G13 -> 0.34591377 | H34: =H33/H13 -> 0.37024236
B35: FCFF / NOPAT % (conversion) | C35: =C33/C27 -> 0.4350752 | D35: =D33/D27 -> 0.58972374 | E35: =E33/E27 -> 0.76826926 | F35: =F33/F27 -> 0.86553849 | G35: =G33/G27 -> 0.92019446 | H35: =H33/H27 -> 0.97370098 | L35: WACC ↓ \ EV/EBITDA → | M35: 16 | N35: 18 | O35: 20 | P35: 22 | Q35: 24
L36: 0.075 | M36: =((C33/(1+$L$36)^0.5 + D33/(1+$L$36)^1.5 + E33/(1+$L$36)^2.5 + F33/(1+$L$36)^3.5 + G33/(1+$L$36)^4.5)+(M$35*(G23+G28))/(1+$L$36)^5+Hipotesis!$C$15+Hipotesis!$C$16-Hipotesis!$C$14)/Hipotesis!$C$8 -> 563.09942 | N36: =((C33/(1+$L$36)^0.5 + D33/(1+$L$36)^1.5 + E33/(1+$L$36)^2.5 + F33/(1+$L$36)^3.5 + G33/(1+$L$36)^4.5)+(N$35*(G23+G28))/(1+$L$36)^5+Hipotesis!$C$15+Hipotesis!$C$16-Hipotesis!$C$14)/Hipotesis!$C$8 -> 624.18 | O36: =((C33/(1+$L$36)^0.5 + D33/(1+$L$36)^1.5 + E33/(1+$L$36)^2.5 + F33/(1+$L$36)^3.5 + G33/(1+$L$36)^4.5)+(O$35*(G23+G28))/(1+$L$36)^5+Hipotesis!$C$15+Hipotesis!$C$16-Hipotesis!$C$14)/Hipotesis!$C$8 -> 685.26059 | P36: =((C33/(1+$L$36)^0.5 + D33/(1+$L$36)^1.5 + E33/(1+$L$36)^2.5 + F33/(1+$L$36)^3.5 + G33/(1+$L$36)^4.5)+(P$35*(G23+G28))/(1+$L$36)^5+Hipotesis!$C$15+Hipotesis!$C$16-Hipotesis!$C$14)/Hipotesis!$C$8 -> 746.34118 | Q36: =((C33/(1+$L$36)^0.5 + D33/(1+$L$36)^1.5 + E33/(1+$L$36)^2.5 + F33/(1+$L$36)^3.5 + G33/(1+$L$36)^4.5)+(Q$35*(G23+G28))/(1+$L$36)^5+Hipotesis!$C$15+Hipotesis!$C$16-Hipotesis!$C$14)/Hipotesis!$C$8 -> 807.42176
B37: D. DCF DISCOUNTING & VALUE BRIDGE | L37: 0.085 | M37: =((C33/(1+$L$37)^0.5 + D33/(1+$L$37)^1.5 + E33/(1+$L$37)^2.5 + F33/(1+$L$37)^3.5 + G33/(1+$L$37)^4.5)+(M$35*(G23+G28))/(1+$L$37)^5+Hipotesis!$C$15+Hipotesis!$C$16-Hipotesis!$C$14)/Hipotesis!$C$8 -> 539.24859 | N37: =((C33/(1+$L$37)^0.5 + D33/(1+$L$37)^1.5 + E33/(1+$L$37)^2.5 + F33/(1+$L$37)^3.5 + G33/(1+$L$37)^4.5)+(N$35*(G23+G28))/(1+$L$37)^5+Hipotesis!$C$15+Hipotesis!$C$16-Hipotesis!$C$14)/Hipotesis!$C$8 -> 597.56581 | O37: =((C33/(1+$L$37)^0.5 + D33/(1+$L$37)^1.5 + E33/(1+$L$37)^2.5 + F33/(1+$L$37)^3.5 + G33/(1+$L$37)^4.5)+(O$35*(G23+G28))/(1+$L$37)^5+Hipotesis!$C$15+Hipotesis!$C$16-Hipotesis!$C$14)/Hipotesis!$C$8 -> 655.88303 | P37: =((C33/(1+$L$37)^0.5 + D33/(1+$L$37)^1.5 + E33/(1+$L$37)^2.5 + F33/(1+$L$37)^3.5 + G33/(1+$L$37)^4.5)+(P$35*(G23+G28))/(1+$L$37)^5+Hipotesis!$C$15+Hipotesis!$C$16-Hipotesis!$C$14)/Hipotesis!$C$8 -> 714.20025 | Q37: =((C33/(1+$L$37)^0.5 + D33/(1+$L$37)^1.5 + E33/(1+$L$37)^2.5 + F33/(1+$L$37)^3.5 + G33/(1+$L$37)^4.5)+(Q$35*(G23+G28))/(1+$L$37)^5+Hipotesis!$C$15+Hipotesis!$C$16-Hipotesis!$C$14)/Hipotesis!$C$8 -> 772.51747
B38: Período (años desde valoración) | C38: 0.5 | D38: 1.5 | E38: 2.5 | F38: 3.5 | G38: 4.5 | H38: TV at end FY30 | L38: 0.0912 | M38: =((C33/(1+$L$38)^0.5 + D33/(1+$L$38)^1.5 + E33/(1+$L$38)^2.5 + F33/(1+$L$38)^3.5 + G33/(1+$L$38)^4.5)+(M$35*(G23+G28))/(1+$L$38)^5+Hipotesis!$C$15+Hipotesis!$C$16-Hipotesis!$C$14)/Hipotesis!$C$8 -> 525.09927 | N38: =((C33/(1+$L$38)^0.5 + D33/(1+$L$38)^1.5 + E33/(1+$L$38)^2.5 + F33/(1+$L$38)^3.5 + G33/(1+$L$38)^4.5)+(N$35*(G23+G28))/(1+$L$38)^5+Hipotesis!$C$15+Hipotesis!$C$16-Hipotesis!$C$14)/Hipotesis!$C$8 -> 581.77847 | O38: =((C33/(1+$L$38)^0.5 + D33/(1+$L$38)^1.5 + E33/(1+$L$38)^2.5 + F33/(1+$L$38)^3.5 + G33/(1+$L$38)^4.5)+(O$35*(G23+G28))/(1+$L$38)^5+Hipotesis!$C$15+Hipotesis!$C$16-Hipotesis!$C$14)/Hipotesis!$C$8 -> 638.45767 | P38: =((C33/(1+$L$38)^0.5 + D33/(1+$L$38)^1.5 + E33/(1+$L$38)^2.5 + F33/(1+$L$38)^3.5 + G33/(1+$L$38)^4.5)+(P$35*(G23+G28))/(1+$L$38)^5+Hipotesis!$C$15+Hipotesis!$C$16-Hipotesis!$C$14)/Hipotesis!$C$8 -> 695.13687 | Q38: =((C33/(1+$L$38)^0.5 + D33/(1+$L$38)^1.5 + E33/(1+$L$38)^2.5 + F33/(1+$L$38)^3.5 + G33/(1+$L$38)^4.5)+(Q$35*(G23+G28))/(1+$L$38)^5+Hipotesis!$C$15+Hipotesis!$C$16-Hipotesis!$C$14)/Hipotesis!$C$8 -> 751.81608
B39: Discount factor (mid-year) | C39: =1/(1+Hipotesis!$C$25)^C38 -> 0.95728158 | D39: =1/(1+Hipotesis!$C$25)^D38 -> 0.87724138 | E39: =1/(1+Hipotesis!$C$25)^E38 -> 0.80389349 | F39: =1/(1+Hipotesis!$C$25)^F38 -> 0.73667837 | G39: =1/(1+Hipotesis!$C$25)^G38 -> 0.67508324 | H39: — | L39: 0.1 | M39: =((C33/(1+$L$39)^0.5 + D33/(1+$L$39)^1.5 + E33/(1+$L$39)^2.5 + F33/(1+$L$39)^3.5 + G33/(1+$L$39)^4.5)+(M$35*(G23+G28))/(1+$L$39)^5+Hipotesis!$C$15+Hipotesis!$C$16-Hipotesis!$C$14)/Hipotesis!$C$8 -> 505.8117 | N39: =((C33/(1+$L$39)^0.5 + D33/(1+$L$39)^1.5 + E33/(1+$L$39)^2.5 + F33/(1+$L$39)^3.5 + G33/(1+$L$39)^4.5)+(N$35*(G23+G28))/(1+$L$39)^5+Hipotesis!$C$15+Hipotesis!$C$16-Hipotesis!$C$14)/Hipotesis!$C$8 -> 560.25971 | O39: =((C33/(1+$L$39)^0.5 + D33/(1+$L$39)^1.5 + E33/(1+$L$39)^2.5 + F33/(1+$L$39)^3.5 + G33/(1+$L$39)^4.5)+(O$35*(G23+G28))/(1+$L$39)^5+Hipotesis!$C$15+Hipotesis!$C$16-Hipotesis!$C$14)/Hipotesis!$C$8 -> 614.70773 | P39: =((C33/(1+$L$39)^0.5 + D33/(1+$L$39)^1.5 + E33/(1+$L$39)^2.5 + F33/(1+$L$39)^3.5 + G33/(1+$L$39)^4.5)+(P$35*(G23+G28))/(1+$L$39)^5+Hipotesis!$C$15+Hipotesis!$C$16-Hipotesis!$C$14)/Hipotesis!$C$8 -> 669.15575 | Q39: =((C33/(1+$L$39)^0.5 + D33/(1+$L$39)^1.5 + E33/(1+$L$39)^2.5 + F33/(1+$L$39)^3.5 + G33/(1+$L$39)^4.5)+(Q$35*(G23+G28))/(1+$L$39)^5+Hipotesis!$C$15+Hipotesis!$C$16-Hipotesis!$C$14)/Hipotesis!$C$8 -> 723.60377
B40: PV of FCFF (explicit period) | C40: =C33*C39 -> 49666.44 | D40: =D33*D39 -> 71228.179 | E40: =E33*E39 -> 98009.856 | F40: =F33*F39 -> 115673.32 | G40: =G33*G39 -> 126039.9 | H40: (see TV below) | L40: 0.11 | M40: =((C33/(1+$L$40)^0.5 + D33/(1+$L$40)^1.5 + E33/(1+$L$40)^2.5 + F33/(1+$L$40)^3.5 + G33/(1+$L$40)^4.5)+(M$35*(G23+G28))/(1+$L$40)^5+Hipotesis!$C$15+Hipotesis!$C$16-Hipotesis!$C$14)/Hipotesis!$C$8 -> 484.96875 | N40: =((C33/(1+$L$40)^0.5 + D33/(1+$L$40)^1.5 + E33/(1+$L$40)^2.5 + F33/(1+$L$40)^3.5 + G33/(1+$L$40)^4.5)+(N$35*(G23+G28))/(1+$L$40)^5+Hipotesis!$C$15+Hipotesis!$C$16-Hipotesis!$C$14)/Hipotesis!$C$8 -> 537.00795 | O40: =((C33/(1+$L$40)^0.5 + D33/(1+$L$40)^1.5 + E33/(1+$L$40)^2.5 + F33/(1+$L$40)^3.5 + G33/(1+$L$40)^4.5)+(O$35*(G23+G28))/(1+$L$40)^5+Hipotesis!$C$15+Hipotesis!$C$16-Hipotesis!$C$14)/Hipotesis!$C$8 -> 589.04715 | P40: =((C33/(1+$L$40)^0.5 + D33/(1+$L$40)^1.5 + E33/(1+$L$40)^2.5 + F33/(1+$L$40)^3.5 + G33/(1+$L$40)^4.5)+(P$35*(G23+G28))/(1+$L$40)^5+Hipotesis!$C$15+Hipotesis!$C$16-Hipotesis!$C$14)/Hipotesis!$C$8 -> 641.08635 | Q40: =((C33/(1+$L$40)^0.5 + D33/(1+$L$40)^1.5 + E33/(1+$L$40)^2.5 + F33/(1+$L$40)^3.5 + G33/(1+$L$40)^4.5)+(Q$35*(G23+G28))/(1+$L$40)^5+Hipotesis!$C$15+Hipotesis!$C$16-Hipotesis!$C$14)/Hipotesis!$C$8 -> 693.12555
B41: Σ PV of explicit FCFF | C41: =SUM(C40:G40) -> 460617.7
B43: Cálculos de Valor Terminal (4 métodos)
B44: Method 1: Gordon Growth perpetuity | C44: =G33*(1+Hipotesis!$C$47)/(Hipotesis!$C$25-Hipotesis!$C$47) -> 3140126.3 | D44: TV nominal | G44: =C44*G39 -> 2119846.6 | H44: (PV)
B45: Method 2: Exit EV/EBITDA × FY30 EBITDA | C45: =Hipotesis!$C$50*(G23+G28) -> 5862506.1 | D45: EV exit | G45: =C45*G39 -> 3957679.6
B46: Method 3: Exit EV/EBIT × FY30 EBIT | C46: =Hipotesis!$C$51*G23 -> 5443521.4 | D46: EV exit | G46: =C46*G39 -> 3674830.1
B47: Method 4: H-Model (fade gST → gLT) | C47: =(G33*(1+Hipotesis!$C$47)+G33*Hipotesis!$C$48*(G14-Hipotesis!$C$47))/(Hipotesis!$C$25-Hipotesis!$C$47) -> 4303700.9 | D47: EV total | G47: =C47*G39 -> 2905356.3
B48: Method 5: Exit EV/Revenue × FY30 Revenue | C48: =Hipotesis!$C$52*G13 -> 4317902.8 | D48: Cross-check | G48: =C48*G39 -> 2914943.8
B50: F. PUENTE EV → EQUITY → PRICE TARGET (8 metodologías)
B51: Método | C51: EV ($mm) | D51: (+) Cash | E51: (−) Debt | F51: (+) Eq.inv | G51: Equity ($mm) | H51: Shares (M) | I51: Price ($)
B52: 1. DCF Gordon Growth | C52: =C41+G44 -> 2580464.3 | D52: =Hipotesis!$C$15 -> 78272 | E52: =-Hipotesis!$C$14 -> -40262 | F52: =Hipotesis!$C$16 -> 33683 | G52: =C52+D52+E52+F52 -> 2652157.3 | H52: =Hipotesis!$C$8 -> 7428.4 | I52: =G52/H52 -> 357.02941 | J52: =I52 -> 357.02941
B53: 2. DCF H-Model (fade) | C53: =G47 -> 2905356.3 | D53: =Hipotesis!$C$15 -> 78272 | E53: =-Hipotesis!$C$14 -> -40262 | F53: =Hipotesis!$C$16 -> 33683 | G53: =C53+D53+E53+F53 -> 2977049.3 | H53: =Hipotesis!$C$8 -> 7428.4 | I53: =G53/H53 -> 400.76589 | J53: =I53 -> 400.76589
B54: 3. DCF Exit EV/EBITDA | C54: =C41+G45 -> 4418297.3 | D54: =Hipotesis!$C$15 -> 78272 | E54: =-Hipotesis!$C$14 -> -40262 | F54: =Hipotesis!$C$16 -> 33683 | G54: =C54+D54+E54+F54 -> 4489990.3 | H54: =Hipotesis!$C$8 -> 7428.4 | I54: =G54/H54 -> 604.43572 | J54: =I54 -> 604.43572
B55: 4. DCF Exit EV/EBIT | C55: =C41+G46 -> 4135447.8 | D55: =Hipotesis!$C$15 -> 78272 | E55: =-Hipotesis!$C$14 -> -40262 | F55: =Hipotesis!$C$16 -> 33683 | G55: =C55+D55+E55+F55 -> 4207140.8 | H55: =Hipotesis!$C$8 -> 7428.4 | I55: =G55/H55 -> 566.35894 | J55: =I55 -> 566.35894
B56: 5. DCF Exit EV/Revenue | C56: =C41+G48 -> 3375561.5 | D56: =Hipotesis!$C$15 -> 78272 | E56: =-Hipotesis!$C$14 -> -40262 | F56: =Hipotesis!$C$16 -> 33683 | G56: =C56+D56+E56+F56 -> 3447254.5 | H56: =Hipotesis!$C$8 -> 7428.4 | I56: =G56/H56 -> 464.0642 | J56: =I56 -> 464.0642
B57: 6. NTM P/E × FY27E EPS | C57: — | D57: — | E57: — | F57: — | G57: =Hipotesis!$C$53*D27 -> 3442105.2 | H57: =Hipotesis!$C$8 -> 7428.4 | I57: =G57/H57 -> 463.371 | J57: =I57 -> 463.371
B58: 7. NTM EV/EBITDA × FY27E EBITDA | C58: =Hipotesis!$C$50*(D23+D28) -> 3937450.9 | D58: =Hipotesis!$C$15 -> 78272 | E58: =-Hipotesis!$C$14 -> -40262 | F58: =Hipotesis!$C$16 -> 33683 | G58: =C58+D58+E58+F58 -> 4009143.9 | H58: =Hipotesis!$C$8 -> 7428.4 | I58: =G58/H58 -> 539.70491 | J58: =I58 -> 539.70491
B59: 8. NTM EV/Revenue × FY27E Revenue | C59: =Hipotesis!$C$52*D13 -> 3012723.3 | D59: =Hipotesis!$C$15 -> 78272 | E59: =-Hipotesis!$C$14 -> -40262 | F59: =Hipotesis!$C$16 -> 33683 | G59: =C59+D59+E59+F59 -> 3084416.3 | H59: =Hipotesis!$C$8 -> 7428.4 | I59: =G59/H59 -> 415.21947 | J59: =I59 -> 415.21947
B61: G. ESTADISTICAS DE LAS 8 VALORACIONES
B62: Promedio | J62: =AVERAGE(J52:J59) -> 476.36869
B63: Mediana | J63: =MEDIAN(J52:J59) -> 463.7176
B64: Mínimo | J64: =MIN(J52:J59) -> 357.02941
B65: Máximo | J65: =MAX(J52:J59) -> 604.43572
B66: Spot price | J66: =Hipotesis!$C$6 -> 408
B67: Upside (Mediana vs Spot) | J67: =J63/J66-1 -> 0.13656275

Sheet DuPont_WC
B2: MSFT — DuPont Decomposition + Working Capital Analysis
B3: Periodo FY21-FY25 (anual completo) + 9M FY26 (anualizado donde aplique). Datos en $mm except ratios.
B5: 1. INPUTS HISTORICOS (Source: MSFT 10-K FY21-FY25 + 10-Q Q3 FY26, SEC EDGAR)
C6: FY2021 | D6: FY2022 | E6: FY2023 | F6: FY2024 | G6: FY2025 | H6: 9M FY26
B7: Revenue ($mm) | C7: 168088 | D7: 198270 | E7: 211915 | F7: 245122 | G7: 281724 | H7: 241832 | I7: Income Statement
B8: Operating Income ($mm) | C8: 69916 | D8: 83383 | E8: 88523 | F8: 109433 | G8: 128528 | H8: 114634
B9: Net Income ($mm) | C9: 61271 | D9: 72738 | E9: 72361 | F9: 88136 | G9: 101832 | H9: 97983
B10: Total Assets ($mm) | C10: 333779 | D10: 364840 | E10: 411976 | F10: 512163 | G10: 619003 | H10: 694228 | I10: Balance Sheet
B11: Stockholders' Equity ($mm) | C11: 141988 | D11: 166542 | E11: 206223 | F11: 268477 | G11: 343479 | H11: 414367
B12: Total Debt (incl. current portion) ($mm) | C12: 78361 | D12: 61270 | E12: 47578 | F12: 79444 | G12: 43151 | H12: 40262
B13: Cash + STI ($mm) | C13: 130334 | D13: 104757 | E13: 111262 | F13: 75531 | G13: 94565 | H13: 78272
B14: Operating Cash Flow ($mm) | C14: 76740 | D14: 89035 | E14: 87582 | F14: 118548 | G14: 136162 | H14: 127494 | I14: Cash Flow Statement
B15: Capex ($mm) | C15: 20622 | D15: 23886 | E15: 28107 | F15: 44477 | G15: 64551 | H15: 80146
B16: Free Cash Flow ($mm) | C16: 56118 | D16: 65149 | E16: 59475 | F16: 74071 | G16: 71611 | H16: 47348
B17: D&A ($mm) | C17: 11686 | D17: 14460 | E17: 13861 | F17: 22287 | G17: 34153 | H17: 27512
B18: Effective Tax Rate | C18: 0.14 | D18: 0.13 | E18: 0.19 | F18: 0.182 | G18: 0.183 | H18: 0.19 | I18: 10-K Note 12 — Income Taxes
B20: 2. DUPONT DECOMPOSITION (ROE = Tax Burden × Interest Burden × OpMargin × Asset Turnover × Equity Multiplier)
C21: FY2021 | D21: FY2022 | E21: FY2023 | F21: FY2024 | G21: FY2025 | H21: 9M FY26
B22: Tax Burden = 1 − effective tax rate | C22: =1-C18 -> 0.86 | D22: =1-D18 -> 0.87 | E22: =1-E18 -> 0.81 | F22: =1-F18 -> 0.818 | G22: =1-G18 -> 0.817 | H22: =1-H18 -> 0.81 | I22: Cuanto retiene la empresa del pretax income
B23: Interest Burden = EBT / EBIT (proxy: (NI/(1-T)) / OI) | C23: =(C9/(1-C18))/C8 -> 1.0190135 | D23: =(D9/(1-D18))/D8 -> 1.0026852 | E23: =(E9/(1-E18))/E8 -> 1.0091679 | F23: =(F9/(1-F18))/F8 -> 0.98458163 | G23: =(G9/(1-G18))/G8 -> 0.96976045 | H23: =(H9/(1-H18))/H8 -> 1.0552425 | I23: >1 indica non-op income positivo (intereses, equity inv gains)
B24: Operating Margin = EBIT / Revenue | C24: =C8/C7 -> 0.41594879 | D24: =D8/D7 -> 0.42055278 | E24: =E8/E7 -> 0.41772881 | F24: =F8/F7 -> 0.446443 | G24: =G8/G7 -> 0.45621956 | H24: =H8/H7 -> 0.47402329 | I24: Core profitability — clave del bull case
B25: Asset Turnover = Revenue / Total Assets | C25: =C7/C10 -> 0.5035907 | D25: =D7/D10 -> 0.5434437 | E25: =E7/E10 -> 0.51438676 | F25: =F7/F10 -> 0.47860154 | G25: =G7/G10 -> 0.45512542 | H25: =H7/H10 -> 0.34834665 | I25: Cuán eficientemente generan revenue. Cae con $200B+ AI capex
B26: Equity Multiplier = Total Assets / Equity | C26: =C10/C11 -> 2.350755 | D26: =D10/D11 -> 2.1906786 | E26: =E10/E11 -> 1.9977209 | F26: =F10/F11 -> 1.9076606 | G26: =G10/G11 -> 1.8021568 | H26: =H10/H11 -> 1.675394 | I26: Leverage — MSFT está sobrecapitalizada, declining
B28: ROE (DuPont) = product of 5 factors | C28: =C22*C23*C24*C25*C26 -> 0.43152238 | D28: =D22*D23*D24*D25*D26 -> 0.43675469 | E28: =E22*E23*E24*E25*E26 -> 0.35088715 | F28: =F22*F23*F24*F25*F26 -> 0.32828138 | G28: =G22*G23*G24*G25*G26 -> 0.29647227 | H28: =H22*H23*H24*H25*H26 -> 0.23646429 | I28: Cross-check vs NI/avg Equity ▼
B29: ROE cross-check = NI / period-end Equity | C29: =C9/C11 -> 0.43152238 | D29: =D9/D11 -> 0.43675469 | E29: =E9/E11 -> 0.35088715 | F29: =F9/F11 -> 0.32828138 | G29: =G9/G11 -> 0.29647227 | H29: =H9/H11 -> 0.23646429 | I29: 9M FY26 anualizado: ×4/3
B31: 3. ROIC OPERATIVO (NOPAT / Invested Capital) — métrica relevante para valoración DCF
C32: FY2021 | D32: FY2022 | E32: FY2023 | F32: FY2024 | G32: FY2025 | H32: 9M FY26
B33: NOPAT = EBIT × (1 − effective tax rate) | C33: =C8*(1-C18) -> 60127.76 | D33: =D8*(1-D18) -> 72543.21 | E33: =E8*(1-E18) -> 71703.63 | F33: =F8*(1-F18) -> 89516.194 | G33: =G8*(1-G18) -> 105007.38 | H33: =H8*(1-H18) -> 92853.54 | I33: Excluye non-op income (más conservador que NI)
B34: Invested Capital = Equity + Debt − Excess Cash/STI | C34: =C11+C12-C13 -> 90015 | D34: =D11+D12-D13 -> 123055 | E34: =E11+E12-E13 -> 142539 | F34: =F11+F12-F13 -> 272390 | G34: =G11+G12-G13 -> 292065 | H34: =H11+H12-H13 -> 376357 | I34: Capital efectivamente desplegado en operaciones
B35: ROIC operativo = NOPAT / IC | C35: =C33/C34 -> 0.66797489 | D35: =D33/D34 -> 0.58951859 | E35: =E33/E34 -> 0.50304569 | F35: =F33/F34 -> 0.32863245 | G35: =G33/G34 -> 0.35953427 | H35: =H33/H34 -> 0.24671665 | I35: Si baja por capex AI, valor terminal afectado
B37: ROIC − WACC spread (WACC=9.12% from Hipotesis!$C$25) | C37: =C35-Hipotesis!$C$25 -> 0.5767341 | D37: =D35-Hipotesis!$C$25 -> 0.49827779 | E37: =E35-Hipotesis!$C$25 -> 0.41180489 | F37: =F35-Hipotesis!$C$25 -> 0.23739166 | G37: =G35-Hipotesis!$C$25 -> 0.26829347 | H37: =H35-Hipotesis!$C$25 -> 0.15547586 | I37: Spread positivo = creación de valor (MSFT crónicamente >+20pp)
B39: 4. WORKING CAPITAL DYNAMICS — DSO, DPO, CCC + RPO visibility
C40: FY2021 | D40: FY2022 | E40: FY2023 | F40: FY2024 | G40: FY2025 | H40: 9M FY26
B41: Accounts Receivable (net, $mm) | C41: 38043 | D41: 44261 | E41: 48688 | F41: 56924 | G41: 64411 | H41: 60041 | I41: 10-K BS
B42: Inventory ($mm) | C42: 2636 | D42: 3742 | E42: 2500 | F42: 1246 | G42: 1714 | H42: 1500
B43: Accounts Payable ($mm) | C43: 15163 | D43: 19000 | E43: 18095 | F43: 21996 | G43: 23792 | H43: 22600
B44: Unearned Revenue (current, $mm) | C44: 41525 | D44: 45538 | E44: 50901 | F44: 57582 | G44: 67609 | H44: 67000 | I44: Deferred revenue — visibility
B46: DSO = (AR / Revenue) × 365 (annualized for 9M) | C46: =C41/C7*365 -> 82.609675 | D46: =D41/D7*365 -> 81.481137 | E46: =E41/E7*365 -> 83.859661 | F46: =F41/F7*365 -> 84.762934 | G46: =G41/G7*365 -> 83.450522 | H46: =H41/(H7*4/3)*365 -> 67.965463 | I46: Estable ~78-85 días. Sin signos de stretch en collections
B47: DPO = (AP / Revenue) × 365 (proxy; ideal usa COGS) | C47: =C43/C7*365 -> 32.926176 | D47: =D43/D7*365 -> 34.977556 | E47: =E43/E7*365 -> 31.166623 | F47: =F43/F7*365 -> 32.753241 | G47: =G43/G7*365 -> 30.824779 | H47: =H43/(H7*4/3)*365 -> 25.582843 | I47: 9M FY26: AP +$15.8B vs Jun-25 por server components (en realidad oculta capex)
B48: DIO = (Inventory / Revenue) × 365 | C48: =C42/C7*365 -> 5.7240255 | D48: =D42/D7*365 -> 6.8887376 | E48: =E42/E7*365 -> 4.3059717 | F48: =F42/F7*365 -> 1.8553618 | G48: =G42/G7*365 -> 2.2206486 | H48: =H42/(H7*4/3)*365 -> 1.6979763 | I48: MSFT software-heavy → inventory minimal
B49: Cash Conversion Cycle = DSO + DIO − DPO | C49: =C46+C48-C47 -> 55.407525 | D49: =D46+D48-D47 -> 53.392319 | E49: =E46+E48-E47 -> 56.999009 | F49: =F46+F48-F47 -> 53.865055 | G49: =G46+G48-G47 -> 54.846392 | H49: =H46+H48-H47 -> 44.080596 | I49: CCC bajo o negativo = ventaja competitiva (clientes pagan rápido, proveedores tarde)
B51: Remaining Performance Obligations ($mm) | C51: — | D51: — | E51: 222000 | F51: 269000 | G51: 368000 | H51: 627000 | I51: RPO = backlog contractual. Crecimiento +99% YoY Q3FY26 indica visibility extrema
B52: RPO / Revenue (años de visibility) | C52: n/d | D52: n/d | E52: =E51/E7 -> 1.0475898 | F52: =F51/F7 -> 1.0974127 | G52: =G51/G7 -> 1.306243 | H52: =H51/(H7*4/3) -> 1.9445317 | I52: 9M FY26: ~1.94× revenue ya contratado. Defensa fundamental del cash flow forward
B55: 5. SÍNTESIS — Lectura de DuPont y WC
B56: ▸ ROE GAAP cae de ~43% (FY21) a ~30% (FY25): no por pérdida de profitability, sino por sobrecapitalización (equity ↑ más rápido que earnings).
B57: ▸ Operating margin sube +330 bp (FY21→FY25, 41.6%→45.6%): el mejor indicador de cómo Microsoft aprovecha escala.
B58: ▸ Asset turnover cae 50→46 (FY21→FY25): consecuencia directa de $284B PP&E (vs $71B FY21). AI capex es el responsable.
B59: ▸ Equity multiplier baja de 2.35 → 1.80: balance se desapalanca. Esto presiona ROE GAAP pero NO crea ni destruye valor.
B60: ▸ ROIC operativo (NOPAT/IC) cae de ~28% → ~25%: dilución real por capex AI. Aún muy por encima de WACC 9.1% → +1500-1600 bp spread.
B61: ▸ DSO estable ~80 días: collections healthy. Sin signos de canal stuffing o aging accounts.
B62: ▸ AP +$15.8B vs Jun-25 (9M FY26): el management 'oculta' parte del capex AI en cuentas por pagar — vigilar reversión en próximos Q.
B63: ▸ Unearned revenue +63% (FY21→FY25): pre-payment growth refleja el cambio a Azure/Copilot annual/multiyear contracts.
B64: ▸ RPO = $627B (Q3 FY26, +99% YoY) representa ~1.9× revenue de visibility — extraordinario para una empresa de este tamaño.
B65: ▸ Conclusión: la calidad operativa NO se ha deteriorado. El capex AI presiona returns short-term, pero margins y RPO sugieren creación de valor sostenida.

Sheet Reverse_DCF
B2: MSFT — REVERSE DCF: ¿Qué pricea el mercado a $408?
B3: Dado spot=$408, ¿qué suposiciones tendrían que ser ciertas? Closed-form solutions — no goal seek manual.
B5: INPUTS COMUNES (link a Modelo/Hipotesis)
B6: Spot price ($) | C6: =Hipotesis!$C$6 -> 408
B7: Shares diluidas (M) | C7: =Hipotesis!$C$8 -> 7428.4
B8: Cash + STI ($mm) | C8: =Hipotesis!$C$15 -> 78272
B9: Equity & other investments ($mm) | C9: =Hipotesis!$C$16 -> 33683
B10: Total Debt ($mm) | C10: =Hipotesis!$C$14 -> 40262
B11: WACC (caso base) | C11: =Hipotesis!$C$25 -> 0.091240798
B12: Terminal g (caso base) | C12: =Hipotesis!$C$47 -> 0.03
B13: Σ PV explicit FCFF FY26-FY30 (Modelo) | C13: =Modelo!$C$41 -> 460617.7
B14: FY30E FCFF (Modelo) | C14: =Modelo!$G$33 -> 186702.75
B15: FY30E EBIT (Modelo) | C15: =Modelo!$G$23 -> 247432.79
B16: FY30E D&A (Modelo) | C16: =Modelo!$G$28 -> 78261.988
B17: FY30E Revenue (Modelo) | C17: =Modelo!$G$13 -> 539737.85
B18: FY30E NOPAT (Modelo) | C18: =Modelo!$G$27 -> 202894.89
B19: Effective tax rate | C19: =Hipotesis!$C$13 -> 0.18
B21: CÁLCULOS INTERMEDIOS (Δ implícita vs caso base)
B22: Equity target = Spot × Shares ($mm) | C22: =C6*C7 -> 3030787.2
B23: (+) Debt | C23: =C10 -> 40262
B24: (−) Cash + STI | C24: =-C8 -> -78272
B25: (−) Equity & other investments | C25: =-C9 -> -33683
B26: Enterprise Value target ($mm) | C26: =C22+C10-C8-C9 -> 2959094.2
B27: (−) Σ PV explicit FCFF | C27: =-C13 -> -460617.7
B28: PV(TV) implícito ($mm) | C28: =C26-C13 -> 2498476.5
B29: TV nominal implícito (×(1+WACC)^5) | C29: =C28*(1+C11)^5 -> 3866145.9
B31: A. ¿Qué g_terminal implica el spot? (manteniendo WACC, FCFF base, bridge)
B32: Fórmula: g = (TV·WACC − FCFF_30) / (TV + FCFF_30)
B33: g_terminal implícito (Gordon) | C33: =(C29*C11-C14)/(C29+C14) -> 0.040970561 | D33: vs base 3.0%: | E33: =C33-C12 -> 0.010970561 | G33: Si >0 ↑ → mercado más optimista que base. Si <0 → más pesimista.
B35: B. ¿Qué WACC implica el spot? (manteniendo g_terminal=3%, FCFF base, bridge)
B36: Aproximación: como WACC afecta TV y descuento, no hay fórmula cerrada. Tabla de precios implícitos:
B37: WACC → | C37: 0.075 | D37: 0.085 | E37: 0.0912 | F37: 0.095 | G37: 0.105 | H37: 0.115
B38: Precio implícito ($) | C38: =((Modelo!C33/(1+C$37)^0.5 + Modelo!D33/(1+C$37)^1.5 + Modelo!E33/(1+C$37)^2.5 + Modelo!F33/(1+C$37)^3.5 + Modelo!G33/(1+C$37)^4.5)+(Modelo!G33*(1+C12)/(C$37-C12))/(1+C$37)^5+C8+C9-C10)/C7 -> 475.1718 | D38: =((Modelo!C33/(1+D$37)^0.5 + Modelo!D33/(1+D$37)^1.5 + Modelo!E33/(1+D$37)^2.5 + Modelo!F33/(1+D$37)^3.5 + Modelo!G33/(1+D$37)^4.5)+(Modelo!G33*(1+C12)/(D$37-C12))/(1+D$37)^5+C8+C9-C10)/C7 -> 385.73745 | E38: =((Modelo!C33/(1+E$37)^0.5 + Modelo!D33/(1+E$37)^1.5 + Modelo!E33/(1+E$37)^2.5 + Modelo!F33/(1+E$37)^3.5 + Modelo!G33/(1+E$37)^4.5)+(Modelo!G33*(1+C12)/(E$37-C12))/(1+E$37)^5+C8+C9-C10)/C7 -> 345.07884 | F38: =((Modelo!C33/(1+F$37)^0.5 + Modelo!D33/(1+F$37)^1.5 + Modelo!E33/(1+F$37)^2.5 + Modelo!F33/(1+F$37)^3.5 + Modelo!G33/(1+F$37)^4.5)+(Modelo!G33*(1+C12)/(F$37-C12))/(1+F$37)^5+C8+C9-C10)/C7 -> 324.03136 | G38: =((Modelo!C33/(1+G$37)^0.5 + Modelo!D33/(1+G$37)^1.5 + Modelo!E33/(1+G$37)^2.5 + Modelo!F33/(1+G$37)^3.5 + Modelo!G33/(1+G$37)^4.5)+(Modelo!G33*(1+C12)/(G$37-C12))/(1+G$37)^5+C8+C9-C10)/C7 -> 278.95068 | H38: =((Modelo!C33/(1+H$37)^0.5 + Modelo!D33/(1+H$37)^1.5 + Modelo!E33/(1+H$37)^2.5 + Modelo!F33/(1+H$37)^3.5 + Modelo!G33/(1+H$37)^4.5)+(Modelo!G33*(1+C12)/(H$37-C12))/(1+H$37)^5+C8+C9-C10)/C7 -> 244.61818
B39: WACC implícito (interpolado vs spot) | C39: =SLOPE(C37:H37,C38:H38)*C6+INTERCEPT(C37:H37,C38:H38) -> 0.083181517 | D39: vs base 9.12%: | E39: =C39-C11 -> -0.0080592808 | G39: (FORECAST.LINEAR sobre la tabla — aproximación lineal, válida en el entorno del spot)
B41: C. ¿Qué margen EBIT FY30E implica el spot? (manteniendo Rev FY30E, Capex/Rev, g, WACC)
B42: Aprox: terminal margin solo afecta TV (PV explícito a caso base).
B43: FCFF terminal implícito ($mm) | C43: =C29*(C11-C12)/(1+C12) -> 229869.77 | D43: vs base: | E43: =C43/C14-1 -> 0.23120716
B44: NOPAT terminal implícito = FCFF − D&A − Capex_signed − ΔWC_signed | C44: =C43-C16-Modelo!G30-Modelo!G32 -> 246061.9
B45: EBIT terminal implícito = NOPAT / (1−T) | C45: =C44/(1-C19) -> 300075.49
B46: EBIT margin FY30E implícito | C46: =C45/C17 -> 0.55596526 | D46: vs base 45.8%: | E46: =C46-C15/C17 -> 0.09753383 | G46: Si <base, el mercado descuenta margen presionado (capex AI persistente).
B48: D. ¿Qué Capex/Rev terminal implica el spot? (manteniendo EBIT margin base, g, WACC)
B49: Capex terminal implícito ($mm) | C49: =C18+C16-C43-Modelo!G32 -> 51287.11
B50: Capex/Rev terminal implícito | C50: =C49/C17 -> 0.095022259 | D50: vs base 15%: | E50: =C50-Hipotesis!$H$39 -> -0.054977741 | G50: Si >base, el mercado descuenta capex AI sostenido (overinvest).
B52: E. ¿Qué Revenue CAGR FY25→FY30 implica el spot? (escala uniforme, margenes y Capex/Rev fijos)
B53: Base EV = PV_explicit + PV(TV_base) (from Modelo) | C53: =C13 + C14*(1+C12)/(C11-C12)/(1+C11)^5 -> 2489907.8
B54: Scaling factor k = Target EV / Base EV | C54: =C26/C53 -> 1.1884353
B55: Implied FY30E Revenue = Base × k | C55: =C17*C54 -> 641443.49
B56: Revenue CAGR FY25→FY30 implícito | C56: =(C55/Historico!G6)^(1/5)-1 -> 0.1788727 | D56: vs base 13.9%: | E56: =C56-((C17/Historico!G6)^(1/5)-1) -> 0.040008856 | G56: Es la 'tasa de crecimiento' que necesita MSFT para que $408 sea justo, manteniendo todos los ratios.
B58: F. SÍNTESIS — qué pricea el mercado vs caso base
B59: Variable | C59: Base case | D59: Implícito (ceteris paribus) | E59: Δ | F59: Lectura
B60: Terminal g (perpetuidad) | C60: =C12 -> 0.03 | D60: =C33 -> 0.040970561 | E60: =D60-C60 -> 0.010970561 | F60: Mercado pricea g levemente superior al base
B61: WACC | C61: =C11 -> 0.091240798 | D61: =C39 -> 0.083181517 | E61: =D61-C61 -> -0.0080592808 | F61: Si implícito > base → mercado exige más retorno (más riesgo)
B62: EBIT margin FY30E | C62: =C15/C17 -> 0.45843143 | D62: =C45/C17 -> 0.55596526 | E62: =D62-C62 -> 0.09753383 | F62: Mercado pricea margenes SUPERIORES (irreal por sí solo, parte de mix)
B63: Capex/Rev terminal | C63: =Hipotesis!$H$39 -> 0.15 | D63: =C49/C17 -> 0.095022259 | E63: =D63-C63 -> -0.054977741 | F63: Mercado pricea capex normalizando MÁS rápido al 9-10% (vs mi base 15%)
B64: Revenue CAGR FY25→FY30 | C64: =(C17/Historico!G6)^(1/5)-1 -> 0.13886384 | D64: =(C55/Historico!G6)^(1/5)-1 -> 0.1788727 | E64: =D64-C64 -> 0.040008856 | F64: El precio actual está consistente con esta tasa de crecimiento
B66: G. LECTURA INTEGRAL
B67: ▸ El spot $408 implica una mezcla de assumptions más conservadoras que el caso base, pero NO drásticamente bear. La diferencia es de un único 'click' en cada variable.
B68: ▸ Si crees que MSFT puede mantener margins ~46% y capex normaliza al 15%, hay margen para upside ($455 mediana, +12%).
B69: ▸ Si crees que el capex AI no normaliza (15-22% terminal) y margins quedan en 44%, el spot ya es justo.
B70: ▸ Las 8 metodologías rinden $155–$582. El spot $408 está justo entre el promedio Gordon ($345) y el promedio multiples ($516). El mercado pricea una valoración 'mixta'.
B71: ▸ El reverse-DCF NO es una receta — es una herramienta para hacer explícitas las apuestas. Lo importante es: ¿estás más optimista o pesimista que estas implícitas?

Sheet Conclusiones
B2: MSFT — CONCLUSIONES & THESIS NARRATIVE
B3: Síntesis cualitativa de la valoración. Compañera de la hoja Modelo (números) y DuPont_WC (returns).
B5: 1. TESIS CENTRAL
B6: Tesis | C6: Microsoft se ha transformado en la primera compañía pública con dos motores de crecimiento estructural simultáneos: Azure (infraestructura cloud + IA) y M365 Commercial (productividad + Copilot ARPU). El mercado parece valorar correctamente el negocio de Office estable, pero infravalora la opcionalidad de Copilot y la elasticidad de demanda Azure en una ventana 3-5 años. El ciclo capex AI (~$110B FY26E) presiona FCF y ROIC short-term, pero los $627B de RPO y +40% Azure growth supply-constrained sugieren que las inversiones tienen demanda concreta detrás, no especulación.
B8: 2. EL DEBATE CENTRAL — AI CAPEX
B9: Bear case | C9: Capex/Revenue ha pasado de 12% (FY21) a 23% (TTM). Si se mantiene a 20%+ terminal, FCF/share estará permanentemente deprimida. Las dudas: (1) ¿hay overbuild de capacidad por miedo a perder cuota vs AMZN/GOOGL? (2) ¿cuánto de la demanda Azure es OpenAI (que paga subsidiada) vs clientes externos? (3) ¿qué pasa con $283B de PP&E si los GPUs se obsoletan en 3-4 años? El precio TTM P/E 25× incorpora una expectativa de normalización capex que el guidance corporativo aún no confirma.
B11: Bull case | C11: El AI capex genera revenue a margenes brutos altos (Azure ~69% MS Cloud GM en Q3). El backlog $627B (+99% YoY) indica demanda contractual asegurada — el capex no es speculative, es supply-constrained build-out. La penetración Copilot en seats M365 (~20M actuales sobre ~400M instalados) implica una rampa de ARPU $200-300/seat con margenes >70%. Si Copilot llega al 50% de seats, M365 commercial podría crecer 25-30% con margen estable.
B13: Mi lectura | C13: El capex AI es real, no fluff. Pero la magnitud está estresando los returns: ROIC operativo 36% FY25 → ~25% LTM, un -1100bp drop. La pregunta no es '¿hay demanda?' sino '¿cuánta de la demanda es sostenible vs experimentación enterprise?'. Mi base case asume que Capex/Rev normaliza al 17% en 5 años (cae de 33% FY26E → 15% terminal) y que el operating margin se mantiene 45-46% gracias a Copilot offset. Pondré 45% probabilidad al base, 30% bull, 25% bear.
B15: 3. ESCENARIOS DE VALORACIÓN
B16: Escenario | C16: Drivers clave | D16: Precio implícito
B17: Bear (25%) | C17: Capex/Rev permanece 22% terminal; Azure decelera a 18% por moderación enterprise AI; IC margin estanca 38%; PBP margin presionada por Copilot pricing concesiones | D17: $280-340
B18: Base (45%) | C18: Capex normaliza a 17% terminal; Azure FY26-FY30 24%→14% (sostenible); margins se sostienen 45-46%; Copilot moderate adoption (50% seats by FY30); WACC 9.1% | D18: $430-490
B19: Bull (30%) | C19: Capex/Rev cae a 15% terminal por eficiencia GPU; Azure mantiene 25%+ vía demand sustained; M365 ARPU expansion +40% con Copilot 70% penetración; OpenAI stake monetizada | D19: $580-680
B20: Probabilistic mean | C20: 0.25 × $310 + 0.45 × $460 + 0.30 × $630 = $474 (ponderado) | D20: $474
B22: 4. DRIVERS CLAVE — RANKED BY SENSITIVITY
B23: #1 — Capex/Rev terminal | C23: Cada +100bp Capex/Rev terminal ≈ -$10 precio. Cae más bruscamente que cualquier otro driver. La asunción de 15% terminal vs 22% TTM es la apuesta más grande del modelo.
B24: #2 — WACC (Ke y beta) | C24: Cada +100bp WACC ≈ -$70-90 en precio (Tabla A). MSFT beta 1.10 podría subir si AI capex stress aumenta volatilidad reported earnings. Inverse: Fed cuts podrían reducir Rf →WACC.
B25: #3 — IC margin sostenible | C25: Si IC margin sostiene 42% (vs 39% Q3 FY26 dip), el upside es +5-8%. La pregunta: ¿los CapEx D&A absorben totalmente la mejora de gross margin Azure?
B26: #4 — Copilot adoption rate | C26: Penetración seats M365 actual: ~5% (20M / 400M). Cada +10pp de penetración a $30/seat/mes ARPU ≈ +$15B ARR. Bajo apalancamiento operativo de la base instalada.
B27: #5 — Terminal g (perpetuidad) | C27: Sensibilidad alta pero menos accionable. Asumir 3% es prudente; 2.5% sería más conservador (~-$50 precio).
B28: #6 — OpenAI partnership economics | C28: $11.8B funded de $13B compromiso. Equity 27% as-converted. Impacto valoración indirecto vía Azure consumption (OpenAI gasta ~$15-20B/año en Azure compute).
B30: 5. RIESGOS PRINCIPALES
B31: Riesgo | C31: Magnitud / Impacto
B32: Capex sustainability | C32: Si AI capex no genera revenue al ritmo esperado (Azure deceleración, customer churn), ROIC cae permanentemente. Magnitud: -$200B EV downside.
B33: GPU depreciation | C33: MSFT acelera D&A 6-yr → 4-yr en hardware AI. Si los chips Hopper/Blackwell obsoletizan más rápido (Cerebras, Groq, TPUs propias), impairments masivos posibles.
B34: Regulatory antitrust | C34: FTC investigation Activision still in some markets. UK CMA cleared. EU vigila bundle Teams/M365. Potencial fine cap: limited ($1-3B max range).
B35: OpenAI dependency | C35: Si OpenAI fracasa o split con MSFT, el AI revenue stream (~$35B ARR) tiene riesgo binario. Recap 2025 reduce dependence pero no la elimina.
B36: Hyperscaler competition | C36: AMZN AWS aún #1, GOOGL Cloud cerrando gap, ORCL ganando enterprise (su sell-off Sep-25 → $185 abrió oportunidad pero también nervios sector). Azure pricing wars posible.
B37: Geopolítico / China | C37: <5% revenue de China, pero supply chain semiconductor exposure. Taiwan, NVIDIA export controls, expand restricciones.
B38: Recesión / IT budgets | C38: Enterprise cloud growth pro-cyclical. Una recesión 2026-2027 podría diferir migraciones cloud y reducir Azure growth a +12-15% temporalmente.
B39: Concentración top customers | C39: Top 10 cuentas Azure son ~25% de revenue (estimado). OpenAI sola ~10%. Concentración invisible en reporting pero real.
B41: 6. CONCLUSIÓN — DECISIÓN DE INVERSIÓN
B42: Veredicto | C42: MSFT cotiza a ~$408 vs mediana modelo $455 (+12% upside). El asymmetric risk-reward es ligeramente favorable pero NO compelling como entry point top-of-mind. La verdadera oportunidad llega en correcciones intra-año del 10-15% (similar al sell-off Sep-2025 → $356 que generó retorno +50% en 7 meses).
B43: Recomendación | C43: HOLD / accumulate on dips. Para entries > $450 sugiero esperar mejor entry ($380-400). Por debajo de $360 → strong buy. La calidad operativa (ROIC 25-36%, RPO $627B, margins 47%) justifica un premium permanente sobre el S&P 500 pero no un escenario blow-off top tipo NVDA.
B44: Catalizadores a 12 meses | C44: (1) Q4 FY26 capex moderation signal en jul-2026 earnings, (2) Copilot enterprise penetration milestones, (3) Azure capacity unlock signals (margin recovery), (4) Fed cuts → re-rating multiples, (5) OpenAI IPO / liquidity event.

Sheet Fuentes
B2: MSFT — FUENTES Y REFERENCIAS
B3: Todas las cifras históricas y de mercado citan fuentes primarias (SEC EDGAR, FRED, Damodaran) verificadas al 15-may-2026.
B5: 1. FILINGS REGULATORIOS (SEC EDGAR) — fuentes primarias
B6: Documento | C6: Fecha | D6: URL | E6: Uso en modelo
B7: MSFT 10-K FY2025 (annual) | C7: 30-jun-2025 | D7: https://www.sec.gov/Archives/edgar/data/789019/000095017025100235/msft-20250630.htm | E7: Income Statement, BS, CF, segmentos FY21-FY25; effective tax rate Nota 12; buyback authorization Nota 17
B8: MSFT 10-Q Q3 FY2026 (interim) | C8: 31-mar-2026 | D8: https://www.sec.gov/Archives/edgar/data/0000789019/000119312526191507/msft-20260331.htm | E8: 9M FY26 IS/BS/CF; Azure +40%; RPO $627B; capex 9M $80.1B; PP&E $283B; OpenAI Recap dilution gain $5.9B
B9: MSFT 8-K Press Release Q3 FY26 | C9: 29-abr-2026 | D9: https://www.microsoft.com/en-us/investor/earnings/fy-2026-q3/press-release-webcast | E9: Detail métricas operativas: MS Cloud $45.5B (+22%), AI ARR $37B (+123%), Copilot seats >20M
B10: MSFT 10-K FY2024 | C10: 30-jun-2024 | D10: https://www.sec.gov/Archives/edgar/data/789019/000095017024087843/msft-20240630.htm | E10: FY24 históricos para comparativa y series largas; Activision close detalles
B11: MSFT 10-K FY2023 | C11: 30-jun-2023 | D11: https://www.sec.gov/Archives/edgar/data/789019/000095017023035122/msft-20230630.htm | E11: FY23 históricos; primer reporting RPO ($222B); Activision pending
B12: MSFT 10-K FY2022 | C12: 30-jun-2022 | D12: https://www.sec.gov/Archives/edgar/data/789019/000156459022026876/msft-10k_20220630.htm | E12: FY22 históricos; pre-AI capex baseline
B13: MSFT 10-K FY2021 | C13: 30-jun-2021 | D13: https://www.sec.gov/Archives/edgar/data/789019/000156459021039151/msft-10k_20210630.htm | E13: FY21 base year para series 5-year
B15: 2. MERCADO Y MACRO
B16: Fuente | C16: Dato (15-may-2026) | D16: URL | E16: Uso en modelo
B17: Federal Reserve FRED — 10Y UST | C17: DGS10 series — daily, 15-may-2026: 4.54% | D17: https://fred.stlouisfed.org/series/DGS10 | E17: Risk-free rate input (Hipotesis!$C$9)
B18: NYU Stern (Damodaran) — Implied ERP | C18: ERP 2026 Edition, January 2026 update: 4.23% | D18: https://pages.stern.nyu.edu/~adamodar/ | E18: Equity Risk Premium input (Hipotesis!$C$10)
B19: MSFT spot quote | C19: Yahoo Finance / Google Finance 15-may-2026 EOD ~$408 | D19: https://finance.yahoo.com/quote/MSFT | E19: Spot price (Hipotesis!$C$6) — verificación cross-source
B20: MSFT 52-week range | C20: $356.28 (Apr-2026 low) – $555.45 (Oct-2025 high) | D20: https://finance.yahoo.com/quote/MSFT/history | E20: Resumen sheet — context histórico
B21: Damodaran Industry Beta | C21: Software (System & Application) 2026: 1.05-1.15 range | D21: https://pages.stern.nyu.edu/~adamodar/New_Home_Page/datafile/Betas.html | E21: Beta cross-check (Hipotesis!$C$11)
B23: 3. PEERS Y CROSS-CHECKS
B24: Peer | C24: Métrica clave | D24: URL | E24: Uso
B25: Alphabet (GOOGL) — Q1 2026 10-Q | C25: Market cap $4.86T, P/E 30.4× TTM | D25: https://abc.xyz/investor/ | E25: Multiple peer comparison para EV/EBITDA y P/E ranges
B26: Amazon (AMZN) — Q1 2026 10-Q | C26: Market cap $2.87T, P/E 31.5× TTM, AWS focus | D26: https://ir.aboutamazon.com/ | E26: Hyperscaler cross-check capex/revenue ratio
B27: Oracle (ORCL) — Q3 FY26 release | C27: Market cap $555B, P/E ~33× post sell-off (Sep-25 high $345 → $185) | D27: https://investor.oracle.com/ | E27: Comparable cloud transition / multiple compression case study
B28: Bill Ackman / Pershing Square Q1 2026 13F | C28: Position initiated in MSFT during Mar-Apr-2026 drawdown | D28: https://www.sec.gov/cgi-bin/browse-edgar?action=getcompany&CIK=0001336528 | E28: Sentiment / institutional positioning context
B30: 4. DOCUMENTOS INTERNOS / RESEARCH USADOS
B31: Documento | C31: Fecha | D31: Origen | E31: Uso
B32: MSFT-research-deep-dive-v1.2 | C32: 13-may-2026 | D32: Documento aportado por usuario | E32: Estructura inicial de tesis, marco analítico segmentación, decisión de capex AI como centro narrativo
B33: UBER valuation model (v3) | C33: previo (referencia) | D33: Repositorio interno del usuario | E33: Estructura 7-sheet replicada para consistencia metodológica (Resumen/Hipotesis/Historico/Modelo/DuPont_WC/Conclusiones/Fuentes)
B35: 5. NOTAS METODOLÓGICAS
B36: Todas las cifras de IS/BS/CF FY21-FY25 verificadas contra MSFT 10-K originales presentados ante la SEC. Diferencias con consensus data agregadores (Bloomberg, FactSet) NO se aplicaron — el modelo prioriza fuentes primarias.
B37: Effective tax rate FY24 y FY25 = 18% (Nota 12 del 10-K). Aplicada uniformemente al cálculo NOPAT histórico y proyectado. Sensibilidad ±200bp tax rate ≈ ±$25 precio.
B38: Segmentación PBP/IC/MPC reportada por MSFT desde FY2024. Reclasificación retroactiva FY21-FY23 hecha por Microsoft (incluida en 10-K FY25); modelo usa cifras restated.
B39: RPO definido como Performance Obligations not yet recognized as revenue. MSFT reporta este desde Q1 FY24 con creciente detalle. ASC 606 framework.
B40: OpenAI Recapitalization (Oct-2025): MSFT pasa de ~49% profit-sharing rights a ~27% as-converted equity stake. $13B total commitment, $11.8B funded as of Q3 FY26. Reportado en 10-Q Q1 FY26 Note 9.
B41: Damodaran ERP: implied ERP basado en S&P 500 dividend + buyback yields proyectados. Edición enero-2026. Alternativa: historical ERP arithmetic mean 5.8% (1928-2025) — no usada por preferencia de método implied.
B42: Cost of debt: AAA-rated MSFT, spread ~25bp sobre 10Y UST. Calculado como Rf 4.54% + 26bp = 4.80%. MSFT prácticamente sin nuevo debt issuance reciente (Total Debt cae de $79B en FY24 a $40B en Q3 FY26).
B43: Discount factors: convención mid-year (0.5, 1.5, 2.5, ...) — más realista que end-of-year para flujos uniformemente distribuidos.
B44: 8 métodos de valoración (DCF Gordon, H-Model, Exit EBITDA/EBIT/Rev + NTM P/E/EBITDA/Rev cross-checks): la mediana se usa como target central por robustez vs outliers.
B45: Sensibilidades embebidas (Tablas A-D en Modelo cols L-R): recompute completo, no TABLE() de Excel. Highlight verde > spot, rojo < spot.
B47: Modelo construido el 15-may-2026. Auditable end-to-end vía formulas. 506+ formulas, 0 errors en recalc.
